Workbook

Sheet Math
B3: 1st Half | C3: 2nd Half | E3: Y2025
A5: Known/Forecasted | B5: =SUM('1 Collections'!E15:J15) -> 1425932.9 | C5: =SUM('1 Collections'!K15:P15) -> 2066373 | E5: =SUM(B5:C5) -> 3492305.9
A6: Unkown | B6: =SUM('1 Collections'!E27:J27) -> 0 | C6: =SUM('1 Collections'!K27:P27) -> 100000 | E6: =SUM(B6:C6) -> 100000
A7: Collections | B7: =SUM(B5:B6) -> 1425932.9 | C7: =SUM(C5:C6) -> 2166373 | E7: =SUM(E5:E6) -> 3592305.9
A9: W2 | B9: =SUM('2 Employees'!C286:H288)+SUM('3 Benefits'!C116:H116) -> 1928165.3 | C9: =SUM('2 Employees'!I289:N289)+SUM('3 Benefits'!I116:N116) -> 1694975.7 | E9: =SUM(B9:C9) -> 3623141
A10: Contractors | B10: =SUM('4 Contractors'!C131:H131) -> 1304965.2 | C10: =SUM('4 Contractors'!I131:N131) -> 1088280.9 | E10: =SUM(B10:C10) -> 2393246
A11: Other | B11: =SUM('6 Other'!C34:H34) -> 3545.63 | C11: =SUM('6 Other'!I34:N34) -> 0 | E11: =SUM(B11:C11) -> 3545.63
A12: Spend | B12: =SUM(B9:B11) -> 3236676.1 | C12: =SUM(C9:C11) -> 2783256.6 | E12: =SUM(E9:E11) -> 6019932.7
A14: Beginning Cash | B14: =+'2025 CF Basic'!E50 -> 3334341 | C14: =+B19 -> 2248597.3 | E14: =+B14 -> 3334341
A16: Net Burn | B16: =+B7-B12 -> -1810743.1 | C16: =+C7-C12 -> -616883.6 | E16: =+E7-E12 -> -2427626.7
A17: Investment | B17: =SUM('6 Other'!D29:H29) -> 724999.44 | C17: =SUM('6 Other'!I29:N29) -> -25000 | E17: =SUM(B17:C17) -> 699999.44
A19: Ending Cash | B19: =+B14+B16+B17 -> 2248597.3 | C19: =+C14+C16+C17 -> 1606713.7 | E19: =+E14+E16+E17 -> 1606713.7
A21: Check | B21: =+B19-'2025 Detail'!H61 -> 225314.04 | C21: =+C19-'2025 Detail'!N61 -> 642602.99 | E21: =+E19-'2025 Detail'!N61 -> 642602.99
B24: =SUM('2025 CF Basic'!E21:J21) -> 1928165.3
B25: =SUM('2025 CF Basic'!E26:J26) -> 1299922.1
B26: =+B10 -> 1304965.2
B28: =+B26-B25 -> 5043.12

Sheet 2026 Summary - BK No Bonus
B2: SYNAPTIC CASH FLOW FORECAST | C2: 46023 | D2: =EDATE(C2,1) -> 46054 | E2: =EDATE(D2,1) -> 46082 | F2: =EDATE(E2,1) -> 46113 | G2: =EDATE(F2,1) -> 46143 | H2: =EDATE(G2,1) -> 46174 | I2: =EDATE(H2,1) -> 46204 | J2: =EDATE(I2,1) -> 46235 | K2: =EDATE(J2,1) -> 46266 | ... N2: =EDATE(M2,1) -> 46357 | P2: Q1 | Q2: Q2 | R2: Q3 | S2: Q4 | U2: 2026 | W2: Check
B3: =+Version!$C$3 -> Y2025 12 v001
B5: Consulting - Classic | C5: =+'2026 Detail'!C8 -> 126737 | D5: =+'2026 Detail'!D8 -> 270160 | E5: =+'2026 Detail'!E8 -> 223350 | F5: =+'2026 Detail'!F8 -> 197930 | G5: =+'2026 Detail'!G8 -> 151930 | H5: =+'2026 Detail'!H8 -> 151930 | I5: =+'2026 Detail'!I8 -> 146930 | J5: =+'2026 Detail'!J8 -> 145000 | ... N5: =+'2026 Detail'!N8 -> 130000 | P5: =SUM(C5:E5) -> 620247 | Q5: =SUM(F5:H5) -> 501790 | R5: =SUM(I5:K5) -> 436930 | S5: =SUM(L5:N5) -> 410000 | U5: =SUM(C5:N5) -> 1968967 | W5: =ROUND(SUM(P5:S5)-U5,2) -> 0
B6: Consulting - AppIQ | C6: =+'2026 Detail'!C13 -> 163027.6 | D6: =+'2026 Detail'!D13 -> 123027.6 | E6: =+'2026 Detail'!E13 -> 366527.6 | F6: =+'2026 Detail'!F13 -> 386527.6 | G6: =+'2026 Detail'!G13 -> 268277.6 | H6: =+'2026 Detail'!H13 -> 268277.6 | I6: =+'2026 Detail'!I13 -> 403277.6 | J6: =+'2026 Detail'!J13 -> 390500 | ... N6: =+'2026 Detail'!N13 -> 550000 | P6: =SUM(C6:E6) -> 652582.8 | Q6: =SUM(F6:H6) -> 923082.8 | R6: =SUM(I6:K6) -> 1079777.6 | S6: =SUM(L6:N6) -> 1487000 | U6: =SUM(C6:N6) -> 4142443.2 | W6: =ROUND(SUM(P6:S6)-U6,2) -> 0
B8: Total Cash Collected | C8: =SUM(C5:C6) -> 289764.6 | D8: =SUM(D5:D6) -> 393187.6 | E8: =SUM(E5:E6) -> 589877.6 | F8: =SUM(F5:F6) -> 584457.6 | G8: =SUM(G5:G6) -> 420207.6 | H8: =SUM(H5:H6) -> 420207.6 | I8: =SUM(I5:I6) -> 550207.6 | J8: =SUM(J5:J6) -> 535500 | ... N8: =SUM(N5:N6) -> 680000 | P8: =SUM(P5:P6) -> 1272829.8 | Q8: =SUM(Q5:Q6) -> 1424872.8 | R8: =SUM(R5:R6) -> 1516707.6 | S8: =SUM(S5:S6) -> 1897000 | U8: =SUM(U5:U6) -> 6111410.2 | W8: =ROUND(SUM(P8:S8)-U8,2) -> 0
B10: Delivery | C10: =+'2026 Detail'!C17+'2026 Detail'!C18 -> 184080 | D10: =C10 -> 184080 | E10: =+'2026 Detail'!E17+'2026 Detail'!E18 -> 187171.8 | F10: =+'2026 Detail'!F17+'2026 Detail'!F18 -> 181171.8 | G10: =+'2026 Detail'!G17+'2026 Detail'!G18 -> 181171.8 | H10: =+'2026 Detail'!H17+'2026 Detail'!H18 -> 181171.8 | I10: =+'2026 Detail'!I17+'2026 Detail'!I18 -> 174671.8 | J10: =+'2026 Detail'!J17+'2026 Detail'!J18 -> 174671.8 | K10: =+'2026 Detail'!K17+'2026 Detail'!K18 -> 174671.8 | L10: =+'2026 Detail'!L17+'2026 Detail'!L18 -> 170171.8 | ... N10: =+'2026 Detail'!N17+'2026 Detail'!N18 -> 170171.8 | P10: =SUM(C10:E10) -> 555331.8 | Q10: =SUM(F10:H10) -> 543515.4 | R10: =SUM(I10:K10) -> 524015.4 | S10: =SUM(L10:N10) -> 510515.4 | U10: =SUM(C10:N10) -> 2133378 | W10: =ROUND(SUM(P10:S10)-U10,2) -> 0
B11: GTM | C11: =+'2026 Detail'!C19+'2026 Detail'!C20 -> 40630 | D11: =C11 -> 40630 | E11: =+'2026 Detail'!E19+'2026 Detail'!E20 -> 41546.5 | F11: =+'2026 Detail'!F19+'2026 Detail'!F20 -> 41546.5 | G11: =+'2026 Detail'!G19+'2026 Detail'!G20 -> 41546.5 | H11: =+'2026 Detail'!H19+'2026 Detail'!H20 -> 41546.5 | I11: =+'2026 Detail'!I19+'2026 Detail'!I20 -> 41546.5 | J11: =+'2026 Detail'!J19+'2026 Detail'!J20 -> 41546.5 | K11: =+'2026 Detail'!K19+'2026 Detail'!K20 -> 41546.5 | L11: =+'2026 Detail'!L19+'2026 Detail'!L20 -> 41546.5 | ... N11: =+'2026 Detail'!N19+'2026 Detail'!N20 -> 41546.5 | P11: =SUM(C11:E11) -> 122806.5 | Q11: =SUM(F11:H11) -> 124639.5 | R11: =SUM(I11:K11) -> 124639.5 | S11: =SUM(L11:N11) -> 124639.5 | U11: =SUM(C11:N11) -> 496725 | W11: =ROUND(SUM(P11:S11)-U11,2) -> 0
B12: Total Spend Classic | C12: =SUM(C10:C11) -> 224710 | D12: =SUM(D10:D11) -> 224710 | E12: =SUM(E10:E11) -> 228718.3 | F12: =SUM(F10:F11) -> 222718.3 | G12: =SUM(G10:G11) -> 222718.3 | H12: =SUM(H10:H11) -> 222718.3 | I12: =SUM(I10:I11) -> 216218.3 | J12: =SUM(J10:J11) -> 216218.3 | ... N12: =SUM(N10:N11) -> 211718.3 | P12: =SUM(P10:P11) -> 678138.3 | Q12: =SUM(Q10:Q11) -> 668154.9 | R12: =SUM(R10:R11) -> 648654.9 | S12: =SUM(S10:S11) -> 635154.9 | U12: =SUM(U10:U11) -> 2630103 | W12: =ROUND(SUM(P12:S12)-U12,2) -> 0
B14: Delivery | C14: =+'2026 Detail'!C23+'2026 Detail'!C24 -> 10600 | D14: =+'2026 Detail'!D23+'2026 Detail'!D24 -> 10600 | E14: =+'2026 Detail'!E23+'2026 Detail'!E24 -> 10600 | F14: =+'2026 Detail'!F23+'2026 Detail'!F24 -> 10600 | G14: =+'2026 Detail'!G23+'2026 Detail'!G24 -> 10600 | H14: =+'2026 Detail'!H23+'2026 Detail'!H24 -> 10600 | I14: =+'2026 Detail'!I23+'2026 Detail'!I24 -> 10600 | J14: =+'2026 Detail'!J23+'2026 Detail'!J24 -> 10600 | ... N14: =+'2026 Detail'!N23+'2026 Detail'!N24 -> 10600 | P14: =SUM(C14:E14) -> 31800 | Q14: =SUM(F14:H14) -> 31800 | R14: =SUM(I14:K14) -> 31800 | S14: =SUM(L14:N14) -> 31800 | U14: =SUM(C14:N14) -> 127200 | W14: =ROUND(SUM(P14:S14)-U14,2) -> 0
B15: GTM | C15: =+'2026 Detail'!C25+'2026 Detail'!C26 -> 47260 | D15: =+'2026 Detail'!D25+'2026 Detail'!D26 -> 47260 | E15: =+'2026 Detail'!E25+'2026 Detail'!E26 -> 47734 | F15: =+'2026 Detail'!F25+'2026 Detail'!F26 -> 34734 | G15: =+'2026 Detail'!G25+'2026 Detail'!G26 -> 34734 | H15: =+'2026 Detail'!H25+'2026 Detail'!H26 -> 34734 | I15: =+'2026 Detail'!I25+'2026 Detail'!I26 -> 34734 | J15: =+'2026 Detail'!J25+'2026 Detail'!J26 -> 34734 | ... N15: =+'2026 Detail'!N25+'2026 Detail'!N26 -> 34734 | P15: =SUM(C15:E15) -> 142254 | Q15: =SUM(F15:H15) -> 104202 | R15: =SUM(I15:K15) -> 104202 | S15: =SUM(L15:N15) -> 104202 | U15: =SUM(C15:N15) -> 454860 | W15: =ROUND(SUM(P15:S15)-U15,2) -> 0
B16: R&D | C16: =+'2026 Detail'!C27+'2026 Detail'!C28 -> 74520 | D16: =C16 -> 74520 | E16: =+'2026 Detail'!E27+'2026 Detail'!E28 -> 75498 | F16: =+'2026 Detail'!F27+'2026 Detail'!F28 -> 75498 | G16: =+'2026 Detail'!G27+'2026 Detail'!G28 -> 75498 | H16: =+'2026 Detail'!H27+'2026 Detail'!H28 -> 75498 | I16: =+'2026 Detail'!I27+'2026 Detail'!I28 -> 75498 | J16: =+'2026 Detail'!J27+'2026 Detail'!J28 -> 75498 | K16: =+'2026 Detail'!K27+'2026 Detail'!K28 -> 75498 | L16: =+'2026 Detail'!L27+'2026 Detail'!L28 -> 75498 | ... N16: =+'2026 Detail'!N27+'2026 Detail'!N28 -> 75498 | P16: =SUM(C16:E16) -> 224538 | Q16: =SUM(F16:H16) -> 226494 | R16: =SUM(I16:K16) -> 226494 | S16: =SUM(L16:N16) -> 226494 | U16: =SUM(C16:N16) -> 904020 | W16: =ROUND(SUM(P16:S16)-U16,2) -> 0
B17: Total Spend AppIQ | C17: =SUM(C14:C16) -> 132380 | D17: =SUM(D14:D16) -> 132380 | E17: =SUM(E14:E16) -> 133832 | F17: =SUM(F14:F16) -> 120832 | G17: =SUM(G14:G16) -> 120832 | H17: =SUM(H14:H16) -> 120832 | I17: =SUM(I14:I16) -> 120832 | J17: =SUM(J14:J16) -> 120832 | ... N17: =SUM(N14:N16) -> 120832 | P17: =SUM(P14:P16) -> 398592 | Q17: =SUM(Q14:Q16) -> 362496 | R17: =SUM(R14:R16) -> 362496 | S17: =SUM(S14:S16) -> 362496 | U17: =SUM(U14:U16) -> 1486080 | W17: =ROUND(SUM(P17:S17)-U17,2) -> 0
B19: Back Office | C19: =+'2026 Detail'!C33 -> 67260 | D19: =C19 -> 67260 | E19: =+'2026 Detail'!E33 -> 67260 | F19: =+'2026 Detail'!F33 -> 65760 | G19: =+'2026 Detail'!G33 -> 65760 | H19: =+'2026 Detail'!H33 -> 65760 | I19: =+'2026 Detail'!I33 -> 65260 | J19: =+'2026 Detail'!J33 -> 65260 | K19: =+'2026 Detail'!K33 -> 65260 | L19: =+'2026 Detail'!L33 -> 65260 | ... N19: =+'2026 Detail'!N33 -> 65260 | P19: =SUM(C19:E19) -> 201780 | Q19: =SUM(F19:H19) -> 197280 | R19: =SUM(I19:K19) -> 195780 | S19: =SUM(L19:N19) -> 195780 | U19: =SUM(C19:N19) -> 790620 | W19: =ROUND(SUM(P19:S19)-U19,2) -> 0
B20: Total Spend Back Office | C20: =SUM(C19:C19) -> 67260 | D20: =C20 -> 67260 | E20: =SUM(E19:E19) -> 67260 | F20: =SUM(F19:F19) -> 65760 | G20: =SUM(G19:G19) -> 65760 | H20: =SUM(H19:H19) -> 65760 | I20: =SUM(I19:I19) -> 65260 | J20: =SUM(J19:J19) -> 65260 | K20: =SUM(K19:K19) -> 65260 | L20: =SUM(L19:L19) -> 65260 | ... N20: =SUM(N19:N19) -> 65260 | P20: =SUM(P19:P19) -> 201780 | Q20: =SUM(Q19:Q19) -> 197280 | R20: =SUM(R19:R19) -> 195780 | S20: =SUM(S19:S19) -> 195780 | U20: =SUM(U19:U19) -> 790620 | W20: =ROUND(SUM(P20:S20)-U20,2) -> 0
B22: Rent | C22: =+'2026 Detail'!C35 -> 3550 | D22: =+'2026 Detail'!D35 -> 3550 | E22: =+'2026 Detail'!E35 -> 3550 | F22: =+'2026 Detail'!F35 -> 3550 | G22: =+'2026 Detail'!G35 -> 3550 | H22: =+'2026 Detail'!H35 -> 3550 | I22: =+'2026 Detail'!I35 -> 3550 | J22: =+'2026 Detail'!J35 -> 3550 | ... N22: =+'2026 Detail'!N35 -> 3550 | P22: =SUM(C22:E22) -> 10650 | Q22: =SUM(F22:H22) -> 10650 | R22: =SUM(I22:K22) -> 10650 | S22: =SUM(L22:N22) -> 10650 | U22: =SUM(C22:N22) -> 42600 | W22: =ROUND(SUM(P22:S22)-U22,2) -> 0
B23: Hardware & Software | C23: =+'2026 Detail'!C36 -> 4060.245 | D23: =+'2026 Detail'!D36 -> 4804.695 | E23: =+'2026 Detail'!E36 -> 13162.958 | F23: =+'2026 Detail'!F36 -> 11670.068 | G23: =+'2026 Detail'!G36 -> 26012.721 | H23: =+'2026 Detail'!H36 -> 24274.236 | I23: =+'2026 Detail'!I36 -> 23138.231 | J23: =+'2026 Detail'!J36 -> 96432.766 | ... N23: =+'2026 Detail'!N36 -> 12600 | P23: =SUM(C23:E23) -> 22027.897 | Q23: =SUM(F23:H23) -> 61957.025 | R23: =SUM(I23:K23) -> 130374.94 | S23: =SUM(L23:N23) -> 50723.253 | U23: =SUM(C23:N23) -> 265083.12 | W23: =ROUND(SUM(P23:S23)-U23,2) -> 0
B24: Office & Supplies | C24: =+'2026 Detail'!C37 -> 750 | D24: =+'2026 Detail'!D37 -> 750 | E24: =+'2026 Detail'!E37 -> 750 | F24: =+'2026 Detail'!F37 -> 750 | G24: =+'2026 Detail'!G37 -> 750 | H24: =+'2026 Detail'!H37 -> 750 | I24: =+'2026 Detail'!I37 -> 750 | J24: =+'2026 Detail'!J37 -> 750 | ... N24: =+'2026 Detail'!N37 -> 750 | P24: =SUM(C24:E24) -> 2250 | Q24: =SUM(F24:H24) -> 2250 | R24: =SUM(I24:K24) -> 2250 | S24: =SUM(L24:N24) -> 2250 | U24: =SUM(C24:N24) -> 9000 | W24: =ROUND(SUM(P24:S24)-U24,2) -> 0
B25: Insurance | C25: =+'2026 Detail'!C38 -> 511.8791 | D25: =+'2026 Detail'!D38 -> 8528.5854 | E25: =+'2026 Detail'!E38 -> 3182.5867 | F25: =+'2026 Detail'!F38 -> 9254.4367 | G25: =+'2026 Detail'!G38 -> 1593.9765 | H25: =+'2026 Detail'!H38 -> 3130.6747 | I25: =+'2026 Detail'!I38 -> 5747.6472 | J25: =+'2026 Detail'!J38 -> 1836.7372 | ... N25: =+'2026 Detail'!N38 -> 2575 | P25: =SUM(C25:E25) -> 12223.051 | Q25: =SUM(F25:H25) -> 13979.088 | R25: =SUM(I25:K25) -> 10715.059 | S25: =SUM(L25:N25) -> 10404.071 | U25: =SUM(C25:N25) -> 47321.269 | W25: =ROUND(SUM(P25:S25)-U25,2) -> 0
B26: Legal Fees | C26: =+'2026 Detail'!C39 -> 12500 | D26: =+'2026 Detail'!D39 -> 12500 | E26: =+'2026 Detail'!E39 -> 12500 | F26: =+'2026 Detail'!F39 -> 10000 | G26: =+'2026 Detail'!G39 -> 10000 | H26: =+'2026 Detail'!H39 -> 10000 | I26: =+'2026 Detail'!I39 -> 8000 | J26: =+'2026 Detail'!J39 -> 8000 | ... N26: =+'2026 Detail'!N39 -> 8000 | P26: =SUM(C26:E26) -> 37500 | Q26: =SUM(F26:H26) -> 30000 | R26: =SUM(I26:K26) -> 24000 | S26: =SUM(L26:N26) -> 24000 | U26: =SUM(C26:N26) -> 115500 | W26: =ROUND(SUM(P26:S26)-U26,2) -> 0
B27: Accounting & Tax Fees | C27: =+'2026 Detail'!C40 -> 2500 | D27: =+'2026 Detail'!D40 -> 1500 | E27: =+'2026 Detail'!E40 -> 2000 | F27: =+'2026 Detail'!F40 -> 1500 | G27: =+'2026 Detail'!G40 -> 1500 | H27: =+'2026 Detail'!H40 -> 2000 | I27: =+'2026 Detail'!I40 -> 1500 | J27: =+'2026 Detail'!J40 -> 1500 | ... N27: =+'2026 Detail'!N40 -> 2000 | P27: =SUM(C27:E27) -> 6000 | Q27: =SUM(F27:H27) -> 5000 | R27: =SUM(I27:K27) -> 5000 | S27: =SUM(L27:N27) -> 5000 | U27: =SUM(C27:N27) -> 21000 | W27: =ROUND(SUM(P27:S27)-U27,2) -> 0
B28: Professional Fees | C28: =+'2026 Detail'!C41 -> 5000 | D28: =+'2026 Detail'!D41 -> 5000 | E28: =+'2026 Detail'!E41 -> 5000 | F28: =+'2026 Detail'!F41 -> 5000 | G28: =+'2026 Detail'!G41 -> 5000 | H28: =+'2026 Detail'!H41 -> 5000 | I28: =+'2026 Detail'!I41 -> 5000 | J28: =+'2026 Detail'!J41 -> 5000 | ... N28: =+'2026 Detail'!N41 -> 5000 | P28: =SUM(C28:E28) -> 15000 | Q28: =SUM(F28:H28) -> 15000 | R28: =SUM(I28:K28) -> 15000 | S28: =SUM(L28:N28) -> 15000 | U28: =SUM(C28:N28) -> 60000 | W28: =ROUND(SUM(P28:S28)-U28,2) -> 0
B29: Taxes, Licenses & Permits | C29: =+'2026 Detail'!C42 -> 250 | D29: =+'2026 Detail'!D42 -> 250 | E29: =+'2026 Detail'!E42 -> 250 | F29: =+'2026 Detail'!F42 -> 250 | G29: =+'2026 Detail'!G42 -> 250 | H29: =+'2026 Detail'!H42 -> 250 | I29: =+'2026 Detail'!I42 -> 250 | J29: =+'2026 Detail'!J42 -> 250 | ... N29: =+'2026 Detail'!N42 -> 250 | P29: =SUM(C29:E29) -> 750 | Q29: =SUM(F29:H29) -> 750 | R29: =SUM(I29:K29) -> 750 | S29: =SUM(L29:N29) -> 750 | U29: =SUM(C29:N29) -> 3000 | W29: =ROUND(SUM(P29:S29)-U29,2) -> 0
B30: Travel & Meals | C30: =+'2026 Detail'!C43 -> 15000 | D30: =+'2026 Detail'!D43 -> 15000 | E30: =+'2026 Detail'!E43 -> 15000 | F30: =+'2026 Detail'!F43 -> 15000 | G30: =+'2026 Detail'!G43 -> 15000 | H30: =+'2026 Detail'!H43 -> 15000 | I30: =+'2026 Detail'!I43 -> 15000 | J30: =+'2026 Detail'!J43 -> 15000 | ... N30: =+'2026 Detail'!N43 -> 15000 | P30: =SUM(C30:E30) -> 45000 | Q30: =SUM(F30:H30) -> 45000 | R30: =SUM(I30:K30) -> 45000 | S30: =SUM(L30:N30) -> 45000 | U30: =SUM(C30:N30) -> 180000 | W30: =ROUND(SUM(P30:S30)-U30,2) -> 0
B31: Total Other Spend | C31: =SUM(C22:C30) -> 44122.124 | D31: =SUM(D22:D30) -> 51883.28 | E31: =SUM(E22:E30) -> 55395.544 | F31: =SUM(F22:F30) -> 56974.504 | G31: =SUM(G22:G30) -> 63656.698 | H31: =SUM(H22:H30) -> 63954.911 | I31: =SUM(I22:I30) -> 62935.878 | J31: =SUM(J22:J30) -> 132319.5 | ... N31: =SUM(N22:N30) -> 49725 | P31: =SUM(P22:P30) -> 151400.95 | Q31: =SUM(Q22:Q30) -> 184586.11 | R31: =SUM(R22:R30) -> 243740 | S31: =SUM(S22:S30) -> 163777.32 | U31: =SUM(U22:U30) -> 743504.38 | W31: =ROUND(SUM(P31:S31)-U31,2) -> 0
B33: Total Cash Disbursements | C33: =+C12+C17+C20+C31 -> 468472.12 | D33: =+D12+D17+D20+D31 -> 476233.28 | E33: =+E12+E17+E20+E31 -> 485205.84 | F33: =+F12+F17+F20+F31 -> 466284.8 | G33: =+G12+G17+G20+G31 -> 472967 | H33: =+H12+H17+H20+H31 -> 473265.21 | I33: =+I12+I17+I20+I31 -> 465246.18 | J33: =+J12+J17+J20+J31 -> 534629.8 | ... N33: =+N12+N17+N20+N31 -> 447535.3 | P33: =+P12+P17+P20+P31 -> 1429911.2 | Q33: =+Q12+Q17+Q20+Q31 -> 1412517 | R33: =+R12+R17+R20+R31 -> 1450670.9 | S33: =+S12+S17+S20+S31 -> 1357208.2 | U33: =+U12+U17+U20+U31 -> 5650307.4 | W33: =ROUND(SUM(P33:S33)-U33,2) -> 0
B35: Guarenteed Payments | C35: =+'2026 Detail'!C48 -> 0 | D35: =+'2026 Detail'!D48 -> 0 | E35: =+'2026 Detail'!E48 -> 0 | F35: =+'2026 Detail'!F48 -> 0 | G35: =+'2026 Detail'!G48 -> 0 | H35: =+'2026 Detail'!H48 -> 0 | I35: =+'2026 Detail'!I48 -> 0 | J35: =+'2026 Detail'!J48 -> 0 | ... N35: =+'2026 Detail'!N48 -> 0 | P35: =SUM(C35:E35) -> 0 | Q35: =SUM(F35:H35) -> 0 | R35: =SUM(I35:K35) -> 0 | S35: =SUM(L35:N35) -> 0 | U35: =SUM(C35:N35) -> 0 | W35: =ROUND(SUM(P35:S35)-U35,2) -> 0
B36: Youreka Labs Inc | C36: =+'2026 Detail'!C49 -> 0 | D36: =+'2026 Detail'!D49 -> 0 | E36: =+'2026 Detail'!E49 -> 0 | F36: =+'2026 Detail'!F49 -> 0 | G36: =+'2026 Detail'!G49 -> 0 | H36: =+'2026 Detail'!H49 -> 0 | I36: =+'2026 Detail'!I49 -> 0 | J36: =+'2026 Detail'!J49 -> 0 | ... N36: =+'2026 Detail'!N49 -> 0 | P36: =SUM(C36:E36) -> 0 | Q36: =SUM(F36:H36) -> 0 | R36: =SUM(I36:K36) -> 0 | S36: =SUM(L36:N36) -> 0 | U36: =SUM(C36:N36) -> 0 | W36: =ROUND(SUM(P36:S36)-U36,2) -> 0
B37: Brex | C37: =+'2026 Detail'!C50 -> 0 | D37: =+'2026 Detail'!D50 -> 0 | E37: =+'2026 Detail'!E50 -> 0 | F37: =+'2026 Detail'!F50 -> 0 | G37: =+'2026 Detail'!G50 -> 0 | H37: =+'2026 Detail'!H50 -> 0 | I37: =+'2026 Detail'!I50 -> 0 | J37: =+'2026 Detail'!J50 -> 0 | ... N37: =+'2026 Detail'!N50 -> 0 | P37: =SUM(C37:E37) -> 0 | Q37: =SUM(F37:H37) -> 0 | R37: =SUM(I37:K37) -> 0 | S37: =SUM(L37:N37) -> 0 | U37: =SUM(C37:N37) -> 0 | W37: =ROUND(SUM(P37:S37)-U37,2) -> 0
B38: Chase Visa | C38: =+'2026 Detail'!C51 -> 0 | D38: =+'2026 Detail'!D51 -> 0 | E38: =+'2026 Detail'!E51 -> 0 | F38: =+'2026 Detail'!F51 -> 0 | G38: =+'2026 Detail'!G51 -> 0 | H38: =+'2026 Detail'!H51 -> 0 | I38: =+'2026 Detail'!I51 -> 0 | J38: =+'2026 Detail'!J51 -> 0 | ... N38: =+'2026 Detail'!N51 -> 0 | P38: =SUM(C38:E38) -> 0 | Q38: =SUM(F38:H38) -> 0 | R38: =SUM(I38:K38) -> 0 | S38: =SUM(L38:N38) -> 0 | U38: =SUM(C38:N38) -> 0 | W38: =ROUND(SUM(P38:S38)-U38,2) -> 0
B39: Ramp | C39: =+'2026 Detail'!C52 -> 0 | D39: =+'2026 Detail'!D52 -> 0 | E39: =+'2026 Detail'!E52 -> 0 | F39: =+'2026 Detail'!F52 -> 0 | G39: =+'2026 Detail'!G52 -> 0 | H39: =+'2026 Detail'!H52 -> 0 | I39: =+'2026 Detail'!I52 -> 0 | J39: =+'2026 Detail'!J52 -> 0 | ... N39: =+'2026 Detail'!N52 -> 0 | P39: =SUM(C39:E39) -> 0 | Q39: =SUM(F39:H39) -> 0 | R39: =SUM(I39:K39) -> 0 | S39: =SUM(L39:N39) -> 0 | U39: =SUM(C39:N39) -> 0 | W39: =ROUND(SUM(P39:S39)-U39,2) -> 0
B40: Bank Fees | C40: =+'2026 Detail'!C53 -> -400 | D40: =+'2026 Detail'!D53 -> -400 | E40: =+'2026 Detail'!E53 -> -400 | F40: =+'2026 Detail'!F53 -> -400 | G40: =+'2026 Detail'!G53 -> -400 | H40: =+'2026 Detail'!H53 -> -400 | I40: =+'2026 Detail'!I53 -> -400 | J40: =+'2026 Detail'!J53 -> -400 | ... N40: =+'2026 Detail'!N53 -> -400 | P40: =SUM(C40:E40) -> -1200 | Q40: =SUM(F40:H40) -> -1200 | R40: =SUM(I40:K40) -> -1200 | S40: =SUM(L40:N40) -> -1200 | U40: =SUM(C40:N40) -> -4800 | W40: =ROUND(SUM(P40:S40)-U40,2) -> 0
B41: Interest | C41: =+'2026 Detail'!C54 -> 500 | D41: =+'2026 Detail'!D54 -> 400 | E41: =+'2026 Detail'!E54 -> 100 | F41: =+'2026 Detail'!F54 -> 200 | G41: =+'2026 Detail'!G54 -> 300 | H41: =+'2026 Detail'!H54 -> 200 | I41: =+'2026 Detail'!I54 -> 200 | J41: =+'2026 Detail'!J54 -> 200 | ... N41: =+'2026 Detail'!N54 -> 400 | P41: =SUM(C41:E41) -> 1000 | Q41: =SUM(F41:H41) -> 700 | R41: =SUM(I41:K41) -> 600 | S41: =SUM(L41:N41) -> 900 | U41: =SUM(C41:N41) -> 3200 | W41: =ROUND(SUM(P41:S41)-U41,2) -> 0
B43: Opening Cash Balance | C43: =+'2026 Detail'!C56 -> 964110.73 | D43: =+C48 -> 785503.21 | E43: =+D48 -> 702457.53 | F43: =+E48 -> 806829.29 | G43: =+F48 -> 924802.09 | H43: =+G48 -> 871942.69 | I43: =+H48 -> 818685.08 | J43: =+I48 -> 903446.5 | K43: =+J48 -> 904116.7 | ... N43: =+M48 -> 1191148.9 | P43: =+C43 -> 964110.73 | Q43: =+P48 -> 806829 | R43: =+Q48 -> 818685 | S43: =+R48 -> 884122 | U43: =+P43 -> 964110.73
B45: Net Change | C45: =C8-C33+SUM(C35:C41) -> -178607.52 | D45: =D8-D33+SUM(D35:D41) -> -83045.68 | E45: =E8-E33+SUM(E35:E41) -> 104371.76 | F45: =F8-F33+SUM(F35:F41) -> 117972.8 | G45: =G8-G33+SUM(G35:G41) -> -52859.398 | H45: =H8-H33+SUM(H35:H41) -> -53257.611 | I45: =I8-I33+SUM(I35:I41) -> 84761.422 | J45: =J8-J33+SUM(J35:J41) -> 670.1963 | ... N45: =N8-N33+SUM(N35:N41) -> 232464.7 | P45: =SUM(C45:E45) -> -157281.45 | Q45: =SUM(F45:H45) -> 11855.788 | R45: =SUM(I45:K45) -> 65436.7 | S45: =SUM(L45:N45) -> 539491.78 | U45: =SUM(C45:N45) -> 459502.82 | W45: =ROUND(SUM(P45:S45)-U45,2) -> 0
B46: Investment | C46: =+'2026 Detail'!C59 -> 0 | D46: =+'2026 Detail'!D59 -> 0 | E46: =+'2026 Detail'!E59 -> 0 | F46: =+'2026 Detail'!F59 -> 0 | G46: =+'2026 Detail'!G59 -> 0 | H46: =+'2026 Detail'!H59 -> 0 | I46: =+'2026 Detail'!I59 -> 0 | J46: =+'2026 Detail'!J59 -> 0 | ... N46: =+'2026 Detail'!N59 -> 0 | P46: =SUM(C46:E46) -> 0 | Q46: =SUM(F46:H46) -> 0 | R46: =SUM(I46:K46) -> 0 | S46: =SUM(L46:N46) -> 0 | U46: =SUM(C46:N46) -> 0 | W46: =ROUND(SUM(P46:S46)-U46,2) -> 0
B48: Ending Cash Balance | C48: =ROUND(+C43+C45+C46,2) -> 785503.21 | D48: =ROUND(+D43+D45+D46,2) -> 702457.53 | E48: =ROUND(+E43+E45+E46,2) -> 806829.29 | F48: =ROUND(+F43+F45+F46,2) -> 924802.09 | G48: =ROUND(+G43+G45+G46,2) -> 871942.69 | H48: =ROUND(+H43+H45+H46,2) -> 818685.08 | I48: =ROUND(+I43+I45+I46,2) -> 903446.5 | J48: =ROUND(+J43+J45+J46,2) -> 904116.7 | ... N48: =ROUND(+N43+N45+N46,2) -> 1423613.6 | P48: =ROUND(+P43+P45+P46,0) -> 806829 | Q48: =ROUND(+Q43+Q45+Q46,0) -> 818685 | R48: =ROUND(+R43+R45+R46,0) -> 884122 | S48: =ROUND(+S43+S45+S46,0) -> 1423614 | U48: =ROUND(+U43+U45+U46,0) -> 1423614
B50: Cash In | C50: =+C8 -> 289764.6 | D50: =+D8 -> 393187.6 | E50: =+E8 -> 589877.6 | F50: =+F8 -> 584457.6 | G50: =+G8 -> 420207.6 | H50: =+H8 -> 420207.6 | I50: =+I8 -> 550207.6 | J50: =+J8 -> 535500 | ... N50: =+N8 -> 680000 | P50: =+P8 -> 1272829.8 | Q50: =+Q8 -> 1424872.8 | R50: =+R8 -> 1516707.6 | S50: =+S8 -> 1897000 | U50: =+U8 -> 6111410.2
B51: Calculated COGS | C51: =+C10+C14 -> 194680 | D51: =+D10+D14 -> 194680 | E51: =+E10+E14 -> 197771.8 | F51: =+F10+F14 -> 191771.8 | G51: =+G10+G14 -> 191771.8 | H51: =+H10+H14 -> 191771.8 | I51: =+I10+I14 -> 185271.8 | J51: =+J10+J14 -> 185271.8 | ... N51: =+N10+N14 -> 180771.8 | P51: =+P10+P14 -> 587131.8 | Q51: =+Q10+Q14 -> 575315.4 | R51: =+R10+R14 -> 555815.4 | S51: =+S10+S14 -> 542315.4 | U51: =+U10+U14 -> 2260578
B52: Gross Margin | C52: =+C50-C51 -> 95084.6 | D52: =+D50-D51 -> 198507.6 | E52: =+E50-E51 -> 392105.8 | F52: =+F50-F51 -> 392685.8 | G52: =+G50-G51 -> 228435.8 | H52: =+H50-H51 -> 228435.8 | I52: =+I50-I51 -> 364935.8 | J52: =+J50-J51 -> 350228.2 | ... N52: =+N50-N51 -> 499228.2 | P52: =+P50-P51 -> 685698 | Q52: =+Q50-Q51 -> 849557.4 | R52: =+R50-R51 -> 960892.2 | S52: =+S50-S51 -> 1354684.6 | U52: =+U50-U51 -> 3850832.2
B53: GM % | C53: =+C52/C50 -> 0.32814429 | D53: =+D52/D50 -> 0.5048674 | E53: =+E52/E50 -> 0.664724 | F53: =+F52/F50 -> 0.67188073 | G53: =+G52/G50 -> 0.54362606 | H53: =+H52/H50 -> 0.54362606 | I53: =+I52/I50 -> 0.66326928 | J53: =+J52/J50 -> 0.65402092 | ... N53: =+N52/N50 -> 0.73415912 | P53: =+P52/P50 -> 0.53871932 | Q53: =+Q52/Q50 -> 0.59623385 | R53: =+R52/R50 -> 0.6335382 | S53: =+S52/S50 -> 0.71411945 | U53: =+U52/U50 -> 0.63010534
B55: Check | C55: =+C48-'2026 Detail'!C61 -> 0 | D55: =+D48-'2026 Detail'!D61 -> 413820.29 | E55: =+E48-'2026 Detail'!E61 -> 413820.29 | F55: =+F48-'2026 Detail'!F61 -> 413820.29 | G55: =+G48-'2026 Detail'!G61 -> 413820.29 | H55: =+H48-'2026 Detail'!H61 -> 413820.29 | I55: =+I48-'2026 Detail'!I61 -> 413820.29 | J55: =+J48-'2026 Detail'!J61 -> 413820.29 | ... N55: =+N48-'2026 Detail'!N61 -> 413820.29
A58: Mark Model (less bonus)
B59: Cash by Customer | C59: 637897.35 | D59: 204430 | E59: 201394.6 | F59: 289457.6 | G59: 349652.6 | H59: 259207.6 | I59: 207395.85 | J59: 192430 | K59: 102930 | L59: 102930 | M59: 102930 | N59: 96930 | P59: =SUM(C59:E59) -> 1043721.9 | Q59: =SUM(F59:H59) -> 898317.8 | R59: =SUM(I59:K59) -> 502755.85 | S59: =SUM(L59:N59) -> 302790 | U59: =SUM(C59:N59) -> 2747585.6
B60: Collections from Future Sales | C60: =+'1 Collections'!R27 -> 62500 | D60: =+'1 Collections'!S27 -> 62500 | E60: =+'1 Collections'!T27 -> 210000 | F60: =+'1 Collections'!U27 -> 160000 | G60: =+'1 Collections'!V27 -> 260000 | H60: =+'1 Collections'!W27 -> 260000 | I60: =+'1 Collections'!X27 -> 390000 | J60: =+'1 Collections'!Y27 -> 390000 | ... N60: =+'1 Collections'!AC27 -> 645000 | P60: =SUM(C60:E60) -> 335000 | Q60: =SUM(F60:H60) -> 680000 | R60: =SUM(I60:K60) -> 1170000 | S60: =SUM(L60:N60) -> 1780000 | U60: =SUM(C60:N60) -> 3965000
B61: Updated Collections | C61: =SUM(C59:C60) -> 700397.35 | D61: =SUM(D59:D60) -> 266930 | E61: =SUM(E59:E60) -> 411394.6 | F61: =SUM(F59:F60) -> 449457.6 | G61: =SUM(G59:G60) -> 609652.6 | H61: =SUM(H59:H60) -> 519207.6 | I61: =SUM(I59:I60) -> 597395.85 | J61: =SUM(J59:J60) -> 582430 | ... N61: =SUM(N59:N60) -> 741930 | P61: =SUM(C61:E61) -> 1378721.9 | Q61: =SUM(F61:H61) -> 1578317.8 | R61: =SUM(I61:K61) -> 1672755.9 | S61: =SUM(L61:N61) -> 2082790 | U61: =SUM(C61:N61) -> 6712585.6
B63: Opening Cash Balance | C63: 812310.92 | D63: =+C66 -> 1044336.1 | E63: =+D66 -> 835032.87 | F63: =+E66 -> 760921.62 | G63: =+F66 -> 743894.42 | H63: =+G66 -> 880480.02 | I63: =+H66 -> 926222.41 | J63: =+I66 -> 1058172.1 | K63: =+J66 -> 1105772.3 | ... N63: =+M66 -> 1578594.4 | P63: =+C63 -> 812310.92 | Q63: =+P66 -> 760921.62 | R63: =+Q66 -> 926222.41 | S63: =+R66 -> 1147707.4 | U63: =+C63 -> 812310.92
B64: Collections | C64: =+C61 -> 700397.35 | D64: =+D61 -> 266930 | E64: =+E61 -> 411394.6 | F64: =+F61 -> 449457.6 | G64: =+G61 -> 609652.6 | H64: =+H61 -> 519207.6 | I64: =+I61 -> 597395.85 | J64: =+J61 -> 582430 | ... N64: =+N61 -> 741930 | P64: =SUM(C64:E64) -> 1378721.9 | Q64: =SUM(F64:H64) -> 1578317.8 | R64: =SUM(I64:K64) -> 1672755.9 | S64: =SUM(L64:N64) -> 2082790 | U64: =SUM(C64:N64) -> 6712585.6
B65: Disbursements | C65: =-+C33+SUM(C35:C41) -> -468372.12 | D65: =-+D33+SUM(D35:D41) -> -476233.28 | E65: =-+E33+SUM(E35:E41) -> -485505.84 | F65: =-+F33+SUM(F35:F41) -> -466484.8 | G65: =-+G33+SUM(G35:G41) -> -473067 | H65: =-+H33+SUM(H35:H41) -> -473465.21 | I65: =-+I33+SUM(I35:I41) -> -465446.18 | J65: =-+J33+SUM(J35:J41) -> -534829.8 | ... N65: =-+N33+SUM(N35:N41) -> -447535.3 | P65: =SUM(C65:E65) -> -1430111.2 | Q65: =SUM(F65:H65) -> -1413017 | R65: =SUM(I65:K65) -> -1451270.9 | S65: =SUM(L65:N65) -> -1357508.2 | U65: =SUM(C65:N65) -> -5651907.4
B66: Ending Cash Balance | C66: =SUM(C63:C65) -> 1044336.1 | D66: =SUM(D63:D65) -> 835032.87 | E66: =SUM(E63:E65) -> 760921.62 | F66: =SUM(F63:F65) -> 743894.42 | G66: =SUM(G63:G65) -> 880480.02 | H66: =SUM(H63:H65) -> 926222.41 | I66: =SUM(I63:I65) -> 1058172.1 | J66: =SUM(J63:J65) -> 1105772.3 | ... N66: =SUM(N63:N65) -> 1872989.1 | P66: =SUM(P63:P65) -> 760921.62 | Q66: =SUM(Q63:Q65) -> 926222.41 | R66: =SUM(R63:R65) -> 1147707.4 | S66: =SUM(S63:S65) -> 1872989.1 | U66: =SUM(U63:U65) -> 1872989.1
B68: Ending Cash Balance | C68: =+C48 -> 785503.21 | D68: =+D48 -> 702457.53 | E68: =+E48 -> 806829.29 | F68: =+F48 -> 924802.09 | G68: =+G48 -> 871942.69 | H68: =+H48 -> 818685.08 | I68: =+I48 -> 903446.5 | J68: =+J48 -> 904116.7 | ... N68: =+N48 -> 1423613.6 | P68: =+P48 -> 806829 | Q68: =+Q48 -> 818685 | R68: =+R48 -> 884122 | S68: =+S48 -> 1423614 | U68: =+U48 -> 1423614
B69: Change from previous forecast | C69: =+C66-C68 -> 258832.94 | D69: =+D66-D68 -> 132575.34 | E69: =+E66-E68 -> -45907.669 | F69: =+F66-F68 -> -180907.67 | G69: =+G66-G68 -> 8537.3296 | H69: =+H66-H68 -> 107537.33 | I69: =+I66-I68 -> 154725.58 | J69: =+J66-J68 -> 201655.58 | ... N69: =+N66-N68 -> 449375.59 | P69: =+P66-P68 -> -45907.379 | Q69: =+Q66-Q68 -> 107537.41 | R69: =+R66-R68 -> 263585.36 | S69: =+S66-S68 -> 449375.14 | U69: =+U66-U68 -> 449375.14
B71: Cash by Customer - Updated | C71: =+C59 -> 637897.35 | D71: =+D59 -> 204430 | E71: =+E59 -> 201394.6 | F71: =+F59 -> 289457.6 | G71: =+G59 -> 349652.6 | H71: =+H59 -> 259207.6 | I71: =+I59 -> 207395.85 | J71: =+J59 -> 192430 | ... N71: =+N59 -> 96930 | P71: =SUM(C71:E71) -> 1043721.9 | Q71: =SUM(F71:H71) -> 898317.8 | R71: =SUM(I71:K71) -> 502755.85 | S71: =SUM(L71:N71) -> 302790 | U71: =SUM(C71:N71) -> 2747585.6
B72: Cash by Customer - Previous | C72: =+'1 Collections'!R15 -> 227264.6 | D72: =+'1 Collections'!S15 -> 330687.6 | E72: =+'1 Collections'!T15 -> 379877.6 | F72: =+'1 Collections'!U15 -> 424457.6 | G72: =+'1 Collections'!V15 -> 160207.6 | H72: =+'1 Collections'!W15 -> 160207.6 | I72: =+'1 Collections'!X15 -> 160207.6 | J72: =+'1 Collections'!Y15 -> 145500 | ... N72: =+'1 Collections'!AC15 -> 35000 | P72: =SUM(C72:E72) -> 937829.8 | Q72: =SUM(F72:H72) -> 744872.8 | R72: =SUM(I72:K72) -> 346707.6 | S72: =SUM(L72:N72) -> 117000 | U72: =SUM(C72:N72) -> 2146410.2
B73: Cash by Customer - Change | C73: =+C71-C72 -> 410632.75 | D73: =+D71-D72 -> -126257.6 | E73: =+E71-E72 -> -178483 | F73: =+F71-F72 -> -135000 | G73: =+G71-G72 -> 189445 | H73: =+H71-H72 -> 99000 | I73: =+I71-I72 -> 47188.25 | J73: =+J71-J72 -> 46930 | ... N73: =+N71-N72 -> 61930 | P73: =SUM(C73:E73) -> 105892.15 | Q73: =SUM(F73:H73) -> 153445 | R73: =SUM(I73:K73) -> 156048.25 | S73: =SUM(L73:N73) -> 185790 | U73: =SUM(C73:N73) -> 601175.4
A75: Bill Model (Real New Recievables, No Business)
B76: Cash by Customer | C76: =C59 -> 637897.35 | D76: =D59 -> 204430 | E76: =E59 -> 201394.6 | F76: =F59 -> 289457.6 | G76: =G59 -> 349652.6 | H76: =H59 -> 259207.6 | I76: =I59 -> 207395.85 | J76: =J59 -> 192430 | ... N76: =N59 -> 96930 | P76: =P59 -> 1043721.9 | Q76: =Q59 -> 898317.8 | R76: =R59 -> 502755.85 | S76: =S59 -> 302790 | U76: =U59 -> 2747585.6
B77: Collections from Future Sales | C77: 0 | D77: 30000 | E77: 50000 | F77: 50000 | G77: 50000 | H77: 100000 | I77: 200000 | J77: 200000 | K77: 250000 | L77: 250000 | M77: 300000 | N77: 300000 | P77: =SUM(C77:E77) -> 80000 | Q77: =SUM(F77:H77) -> 200000 | R77: =SUM(I77:K77) -> 650000 | S77: =SUM(L77:N77) -> 850000 | U77: =SUM(C77:N77) -> 1780000
B78: Updated Collections | C78: =C76+C77 -> 637897.35 | D78: =D76+D77 -> 234430 | E78: =E76+E77 -> 251394.6 | F78: =F76+F77 -> 339457.6 | G78: =G76+G77 -> 399652.6 | H78: =H76+H77 -> 359207.6 | I78: =I76+I77 -> 407395.85 | J78: =J76+J77 -> 392430 | ... N78: =N76+N77 -> 396930 | P78: =P76+P77 -> 1123721.9 | Q78: =Q76+Q77 -> 1098317.8 | R78: =R76+R77 -> 1152755.9 | S78: =S76+S77 -> 1152790 | U78: =U76+U77 -> 4527585.6
B80: Opening Cash Balance | C80: =C63 -> 812310.92 | D80: =D63 -> 1044336.1 | E80: =E63 -> 835032.87 | F80: =F63 -> 760921.62 | G80: =G63 -> 743894.42 | H80: =H63 -> 880480.02 | I80: =I63 -> 926222.41 | J80: =J63 -> 1058172.1 | ... N80: =N63 -> 1578594.4 | P80: =P63 -> 812310.92 | Q80: =Q63 -> 760921.62 | R80: =R63 -> 926222.41 | S80: =S63 -> 1147707.4 | U80: =U63 -> 812310.92
B81: Collections | C81: =C64 -> 700397.35 | D81: =D64 -> 266930 | E81: =E64 -> 411394.6 | F81: =F64 -> 449457.6 | G81: =G64 -> 609652.6 | H81: =H64 -> 519207.6 | I81: =I64 -> 597395.85 | J81: =J64 -> 582430 | ... N81: =N64 -> 741930 | P81: =P64 -> 1378721.9 | Q81: =Q64 -> 1578317.8 | R81: =R64 -> 1672755.9 | S81: =S64 -> 2082790 | U81: =U64 -> 6712585.6
B82: Disbursements | C82: =C65 -> -468372.12 | D82: =D65 -> -476233.28 | E82: =E65 -> -485505.84 | F82: =F65 -> -466484.8 | G82: =G65 -> -473067 | H82: =H65 -> -473465.21 | I82: =I65 -> -465446.18 | J82: =J65 -> -534829.8 | ... N82: =N65 -> -447535.3 | P82: =P65 -> -1430111.2 | Q82: =Q65 -> -1413017 | R82: =R65 -> -1451270.9 | S82: =S65 -> -1357508.2 | U82: =U65 -> -5651907.4
B83: Net Cash Burned | C83: =C81+C82 -> 232025.23 | D83: =D81+D82 -> -209303.28 | E83: =E81+E82 -> -74111.244 | F83: =F81+F82 -> -17027.204 | G83: =G81+G82 -> 136585.6 | H83: =H81+H82 -> 45742.389 | I83: =I81+I82 -> 131949.67 | J83: =J81+J82 -> 47600.196 | ... N83: =N81+N82 -> 294394.7 | P83: =SUM(C83:E83) -> -51389.299 | Q83: =SUM(F83:H83) -> 165300.79 | R83: =SUM(I83:K83) -> 221484.95 | S83: =SUM(L83:N83) -> 725281.78 | U83: =SUM(C83:N83) -> 1060678.2
B84: Ending Cash Balance | C84: =C66 -> 1044336.1 | D84: =D66 -> 835032.87 | E84: =E66 -> 760921.62 | F84: =F66 -> 743894.42 | G84: =G66 -> 880480.02 | H84: =H66 -> 926222.41 | I84: =I66 -> 1058172.1 | J84: =J66 -> 1105772.3 | ... N84: =N66 -> 1872989.1 | P84: =P66 -> 760921.62 | Q84: =Q66 -> 926222.41 | R84: =R66 -> 1147707.4 | S84: =S66 -> 1872989.1 | U84: =U66 -> 1872989.1
P86: =P82/3 -> -476703.75 | Q86: =Q82/3 -> -471005.67 | R86: =R82/3 -> -483756.97 | S86: =S82/3 -> -452502.74 | U86: =U82/12 -> -470992.28
B89: Ending Cash Balance | C89: =C68 -> 785503.21 | D89: =D68 -> 702457.53 | E89: =E68 -> 806829.29 | F89: =F68 -> 924802.09 | G89: =G68 -> 871942.69 | H89: =H68 -> 818685.08 | I89: =I68 -> 903446.5 | J89: =J68 -> 904116.7 | ... N89: =N68 -> 1423613.6 | P89: =P68 -> 806829 | Q89: =Q68 -> 818685 | R89: =R68 -> 884122 | S89: =S68 -> 1423614 | U89: =U68 -> 1423614
B90: Change from previous forecast | C90: =C69 -> 258832.94 | D90: =D69 -> 132575.34 | E90: =E69 -> -45907.669 | F90: =F69 -> -180907.67 | G90: =G69 -> 8537.3296 | H90: =H69 -> 107537.33 | I90: =I69 -> 154725.58 | J90: =J69 -> 201655.58 | ... N90: =N69 -> 449375.59 | P90: =P69 -> -45907.379 | Q90: =Q69 -> 107537.41 | R90: =R69 -> 263585.36 | S90: =S69 -> 449375.14 | U90: =U69 -> 449375.14
B92: Cash by Customer - Updated | C92: =C71 -> 637897.35 | D92: =D71 -> 204430 | E92: =E71 -> 201394.6 | F92: =F71 -> 289457.6 | G92: =G71 -> 349652.6 | H92: =H71 -> 259207.6 | I92: =I71 -> 207395.85 | J92: =J71 -> 192430 | ... N92: =N71 -> 96930 | P92: =P71 -> 1043721.9 | Q92: =Q71 -> 898317.8 | R92: =R71 -> 502755.85 | S92: =S71 -> 302790 | U92: =U71 -> 2747585.6
B93: Cash by Customer - Previous | C93: =C72 -> 227264.6 | D93: =D72 -> 330687.6 | E93: =E72 -> 379877.6 | F93: =F72 -> 424457.6 | G93: =G72 -> 160207.6 | H93: =H72 -> 160207.6 | I93: =I72 -> 160207.6 | J93: =J72 -> 145500 | ... N93: =N72 -> 35000 | P93: =P72 -> 937829.8 | Q93: =Q72 -> 744872.8 | R93: =R72 -> 346707.6 | S93: =S72 -> 117000 | U93: =U72 -> 2146410.2
B94: Cash by Customer - Change | C94: =C73 -> 410632.75 | D94: =D73 -> -126257.6 | E94: =E73 -> -178483 | F94: =F73 -> -135000 | G94: =G73 -> 189445 | H94: =H73 -> 99000 | I94: =I73 -> 47188.25 | J94: =J73 -> 46930 | ... N94: =N73 -> 61930 | P94: =P73 -> 105892.15 | Q94: =Q73 -> 153445 | R94: =R73 -> 156048.25 | S94: =S73 -> 185790 | U94: =U73 -> 601175.4

Sheet 2026 Summary (2)
B2: SYNAPTIC CASH FLOW FORECAST | C2: 46023 | D2: =EDATE(C2,1) -> 46054 | E2: =EDATE(D2,1) -> 46082 | F2: =EDATE(E2,1) -> 46113 | G2: =EDATE(F2,1) -> 46143 | H2: =EDATE(G2,1) -> 46174 | I2: =EDATE(H2,1) -> 46204 | J2: =EDATE(I2,1) -> 46235 | K2: =EDATE(J2,1) -> 46266 | ... N2: =EDATE(M2,1) -> 46357 | P2: Q1 | Q2: Q2 | R2: Q3 | S2: Q4 | U2: 2026 | W2: Check
B3: =+Version!$C$3 -> Y2025 12 v001
B5: Consulting - Classic | C5: =+'2026 Detail'!C8 -> 126737 | D5: =+'2026 Detail'!D8 -> 270160 | E5: =+'2026 Detail'!E8 -> 223350 | F5: =+'2026 Detail'!F8 -> 197930 | G5: =+'2026 Detail'!G8 -> 151930 | H5: =+'2026 Detail'!H8 -> 151930 | I5: =+'2026 Detail'!I8 -> 146930 | J5: =+'2026 Detail'!J8 -> 145000 | ... N5: =+'2026 Detail'!N8 -> 130000 | P5: =SUM(C5:E5) -> 620247 | Q5: =SUM(F5:H5) -> 501790 | R5: =SUM(I5:K5) -> 436930 | S5: =SUM(L5:N5) -> 410000 | U5: =SUM(C5:N5) -> 1968967 | W5: =ROUND(SUM(P5:S5)-U5,2) -> 0
B6: Consulting - AppIQ | C6: =+'2026 Detail'!C13 -> 163027.6 | D6: =+'2026 Detail'!D13 -> 123027.6 | E6: =+'2026 Detail'!E13 -> 366527.6 | F6: =+'2026 Detail'!F13 -> 386527.6 | G6: =+'2026 Detail'!G13 -> 268277.6 | H6: =+'2026 Detail'!H13 -> 268277.6 | I6: =+'2026 Detail'!I13 -> 403277.6 | J6: =+'2026 Detail'!J13 -> 390500 | ... N6: =+'2026 Detail'!N13 -> 550000 | P6: =SUM(C6:E6) -> 652582.8 | Q6: =SUM(F6:H6) -> 923082.8 | R6: =SUM(I6:K6) -> 1079777.6 | S6: =SUM(L6:N6) -> 1487000 | U6: =SUM(C6:N6) -> 4142443.2 | W6: =ROUND(SUM(P6:S6)-U6,2) -> 0
B8: Total Cash Collected | C8: =SUM(C5:C6) -> 289764.6 | D8: =SUM(D5:D6) -> 393187.6 | E8: =SUM(E5:E6) -> 589877.6 | F8: =SUM(F5:F6) -> 584457.6 | G8: =SUM(G5:G6) -> 420207.6 | H8: =SUM(H5:H6) -> 420207.6 | I8: =SUM(I5:I6) -> 550207.6 | J8: =SUM(J5:J6) -> 535500 | ... N8: =SUM(N5:N6) -> 680000 | P8: =SUM(P5:P6) -> 1272829.8 | Q8: =SUM(Q5:Q6) -> 1424872.8 | R8: =SUM(R5:R6) -> 1516707.6 | S8: =SUM(S5:S6) -> 1897000 | U8: =SUM(U5:U6) -> 6111410.2 | W8: =ROUND(SUM(P8:S8)-U8,2) -> 0
B10: Delivery | C10: =+'2026 Detail'!C17+'2026 Detail'!C18 -> 184080 | D10: =+'2026 Detail'!D17+'2026 Detail'!D18 -> 358933.05 | E10: =+'2026 Detail'!E17+'2026 Detail'!E18 -> 187171.8 | F10: =+'2026 Detail'!F17+'2026 Detail'!F18 -> 181171.8 | G10: =+'2026 Detail'!G17+'2026 Detail'!G18 -> 181171.8 | H10: =+'2026 Detail'!H17+'2026 Detail'!H18 -> 181171.8 | I10: =+'2026 Detail'!I17+'2026 Detail'!I18 -> 174671.8 | J10: =+'2026 Detail'!J17+'2026 Detail'!J18 -> 174671.8 | ... N10: =+'2026 Detail'!N17+'2026 Detail'!N18 -> 170171.8 | P10: =SUM(C10:E10) -> 730184.85 | Q10: =SUM(F10:H10) -> 543515.4 | R10: =SUM(I10:K10) -> 524015.4 | S10: =SUM(L10:N10) -> 510515.4 | U10: =SUM(C10:N10) -> 2308231 | W10: =ROUND(SUM(P10:S10)-U10,2) -> 0
B11: GTM | C11: =+'2026 Detail'!C19+'2026 Detail'!C20 -> 40630 | D11: =+'2026 Detail'!D19+'2026 Detail'!D20 -> 103559.49 | E11: =+'2026 Detail'!E19+'2026 Detail'!E20 -> 41546.5 | F11: =+'2026 Detail'!F19+'2026 Detail'!F20 -> 41546.5 | G11: =+'2026 Detail'!G19+'2026 Detail'!G20 -> 41546.5 | H11: =+'2026 Detail'!H19+'2026 Detail'!H20 -> 41546.5 | I11: =+'2026 Detail'!I19+'2026 Detail'!I20 -> 41546.5 | J11: =+'2026 Detail'!J19+'2026 Detail'!J20 -> 41546.5 | ... N11: =+'2026 Detail'!N19+'2026 Detail'!N20 -> 41546.5 | P11: =SUM(C11:E11) -> 185735.99 | Q11: =SUM(F11:H11) -> 124639.5 | R11: =SUM(I11:K11) -> 124639.5 | S11: =SUM(L11:N11) -> 124639.5 | U11: =SUM(C11:N11) -> 559654.49 | W11: =ROUND(SUM(P11:S11)-U11,2) -> 0
B12: Total Spend Classic | C12: =SUM(C10:C11) -> 224710 | D12: =SUM(D10:D11) -> 462492.54 | E12: =SUM(E10:E11) -> 228718.3 | F12: =SUM(F10:F11) -> 222718.3 | G12: =SUM(G10:G11) -> 222718.3 | H12: =SUM(H10:H11) -> 222718.3 | I12: =SUM(I10:I11) -> 216218.3 | J12: =SUM(J10:J11) -> 216218.3 | ... N12: =SUM(N10:N11) -> 211718.3 | P12: =SUM(P10:P11) -> 915920.84 | Q12: =SUM(Q10:Q11) -> 668154.9 | R12: =SUM(R10:R11) -> 648654.9 | S12: =SUM(S10:S11) -> 635154.9 | U12: =SUM(U10:U11) -> 2867885.5 | W12: =ROUND(SUM(P12:S12)-U12,2) -> 0
B14: Delivery | C14: =+'2026 Detail'!C23+'2026 Detail'!C24 -> 10600 | D14: =+'2026 Detail'!D23+'2026 Detail'!D24 -> 10600 | E14: =+'2026 Detail'!E23+'2026 Detail'!E24 -> 10600 | F14: =+'2026 Detail'!F23+'2026 Detail'!F24 -> 10600 | G14: =+'2026 Detail'!G23+'2026 Detail'!G24 -> 10600 | H14: =+'2026 Detail'!H23+'2026 Detail'!H24 -> 10600 | I14: =+'2026 Detail'!I23+'2026 Detail'!I24 -> 10600 | J14: =+'2026 Detail'!J23+'2026 Detail'!J24 -> 10600 | ... N14: =+'2026 Detail'!N23+'2026 Detail'!N24 -> 10600 | P14: =SUM(C14:E14) -> 31800 | Q14: =SUM(F14:H14) -> 31800 | R14: =SUM(I14:K14) -> 31800 | S14: =SUM(L14:N14) -> 31800 | U14: =SUM(C14:N14) -> 127200 | W14: =ROUND(SUM(P14:S14)-U14,2) -> 0
B15: GTM | C15: =+'2026 Detail'!C25+'2026 Detail'!C26 -> 47260 | D15: =+'2026 Detail'!D25+'2026 Detail'!D26 -> 47260 | E15: =+'2026 Detail'!E25+'2026 Detail'!E26 -> 47734 | F15: =+'2026 Detail'!F25+'2026 Detail'!F26 -> 34734 | G15: =+'2026 Detail'!G25+'2026 Detail'!G26 -> 34734 | H15: =+'2026 Detail'!H25+'2026 Detail'!H26 -> 34734 | I15: =+'2026 Detail'!I25+'2026 Detail'!I26 -> 34734 | J15: =+'2026 Detail'!J25+'2026 Detail'!J26 -> 34734 | ... N15: =+'2026 Detail'!N25+'2026 Detail'!N26 -> 34734 | P15: =SUM(C15:E15) -> 142254 | Q15: =SUM(F15:H15) -> 104202 | R15: =SUM(I15:K15) -> 104202 | S15: =SUM(L15:N15) -> 104202 | U15: =SUM(C15:N15) -> 454860 | W15: =ROUND(SUM(P15:S15)-U15,2) -> 0
B16: R&D | C16: =+'2026 Detail'!C27+'2026 Detail'!C28 -> 74520 | D16: =+'2026 Detail'!D27+'2026 Detail'!D28 -> 99357.75 | E16: =+'2026 Detail'!E27+'2026 Detail'!E28 -> 75498 | F16: =+'2026 Detail'!F27+'2026 Detail'!F28 -> 75498 | G16: =+'2026 Detail'!G27+'2026 Detail'!G28 -> 75498 | H16: =+'2026 Detail'!H27+'2026 Detail'!H28 -> 75498 | I16: =+'2026 Detail'!I27+'2026 Detail'!I28 -> 75498 | J16: =+'2026 Detail'!J27+'2026 Detail'!J28 -> 75498 | ... N16: =+'2026 Detail'!N27+'2026 Detail'!N28 -> 75498 | P16: =SUM(C16:E16) -> 249375.75 | Q16: =SUM(F16:H16) -> 226494 | R16: =SUM(I16:K16) -> 226494 | S16: =SUM(L16:N16) -> 226494 | U16: =SUM(C16:N16) -> 928857.75 | W16: =ROUND(SUM(P16:S16)-U16,2) -> 0
B17: Total Spend AppIQ | C17: =SUM(C14:C16) -> 132380 | D17: =SUM(D14:D16) -> 157217.75 | E17: =SUM(E14:E16) -> 133832 | F17: =SUM(F14:F16) -> 120832 | G17: =SUM(G14:G16) -> 120832 | H17: =SUM(H14:H16) -> 120832 | I17: =SUM(I14:I16) -> 120832 | J17: =SUM(J14:J16) -> 120832 | ... N17: =SUM(N14:N16) -> 120832 | P17: =SUM(P14:P16) -> 423429.75 | Q17: =SUM(Q14:Q16) -> 362496 | R17: =SUM(R14:R16) -> 362496 | S17: =SUM(S14:S16) -> 362496 | U17: =SUM(U14:U16) -> 1510917.8 | W17: =ROUND(SUM(P17:S17)-U17,2) -> 0
B19: Back Office | C19: =+'2026 Detail'!C33 -> 67260 | D19: =+'2026 Detail'!D33 -> 218460 | E19: =+'2026 Detail'!E33 -> 67260 | F19: =+'2026 Detail'!F33 -> 65760 | G19: =+'2026 Detail'!G33 -> 65760 | H19: =+'2026 Detail'!H33 -> 65760 | I19: =+'2026 Detail'!I33 -> 65260 | J19: =+'2026 Detail'!J33 -> 65260 | ... N19: =+'2026 Detail'!N33 -> 65260 | P19: =SUM(C19:E19) -> 352980 | Q19: =SUM(F19:H19) -> 197280 | R19: =SUM(I19:K19) -> 195780 | S19: =SUM(L19:N19) -> 195780 | U19: =SUM(C19:N19) -> 941820 | W19: =ROUND(SUM(P19:S19)-U19,2) -> 0
B20: Total Spend Back Office | C20: =SUM(C19:C19) -> 67260 | D20: =SUM(D19:D19) -> 218460 | E20: =SUM(E19:E19) -> 67260 | F20: =SUM(F19:F19) -> 65760 | G20: =SUM(G19:G19) -> 65760 | H20: =SUM(H19:H19) -> 65760 | I20: =SUM(I19:I19) -> 65260 | J20: =SUM(J19:J19) -> 65260 | ... N20: =SUM(N19:N19) -> 65260 | P20: =SUM(P19:P19) -> 352980 | Q20: =SUM(Q19:Q19) -> 197280 | R20: =SUM(R19:R19) -> 195780 | S20: =SUM(S19:S19) -> 195780 | U20: =SUM(U19:U19) -> 941820 | W20: =ROUND(SUM(P20:S20)-U20,2) -> 0
B22: Rent | C22: =+'2026 Detail'!C35 -> 3550 | D22: =+'2026 Detail'!D35 -> 3550 | E22: =+'2026 Detail'!E35 -> 3550 | F22: =+'2026 Detail'!F35 -> 3550 | G22: =+'2026 Detail'!G35 -> 3550 | H22: =+'2026 Detail'!H35 -> 3550 | I22: =+'2026 Detail'!I35 -> 3550 | J22: =+'2026 Detail'!J35 -> 3550 | ... N22: =+'2026 Detail'!N35 -> 3550 | P22: =SUM(C22:E22) -> 10650 | Q22: =SUM(F22:H22) -> 10650 | R22: =SUM(I22:K22) -> 10650 | S22: =SUM(L22:N22) -> 10650 | U22: =SUM(C22:N22) -> 42600 | W22: =ROUND(SUM(P22:S22)-U22,2) -> 0
B23: Hardware & Software | C23: =+'2026 Detail'!C36 -> 4060.245 | D23: =+'2026 Detail'!D36 -> 4804.695 | E23: =+'2026 Detail'!E36 -> 13162.958 | F23: =+'2026 Detail'!F36 -> 11670.068 | G23: =+'2026 Detail'!G36 -> 26012.721 | H23: =+'2026 Detail'!H36 -> 24274.236 | I23: =+'2026 Detail'!I36 -> 23138.231 | J23: =+'2026 Detail'!J36 -> 96432.766 | ... N23: =+'2026 Detail'!N36 -> 12600 | P23: =SUM(C23:E23) -> 22027.897 | Q23: =SUM(F23:H23) -> 61957.025 | R23: =SUM(I23:K23) -> 130374.94 | S23: =SUM(L23:N23) -> 50723.253 | U23: =SUM(C23:N23) -> 265083.12 | W23: =ROUND(SUM(P23:S23)-U23,2) -> 0
B24: Office & Supplies | C24: =+'2026 Detail'!C37 -> 750 | D24: =+'2026 Detail'!D37 -> 750 | E24: =+'2026 Detail'!E37 -> 750 | F24: =+'2026 Detail'!F37 -> 750 | G24: =+'2026 Detail'!G37 -> 750 | H24: =+'2026 Detail'!H37 -> 750 | I24: =+'2026 Detail'!I37 -> 750 | J24: =+'2026 Detail'!J37 -> 750 | ... N24: =+'2026 Detail'!N37 -> 750 | P24: =SUM(C24:E24) -> 2250 | Q24: =SUM(F24:H24) -> 2250 | R24: =SUM(I24:K24) -> 2250 | S24: =SUM(L24:N24) -> 2250 | U24: =SUM(C24:N24) -> 9000 | W24: =ROUND(SUM(P24:S24)-U24,2) -> 0
B25: Insurance | C25: =+'2026 Detail'!C38 -> 511.8791 | D25: =+'2026 Detail'!D38 -> 8528.5854 | E25: =+'2026 Detail'!E38 -> 3182.5867 | F25: =+'2026 Detail'!F38 -> 9254.4367 | G25: =+'2026 Detail'!G38 -> 1593.9765 | H25: =+'2026 Detail'!H38 -> 3130.6747 | I25: =+'2026 Detail'!I38 -> 5747.6472 | J25: =+'2026 Detail'!J38 -> 1836.7372 | ... N25: =+'2026 Detail'!N38 -> 2575 | P25: =SUM(C25:E25) -> 12223.051 | Q25: =SUM(F25:H25) -> 13979.088 | R25: =SUM(I25:K25) -> 10715.059 | S25: =SUM(L25:N25) -> 10404.071 | U25: =SUM(C25:N25) -> 47321.269 | W25: =ROUND(SUM(P25:S25)-U25,2) -> 0
B26: Legal Fees | C26: =+'2026 Detail'!C39 -> 12500 | D26: =+'2026 Detail'!D39 -> 12500 | E26: =+'2026 Detail'!E39 -> 12500 | F26: =+'2026 Detail'!F39 -> 10000 | G26: =+'2026 Detail'!G39 -> 10000 | H26: =+'2026 Detail'!H39 -> 10000 | I26: =+'2026 Detail'!I39 -> 8000 | J26: =+'2026 Detail'!J39 -> 8000 | ... N26: =+'2026 Detail'!N39 -> 8000 | P26: =SUM(C26:E26) -> 37500 | Q26: =SUM(F26:H26) -> 30000 | R26: =SUM(I26:K26) -> 24000 | S26: =SUM(L26:N26) -> 24000 | U26: =SUM(C26:N26) -> 115500 | W26: =ROUND(SUM(P26:S26)-U26,2) -> 0
B27: Accounting & Tax Fees | C27: =+'2026 Detail'!C40 -> 2500 | D27: =+'2026 Detail'!D40 -> 1500 | E27: =+'2026 Detail'!E40 -> 2000 | F27: =+'2026 Detail'!F40 -> 1500 | G27: =+'2026 Detail'!G40 -> 1500 | H27: =+'2026 Detail'!H40 -> 2000 | I27: =+'2026 Detail'!I40 -> 1500 | J27: =+'2026 Detail'!J40 -> 1500 | ... N27: =+'2026 Detail'!N40 -> 2000 | P27: =SUM(C27:E27) -> 6000 | Q27: =SUM(F27:H27) -> 5000 | R27: =SUM(I27:K27) -> 5000 | S27: =SUM(L27:N27) -> 5000 | U27: =SUM(C27:N27) -> 21000 | W27: =ROUND(SUM(P27:S27)-U27,2) -> 0
B28: Professional Fees | C28: =+'2026 Detail'!C41 -> 5000 | D28: =+'2026 Detail'!D41 -> 5000 | E28: =+'2026 Detail'!E41 -> 5000 | F28: =+'2026 Detail'!F41 -> 5000 | G28: =+'2026 Detail'!G41 -> 5000 | H28: =+'2026 Detail'!H41 -> 5000 | I28: =+'2026 Detail'!I41 -> 5000 | J28: =+'2026 Detail'!J41 -> 5000 | ... N28: =+'2026 Detail'!N41 -> 5000 | P28: =SUM(C28:E28) -> 15000 | Q28: =SUM(F28:H28) -> 15000 | R28: =SUM(I28:K28) -> 15000 | S28: =SUM(L28:N28) -> 15000 | U28: =SUM(C28:N28) -> 60000 | W28: =ROUND(SUM(P28:S28)-U28,2) -> 0
B29: Taxes, Licenses & Permits | C29: =+'2026 Detail'!C42 -> 250 | D29: =+'2026 Detail'!D42 -> 250 | E29: =+'2026 Detail'!E42 -> 250 | F29: =+'2026 Detail'!F42 -> 250 | G29: =+'2026 Detail'!G42 -> 250 | H29: =+'2026 Detail'!H42 -> 250 | I29: =+'2026 Detail'!I42 -> 250 | J29: =+'2026 Detail'!J42 -> 250 | ... N29: =+'2026 Detail'!N42 -> 250 | P29: =SUM(C29:E29) -> 750 | Q29: =SUM(F29:H29) -> 750 | R29: =SUM(I29:K29) -> 750 | S29: =SUM(L29:N29) -> 750 | U29: =SUM(C29:N29) -> 3000 | W29: =ROUND(SUM(P29:S29)-U29,2) -> 0
B30: Travel & Meals | C30: =+'2026 Detail'!C43 -> 15000 | D30: =+'2026 Detail'!D43 -> 15000 | E30: =+'2026 Detail'!E43 -> 15000 | F30: =+'2026 Detail'!F43 -> 15000 | G30: =+'2026 Detail'!G43 -> 15000 | H30: =+'2026 Detail'!H43 -> 15000 | I30: =+'2026 Detail'!I43 -> 15000 | J30: =+'2026 Detail'!J43 -> 15000 | ... N30: =+'2026 Detail'!N43 -> 15000 | P30: =SUM(C30:E30) -> 45000 | Q30: =SUM(F30:H30) -> 45000 | R30: =SUM(I30:K30) -> 45000 | S30: =SUM(L30:N30) -> 45000 | U30: =SUM(C30:N30) -> 180000 | W30: =ROUND(SUM(P30:S30)-U30,2) -> 0
B31: Total Other Spend | C31: =SUM(C22:C30) -> 44122.124 | D31: =SUM(D22:D30) -> 51883.28 | E31: =SUM(E22:E30) -> 55395.544 | F31: =SUM(F22:F30) -> 56974.504 | G31: =SUM(G22:G30) -> 63656.698 | H31: =SUM(H22:H30) -> 63954.911 | I31: =SUM(I22:I30) -> 62935.878 | J31: =SUM(J22:J30) -> 132319.5 | ... N31: =SUM(N22:N30) -> 49725 | P31: =SUM(P22:P30) -> 151400.95 | Q31: =SUM(Q22:Q30) -> 184586.11 | R31: =SUM(R22:R30) -> 243740 | S31: =SUM(S22:S30) -> 163777.32 | U31: =SUM(U22:U30) -> 743504.38 | W31: =ROUND(SUM(P31:S31)-U31,2) -> 0
B33: Total Cash Disbursements | C33: =+C12+C17+C20+C31 -> 468472.12 | D33: =+D12+D17+D20+D31 -> 890053.57 | E33: =+E12+E17+E20+E31 -> 485205.84 | F33: =+F12+F17+F20+F31 -> 466284.8 | G33: =+G12+G17+G20+G31 -> 472967 | H33: =+H12+H17+H20+H31 -> 473265.21 | I33: =+I12+I17+I20+I31 -> 465246.18 | J33: =+J12+J17+J20+J31 -> 534629.8 | ... N33: =+N12+N17+N20+N31 -> 447535.3 | P33: =+P12+P17+P20+P31 -> 1843731.5 | Q33: =+Q12+Q17+Q20+Q31 -> 1412517 | R33: =+R12+R17+R20+R31 -> 1450670.9 | S33: =+S12+S17+S20+S31 -> 1357208.2 | U33: =+U12+U17+U20+U31 -> 6064127.7 | W33: =ROUND(SUM(P33:S33)-U33,2) -> 0
B35: Guarenteed Payments | C35: =+'2026 Detail'!C48 -> 0 | D35: =+'2026 Detail'!D48 -> 0 | E35: =+'2026 Detail'!E48 -> 0 | F35: =+'2026 Detail'!F48 -> 0 | G35: =+'2026 Detail'!G48 -> 0 | H35: =+'2026 Detail'!H48 -> 0 | I35: =+'2026 Detail'!I48 -> 0 | J35: =+'2026 Detail'!J48 -> 0 | ... N35: =+'2026 Detail'!N48 -> 0 | P35: =SUM(C35:E35) -> 0 | Q35: =SUM(F35:H35) -> 0 | R35: =SUM(I35:K35) -> 0 | S35: =SUM(L35:N35) -> 0 | U35: =SUM(C35:N35) -> 0 | W35: =ROUND(SUM(P35:S35)-U35,2) -> 0
B36: Youreka Labs Inc | C36: =+'2026 Detail'!C49 -> 0 | D36: =+'2026 Detail'!D49 -> 0 | E36: =+'2026 Detail'!E49 -> 0 | F36: =+'2026 Detail'!F49 -> 0 | G36: =+'2026 Detail'!G49 -> 0 | H36: =+'2026 Detail'!H49 -> 0 | I36: =+'2026 Detail'!I49 -> 0 | J36: =+'2026 Detail'!J49 -> 0 | ... N36: =+'2026 Detail'!N49 -> 0 | P36: =SUM(C36:E36) -> 0 | Q36: =SUM(F36:H36) -> 0 | R36: =SUM(I36:K36) -> 0 | S36: =SUM(L36:N36) -> 0 | U36: =SUM(C36:N36) -> 0 | W36: =ROUND(SUM(P36:S36)-U36,2) -> 0
B37: Brex | C37: =+'2026 Detail'!C50 -> 0 | D37: =+'2026 Detail'!D50 -> 0 | E37: =+'2026 Detail'!E50 -> 0 | F37: =+'2026 Detail'!F50 -> 0 | G37: =+'2026 Detail'!G50 -> 0 | H37: =+'2026 Detail'!H50 -> 0 | I37: =+'2026 Detail'!I50 -> 0 | J37: =+'2026 Detail'!J50 -> 0 | ... N37: =+'2026 Detail'!N50 -> 0 | P37: =SUM(C37:E37) -> 0 | Q37: =SUM(F37:H37) -> 0 | R37: =SUM(I37:K37) -> 0 | S37: =SUM(L37:N37) -> 0 | U37: =SUM(C37:N37) -> 0 | W37: =ROUND(SUM(P37:S37)-U37,2) -> 0
B38: Chase Visa | C38: =+'2026 Detail'!C51 -> 0 | D38: =+'2026 Detail'!D51 -> 0 | E38: =+'2026 Detail'!E51 -> 0 | F38: =+'2026 Detail'!F51 -> 0 | G38: =+'2026 Detail'!G51 -> 0 | H38: =+'2026 Detail'!H51 -> 0 | I38: =+'2026 Detail'!I51 -> 0 | J38: =+'2026 Detail'!J51 -> 0 | ... N38: =+'2026 Detail'!N51 -> 0 | P38: =SUM(C38:E38) -> 0 | Q38: =SUM(F38:H38) -> 0 | R38: =SUM(I38:K38) -> 0 | S38: =SUM(L38:N38) -> 0 | U38: =SUM(C38:N38) -> 0 | W38: =ROUND(SUM(P38:S38)-U38,2) -> 0
B39: Ramp | C39: =+'2026 Detail'!C52 -> 0 | D39: =+'2026 Detail'!D52 -> 0 | E39: =+'2026 Detail'!E52 -> 0 | F39: =+'2026 Detail'!F52 -> 0 | G39: =+'2026 Detail'!G52 -> 0 | H39: =+'2026 Detail'!H52 -> 0 | I39: =+'2026 Detail'!I52 -> 0 | J39: =+'2026 Detail'!J52 -> 0 | ... N39: =+'2026 Detail'!N52 -> 0 | P39: =SUM(C39:E39) -> 0 | Q39: =SUM(F39:H39) -> 0 | R39: =SUM(I39:K39) -> 0 | S39: =SUM(L39:N39) -> 0 | U39: =SUM(C39:N39) -> 0 | W39: =ROUND(SUM(P39:S39)-U39,2) -> 0
B40: Bank Fees | C40: =+'2026 Detail'!C53 -> -400 | D40: =+'2026 Detail'!D53 -> -400 | E40: =+'2026 Detail'!E53 -> -400 | F40: =+'2026 Detail'!F53 -> -400 | G40: =+'2026 Detail'!G53 -> -400 | H40: =+'2026 Detail'!H53 -> -400 | I40: =+'2026 Detail'!I53 -> -400 | J40: =+'2026 Detail'!J53 -> -400 | ... N40: =+'2026 Detail'!N53 -> -400 | P40: =SUM(C40:E40) -> -1200 | Q40: =SUM(F40:H40) -> -1200 | R40: =SUM(I40:K40) -> -1200 | S40: =SUM(L40:N40) -> -1200 | U40: =SUM(C40:N40) -> -4800 | W40: =ROUND(SUM(P40:S40)-U40,2) -> 0
B41: Interest | C41: =+'2026 Detail'!C54 -> 500 | D41: =+'2026 Detail'!D54 -> 400 | E41: =+'2026 Detail'!E54 -> 100 | F41: =+'2026 Detail'!F54 -> 200 | G41: =+'2026 Detail'!G54 -> 300 | H41: =+'2026 Detail'!H54 -> 200 | I41: =+'2026 Detail'!I54 -> 200 | J41: =+'2026 Detail'!J54 -> 200 | ... N41: =+'2026 Detail'!N54 -> 400 | P41: =SUM(C41:E41) -> 1000 | Q41: =SUM(F41:H41) -> 700 | R41: =SUM(I41:K41) -> 600 | S41: =SUM(L41:N41) -> 900 | U41: =SUM(C41:N41) -> 3200 | W41: =ROUND(SUM(P41:S41)-U41,2) -> 0
B43: Opening Cash Balance | C43: =+'2026 Detail'!C56 -> 964110.73 | D43: =+C48 -> 785503.21 | E43: =+D48 -> 288637.24 | F43: =+E48 -> 393009 | G43: =+F48 -> 510981.8 | H43: =+G48 -> 458122.4 | I43: =+H48 -> 404864.79 | J43: =+I48 -> 489626.21 | K43: =+J48 -> 490296.41 | ... N43: =+M48 -> 777328.56 | P43: =+C43 -> 964110.73 | Q43: =+P48 -> 393009 | R43: =+Q48 -> 404865 | S43: =+R48 -> 470302 | U43: =+P43 -> 964110.73
B45: Net Change | C45: =C8-C33+SUM(C35:C41) -> -178607.52 | D45: =D8-D33+SUM(D35:D41) -> -496865.97 | E45: =E8-E33+SUM(E35:E41) -> 104371.76 | F45: =F8-F33+SUM(F35:F41) -> 117972.8 | G45: =G8-G33+SUM(G35:G41) -> -52859.398 | H45: =H8-H33+SUM(H35:H41) -> -53257.611 | I45: =I8-I33+SUM(I35:I41) -> 84761.422 | J45: =J8-J33+SUM(J35:J41) -> 670.1963 | ... N45: =N8-N33+SUM(N35:N41) -> 232464.7 | P45: =SUM(C45:E45) -> -571101.74 | Q45: =SUM(F45:H45) -> 11855.788 | R45: =SUM(I45:K45) -> 65436.7 | S45: =SUM(L45:N45) -> 539491.78 | U45: =SUM(C45:N45) -> 45682.528 | W45: =ROUND(SUM(P45:S45)-U45,2) -> 0
B46: Investment | C46: =+'2026 Detail'!C59 -> 0 | D46: =+'2026 Detail'!D59 -> 0 | E46: =+'2026 Detail'!E59 -> 0 | F46: =+'2026 Detail'!F59 -> 0 | G46: =+'2026 Detail'!G59 -> 0 | H46: =+'2026 Detail'!H59 -> 0 | I46: =+'2026 Detail'!I59 -> 0 | J46: =+'2026 Detail'!J59 -> 0 | ... N46: =+'2026 Detail'!N59 -> 0 | P46: =SUM(C46:E46) -> 0 | Q46: =SUM(F46:H46) -> 0 | R46: =SUM(I46:K46) -> 0 | S46: =SUM(L46:N46) -> 0 | U46: =SUM(C46:N46) -> 0 | W46: =ROUND(SUM(P46:S46)-U46,2) -> 0
B48: Ending Cash Balance | C48: =ROUND(+C43+C45+C46,2) -> 785503.21 | D48: =ROUND(+D43+D45+D46,2) -> 288637.24 | E48: =ROUND(+E43+E45+E46,2) -> 393009 | F48: =ROUND(+F43+F45+F46,2) -> 510981.8 | G48: =ROUND(+G43+G45+G46,2) -> 458122.4 | H48: =ROUND(+H43+H45+H46,2) -> 404864.79 | I48: =ROUND(+I43+I45+I46,2) -> 489626.21 | J48: =ROUND(+J43+J45+J46,2) -> 490296.41 | ... N48: =ROUND(+N43+N45+N46,2) -> 1009793.3 | P48: =ROUND(+P43+P45+P46,0) -> 393009 | Q48: =ROUND(+Q43+Q45+Q46,0) -> 404865 | R48: =ROUND(+R43+R45+R46,0) -> 470302 | S48: =ROUND(+S43+S45+S46,0) -> 1009794 | U48: =ROUND(+U43+U45+U46,0) -> 1009793
B50: Cash In | C50: =+C8 -> 289764.6 | D50: =+D8 -> 393187.6 | E50: =+E8 -> 589877.6 | F50: =+F8 -> 584457.6 | G50: =+G8 -> 420207.6 | H50: =+H8 -> 420207.6 | I50: =+I8 -> 550207.6 | J50: =+J8 -> 535500 | ... N50: =+N8 -> 680000 | P50: =+P8 -> 1272829.8 | Q50: =+Q8 -> 1424872.8 | R50: =+R8 -> 1516707.6 | S50: =+S8 -> 1897000 | U50: =+U8 -> 6111410.2
B51: Calculated COGS | C51: =+C10+C14 -> 194680 | D51: =+D10+D14 -> 369533.05 | E51: =+E10+E14 -> 197771.8 | F51: =+F10+F14 -> 191771.8 | G51: =+G10+G14 -> 191771.8 | H51: =+H10+H14 -> 191771.8 | I51: =+I10+I14 -> 185271.8 | J51: =+J10+J14 -> 185271.8 | ... N51: =+N10+N14 -> 180771.8 | P51: =+P10+P14 -> 761984.85 | Q51: =+Q10+Q14 -> 575315.4 | R51: =+R10+R14 -> 555815.4 | S51: =+S10+S14 -> 542315.4 | U51: =+U10+U14 -> 2435431
B52: Gross Margin | C52: =+C50-C51 -> 95084.6 | D52: =+D50-D51 -> 23654.551 | E52: =+E50-E51 -> 392105.8 | F52: =+F50-F51 -> 392685.8 | G52: =+G50-G51 -> 228435.8 | H52: =+H50-H51 -> 228435.8 | I52: =+I50-I51 -> 364935.8 | J52: =+J50-J51 -> 350228.2 | ... N52: =+N50-N51 -> 499228.2 | P52: =+P50-P51 -> 510844.95 | Q52: =+Q50-Q51 -> 849557.4 | R52: =+R50-R51 -> 960892.2 | S52: =+S50-S51 -> 1354684.6 | U52: =+U50-U51 -> 3675979.2
B53: GM % | C53: =+C52/C50 -> 0.32814429 | D53: =+D52/D50 -> 0.060160979 | E53: =+E52/E50 -> 0.664724 | F53: =+F52/F50 -> 0.67188073 | G53: =+G52/G50 -> 0.54362606 | H53: =+H52/H50 -> 0.54362606 | I53: =+I52/I50 -> 0.66326928 | J53: =+J52/J50 -> 0.65402092 | ... N53: =+N52/N50 -> 0.73415912 | P53: =+P52/P50 -> 0.40134584 | Q53: =+Q52/Q50 -> 0.59623385 | R53: =+R52/R50 -> 0.6335382 | S53: =+S52/S50 -> 0.71411945 | U53: =+U52/U50 -> 0.60149442
B55: Check | C55: =+C48-'2026 Detail'!C61 -> 0 | D55: =+D48-'2026 Detail'!D61 -> 0 | E55: =+E48-'2026 Detail'!E61 -> 0 | F55: =+F48-'2026 Detail'!F61 -> 0 | G55: =+G48-'2026 Detail'!G61 -> 0 | H55: =+H48-'2026 Detail'!H61 -> 0 | I55: =+I48-'2026 Detail'!I61 -> 0 | J55: =+J48-'2026 Detail'!J61 -> 0 | ... N55: =+N48-'2026 Detail'!N61 -> 0
B59: Cash by Customer | C59: 637897.35 | D59: 204430 | E59: 201394.6 | F59: 289457.6 | G59: 349652.6 | H59: 259207.6 | I59: 207395.85 | J59: 192430 | K59: 102930 | L59: 102930 | M59: 102930 | N59: 96930 | P59: =SUM(C59:E59) -> 1043721.9 | Q59: =SUM(F59:H59) -> 898317.8 | R59: =SUM(I59:K59) -> 502755.85 | S59: =SUM(L59:N59) -> 302790 | U59: =SUM(C59:N59) -> 2747585.6
B60: Collections from Future Sales | C60: =+'1 Collections'!R27 -> 62500 | D60: =+'1 Collections'!S27 -> 62500 | E60: =+'1 Collections'!T27 -> 210000 | F60: =+'1 Collections'!U27 -> 160000 | G60: =+'1 Collections'!V27 -> 260000 | H60: =+'1 Collections'!W27 -> 260000 | I60: =+'1 Collections'!X27 -> 390000 | J60: =+'1 Collections'!Y27 -> 390000 | ... N60: =+'1 Collections'!AC27 -> 645000 | P60: =SUM(C60:E60) -> 335000 | Q60: =SUM(F60:H60) -> 680000 | R60: =SUM(I60:K60) -> 1170000 | S60: =SUM(L60:N60) -> 1780000 | U60: =SUM(C60:N60) -> 3965000
B61: Updated Collections | C61: =SUM(C59:C60) -> 700397.35 | D61: =SUM(D59:D60) -> 266930 | E61: =SUM(E59:E60) -> 411394.6 | F61: =SUM(F59:F60) -> 449457.6 | G61: =SUM(G59:G60) -> 609652.6 | H61: =SUM(H59:H60) -> 519207.6 | I61: =SUM(I59:I60) -> 597395.85 | J61: =SUM(J59:J60) -> 582430 | ... N61: =SUM(N59:N60) -> 741930 | P61: =SUM(C61:E61) -> 1378721.9 | Q61: =SUM(F61:H61) -> 1578317.8 | R61: =SUM(I61:K61) -> 1672755.9 | S61: =SUM(L61:N61) -> 2082790 | U61: =SUM(C61:N61) -> 6712585.6
B63: Opening Cash Balance | C63: 812310.92 | D63: =+C66 -> 1044336.1 | E63: =+D66 -> 421212.58 | F63: =+E66 -> 347101.33 | G63: =+F66 -> 330074.13 | H63: =+G66 -> 466659.73 | I63: =+H66 -> 512402.12 | J63: =+I66 -> 644351.79 | K63: =+J66 -> 691951.99 | ... N63: =+M66 -> 1164774.1 | P63: =+C63 -> 812310.92 | Q63: =+P66 -> 347101.33 | R63: =+Q66 -> 512402.12 | S63: =+R66 -> 733887.07 | U63: =+C63 -> 812310.92
B64: Collections | C64: =+C61 -> 700397.35 | D64: =+D61 -> 266930 | E64: =+E61 -> 411394.6 | F64: =+F61 -> 449457.6 | G64: =+G61 -> 609652.6 | H64: =+H61 -> 519207.6 | I64: =+I61 -> 597395.85 | J64: =+J61 -> 582430 | ... N64: =+N61 -> 741930 | P64: =SUM(C64:E64) -> 1378721.9 | Q64: =SUM(F64:H64) -> 1578317.8 | R64: =SUM(I64:K64) -> 1672755.9 | S64: =SUM(L64:N64) -> 2082790 | U64: =SUM(C64:N64) -> 6712585.6
B65: Disbursements | C65: =-+C33+SUM(C35:C41) -> -468372.12 | D65: =-+D33+SUM(D35:D41) -> -890053.57 | E65: =-+E33+SUM(E35:E41) -> -485505.84 | F65: =-+F33+SUM(F35:F41) -> -466484.8 | G65: =-+G33+SUM(G35:G41) -> -473067 | H65: =-+H33+SUM(H35:H41) -> -473465.21 | I65: =-+I33+SUM(I35:I41) -> -465446.18 | J65: =-+J33+SUM(J35:J41) -> -534829.8 | ... N65: =-+N33+SUM(N35:N41) -> -447535.3 | P65: =SUM(C65:E65) -> -1843931.5 | Q65: =SUM(F65:H65) -> -1413017 | R65: =SUM(I65:K65) -> -1451270.9 | S65: =SUM(L65:N65) -> -1357508.2 | U65: =SUM(C65:N65) -> -6065727.7
B66: Ending Cash Balance | C66: =SUM(C63:C65) -> 1044336.1 | D66: =SUM(D63:D65) -> 421212.58 | E66: =SUM(E63:E65) -> 347101.33 | F66: =SUM(F63:F65) -> 330074.13 | G66: =SUM(G63:G65) -> 466659.73 | H66: =SUM(H63:H65) -> 512402.12 | I66: =SUM(I63:I65) -> 644351.79 | J66: =SUM(J63:J65) -> 691951.99 | ... N66: =SUM(N63:N65) -> 1459168.8 | P66: =SUM(P63:P65) -> 347101.33 | Q66: =SUM(Q63:Q65) -> 512402.12 | R66: =SUM(R63:R65) -> 733887.07 | S66: =SUM(S63:S65) -> 1459168.8 | U66: =SUM(U63:U65) -> 1459168.8
B68: Ending Cash Balance | C68: =+C48 -> 785503.21 | D68: =+D48 -> 288637.24 | E68: =+E48 -> 393009 | F68: =+F48 -> 510981.8 | G68: =+G48 -> 458122.4 | H68: =+H48 -> 404864.79 | I68: =+I48 -> 489626.21 | J68: =+J48 -> 490296.41 | ... N68: =+N48 -> 1009793.3 | P68: =+P48 -> 393009 | Q68: =+Q48 -> 404865 | R68: =+R48 -> 470302 | S68: =+S48 -> 1009794 | U68: =+U48 -> 1009793
B69: Change from previous forecast | C69: =+C66-C68 -> 258832.94 | D69: =+D66-D68 -> 132575.34 | E69: =+E66-E68 -> -45907.665 | F69: =+F66-F68 -> -180907.67 | G69: =+G66-G68 -> 8537.3329 | H69: =+H66-H68 -> 107537.33 | I69: =+I66-I68 -> 154725.58 | J69: =+J66-J68 -> 201655.58 | ... N69: =+N66-N68 -> 449375.59 | P69: =+P66-P68 -> -45907.665 | Q69: =+Q66-Q68 -> 107537.12 | R69: =+R66-R68 -> 263585.07 | S69: =+S66-S68 -> 449374.85 | U69: =+U66-U68 -> 449375.85
B73: Cash by Customer - Updated | C73: =+C59 -> 637897.35 | D73: =+D59 -> 204430 | E73: =+E59 -> 201394.6 | F73: =+F59 -> 289457.6 | G73: =+G59 -> 349652.6 | H73: =+H59 -> 259207.6 | I73: =+I59 -> 207395.85 | J73: =+J59 -> 192430 | ... N73: =+N59 -> 96930 | P73: =SUM(C73:E73) -> 1043721.9 | Q73: =SUM(F73:H73) -> 898317.8 | R73: =SUM(I73:K73) -> 502755.85 | S73: =SUM(L73:N73) -> 302790 | U73: =SUM(C73:N73) -> 2747585.6
B74: Cash by Customer - Previous | C74: =+'1 Collections'!R15 -> 227264.6 | D74: =+'1 Collections'!S15 -> 330687.6 | E74: =+'1 Collections'!T15 -> 379877.6 | F74: =+'1 Collections'!U15 -> 424457.6 | G74: =+'1 Collections'!V15 -> 160207.6 | H74: =+'1 Collections'!W15 -> 160207.6 | I74: =+'1 Collections'!X15 -> 160207.6 | J74: =+'1 Collections'!Y15 -> 145500 | ... N74: =+'1 Collections'!AC15 -> 35000 | P74: =SUM(C74:E74) -> 937829.8 | Q74: =SUM(F74:H74) -> 744872.8 | R74: =SUM(I74:K74) -> 346707.6 | S74: =SUM(L74:N74) -> 117000 | U74: =SUM(C74:N74) -> 2146410.2
B75: Cash by Customer - Change | C75: =+C73-C74 -> 410632.75 | D75: =+D73-D74 -> -126257.6 | E75: =+E73-E74 -> -178483 | F75: =+F73-F74 -> -135000 | G75: =+G73-G74 -> 189445 | H75: =+H73-H74 -> 99000 | I75: =+I73-I74 -> 47188.25 | J75: =+J73-J74 -> 46930 | ... N75: =+N73-N74 -> 61930 | P75: =SUM(C75:E75) -> 105892.15 | Q75: =SUM(F75:H75) -> 153445 | R75: =SUM(I75:K75) -> 156048.25 | S75: =SUM(L75:N75) -> 185790 | U75: =SUM(C75:N75) -> 601175.4

Sheet Assumptions
A1: Assumptions
A2: =+Version!$C$3 -> Y2025 12 v001
A4: =ROW()-3 -> 1 | B4: Y2025 cash collections based on actual & known invoicing
A5: =ROW()-3 -> 2 | B5: Y2026 cash collections based on actual, known & forecast (highighted in purple on (1) Collections tab
A6: =ROW()-3 -> 3 | B6: Employee bonus payouts @ 70% (equal to Y2025 accrual) and paid out in February 2026
A7: =ROW()-3 -> 4 | B7: Employee raises of 3% effective in March 2026
A8: =ROW()-3 -> 5 | B8: Employee commissions of $4600 per month beginning October 2025
A9: =ROW()-3 -> 6 | B9: No headcount changes to current team of 14
A10: =ROW()-3 -> 7 | B10: Benefit increase of 6.1% covered by employer
A11: =ROW()-3 -> 8 | B11: Contractors at current levels with some additions - need to review one by one together to confirm
A12: =ROW()-3 -> 9 | B12: Hardware and software cost increase by 5% from 2025 to 2026
A13: =ROW()-3 -> 10 | B13: Office & insurance cost remain flat year over year
A14: =ROW()-3 -> 11 | B14: Legal cost reduces to run rate at end of Y2025
A15: =ROW()-3 -> 12 | B15: Accounting & tax cost reduced due to new agreement with SC&H
... A17: =ROW()-3 -> 14 | B17: Travel cost baselined at last four months of Y2025

Sheet Overview
B2: SYNAPTIC CASH FLOW FORECAST | C2: Q1-2025 | D2: Q2-2025 | E2: Q3-2025 | F2: Q4-2025 | H2: Q1-2026 | I2: Q2-2026 | J2: Q3-2026 | K2: Q4-2026 | M2: 2025 | N2: 2026 | P2: 26v25 B (W) $ | Q2: 26v25 B (W) %
B3: =+Version!$C$3 -> Y2025 12 v001
B5: Classic | C5: =+'2025 Detail'!P8 -> 728757.46 | D5: =+'2025 Detail'!Q8 -> 444190.5 | E5: =+'2025 Detail'!R8 -> 447319.5 | F5: =+'2025 Detail'!S8 -> 766915.5 | H5: =+'2026 Detail'!P8 -> 620247 | I5: =+'2026 Detail'!Q8 -> 501790 | J5: =+'2026 Detail'!R8 -> 436930 | K5: =+'2026 Detail'!S8 -> 410000 | M5: =SUM(C5:F5) -> 2387183 | N5: =SUM(H5:K5) -> 1968967 | P5: =+N5-M5 -> -418215.96 | Q5: =+P5/M5 -> -0.17519225
B6: AppIQ | C6: =+'2025 Detail'!P13 -> 176292.98 | D6: =+'2025 Detail'!Q13 -> 76692 | E6: =+'2025 Detail'!R13 -> 172277.6 | F6: =+'2025 Detail'!S13 -> 779860.4 | H6: =+'2026 Detail'!P13 -> 652582.8 | I6: =+'2026 Detail'!Q13 -> 923082.8 | J6: =+'2026 Detail'!R13 -> 1079777.6 | K6: =+'2026 Detail'!S13 -> 1487000 | M6: =SUM(C6:F6) -> 1205123 | N6: =SUM(H6:K6) -> 4142443.2 | P6: =+N6-M6 -> 2937320.2 | Q6: =+P6/M6 -> 2.4373614
B7: Cash Collected | C7: =SUM(C5:C6) -> 905050.44 | D7: =SUM(D5:D6) -> 520882.5 | E7: =SUM(E5:E6) -> 619597.1 | F7: =SUM(F5:F6) -> 1546775.9 | H7: =SUM(H5:H6) -> 1272829.8 | I7: =SUM(I5:I6) -> 1424872.8 | J7: =SUM(J5:J6) -> 1516707.6 | K7: =SUM(K5:K6) -> 1897000 | M7: =SUM(M5:M6) -> 3592305.9 | N7: =SUM(N5:N6) -> 6111410.2 | P7: =SUM(P5:P6) -> 2519104.3 | Q7: =+P7/M7 -> 0.70124992
N8: 6.2
B9: Classic | C9: =+C5/C$7 -> 0.80521198 | D9: =+D5/D$7 -> 0.85276526 | E9: =+E5/E$7 -> 0.72195222 | F9: =+F5/F$7 -> 0.49581552 | H9: =+H5/H$7 -> 0.48729767 | I9: =+I5/I$7 -> 0.35216477 | J9: =+J5/J$7 -> 0.28807794 | K9: =+K5/K$7 -> 0.21613073 | M9: =+M5/M$7 -> 0.66452663 | N9: =+N5/N$7 -> 0.32217883
B10: AppIQ | C10: =+C6/C$7 -> 0.19478802 | D10: =+D6/D$7 -> 0.14723474 | E10: =+E6/E$7 -> 0.27804778 | F10: =+F6/F$7 -> 0.50418448 | H10: =+H6/H$7 -> 0.51270233 | I10: =+I6/I$7 -> 0.64783523 | J10: =+J6/J$7 -> 0.71192206 | K10: =+K6/K$7 -> 0.78386927 | M10: =+M6/M$7 -> 0.33547337 | N10: =+N6/N$7 -> 0.67782117
B12: Delivery (COGS) | C12: =+'2025 Detail'!P17+'2025 Detail'!P18+'2025 Detail'!P23+'2025 Detail'!P24 -> 834144.13 | D12: =+'2025 Detail'!Q17+'2025 Detail'!Q18+'2025 Detail'!Q23+'2025 Detail'!Q24 -> 576858.66 | E12: =+'2025 Detail'!R17+'2025 Detail'!R18+'2025 Detail'!R23+'2025 Detail'!R24 -> 562447.14 | F12: =+'2025 Detail'!S17+'2025 Detail'!S18+'2025 Detail'!S23+'2025 Detail'!S24 -> 584581.13 | H12: =+'2026 Detail'!P17+'2026 Detail'!P18+'2026 Detail'!P23+'2026 Detail'!P24 -> 761984.85 | I12: =+'2026 Detail'!Q17+'2026 Detail'!Q18+'2026 Detail'!Q23+'2026 Detail'!Q24 -> 575315.4 | J12: =+'2026 Detail'!R17+'2026 Detail'!R18+'2026 Detail'!R23+'2026 Detail'!R24 -> 555815.4 | K12: =+'2026 Detail'!S17+'2026 Detail'!S18+'2026 Detail'!S23+'2026 Detail'!S24 -> 542315.4 | M12: =SUM(C12:F12) -> 2558031.1 | N12: =SUM(H12:K12) -> 2435431 | P12: =+M12-N12 -> 122600.02 | Q12: =+P12/M12 -> 0.047927493
B14: Gross Margin | C14: =+C7-C12 -> 70906.308 | D14: =+D7-D12 -> -55976.161 | E14: =+E7-E12 -> 57149.956 | F14: =+F7-F12 -> 962194.77 | H14: =+H7-H12 -> 510844.95 | I14: =+I7-I12 -> 849557.4 | J14: =+J7-J12 -> 960892.2 | K14: =+K7-K12 -> 1354684.6 | M14: =+M7-M12 -> 1034274.9 | N14: =+N7-N12 -> 3675979.2 | P14: =+N14-M14 -> 2641704.3 | Q14: =+P14/M14 -> 2.5541607
B15: Gross Margin % | C15: =+C14/C7 -> 0.078345146 | D15: =+D14/D7 -> -0.10746408 | E15: =+E14/E7 -> 0.092237288 | F15: =+F14/F7 -> 0.62206476 | H15: =+H14/H7 -> 0.40134584 | I15: =+I14/I7 -> 0.59623385 | J15: =+J14/J7 -> 0.6335382 | K15: =+K14/K7 -> 0.71411945 | M15: =+M14/M7 -> 0.28791392 | N15: =+N14/N7 -> 0.60149442
B17: Research & Development | C17: =+'2025 Detail'!P27+'2025 Detail'!P28 -> 238999.44 | D17: =+'2025 Detail'!Q27+'2025 Detail'!Q28 -> 293164.95 | E17: =+'2025 Detail'!R27+'2025 Detail'!R28 -> 304995.69 | F17: =+'2025 Detail'!S27+'2025 Detail'!S28 -> 260047.26 | H17: =+'2026 Detail'!P27+'2026 Detail'!P28 -> 249375.75 | I17: =+'2026 Detail'!Q27+'2026 Detail'!Q28 -> 226494 | J17: =+'2026 Detail'!R27+'2026 Detail'!R28 -> 226494 | K17: =+'2026 Detail'!S27+'2026 Detail'!S28 -> 226494 | M17: =SUM(C17:F17) -> 1097207.3 | N17: =SUM(H17:K17) -> 928857.75 | P17: =+M17-N17 -> 168349.59 | Q17: =+P17/M17 -> 0.15343462
B18: Go to Market | C18: =+'2025 Detail'!P19+'2025 Detail'!P20+'2025 Detail'!P25+'2025 Detail'!P26 -> 344879.09 | D18: =+'2025 Detail'!Q19+'2025 Detail'!Q20+'2025 Detail'!Q25+'2025 Detail'!Q26 -> 434425.35 | E18: =+'2025 Detail'!R19+'2025 Detail'!R20+'2025 Detail'!R25+'2025 Detail'!R26 -> 354262.14 | F18: =+'2025 Detail'!S19+'2025 Detail'!S20+'2025 Detail'!S25+'2025 Detail'!S26 -> 271117.28 | H18: =+'2026 Detail'!P19+'2026 Detail'!P20+'2026 Detail'!P25+'2026 Detail'!P26 -> 327989.99 | I18: =+'2026 Detail'!Q19+'2026 Detail'!Q20+'2026 Detail'!Q25+'2026 Detail'!Q26 -> 228841.5 | J18: =+'2026 Detail'!R19+'2026 Detail'!R20+'2026 Detail'!R25+'2026 Detail'!R26 -> 228841.5 | K18: =+'2026 Detail'!S19+'2026 Detail'!S20+'2026 Detail'!S25+'2026 Detail'!S26 -> 228841.5 | M18: =SUM(C18:F18) -> 1404683.9 | N18: =SUM(H18:K18) -> 1014514.5 | P18: =+M18-N18 -> 390169.37 | Q18: =+P18/M18 -> 0.27776312
B19: Back Office & Administrative | C19: =+'2025 Detail'!P33 -> 277163.6 | D19: =+'2025 Detail'!Q33 -> 233495.23 | E19: =+'2025 Detail'!R33 -> 235870.15 | F19: =+'2025 Detail'!S33 -> 209935.82 | H19: =+'2026 Detail'!P33 -> 352980 | I19: =+'2026 Detail'!Q33 -> 197280 | J19: =+'2026 Detail'!R33 -> 195780 | K19: =+'2026 Detail'!S33 -> 195780 | M19: =SUM(C19:F19) -> 956464.79 | N19: =SUM(H19:K19) -> 941820 | P19: =+M19-N19 -> 14644.792 | Q19: =+P19/M19 -> 0.015311376
B20: Other | C20: ='2025 Detail'!P44-SUM('2025 Detail'!P48:P54) -> 168230.69 | D20: ='2025 Detail'!Q44-SUM('2025 Detail'!Q48:Q54) -> 260628.4 | E20: ='2025 Detail'!R44-SUM('2025 Detail'!R48:R54) -> 231119.46 | F20: ='2025 Detail'!S44-SUM('2025 Detail'!S48:S54) -> 186169.49 | H20: ='2026 Detail'!P44-SUM('2026 Detail'!P48:P54) -> 151600.95 | I20: ='2026 Detail'!Q44-SUM('2026 Detail'!Q48:Q54) -> 185086.11 | J20: ='2026 Detail'!R44-SUM('2026 Detail'!R48:R54) -> 244340 | K20: ='2026 Detail'!S44-SUM('2026 Detail'!S48:S54) -> 164077.32 | M20: =SUM(C20:F20) -> 846148.04 | N20: =SUM(H20:K20) -> 745104.38 | P20: =+M20-N20 -> 101043.66 | Q20: =+P20/M20 -> 0.11941605
B21: Operating Cost | C21: =SUM(C17:C20) -> 1029272.8 | D21: =SUM(D17:D20) -> 1221713.9 | E21: =SUM(E17:E20) -> 1126247.4 | F21: =SUM(F17:F20) -> 927269.84 | H21: =SUM(H17:H20) -> 1081946.7 | I21: =SUM(I17:I20) -> 837701.61 | J21: =SUM(J17:J20) -> 895455.5 | K21: =SUM(K17:K20) -> 815192.82 | M21: =SUM(M17:M20) -> 4304504 | N21: =SUM(N17:N20) -> 3630296.6 | P21: =+M21-N21 -> 674207.4 | Q21: =+P21/M21 -> 0.15662836
B23: Research & Development | C23: =+C17/C$7 -> 0.26407306 | D23: =+D17/D$7 -> 0.56282357 | E23: =+E17/E$7 -> 0.49224842 | F23: =+F17/F$7 -> 0.16812213 | H23: =+H17/H$7 -> 0.19592231 | I23: =+I17/I$7 -> 0.15895735 | J23: =+J17/J$7 -> 0.14933267 | K23: =+K17/K$7 -> 0.11939589 | M23: =+M17/M$7 -> 0.3054326 | N23: =+N17/N$7 -> 0.15198747
B24: Go to Market | C24: =+C18/C$7 -> 0.38106063 | D24: =+D18/D$7 -> 0.83401795 | E24: =+E18/E$7 -> 0.5717621 | F24: =+F18/F$7 -> 0.17527896 | H24: =+H18/H$7 -> 0.25768566 | I24: =+I18/I$7 -> 0.16060486 | J24: =+J18/J$7 -> 0.15088043 | K24: =+K18/K$7 -> 0.12063337 | M24: =+M18/M$7 -> 0.39102568 | N24: =+N18/N$7 -> 0.16600334
B25: Back Office & Administrative | C25: =+C20/C$7 -> 0.18587991 | D25: =+D20/D$7 -> 0.50035929 | E25: =+E20/E$7 -> 0.37301572 | F25: =+F20/F$7 -> 0.1203597 | H25: =+H20/H$7 -> 0.11910544 | I25: =+I20/I$7 -> 0.12989659 | J25: =+J20/J$7 -> 0.16109895 | K25: =+K20/K$7 -> 0.086493054 | M25: =+M20/M$7 -> 0.23554454 | N25: =+N20/N$7 -> 0.12192021
B27: Opening Cash Balance | C27: =+'2025 Detail'!P56 -> 3334341 | D27: =+C32 -> 3325973 | E27: =+D32 -> 2023283 | F27: =+E32 -> 954186 | H27: =+F32 -> 964111 | I27: =+H32 -> 393009 | J27: =+I32 -> 404865 | K27: =+J32 -> 470302 | M27: =+C27 -> 3334341 | N27: =+M32 -> 964111
B29: Net Change | C29: =+C7-C12-C21 -> -958366.51 | D29: =+D7-D12-D21 -> -1277690.1 | E29: =+E7-E12-E21 -> -1069097.5 | F29: =+F7-F12-F21 -> 34924.93 | H29: =+H7-H12-H21 -> -571101.74 | I29: =+I7-I12-I21 -> 11855.788 | J29: =+J7-J12-J21 -> 65436.7 | K29: =+K7-K12-K21 -> 539491.78 | M29: =SUM(C29:F29) -> -3270229.2 | N29: =SUM(H29:K29) -> 45682.528 | P29: =+N29-M29 -> 3315911.7 | Q29: =+P29/ABS(M29) -> 1.0139692
B30: Investment | C30: =+'2025 Detail'!P59 -> 949998.86 | D30: =+'2025 Detail'!Q59 -> -25000 | E30: =+'2025 Detail'!R59 -> 0 | F30: =+'2025 Detail'!S59 -> -25000 | H30: =+'2026 Detail'!P59 -> 0 | I30: =+'2026 Detail'!Q59 -> 0 | J30: =+'2026 Detail'!R59 -> 0 | K30: =+'2026 Detail'!S59 -> 0 | M30: =SUM(C30:F30) -> 899998.86 | N30: =SUM(H30:K30) -> 0
B32: Ending Cash Balance | C32: =ROUND(+C27+C29+C30,0) -> 3325973 | D32: =ROUND(+D27+D29+D30,0) -> 2023283 | E32: =ROUND(+E27+E29+E30,0) -> 954186 | F32: =ROUND(+F27+F29+F30,0) -> 964111 | H32: =ROUND(+H27+H29+H30,0) -> 393009 | I32: =ROUND(+I27+I29+I30,0) -> 404865 | J32: =ROUND(+J27+J29+J30,0) -> 470302 | K32: =ROUND(+K27+K29+K30,0) -> 1009794 | M32: =ROUND(+M27+M29+M30,0) -> 964111 | N32: =ROUND(+N27+N29+N30,0) -> 1009794
B34: Check | C34: =+C32-'2025 Detail'!P61 -> 0 | D34: =+D32-'2025 Detail'!Q61 -> 0 | E34: =+E32-'2025 Detail'!R61 -> 0 | F34: =+F32-'2025 Detail'!S61 -> 0 | H34: =+H32-'2026 Detail'!P61 -> 0 | I34: =+I32-'2026 Detail'!Q61 -> 0 | J34: =+J32-'2026 Detail'!R61 -> 0 | K34: =+K32-'2026 Detail'!S61 -> 0 | M34: =+M32-'2025 Detail'!U61 -> 0 | N34: =+N32-'2026 Detail'!U61 -> 1

Sheet 2025 to 2026 Detail View
B2: SYNAPTIC CASH FLOW FORECAST | C2: Q1-2025 | D2: Q2-2025 | E2: Q3-2025 | F2: Q4-2025 | H2: Q1-2026 | I2: Q2-2026 | J2: Q3-2026 | K2: Q4-2026 | M2: 2025 | N2: 2026 | P2: 26v25 B (W) $ | Q2: 26v25 B (W) % | S2: Check | T2: Check
B3: =+Version!$C$3 -> Y2025 12 v001
B5: HLS | C5: =+'2025 Detail'!P5 -> 144854.4 | D5: =+'2025 Detail'!Q5 -> 68681.25 | E5: =+'2025 Detail'!R5 -> 28510 | F5: =+'2025 Detail'!S5 -> 6540 | H5: =+'2026 Detail'!P5 -> 5790 | I5: =+'2026 Detail'!Q5 -> 5790 | J5: =+'2026 Detail'!R5 -> 1930 | K5: =+'2026 Detail'!S5 -> 0 | M5: =SUM(C5:F5) -> 248585.65 | N5: =SUM(H5:K5) -> 13510 | P5: =+N5-M5 -> -235075.65 | Q5: =+P5/M5 -> -0.94565253 | S5: =+M5-'2025 Detail'!U5 -> 0 | T5: =+N5-'2026 Detail'!U5 -> 0
B6: PSS | C6: =+'2025 Detail'!P6 -> 374941.7 | D6: =+'2025 Detail'!Q6 -> 349616.4 | E6: =+'2025 Detail'!R6 -> 281609.6 | F6: =+'2025 Detail'!S6 -> 534745 | H6: =+'2026 Detail'!P6 -> 494607 | I6: =+'2026 Detail'!Q6 -> 376000 | J6: =+'2026 Detail'!R6 -> 330000 | K6: =+'2026 Detail'!S6 -> 320000 | M6: =SUM(C6:F6) -> 1540912.7 | N6: =SUM(H6:K6) -> 1520607 | P6: =+N6-M6 -> -20305.7 | Q6: =+P6/M6 -> -0.01317771 | S6: =+M6-'2025 Detail'!U6 -> 0 | T6: =+N6-'2026 Detail'!U6 -> 0
B7: ENT | C7: =+'2025 Detail'!P7 -> 208961.36 | D7: =+'2025 Detail'!Q7 -> 25892.85 | E7: =+'2025 Detail'!R7 -> 137199.9 | F7: =+'2025 Detail'!S7 -> 225630.5 | H7: =+'2026 Detail'!P7 -> 119850 | I7: =+'2026 Detail'!Q7 -> 120000 | J7: =+'2026 Detail'!R7 -> 105000 | K7: =+'2026 Detail'!S7 -> 90000 | M7: =SUM(C7:F7) -> 597684.61 | N7: =SUM(H7:K7) -> 434850 | P7: =+N7-M7 -> -162834.61 | Q7: =+P7/M7 -> -0.27244237 | S7: =+M7-'2025 Detail'!U7 -> 0 | T7: =+N7-'2026 Detail'!U7 -> 0
B8: Total Classic | C8: =SUM(C5:C7) -> 728757.46 | D8: =SUM(D5:D7) -> 444190.5 | E8: =SUM(E5:E7) -> 447319.5 | F8: =SUM(F5:F7) -> 766915.5 | H8: =SUM(H5:H7) -> 620247 | I8: =SUM(I5:I7) -> 501790 | J8: =SUM(J5:J7) -> 436930 | K8: =SUM(K5:K7) -> 410000 | M8: =SUM(M5:M7) -> 2387183 | N8: =SUM(N5:N7) -> 1968967 | P8: =+N8-M8 -> -418215.96 | Q8: =+P8/M8 -> -0.17519225 | S8: =+M8-'2025 Detail'!U8 -> 0 | T8: =+N8-'2026 Detail'!U8 -> 0
B10: HLS | C10: =+'2025 Detail'!P10 -> 176292.98 | D10: =+'2025 Detail'!Q10 -> 41705 | E10: =+'2025 Detail'!R10 -> 0 | F10: =+'2025 Detail'!S10 -> 306250 | H10: =+'2026 Detail'!P10 -> 190750 | I10: =+'2026 Detail'!Q10 -> 336250 | J10: =+'2026 Detail'!R10 -> 456000 | K10: =+'2026 Detail'!S10 -> 550000 | M10: =SUM(C10:F10) -> 524247.98 | N10: =SUM(H10:K10) -> 1533000 | P10: =+N10-M10 -> 1008752 | Q10: =+P10/M10 -> 1.9241887 | S10: =+M10-'2025 Detail'!U10 -> 0 | T10: =+N10-'2026 Detail'!U10 -> 0
B11: PSS | C11: =+'2025 Detail'!P11 -> 0 | D11: =+'2025 Detail'!Q11 -> 9987 | E11: =+'2025 Detail'!R11 -> 39277.6 | F11: =+'2025 Detail'!S11 -> 387610.4 | H11: =+'2026 Detail'!P11 -> 367832.8 | I11: =+'2026 Detail'!Q11 -> 472832.8 | J11: =+'2026 Detail'!R11 -> 503777.6 | K11: =+'2026 Detail'!S11 -> 750000 | M11: =SUM(C11:F11) -> 436875 | N11: =SUM(H11:K11) -> 2094443.2 | P11: =+N11-M11 -> 1657568.2 | Q11: =+P11/M11 -> 3.7941475 | S11: =+M11-'2025 Detail'!U11 -> 0 | T11: =+N11-'2026 Detail'!U11 -> 0
B12: ENT | C12: =+'2025 Detail'!P12 -> 0 | D12: =+'2025 Detail'!Q12 -> 25000 | E12: =+'2025 Detail'!R12 -> 133000 | F12: =+'2025 Detail'!S12 -> 86000 | H12: =+'2026 Detail'!P12 -> 94000 | I12: =+'2026 Detail'!Q12 -> 114000 | J12: =+'2026 Detail'!R12 -> 120000 | K12: =+'2026 Detail'!S12 -> 187000 | M12: =SUM(C12:F12) -> 244000 | N12: =SUM(H12:K12) -> 515000 | P12: =+N12-M12 -> 271000 | Q12: =+P12/M12 -> 1.1106557 | S12: =+M12-'2025 Detail'!U12 -> 0 | T12: =+N12-'2026 Detail'!U12 -> 0
B13: Total AppIQ | C13: =SUM(C10:C12) -> 176292.98 | D13: =SUM(D10:D12) -> 76692 | E13: =SUM(E10:E12) -> 172277.6 | F13: =SUM(F10:F12) -> 779860.4 | H13: =SUM(H10:H12) -> 652582.8 | I13: =SUM(I10:I12) -> 923082.8 | J13: =SUM(J10:J12) -> 1079777.6 | K13: =SUM(K10:K12) -> 1487000 | M13: =SUM(M10:M12) -> 1205123 | N13: =SUM(N10:N12) -> 4142443.2 | P13: =+N13-M13 -> 2937320.2 | Q13: =+P13/M13 -> 2.4373614 | S13: =+M13-'2025 Detail'!U13 -> 0 | T13: =+N13-'2026 Detail'!U13 -> 0
B15: Total Cash Collected | C15: =+C8+C13 -> 905050.44 | D15: =+D8+D13 -> 520882.5 | E15: =+E8+E13 -> 619597.1 | F15: =+F8+F13 -> 1546775.9 | H15: =+H8+H13 -> 1272829.8 | I15: =+I8+I13 -> 1424872.8 | J15: =+J8+J13 -> 1516707.6 | K15: =+K8+K13 -> 1897000 | M15: =+M8+M13 -> 3592305.9 | N15: =+N8+N13 -> 6111410.2 | P15: =+P8+P13 -> 2519104.3 | Q15: =+P15/M15 -> 0.70124992 | S15: =+M15-'2025 Detail'!U15 -> 0 | T15: =+N15-'2026 Detail'!U15 -> 0
B17: Delivery - W2 | C17: =+'2025 Detail'!P17 -> 569426.75 | D17: =+'2025 Detail'!Q17 -> 382702.66 | E17: =+'2025 Detail'!R17 -> 374597.06 | F17: =+'2025 Detail'!S17 -> 372284.88 | H17: =+'2026 Detail'!P17 -> 557684.85 | I17: =+'2026 Detail'!Q17 -> 389015.4 | J17: =+'2026 Detail'!R17 -> 389015.4 | K17: =+'2026 Detail'!S17 -> 389015.4 | M17: =SUM(C17:F17) -> 1699011.4 | N17: =SUM(H17:K17) -> 1724731 | P17: =+M17-N17 -> -25719.694 | Q17: =+P17/M17 -> -0.015138035 | S17: =+M17-'2025 Detail'!U17 -> 0 | T17: =+N17-'2026 Detail'!U17 -> 0
B18: Delivery - Contractor | C18: =+'2025 Detail'!P18 -> 262557.38 | D18: =+'2025 Detail'!Q18 -> 179055 | E18: =+'2025 Detail'!R18 -> 152843.08 | F18: =+'2025 Detail'!S18 -> 190104.25 | H18: =+'2026 Detail'!P18 -> 172500 | I18: =+'2026 Detail'!Q18 -> 154500 | J18: =+'2026 Detail'!R18 -> 135000 | K18: =+'2026 Detail'!S18 -> 121500 | M18: =SUM(C18:F18) -> 784559.71 | N18: =SUM(H18:K18) -> 583500 | P18: =+M18-N18 -> 201059.71 | Q18: =+P18/M18 -> 0.25627076 | S18: =+M18-'2025 Detail'!U18 -> 0 | T18: =+N18-'2026 Detail'!U18 -> 0
B19: GTM - W2 | C19: =+'2025 Detail'!P19 -> 152481.58 | D19: =+'2025 Detail'!Q19 -> 122020.49 | E19: =+'2025 Detail'!R19 -> 120181.18 | F19: =+'2025 Detail'!S19 -> 119549.89 | H19: =+'2026 Detail'!P19 -> 185735.99 | I19: =+'2026 Detail'!Q19 -> 124639.5 | J19: =+'2026 Detail'!R19 -> 124639.5 | K19: =+'2026 Detail'!S19 -> 124639.5 | M19: =SUM(C19:F19) -> 514233.15 | N19: =SUM(H19:K19) -> 559654.49 | P19: =+M19-N19 -> -45421.339 | Q19: =+P19/M19 -> -0.088328297 | S19: =+M19-'2025 Detail'!U19 -> 0 | T19: =+N19-'2026 Detail'!U19 -> 0
B20: GTM - Contractor | C20: =+'2025 Detail'!P20 -> 40262.81 | D20: =+'2025 Detail'!Q20 -> 36199.26 | E20: =+'2025 Detail'!R20 -> 8000 | F20: =+'2025 Detail'!S20 -> 0 | H20: =+'2026 Detail'!P20 -> 0 | I20: =+'2026 Detail'!Q20 -> 0 | J20: =+'2026 Detail'!R20 -> 0 | K20: =+'2026 Detail'!S20 -> 0 | M20: =SUM(C20:F20) -> 84462.07 | N20: =SUM(H20:K20) -> 0 | P20: =+M20-N20 -> 84462.07 | Q20: =+P20/M20 -> 1 | S20: =+M20-'2025 Detail'!U20 -> 0 | T20: =+N20-'2026 Detail'!U20 -> 0
B21: Total Spend Classic | C21: =SUM(C17:C20) -> 1024728.5 | D21: =SUM(D17:D20) -> 719977.41 | E21: =SUM(E17:E20) -> 655621.33 | F21: =SUM(F17:F20) -> 681939.02 | H21: =SUM(H17:H20) -> 915920.84 | I21: =SUM(I17:I20) -> 668154.9 | J21: =SUM(J17:J20) -> 648654.9 | K21: =SUM(K17:K20) -> 635154.9 | M21: =SUM(M17:M20) -> 3082266.3 | N21: =SUM(N17:N20) -> 2867885.5 | P21: =+M21-N21 -> 214380.75 | Q21: =+P21/M21 -> 0.069552961 | S21: =+M21-'2025 Detail'!U21 -> 0 | T21: =+N21-'2026 Detail'!U21 -> 0
B23: Delivery - W2 | C23: =+'2025 Detail'!P23 -> 0 | D23: =+'2025 Detail'!Q23 -> 0 | E23: =+'2025 Detail'!R23 -> 0 | F23: =+'2025 Detail'!S23 -> 0 | H23: =+'2026 Detail'!P23 -> 0 | I23: =+'2026 Detail'!Q23 -> 0 | J23: =+'2026 Detail'!R23 -> 0 | K23: =+'2026 Detail'!S23 -> 0 | M23: =SUM(C23:F23) -> 0 | N23: =SUM(H23:K23) -> 0 | P23: =+M23-N23 -> 0 | Q23: 0 | S23: =+M23-'2025 Detail'!U23 -> 0 | T23: =+N23-'2026 Detail'!U23 -> 0
B24: Delivery - Contractor | C24: =+'2025 Detail'!P24 -> 2160 | D24: =+'2025 Detail'!Q24 -> 15101 | E24: =+'2025 Detail'!R24 -> 35007 | F24: =+'2025 Detail'!S24 -> 22192 | H24: =+'2026 Detail'!P24 -> 31800 | I24: =+'2026 Detail'!Q24 -> 31800 | J24: =+'2026 Detail'!R24 -> 31800 | K24: =+'2026 Detail'!S24 -> 31800 | M24: =SUM(C24:F24) -> 74460 | N24: =SUM(H24:K24) -> 127200 | P24: =+M24-N24 -> -52740 | Q24: =+P24/M24 -> -0.70829976 | S24: =+M24-'2025 Detail'!U24 -> 0 | T24: =+N24-'2026 Detail'!U24 -> 0
B25: GTM - W2 | C25: =+'2025 Detail'!P25 -> 0 | D25: =+'2025 Detail'!Q25 -> 127402.36 | E25: =+'2025 Detail'!R25 -> 83403.975 | F25: =+'2025 Detail'!S25 -> 65469.754 | H25: =+'2026 Detail'!P25 -> 72654 | I25: =+'2026 Detail'!Q25 -> 73602 | J25: =+'2026 Detail'!R25 -> 73602 | K25: =+'2026 Detail'!S25 -> 73602 | M25: =SUM(C25:F25) -> 276276.09 | N25: =SUM(H25:K25) -> 293460 | P25: =+M25-N25 -> -17183.912 | Q25: =+P25/M25 -> -0.062198331 | S25: =+M25-'2025 Detail'!U25 -> 0 | T25: =+N25-'2026 Detail'!U25 -> 0
B26: GTM - Contractor | C26: =+'2025 Detail'!P26 -> 152134.7 | D26: =+'2025 Detail'!Q26 -> 148803.24 | E26: =+'2025 Detail'!R26 -> 142676.98 | F26: =+'2025 Detail'!S26 -> 86097.63 | H26: =+'2026 Detail'!P26 -> 69600 | I26: =+'2026 Detail'!Q26 -> 30600 | J26: =+'2026 Detail'!R26 -> 30600 | K26: =+'2026 Detail'!S26 -> 30600 | M26: =SUM(C26:F26) -> 529712.55 | N26: =SUM(H26:K26) -> 161400 | P26: =+M26-N26 -> 368312.55 | Q26: =+P26/M26 -> 0.69530644 | S26: =+M26-'2025 Detail'!U26 -> 0 | T26: =+N26-'2026 Detail'!U26 -> 0
B27: R&D - W2 | C27: =+'2025 Detail'!P27 -> 89658.188 | D27: =+'2025 Detail'!Q27 -> 121200.97 | E27: =+'2025 Detail'!R27 -> 155392.55 | F27: =+'2025 Detail'!S27 -> 116272.13 | H27: =+'2026 Detail'!P27 -> 143775.75 | I27: =+'2026 Detail'!Q27 -> 120894 | J27: =+'2026 Detail'!R27 -> 120894 | K27: =+'2026 Detail'!S27 -> 120894 | M27: =SUM(C27:F27) -> 482523.84 | N27: =SUM(H27:K27) -> 506457.75 | P27: =+M27-N27 -> -23933.914 | Q27: =+P27/M27 -> -0.049601518 | S27: =+M27-'2025 Detail'!U27 -> 0 | T27: =+N27-'2026 Detail'!U27 -> 0
B28: R&D - Contractor | C28: =+'2025 Detail'!P28 -> 149341.25 | D28: =+'2025 Detail'!Q28 -> 171963.98 | E28: =+'2025 Detail'!R28 -> 149603.14 | F28: =+'2025 Detail'!S28 -> 143775.13 | H28: =+'2026 Detail'!P28 -> 105600 | I28: =+'2026 Detail'!Q28 -> 105600 | J28: =+'2026 Detail'!R28 -> 105600 | K28: =+'2026 Detail'!S28 -> 105600 | M28: =SUM(C28:F28) -> 614683.5 | N28: =SUM(H28:K28) -> 422400 | P28: =+M28-N28 -> 192283.5 | Q28: =+P28/M28 -> 0.31281708 | S28: =+M28-'2025 Detail'!U28 -> 0 | T28: =+N28-'2026 Detail'!U28 -> 0
B29: Total Spend AppIQ | C29: =SUM(C23:C28) -> 393294.14 | D29: =SUM(D23:D28) -> 584471.55 | E29: =SUM(E23:E28) -> 566083.65 | F29: =SUM(F23:F28) -> 433806.64 | H29: =SUM(H23:H28) -> 423429.75 | I29: =SUM(I23:I28) -> 362496 | J29: =SUM(J23:J28) -> 362496 | K29: =SUM(K23:K28) -> 362496 | M29: =SUM(M23:M28) -> 1977656 | N29: =SUM(N23:N28) -> 1510917.8 | P29: =+M29-N29 -> 466738.22 | Q29: =+P29/M29 -> 0.23600577 | S29: =+M29-'2025 Detail'!U29 -> 0 | T29: =+N29-'2026 Detail'!U29 -> 0
B31: Back Office - W2 | C31: =+'2025 Detail'!P31 -> 208503.7 | D31: =+'2025 Detail'!Q31 -> 154768.57 | E31: =+'2025 Detail'!R31 -> 155135.16 | F31: =+'2025 Detail'!S31 -> 132689.16 | H31: =+'2026 Detail'!P31 -> 274680 | I31: =+'2026 Detail'!Q31 -> 123480 | J31: =+'2026 Detail'!R31 -> 123480 | K31: =+'2026 Detail'!S31 -> 123480 | M31: =SUM(C31:F31) -> 651096.58 | N31: =SUM(H31:K31) -> 645120 | P31: =+M31-N31 -> 5976.582 | Q31: =+P31/M31 -> 0.0091792557 | S31: =+M31-'2025 Detail'!U31 -> 0 | T31: =+N31-'2026 Detail'!U31 -> 0
B32: Back Office - Contractor | C32: =+'2025 Detail'!P32 -> 68659.9 | D32: =+'2025 Detail'!Q32 -> 78726.66 | E32: =+'2025 Detail'!R32 -> 80734.99 | F32: =+'2025 Detail'!S32 -> 77246.66 | H32: =+'2026 Detail'!P32 -> 78300 | I32: =+'2026 Detail'!Q32 -> 73800 | J32: =+'2026 Detail'!R32 -> 72300 | K32: =+'2026 Detail'!S32 -> 72300 | M32: =SUM(C32:F32) -> 305368.21 | N32: =SUM(H32:K32) -> 296700 | P32: =+M32-N32 -> 8668.21 | Q32: =+P32/M32 -> 0.028386092 | S32: =+M32-'2025 Detail'!U32 -> 0 | T32: =+N32-'2026 Detail'!U32 -> 0
B33: Total Spend Back Office | C33: =SUM(C31:C32) -> 277163.6 | D33: =SUM(D31:D32) -> 233495.23 | E33: =SUM(E31:E32) -> 235870.15 | F33: =SUM(F31:F32) -> 209935.82 | H33: =SUM(H31:H32) -> 352980 | I33: =SUM(I31:I32) -> 197280 | J33: =SUM(J31:J32) -> 195780 | K33: =SUM(K31:K32) -> 195780 | M33: =SUM(M31:M32) -> 956464.79 | N33: =SUM(N31:N32) -> 941820 | P33: =+M33-N33 -> 14644.792 | Q33: =+P33/M33 -> 0.015311376 | S33: =+M33-'2025 Detail'!U33 -> 0 | T33: =+N33-'2026 Detail'!U33 -> 0
B35: Rent | C35: =+'2025 Detail'!P35 -> 0 | D35: =+'2025 Detail'!Q35 -> 7091.26 | E35: =+'2025 Detail'!R35 -> 14182.52 | F35: =+'2025 Detail'!S35 -> 10641.26 | H35: =+'2026 Detail'!P35 -> 10650 | I35: =+'2026 Detail'!Q35 -> 10650 | J35: =+'2026 Detail'!R35 -> 10650 | K35: =+'2026 Detail'!S35 -> 10650 | M35: =SUM(C35:F35) -> 31915.04 | N35: =SUM(H35:K35) -> 42600 | P35: =+M35-N35 -> -10684.96 | Q35: =+P35/M35 -> -0.33479388 | S35: =+M35-'2025 Detail'!U35 -> 0 | T35: =+N35-'2026 Detail'!U35 -> 0
B36: Hardware & Software | C36: =+'2025 Detail'!P36 -> 20978.95 | D36: =+'2025 Detail'!Q36 -> 59006.69 | E36: =+'2025 Detail'!R36 -> 124166.61 | F36: =+'2025 Detail'!S36 -> 48307.86 | H36: =+'2026 Detail'!P36 -> 22027.897 | I36: =+'2026 Detail'!Q36 -> 61957.025 | J36: =+'2026 Detail'!R36 -> 130374.94 | K36: =+'2026 Detail'!S36 -> 50723.253 | M36: =SUM(C36:F36) -> 252460.11 | N36: =SUM(H36:K36) -> 265083.12 | P36: =+M36-N36 -> -12623.006 | Q36: =+P36/M36 -> -0.05 | S36: =+M36-'2025 Detail'!U36 -> 0 | T36: =+N36-'2026 Detail'!U36 -> 0
B37: Office & Supplies | C37: =+'2025 Detail'!P37 -> 1627.55 | D37: =+'2025 Detail'!Q37 -> 2041.36 | E37: =+'2025 Detail'!R37 -> 3176.35 | F37: =+'2025 Detail'!S37 -> 5020.86 | H37: =+'2026 Detail'!P37 -> 2250 | I37: =+'2026 Detail'!Q37 -> 2250 | J37: =+'2026 Detail'!R37 -> 2250 | K37: =+'2026 Detail'!S37 -> 2250 | M37: =SUM(C37:F37) -> 11866.12 | N37: =SUM(H37:K37) -> 9000 | P37: =+M37-N37 -> 2866.12 | Q37: =+P37/M37 -> 0.24153809 | S37: =+M37-'2025 Detail'!U37 -> 0 | T37: =+N37-'2026 Detail'!U37 -> 0
B38: Insurance | C38: =+'2025 Detail'!P38 -> 11867.04 | D38: =+'2025 Detail'!Q38 -> 13571.93 | E38: =+'2025 Detail'!R38 -> 10402.97 | F38: =+'2025 Detail'!S38 -> 10101.04 | H38: =+'2026 Detail'!P38 -> 12223.051 | I38: =+'2026 Detail'!Q38 -> 13979.088 | J38: =+'2026 Detail'!R38 -> 10715.059 | K38: =+'2026 Detail'!S38 -> 10404.071 | M38: =SUM(C38:F38) -> 45942.98 | N38: =SUM(H38:K38) -> 47321.269 | P38: =+M38-N38 -> -1378.2894 | Q38: =+P38/M38 -> -0.03 | S38: =+M38-'2025 Detail'!U38 -> 0 | T38: =+N38-'2026 Detail'!U38 -> 0
B39: Legal Fees | C39: =+'2025 Detail'!P39 -> 44883.5 | D39: =+'2025 Detail'!Q39 -> 61545.85 | E39: =+'2025 Detail'!R39 -> 18957 | F39: =+'2025 Detail'!S39 -> 21626.7 | H39: =+'2026 Detail'!P39 -> 37500 | I39: =+'2026 Detail'!Q39 -> 30000 | J39: =+'2026 Detail'!R39 -> 24000 | K39: =+'2026 Detail'!S39 -> 24000 | M39: =SUM(C39:F39) -> 147013.05 | N39: =SUM(H39:K39) -> 115500 | P39: =+M39-N39 -> 31513.05 | Q39: =+P39/M39 -> 0.21435546 | S39: =+M39-'2025 Detail'!U39 -> 0 | T39: =+N39-'2026 Detail'!U39 -> 0
B40: Accounting & Tax Fees | C40: =+'2025 Detail'!P40 -> 0 | D40: =+'2025 Detail'!Q40 -> 22770 | E40: =+'2025 Detail'!R40 -> 1100 | F40: =+'2025 Detail'!S40 -> 12500 | H40: =+'2026 Detail'!P40 -> 6000 | I40: =+'2026 Detail'!Q40 -> 5000 | J40: =+'2026 Detail'!R40 -> 5000 | K40: =+'2026 Detail'!S40 -> 5000 | M40: =SUM(C40:F40) -> 36370 | N40: =SUM(H40:K40) -> 21000 | P40: =+M40-N40 -> 15370 | Q40: =+P40/M40 -> 0.42260104 | S40: =+M40-'2025 Detail'!U40 -> 0 | T40: =+N40-'2026 Detail'!U40 -> 0
B41: Professional Fees | C41: =+'2025 Detail'!P41 -> 63750 | D41: =+'2025 Detail'!Q41 -> 25000 | E41: =+'2025 Detail'!R41 -> 0 | F41: =+'2025 Detail'!S41 -> 35000 | H41: =+'2026 Detail'!P41 -> 15000 | I41: =+'2026 Detail'!Q41 -> 15000 | J41: =+'2026 Detail'!R41 -> 15000 | K41: =+'2026 Detail'!S41 -> 15000 | M41: =SUM(C41:F41) -> 123750 | N41: =SUM(H41:K41) -> 60000 | P41: =+M41-N41 -> 63750 | Q41: =+P41/M41 -> 0.51515152 | S41: =+M41-'2025 Detail'!U41 -> 0 | T41: =+N41-'2026 Detail'!U41 -> 0
B42: Taxes, Licenses & Permits | C42: =+'2025 Detail'!P42 -> 4036 | D42: =+'2025 Detail'!Q42 -> -110.17 | E42: =+'2025 Detail'!R42 -> 80.92 | F42: =+'2025 Detail'!S42 -> 438.43 | H42: =+'2026 Detail'!P42 -> 750 | I42: =+'2026 Detail'!Q42 -> 750 | J42: =+'2026 Detail'!R42 -> 750 | K42: =+'2026 Detail'!S42 -> 750 | M42: =SUM(C42:F42) -> 4445.18 | N42: =SUM(H42:K42) -> 3000 | P42: =+M42-N42 -> 1445.18 | Q42: =+P42/M42 -> 0.32511169 | S42: =+M42-'2025 Detail'!U42 -> 0 | T42: =+N42-'2026 Detail'!U42 -> 0
B43: Travel & Meals | C43: =+'2025 Detail'!P43 -> 27924.02 | D43: =+'2025 Detail'!Q43 -> 72052.59 | E43: =+'2025 Detail'!R43 -> 62980.77 | F43: =+'2025 Detail'!S43 -> 42706.5 | H43: =+'2026 Detail'!P43 -> 45000 | I43: =+'2026 Detail'!Q43 -> 45000 | J43: =+'2026 Detail'!R43 -> 45000 | K43: =+'2026 Detail'!S43 -> 45000 | M43: =SUM(C43:F43) -> 205663.88 | N43: =SUM(H43:K43) -> 180000 | P43: =+M43-N43 -> 25663.88 | Q43: =+P43/M43 -> 0.12478555 | S43: =+M43-'2025 Detail'!U43 -> 0 | T43: =+N43-'2026 Detail'!U43 -> 0
B44: Total Other Spend | C44: =SUM(C35:C43) -> 175067.06 | D44: =SUM(D35:D43) -> 262969.51 | E44: =SUM(E35:E43) -> 235047.14 | F44: =SUM(F35:F43) -> 186342.65 | H44: =SUM(H35:H43) -> 151400.95 | I44: =SUM(I35:I43) -> 184586.11 | J44: =SUM(J35:J43) -> 243740 | K44: =SUM(K35:K43) -> 163777.32 | M44: =SUM(M35:M43) -> 859426.36 | N44: =SUM(N35:N43) -> 743504.38 | P44: =+M44-N44 -> 115921.98 | Q44: =+P44/M44 -> 0.13488296 | S44: =+M44-'2025 Detail'!U44 -> 0 | T44: =+N44-'2026 Detail'!U44 -> 0
B46: Total Cash Disbursements | C46: =+C21+C29+C33+C44 -> 1870253.3 | D46: =+D21+D29+D33+D44 -> 1800913.7 | E46: =+E21+E29+E33+E44 -> 1692622.3 | F46: =+F21+F29+F33+F44 -> 1512024.1 | H46: =+H21+H29+H33+H44 -> 1843731.5 | I46: =+I21+I29+I33+I44 -> 1412517 | J46: =+J21+J29+J33+J44 -> 1450670.9 | K46: =+K21+K29+K33+K44 -> 1357208.2 | M46: =+M21+M29+M33+M44 -> 6875813.4 | N46: =+N21+N29+N33+N44 -> 6064127.7 | P46: =+M46-N46 -> 811685.74 | Q46: =+P46/M46 -> 0.11804941 | S46: =+M46-'2025 Detail'!U46 -> 0 | T46: =+N46-'2026 Detail'!U46 -> 0
B48: Guarenteed Payments | C48: =+'2025 Detail'!P48 -> 0 | D48: =+'2025 Detail'!Q48 -> 0 | E48: =+'2025 Detail'!R48 -> 0 | F48: =+'2025 Detail'!S48 -> 0 | H48: =+'2026 Detail'!P48 -> 0 | I48: =+'2026 Detail'!Q48 -> 0 | J48: =+'2026 Detail'!R48 -> 0 | K48: =+'2026 Detail'!S48 -> 0 | M48: =SUM(C48:F48) -> 0 | N48: =SUM(H48:K48) -> 0 | P48: =+N48-M48 -> 0 | Q48: =IFERROR(+P48/ABS(M48),0) -> 0 | S48: =+M48-'2025 Detail'!U48 -> 0 | T48: =+N48-'2026 Detail'!U48 -> 0
B49: Youreka Labs Inc | C49: =+'2025 Detail'!P49 -> 0 | D49: =+'2025 Detail'!Q49 -> 0 | E49: =+'2025 Detail'!R49 -> 0 | F49: =+'2025 Detail'!S49 -> 0 | H49: =+'2026 Detail'!P49 -> 0 | I49: =+'2026 Detail'!Q49 -> 0 | J49: =+'2026 Detail'!R49 -> 0 | K49: =+'2026 Detail'!S49 -> 0 | M49: =SUM(C49:F49) -> 0 | N49: =SUM(H49:K49) -> 0 | P49: =+N49-M49 -> 0 | Q49: =IFERROR(+P49/ABS(M49),0) -> 0 | S49: =+M49-'2025 Detail'!U49 -> 0 | T49: =+N49-'2026 Detail'!U49 -> 0
B50: Brex | C50: =+'2025 Detail'!P50 -> -15247.08 | D50: =+'2025 Detail'!Q50 -> -7164.46 | E50: =+'2025 Detail'!R50 -> -183.94 | F50: =+'2025 Detail'!S50 -> 0 | H50: =+'2026 Detail'!P50 -> 0 | I50: =+'2026 Detail'!Q50 -> 0 | J50: =+'2026 Detail'!R50 -> 0 | K50: =+'2026 Detail'!S50 -> 0 | M50: =SUM(C50:F50) -> -22595.48 | N50: =SUM(H50:K50) -> 0 | P50: =+N50-M50 -> 22595.48 | Q50: =IFERROR(+P50/ABS(M50),0) -> 1 | S50: =+M50-'2025 Detail'!U50 -> 0 | T50: =+N50-'2026 Detail'!U50 -> 0
B51: Chase Visa | C51: =+'2025 Detail'!P51 -> -1010.7 | D51: =+'2025 Detail'!Q51 -> -5131.26 | E51: =+'2025 Detail'!R51 -> -1231.85 | F51: =+'2025 Detail'!S51 -> 0 | H51: =+'2026 Detail'!P51 -> 0 | I51: =+'2026 Detail'!Q51 -> 0 | J51: =+'2026 Detail'!R51 -> 0 | K51: =+'2026 Detail'!S51 -> 0 | M51: =SUM(C51:F51) -> -7373.81 | N51: =SUM(H51:K51) -> 0 | P51: =+N51-M51 -> 7373.81 | Q51: =IFERROR(+P51/ABS(M51),0) -> 1 | S51: =+M51-'2025 Detail'!U51 -> 0 | T51: =+N51-'2026 Detail'!U51 -> 0
B52: Ramp | C52: =+'2025 Detail'!P52 -> 0 | D52: =+'2025 Detail'!Q52 -> 0 | E52: =+'2025 Detail'!R52 -> 0 | F52: =+'2025 Detail'!S52 -> 0 | H52: =+'2026 Detail'!P52 -> 0 | I52: =+'2026 Detail'!Q52 -> 0 | J52: =+'2026 Detail'!R52 -> 0 | K52: =+'2026 Detail'!S52 -> 0 | M52: =SUM(C52:F52) -> 0 | N52: =SUM(H52:K52) -> 0 | P52: =+N52-M52 -> 0 | Q52: =IFERROR(+P52/ABS(M52),0) -> 0 | S52: =+M52-'2025 Detail'!U52 -> 0 | T52: =+N52-'2026 Detail'!U52 -> 0
B53: Bank Fees | C53: =+'2025 Detail'!P53 -> -1151.07 | D53: =+'2025 Detail'!Q53 -> -1367.77 | E53: =+'2025 Detail'!R53 -> -1045.49 | F53: =+'2025 Detail'!S53 -> -1052.45 | H53: =+'2026 Detail'!P53 -> -1200 | I53: =+'2026 Detail'!Q53 -> -1200 | J53: =+'2026 Detail'!R53 -> -1200 | K53: =+'2026 Detail'!S53 -> -1200 | M53: =SUM(C53:F53) -> -4616.78 | N53: =SUM(H53:K53) -> -4800 | P53: =+N53-M53 -> -183.22 | Q53: =IFERROR(+P53/ABS(M53),0) -> -0.039685668 | S53: =+M53-'2025 Detail'!U53 -> 0 | T53: =+N53-'2026 Detail'!U53 -> 0
B54: Interest | C54: =+'2025 Detail'!P54 -> 24245.22 | D54: =+'2025 Detail'!Q54 -> 16004.6 | E54: =+'2025 Detail'!R54 -> 6388.96 | F54: =+'2025 Detail'!S54 -> 1225.61 | H54: =+'2026 Detail'!P54 -> 1000 | I54: =+'2026 Detail'!Q54 -> 700 | J54: =+'2026 Detail'!R54 -> 600 | K54: =+'2026 Detail'!S54 -> 900 | M54: =SUM(C54:F54) -> 47864.39 | N54: =SUM(H54:K54) -> 3200 | P54: =+N54-M54 -> -44664.39 | Q54: =IFERROR(+P54/ABS(M54),0) -> -0.93314445 | S54: =+M54-'2025 Detail'!U54 -> 0 | T54: =+N54-'2026 Detail'!U54 -> 0
B56: Opening Cash Balance | C56: =+'2025 Detail'!C56 -> 3334341 | D56: =+C61 -> 3325973 | E56: =+D61 -> 2023283 | F56: =+E61 -> 954186 | H56: =+F61 -> 964111 | I56: =+H61 -> 393009 | J56: =+I61 -> 404865 | K56: =+J61 -> 470302 | M56: =+C56 -> 3334341 | N56: =+M61 -> 964111
B58: Net Change | C58: =C15-C46+SUM(C48:C54) -> -958366.51 | D58: =D15-D46+SUM(D48:D54) -> -1277690.1 | E58: =E15-E46+SUM(E48:E54) -> -1069097.5 | F58: =F15-F46+SUM(F48:F54) -> 34924.93 | H58: =H15-H46+SUM(H48:H54) -> -571101.74 | I58: =I15-I46+SUM(I48:I54) -> 11855.788 | J58: =J15-J46+SUM(J48:J54) -> 65436.7 | K58: =K15-K46+SUM(K48:K54) -> 539491.78 | M58: =M15-M46+SUM(M48:M54) -> -3270229.2 | N58: =N15-N46+SUM(N48:N54) -> 45682.528 | P58: =+N58-M58 -> 3315911.7 | Q58: =IFERROR(+P58/ABS(M58),0) -> 1.0139692 | S58: =+M58-'2025 Detail'!U58 -> 0 | T58: =+N58-'2026 Detail'!U58 -> 1.0477379e-09
B59: Investment | C59: =+'2025 Detail'!P59 -> 949998.86 | D59: =+'2025 Detail'!Q59 -> -25000 | E59: =+'2025 Detail'!R59 -> 0 | F59: =+'2025 Detail'!S59 -> -25000 | H59: =+'2026 Detail'!P59 -> 0 | I59: =+'2026 Detail'!Q59 -> 0 | J59: =+'2026 Detail'!R59 -> 0 | K59: =+'2026 Detail'!S59 -> 0 | M59: =SUM(C59:F59) -> 899998.86 | N59: =SUM(H59:K59) -> 0 | P59: =+N59-M59 -> -899998.86 | Q59: =IFERROR(+P59/ABS(M59),0) -> -1 | S59: =+M59-'2025 Detail'!U59 -> 0 | T59: =+N59-'2026 Detail'!U59 -> 0
B61: Ending Cash Balance | C61: =ROUND(+C56+C58+C59,0) -> 3325973 | D61: =ROUND(+D56+D58+D59,0) -> 2023283 | E61: =ROUND(+E56+E58+E59,0) -> 954186 | F61: =ROUND(+F56+F58+F59,0) -> 964111 | H61: =ROUND(+H56+H58+H59,0) -> 393009 | I61: =ROUND(+I56+I58+I59,0) -> 404865 | J61: =ROUND(+J56+J58+J59,0) -> 470302 | K61: =ROUND(+K56+K58+K59,0) -> 1009794 | M61: =ROUND(+M56+M58+M59,0) -> 964111 | N61: =ROUND(+N56+N58+N59,0) -> 1009794
B63: Cash In | C63: =+C15 -> 905050.44 | D63: =+D15 -> 520882.5 | E63: =+E15 -> 619597.1 | F63: =+F15 -> 1546775.9 | H63: =+H15 -> 1272829.8 | I63: =+I15 -> 1424872.8 | J63: =+J15 -> 1516707.6 | K63: =+K15 -> 1897000 | M63: =+M15 -> 3592305.9 | N63: =+N15 -> 6111410.2
B64: Calculated COGS | C64: =SUM(C17:C18,C23:C24) -> 834144.13 | D64: =SUM(D17:D18,D23:D24) -> 576858.66 | E64: =SUM(E17:E18,E23:E24) -> 562447.14 | F64: =SUM(F17:F18,F23:F24) -> 584581.13 | H64: =SUM(H17:H18,H23:H24) -> 761984.85 | I64: =SUM(I17:I18,I23:I24) -> 575315.4 | J64: =SUM(J17:J18,J23:J24) -> 555815.4 | K64: =SUM(K17:K18,K23:K24) -> 542315.4 | M64: =SUM(M17:M18,M23:M24) -> 2558031.1 | N64: =SUM(N17:N18,N23:N24) -> 2435431
B65: Gross Margin | C65: =+C63-C64 -> 70906.308 | D65: =+D63-D64 -> -55976.161 | E65: =+E63-E64 -> 57149.956 | F65: =+F63-F64 -> 962194.77 | H65: =+H63-H64 -> 510844.95 | I65: =+I63-I64 -> 849557.4 | J65: =+J63-J64 -> 960892.2 | K65: =+K63-K64 -> 1354684.6 | M65: =+M63-M64 -> 1034274.9 | N65: =+N63-N64 -> 3675979.2
B66: GM % | C66: =+C65/C63 -> 0.078345146 | D66: =+D65/D63 -> -0.10746408 | E66: =+E65/E63 -> 0.092237288 | F66: =+F65/F63 -> 0.62206476 | H66: =+H65/H63 -> 0.40134584 | I66: =+I65/I63 -> 0.59623385 | J66: =+J65/J63 -> 0.6335382 | K66: =+K65/K63 -> 0.71411945 | M66: =+M65/M63 -> 0.28791392 | N66: =+N65/N63 -> 0.60149442
B69: M&T Operating
B70: M&T IntraFi Network Sweep
B71: Ramp Credit Card
B73: Check

Sheet 2025 Summary
B2: SYNAPTIC CASH FLOW FORECAST | C2: 45658 | D2: =EDATE(C2,1) -> 45689 | E2: =EDATE(D2,1) -> 45717 | F2: =EDATE(E2,1) -> 45748 | G2: =EDATE(F2,1) -> 45778 | H2: =EDATE(G2,1) -> 45809 | I2: =EDATE(H2,1) -> 45839 | J2: =EDATE(I2,1) -> 45870 | K2: =EDATE(J2,1) -> 45901 | ... N2: =EDATE(M2,1) -> 45992 | P2: Q1 | Q2: Q2 | R2: Q3 | S2: Q4 | U2: 2025 | W2: Check
B3: =+Version!$C$3 -> Y2025 12 v001
B5: Consulting - Classic | C5: =+'2025 Detail'!C8 -> 276138.86 | D5: =+'2025 Detail'!D8 -> 303659.1 | E5: =+'2025 Detail'!E8 -> 148959.5 | F5: =+'2025 Detail'!F8 -> 175655.2 | G5: =+'2025 Detail'!G8 -> 192782.4 | H5: =+'2025 Detail'!H8 -> 75752.9 | I5: =+'2025 Detail'!I8 -> 256181 | J5: =+'2025 Detail'!J8 -> 104161 | ... N5: =+'2025 Detail'!N8 -> 335155 | P5: =SUM(C5:E5) -> 728757.46 | Q5: =SUM(F5:H5) -> 444190.5 | R5: =SUM(I5:K5) -> 447319.5 | S5: =SUM(L5:N5) -> 766915.5 | U5: =SUM(C5:N5) -> 2387183 | W5: =ROUND(SUM(P5:S5)-U5,2) -> 0
B6: Consulting - AppIQ | C6: =+'2025 Detail'!C13 -> 0 | D6: =+'2025 Detail'!D13 -> 50000 | E6: =+'2025 Detail'!E13 -> 126292.98 | F6: =+'2025 Detail'!F13 -> 36377.5 | G6: =+'2025 Detail'!G13 -> 0 | H6: =+'2025 Detail'!H13 -> 40314.5 | I6: =+'2025 Detail'!I13 -> 69000 | J6: =+'2025 Detail'!J13 -> 81277.6 | ... N6: =+'2025 Detail'!N13 -> 512777.6 | P6: =SUM(C6:E6) -> 176292.98 | Q6: =SUM(F6:H6) -> 76692 | R6: =SUM(I6:K6) -> 172277.6 | S6: =SUM(L6:N6) -> 779860.4 | U6: =SUM(C6:N6) -> 1205123 | W6: =ROUND(SUM(P6:S6)-U6,2) -> 0
B8: Total Cash Collected | C8: =SUM(C5:C6) -> 276138.86 | D8: =SUM(D5:D6) -> 353659.1 | E8: =SUM(E5:E6) -> 275252.48 | F8: =SUM(F5:F6) -> 212032.7 | G8: =SUM(G5:G6) -> 192782.4 | H8: =SUM(H5:H6) -> 116067.4 | I8: =SUM(I5:I6) -> 325181 | J8: =SUM(J5:J6) -> 185438.6 | ... N8: =SUM(N5:N6) -> 847932.6 | P8: =SUM(P5:P6) -> 905050.44 | Q8: =SUM(Q5:Q6) -> 520882.5 | R8: =SUM(R5:R6) -> 619597.1 | S8: =SUM(S5:S6) -> 1546775.9 | U8: =SUM(U5:U6) -> 3592305.9 | W8: =ROUND(SUM(P8:S8)-U8,2) -> 0
B10: Delivery | C10: =+'2025 Detail'!C17+'2025 Detail'!C18 -> 237094.69 | D10: =+'2025 Detail'!D17+'2025 Detail'!D18 -> 373512.69 | E10: =+'2025 Detail'!E17+'2025 Detail'!E18 -> 221376.76 | F10: =+'2025 Detail'!F17+'2025 Detail'!F18 -> 184839.78 | G10: =+'2025 Detail'!G17+'2025 Detail'!G18 -> 188333.05 | H10: =+'2025 Detail'!H17+'2025 Detail'!H18 -> 188584.83 | I10: =+'2025 Detail'!I17+'2025 Detail'!I18 -> 175141.92 | J10: =+'2025 Detail'!J17+'2025 Detail'!J18 -> 174584.84 | ... N10: =+'2025 Detail'!N17+'2025 Detail'!N18 -> 184010 | P10: =SUM(C10:E10) -> 831984.13 | Q10: =SUM(F10:H10) -> 561757.66 | R10: =SUM(I10:K10) -> 527440.14 | S10: =SUM(L10:N10) -> 562389.13 | U10: =SUM(C10:N10) -> 2483571.1 | W10: =ROUND(SUM(P10:S10)-U10,2) -> 0
B11: GTM | C11: =+'2025 Detail'!C19+'2025 Detail'!C20 -> 52563.352 | D11: =+'2025 Detail'!D19+'2025 Detail'!D20 -> 85453.686 | E11: =+'2025 Detail'!E19+'2025 Detail'!E20 -> 54727.353 | F11: =+'2025 Detail'!F19+'2025 Detail'!F20 -> 52144.619 | G11: =+'2025 Detail'!G19+'2025 Detail'!G20 -> 52637.907 | H11: =+'2025 Detail'!H19+'2025 Detail'!H20 -> 53437.228 | I11: =+'2025 Detail'!I19+'2025 Detail'!I20 -> 48525.576 | J11: =+'2025 Detail'!J19+'2025 Detail'!J20 -> 40196.537 | ... N11: =+'2025 Detail'!N19+'2025 Detail'!N20 -> 40600 | P11: =SUM(C11:E11) -> 192744.39 | Q11: =SUM(F11:H11) -> 158219.75 | R11: =SUM(I11:K11) -> 128181.18 | S11: =SUM(L11:N11) -> 119549.89 | U11: =SUM(C11:N11) -> 598695.22 | W11: =ROUND(SUM(P11:S11)-U11,2) -> 0
B12: Total Spend Classic | C12: =SUM(C10:C11) -> 289658.04 | D12: =SUM(D10:D11) -> 458966.37 | E12: =SUM(E10:E11) -> 276104.11 | F12: =SUM(F10:F11) -> 236984.4 | G12: =SUM(G10:G11) -> 240970.96 | H12: =SUM(H10:H11) -> 242022.06 | I12: =SUM(I10:I11) -> 223667.5 | J12: =SUM(J10:J11) -> 214781.38 | ... N12: =SUM(N10:N11) -> 224610 | P12: =SUM(P10:P11) -> 1024728.5 | Q12: =SUM(Q10:Q11) -> 719977.41 | R12: =SUM(R10:R11) -> 655621.33 | S12: =SUM(S10:S11) -> 681939.02 | U12: =SUM(U10:U11) -> 3082266.3 | W12: =ROUND(SUM(P12:S12)-U12,2) -> 0
B14: Delivery | C14: =+'2025 Detail'!C23+'2025 Detail'!C24 -> 0 | D14: =+'2025 Detail'!D23+'2025 Detail'!D24 -> 0 | E14: =+'2025 Detail'!E23+'2025 Detail'!E24 -> 2160 | F14: =+'2025 Detail'!F23+'2025 Detail'!F24 -> 3024 | G14: =+'2025 Detail'!G23+'2025 Detail'!G24 -> 3430 | H14: =+'2025 Detail'!H23+'2025 Detail'!H24 -> 8647 | I14: =+'2025 Detail'!I23+'2025 Detail'!I24 -> 12647 | J14: =+'2025 Detail'!J23+'2025 Detail'!J24 -> 11548 | ... N14: =+'2025 Detail'!N23+'2025 Detail'!N24 -> 10600 | P14: =SUM(C14:E14) -> 2160 | Q14: =SUM(F14:H14) -> 15101 | R14: =SUM(I14:K14) -> 35007 | S14: =SUM(L14:N14) -> 22192 | U14: =SUM(C14:N14) -> 74460 | W14: =ROUND(SUM(P14:S14)-U14,2) -> 0
B15: GTM | C15: =+'2025 Detail'!C25+'2025 Detail'!C26 -> 25440.49 | D15: =+'2025 Detail'!D25+'2025 Detail'!D26 -> 54928.6 | E15: =+'2025 Detail'!E25+'2025 Detail'!E26 -> 71765.61 | F15: =+'2025 Detail'!F25+'2025 Detail'!F26 -> 109403.48 | G15: =+'2025 Detail'!G25+'2025 Detail'!G26 -> 91516.151 | H15: =+'2025 Detail'!H25+'2025 Detail'!H26 -> 75285.972 | I15: =+'2025 Detail'!I25+'2025 Detail'!I26 -> 143725.31 | J15: =+'2025 Detail'!J25+'2025 Detail'!J26 -> 47373.468 | ... N15: =+'2025 Detail'!N25+'2025 Detail'!N26 -> 80550 | P15: =SUM(C15:E15) -> 152134.7 | Q15: =SUM(F15:H15) -> 276205.6 | R15: =SUM(I15:K15) -> 226080.96 | S15: =SUM(L15:N15) -> 151567.38 | U15: =SUM(C15:N15) -> 805988.64 | W15: =ROUND(SUM(P15:S15)-U15,2) -> 0
B16: R&D | C16: =+'2025 Detail'!C27+'2025 Detail'!C28 -> 67048.031 | D16: =+'2025 Detail'!D27+'2025 Detail'!D28 -> 80129.362 | E16: =+'2025 Detail'!E27+'2025 Detail'!E28 -> 91822.045 | F16: =+'2025 Detail'!F27+'2025 Detail'!F28 -> 92862.959 | G16: =+'2025 Detail'!G27+'2025 Detail'!G28 -> 94487.781 | H16: =+'2025 Detail'!H27+'2025 Detail'!H28 -> 105814.21 | I16: =+'2025 Detail'!I27+'2025 Detail'!I28 -> 108222.56 | J16: =+'2025 Detail'!J27+'2025 Detail'!J28 -> 111190.82 | ... N16: =+'2025 Detail'!N27+'2025 Detail'!N28 -> 60761.95 | P16: =SUM(C16:E16) -> 238999.44 | Q16: =SUM(F16:H16) -> 293164.95 | R16: =SUM(I16:K16) -> 304995.69 | S16: =SUM(L16:N16) -> 260047.26 | U16: =SUM(C16:N16) -> 1097207.3 | W16: =ROUND(SUM(P16:S16)-U16,2) -> 0
B17: Total Spend AppIQ | C17: =SUM(C14:C16) -> 92488.521 | D17: =SUM(D14:D16) -> 135057.96 | E17: =SUM(E14:E16) -> 165747.66 | F17: =SUM(F14:F16) -> 205290.43 | G17: =SUM(G14:G16) -> 189433.93 | H17: =SUM(H14:H16) -> 189747.18 | I17: =SUM(I14:I16) -> 264594.86 | J17: =SUM(J14:J16) -> 170112.28 | ... N17: =SUM(N14:N16) -> 151911.95 | P17: =SUM(P14:P16) -> 393294.14 | Q17: =SUM(Q14:Q16) -> 584471.55 | R17: =SUM(R14:R16) -> 566083.65 | S17: =SUM(S14:S16) -> 433806.64 | U17: =SUM(U14:U16) -> 1977656 | W17: =ROUND(SUM(P17:S17)-U17,2) -> 0
B19: Back Office | C19: =+'2025 Detail'!C33 -> 73639.481 | D19: =+'2025 Detail'!D33 -> 121103.33 | E19: =+'2025 Detail'!E33 -> 82420.785 | F19: =+'2025 Detail'!F33 -> 78711.866 | G19: =+'2025 Detail'!G33 -> 77283.821 | H19: =+'2025 Detail'!H33 -> 77499.542 | I19: =+'2025 Detail'!I33 -> 80961.528 | J19: =+'2025 Detail'!J33 -> 77064.908 | ... N19: =+'2025 Detail'!N33 -> 66550 | P19: =SUM(C19:E19) -> 277163.6 | Q19: =SUM(F19:H19) -> 233495.23 | R19: =SUM(I19:K19) -> 235870.15 | S19: =SUM(L19:N19) -> 209935.82 | U19: =SUM(C19:N19) -> 956464.79 | W19: =ROUND(SUM(P19:S19)-U19,2) -> 0
B20: Total Spend Back Office | C20: =SUM(C19:C19) -> 73639.481 | D20: =SUM(D19:D19) -> 121103.33 | E20: =SUM(E19:E19) -> 82420.785 | F20: =SUM(F19:F19) -> 78711.866 | G20: =SUM(G19:G19) -> 77283.821 | H20: =SUM(H19:H19) -> 77499.542 | I20: =SUM(I19:I19) -> 80961.528 | J20: =SUM(J19:J19) -> 77064.908 | ... N20: =SUM(N19:N19) -> 66550 | P20: =SUM(P19:P19) -> 277163.6 | Q20: =SUM(Q19:Q19) -> 233495.23 | R20: =SUM(R19:R19) -> 235870.15 | S20: =SUM(S19:S19) -> 209935.82 | U20: =SUM(U19:U19) -> 956464.79 | W20: =ROUND(SUM(P20:S20)-U20,2) -> 0
B22: Rent | C22: =+'2025 Detail'!C35 -> 0 | D22: =+'2025 Detail'!D35 -> 0 | E22: =+'2025 Detail'!E35 -> 0 | F22: =+'2025 Detail'!F35 -> 0 | G22: =+'2025 Detail'!G35 -> 3545.63 | H22: =+'2025 Detail'!H35 -> 3545.63 | I22: =+'2025 Detail'!I35 -> 7091.26 | J22: =+'2025 Detail'!J35 -> 3545.63 | ... N22: =+'2025 Detail'!N35 -> 3550 | P22: =SUM(C22:E22) -> 0 | Q22: =SUM(F22:H22) -> 7091.26 | R22: =SUM(I22:K22) -> 14182.52 | S22: =SUM(L22:N22) -> 10641.26 | U22: =SUM(C22:N22) -> 31915.04 | W22: =ROUND(SUM(P22:S22)-U22,2) -> 0
B23: Hardware & Software | C23: =+'2025 Detail'!C36 -> 3866.9 | D23: =+'2025 Detail'!D36 -> 4575.9 | E23: =+'2025 Detail'!E36 -> 12536.15 | F23: =+'2025 Detail'!F36 -> 11114.35 | G23: =+'2025 Detail'!G36 -> 24774.02 | H23: =+'2025 Detail'!H36 -> 23118.32 | I23: =+'2025 Detail'!I36 -> 22036.41 | J23: =+'2025 Detail'!J36 -> 91840.73 | ... N23: =+'2025 Detail'!N36 -> 12000 | P23: =SUM(C23:E23) -> 20978.95 | Q23: =SUM(F23:H23) -> 59006.69 | R23: =SUM(I23:K23) -> 124166.61 | S23: =SUM(L23:N23) -> 48307.86 | U23: =SUM(C23:N23) -> 252460.11 | W23: =ROUND(SUM(P23:S23)-U23,2) -> 0
B24: Office & Supplies | C24: =+'2025 Detail'!C37 -> 263.76 | D24: =+'2025 Detail'!D37 -> 807.23 | E24: =+'2025 Detail'!E37 -> 556.56 | F24: =+'2025 Detail'!F37 -> 556 | G24: =+'2025 Detail'!G37 -> 354.79 | H24: =+'2025 Detail'!H37 -> 1130.57 | I24: =+'2025 Detail'!I37 -> 355.28 | J24: =+'2025 Detail'!J37 -> 1606.02 | ... N24: =+'2025 Detail'!N37 -> 500 | P24: =SUM(C24:E24) -> 1627.55 | Q24: =SUM(F24:H24) -> 2041.36 | R24: =SUM(I24:K24) -> 3176.35 | S24: =SUM(L24:N24) -> 5020.86 | U24: =SUM(C24:N24) -> 11866.12 | W24: =ROUND(SUM(P24:S24)-U24,2) -> 0
B25: Insurance | C25: =+'2025 Detail'!C38 -> 496.97 | D25: =+'2025 Detail'!D38 -> 8280.18 | E25: =+'2025 Detail'!E38 -> 3089.89 | F25: =+'2025 Detail'!F38 -> 8984.89 | G25: =+'2025 Detail'!G38 -> 1547.55 | H25: =+'2025 Detail'!H38 -> 3039.49 | I25: =+'2025 Detail'!I38 -> 5580.24 | J25: =+'2025 Detail'!J38 -> 1783.24 | ... N25: =+'2025 Detail'!N38 -> 2500 | P25: =SUM(C25:E25) -> 11867.04 | Q25: =SUM(F25:H25) -> 13571.93 | R25: =SUM(I25:K25) -> 10402.97 | S25: =SUM(L25:N25) -> 10101.04 | U25: =SUM(C25:N25) -> 45942.98 | W25: =ROUND(SUM(P25:S25)-U25,2) -> 0
B26: Legal Fees | C26: =+'2025 Detail'!C39 -> 10550 | D26: =+'2025 Detail'!D39 -> 15467.5 | E26: =+'2025 Detail'!E39 -> 18866 | F26: =+'2025 Detail'!F39 -> 28130 | G26: =+'2025 Detail'!G39 -> 23029.4 | H26: =+'2025 Detail'!H39 -> 10386.45 | I26: =+'2025 Detail'!I39 -> 9005.5 | J26: =+'2025 Detail'!J39 -> 1950.5 | ... N26: =+'2025 Detail'!N39 -> 11000 | P26: =SUM(C26:E26) -> 44883.5 | Q26: =SUM(F26:H26) -> 61545.85 | R26: =SUM(I26:K26) -> 18957 | S26: =SUM(L26:N26) -> 21626.7 | U26: =SUM(C26:N26) -> 147013.05 | W26: =ROUND(SUM(P26:S26)-U26,2) -> 0
B27: Accounting & Tax Fees | C27: =+'2025 Detail'!C40 -> 0 | D27: =+'2025 Detail'!D40 -> 0 | E27: =+'2025 Detail'!E40 -> 0 | F27: =+'2025 Detail'!F40 -> 0 | G27: =+'2025 Detail'!G40 -> 22482.5 | H27: =+'2025 Detail'!H40 -> 287.5 | I27: =+'2025 Detail'!I40 -> 535 | J27: =+'2025 Detail'!J40 -> 0 | ... N27: =+'2025 Detail'!N40 -> 12500 | P27: =SUM(C27:E27) -> 0 | Q27: =SUM(F27:H27) -> 22770 | R27: =SUM(I27:K27) -> 1100 | S27: =SUM(L27:N27) -> 12500 | U27: =SUM(C27:N27) -> 36370 | W27: =ROUND(SUM(P27:S27)-U27,2) -> 0
B28: Professional Fees | C28: =+'2025 Detail'!C41 -> 0 | D28: =+'2025 Detail'!D41 -> 0 | E28: =+'2025 Detail'!E41 -> 63750 | F28: =+'2025 Detail'!F41 -> 0 | G28: =+'2025 Detail'!G41 -> 25000 | H28: =+'2025 Detail'!H41 -> 0 | I28: =+'2025 Detail'!I41 -> 0 | J28: =+'2025 Detail'!J41 -> 0 | ... N28: =+'2025 Detail'!N41 -> 35000 | P28: =SUM(C28:E28) -> 63750 | Q28: =SUM(F28:H28) -> 25000 | R28: =SUM(I28:K28) -> 0 | S28: =SUM(L28:N28) -> 35000 | U28: =SUM(C28:N28) -> 123750 | W28: =ROUND(SUM(P28:S28)-U28,2) -> 0
B29: Taxes, Licenses & Permits | C29: =+'2025 Detail'!C42 -> 0 | D29: =+'2025 Detail'!D42 -> 0 | E29: =+'2025 Detail'!E42 -> 4036 | F29: =+'2025 Detail'!F42 -> 20 | G29: =+'2025 Detail'!G42 -> -326.17 | H29: =+'2025 Detail'!H42 -> 196 | I29: =+'2025 Detail'!I42 -> 112.92 | J29: =+'2025 Detail'!J42 -> 0 | ... N29: =+'2025 Detail'!N42 -> 250 | P29: =SUM(C29:E29) -> 4036 | Q29: =SUM(F29:H29) -> -110.17 | R29: =SUM(I29:K29) -> 80.92 | S29: =SUM(L29:N29) -> 438.43 | U29: =SUM(C29:N29) -> 4445.18 | W29: =ROUND(SUM(P29:S29)-U29,2) -> 0
B30: Travel & Meals | C30: =+'2025 Detail'!C43 -> 24863.58 | D30: =+'2025 Detail'!D43 -> 829.94 | E30: =+'2025 Detail'!E43 -> 2230.5 | F30: =+'2025 Detail'!F43 -> 13849.7 | G30: =+'2025 Detail'!G43 -> 20024.03 | H30: =+'2025 Detail'!H43 -> 38178.86 | I30: =+'2025 Detail'!I43 -> 9873.21 | J30: =+'2025 Detail'!J43 -> 21014.37 | ... N30: =+'2025 Detail'!N43 -> 8500 | P30: =SUM(C30:E30) -> 27924.02 | Q30: =SUM(F30:H30) -> 72052.59 | R30: =SUM(I30:K30) -> 62980.77 | S30: =SUM(L30:N30) -> 42706.5 | U30: =SUM(C30:N30) -> 205663.88 | W30: =ROUND(SUM(P30:S30)-U30,2) -> 0
B31: Total Other Spend | C31: =SUM(C22:C30) -> 40041.21 | D31: =SUM(D22:D30) -> 29960.75 | E31: =SUM(E22:E30) -> 105065.1 | F31: =SUM(F22:F30) -> 62654.94 | G31: =SUM(G22:G30) -> 120431.75 | H31: =SUM(H22:H30) -> 79882.82 | I31: =SUM(I22:I30) -> 54589.82 | J31: =SUM(J22:J30) -> 121740.49 | ... N31: =SUM(N22:N30) -> 85800 | P31: =SUM(P22:P30) -> 175067.06 | Q31: =SUM(Q22:Q30) -> 262969.51 | R31: =SUM(R22:R30) -> 235047.14 | S31: =SUM(S22:S30) -> 186342.65 | U31: =SUM(U22:U30) -> 859426.36 | W31: =ROUND(SUM(P31:S31)-U31,2) -> 0
B33: Total Cash Disbursements | C33: =+C12+C17+C20+C31 -> 495827.25 | D33: =+D12+D17+D20+D31 -> 745088.42 | E33: =+E12+E17+E20+E31 -> 629337.65 | F33: =+F12+F17+F20+F31 -> 583641.64 | G33: =+G12+G17+G20+G31 -> 628120.46 | H33: =+H12+H17+H20+H31 -> 589151.6 | I33: =+I12+I17+I20+I31 -> 623813.71 | J33: =+J12+J17+J20+J31 -> 583699.06 | ... N33: =+N12+N17+N20+N31 -> 528871.95 | P33: =+P12+P17+P20+P31 -> 1870253.3 | Q33: =+Q12+Q17+Q20+Q31 -> 1800913.7 | R33: =+R12+R17+R20+R31 -> 1692622.3 | S33: =+S12+S17+S20+S31 -> 1512024.1 | U33: =+U12+U17+U20+U31 -> 6875813.4 | W33: =ROUND(SUM(P33:S33)-U33,2) -> 0
B35: Guarenteed Payments | C35: =+'2025 Detail'!C48 -> 0 | D35: =+'2025 Detail'!D48 -> 0 | E35: =+'2025 Detail'!E48 -> 0 | F35: =+'2025 Detail'!F48 -> 0 | G35: =+'2025 Detail'!G48 -> 0 | H35: =+'2025 Detail'!H48 -> 0 | I35: =+'2025 Detail'!I48 -> 0 | J35: =+'2025 Detail'!J48 -> 0 | ... N35: =+'2025 Detail'!N48 -> 0 | P35: =SUM(C35:E35) -> 0 | Q35: =SUM(F35:H35) -> 0 | R35: =SUM(I35:K35) -> 0 | S35: =SUM(L35:N35) -> 0 | U35: =SUM(C35:N35) -> 0 | W35: =ROUND(SUM(P35:S35)-U35,2) -> 0
B36: Youreka Labs Inc | C36: =+'2025 Detail'!C49 -> 0 | D36: =+'2025 Detail'!D49 -> 0 | E36: =+'2025 Detail'!E49 -> 0 | F36: =+'2025 Detail'!F49 -> 0 | G36: =+'2025 Detail'!G49 -> 0 | H36: =+'2025 Detail'!H49 -> 0 | I36: =+'2025 Detail'!I49 -> 0 | J36: =+'2025 Detail'!J49 -> 0 | ... N36: =+'2025 Detail'!N49 -> 0 | P36: =SUM(C36:E36) -> 0 | Q36: =SUM(F36:H36) -> 0 | R36: =SUM(I36:K36) -> 0 | S36: =SUM(L36:N36) -> 0 | U36: =SUM(C36:N36) -> 0 | W36: =ROUND(SUM(P36:S36)-U36,2) -> 0
B37: Brex | C37: =+'2025 Detail'!C50 -> -5043.37 | D37: =+'2025 Detail'!D50 -> -5518.34 | E37: =+'2025 Detail'!E50 -> -4685.37 | F37: =+'2025 Detail'!F50 -> -3686.29 | G37: =+'2025 Detail'!G50 -> -2521.11 | H37: =+'2025 Detail'!H50 -> -957.06 | I37: =+'2025 Detail'!I50 -> -183.94 | J37: =+'2025 Detail'!J50 -> 0 | ... N37: =+'2025 Detail'!N50 -> 0 | P37: =SUM(C37:E37) -> -15247.08 | Q37: =SUM(F37:H37) -> -7164.46 | R37: =SUM(I37:K37) -> -183.94 | S37: =SUM(L37:N37) -> 0 | U37: =SUM(C37:N37) -> -22595.48 | W37: =ROUND(SUM(P37:S37)-U37,2) -> 0
B38: Chase Visa | C38: =+'2025 Detail'!C51 -> 0 | D38: =+'2025 Detail'!D51 -> -1010.7 | E38: =+'2025 Detail'!E51 -> 0 | F38: =+'2025 Detail'!F51 -> -1222.92 | G38: =+'2025 Detail'!G51 -> -2784.15 | H38: =+'2025 Detail'!H51 -> -1124.19 | I38: =+'2025 Detail'!I51 -> -1126.11 | J38: =+'2025 Detail'!J51 -> -105.74 | ... N38: =+'2025 Detail'!N51 -> 0 | P38: =SUM(C38:E38) -> -1010.7 | Q38: =SUM(F38:H38) -> -5131.26 | R38: =SUM(I38:K38) -> -1231.85 | S38: =SUM(L38:N38) -> 0 | U38: =SUM(C38:N38) -> -7373.81 | W38: =ROUND(SUM(P38:S38)-U38,2) -> 0
B39: Ramp | C39: =+'2025 Detail'!C52 -> 0 | D39: =+'2025 Detail'!D52 -> 0 | E39: =+'2025 Detail'!E52 -> 0 | F39: =+'2025 Detail'!F52 -> 0 | G39: =+'2025 Detail'!G52 -> 0 | H39: =+'2025 Detail'!H52 -> 0 | I39: =+'2025 Detail'!I52 -> 0 | J39: =+'2025 Detail'!J52 -> 0 | ... N39: =+'2025 Detail'!N52 -> 0 | P39: =SUM(C39:E39) -> 0 | Q39: =SUM(F39:H39) -> 0 | R39: =SUM(I39:K39) -> 0 | S39: =SUM(L39:N39) -> 0 | U39: =SUM(C39:N39) -> 0 | W39: =ROUND(SUM(P39:S39)-U39,2) -> 0
B40: Bank Fees | C40: =+'2025 Detail'!C53 -> -246.35 | D40: =+'2025 Detail'!D53 -> -433.54 | E40: =+'2025 Detail'!E53 -> -471.18 | F40: =+'2025 Detail'!F53 -> -346.98 | G40: =+'2025 Detail'!G53 -> -328.79 | H40: =+'2025 Detail'!H53 -> -692 | I40: =+'2025 Detail'!I53 -> -386.11 | J40: =+'2025 Detail'!J53 -> -335.21 | ... N40: =+'2025 Detail'!N53 -> -400 | P40: =SUM(C40:E40) -> -1151.07 | Q40: =SUM(F40:H40) -> -1367.77 | R40: =SUM(I40:K40) -> -1045.49 | S40: =SUM(L40:N40) -> -1052.45 | U40: =SUM(C40:N40) -> -4616.78 | W40: =ROUND(SUM(P40:S40)-U40,2) -> 0
B41: Interest | C41: =+'2025 Detail'!C54 -> 7748.71 | D41: =+'2025 Detail'!D54 -> 8351.29 | E41: =+'2025 Detail'!E54 -> 8145.22 | F41: =+'2025 Detail'!F54 -> 6912.1 | G41: =+'2025 Detail'!G54 -> 5204.78 | H41: =+'2025 Detail'!H54 -> 3887.72 | I41: =+'2025 Detail'!I54 -> 3150.25 | J41: =+'2025 Detail'!J54 -> 2155.66 | ... N41: =+'2025 Detail'!N54 -> 300 | P41: =SUM(C41:E41) -> 24245.22 | Q41: =SUM(F41:H41) -> 16004.6 | R41: =SUM(I41:K41) -> 6388.96 | S41: =SUM(L41:N41) -> 1225.61 | U41: =SUM(C41:N41) -> 47864.39 | W41: =ROUND(SUM(P41:S41)-U41,2) -> 0
B43: Opening Cash Balance | C43: =+'2025 Detail'!C56 -> 3334341 | D43: =+C48 -> 3317111 | E43: =+D48 -> 3677069.9 | F43: =+E48 -> 3325973.4 | G43: =+F48 -> 2956020.3 | H43: =+G48 -> 2520253 | I43: =+H48 -> 2023283.3 | J43: =+I48 -> 1726104.7 | K43: =+J48 -> 1329558.9 | ... N43: =+M48 -> 670150.08 | P43: =+C43 -> 3334341 | Q43: =+P48 -> 3325973 | R43: =+Q48 -> 2023283 | S43: =+R48 -> 954186 | U43: =+P43 -> 3334341
B45: Net Change | C45: =C8-C33+SUM(C35:C41) -> -217229.4 | D45: =D8-D33+SUM(D35:D41) -> -390040.61 | E45: =E8-E33+SUM(E35:E41) -> -351096.5 | F45: =F8-F33+SUM(F35:F41) -> -369953.03 | G45: =G8-G33+SUM(G35:G41) -> -435767.33 | H45: =H8-H33+SUM(H35:H41) -> -471969.73 | I45: =I8-I33+SUM(I35:I41) -> -297178.62 | J45: =J8-J33+SUM(J35:J41) -> -396545.75 | ... N45: =N8-N33+SUM(N35:N41) -> 318960.65 | P45: =SUM(C45:E45) -> -958366.51 | Q45: =SUM(F45:H45) -> -1277690.1 | R45: =SUM(I45:K45) -> -1069097.5 | S45: =SUM(L45:N45) -> 34924.93 | U45: =SUM(C45:N45) -> -3270229.1 | W45: =ROUND(SUM(P45:S45)-U45,2) -> 0
B46: Investment | C46: =+'2025 Detail'!C59 -> 199999.42 | D46: =+'2025 Detail'!D59 -> 749999.44 | E46: =+'2025 Detail'!E59 -> 0 | F46: =+'2025 Detail'!F59 -> 0 | G46: =+'2025 Detail'!G59 -> 0 | H46: =+'2025 Detail'!H59 -> -25000 | I46: =+'2025 Detail'!I59 -> 0 | J46: =+'2025 Detail'!J59 -> 0 | ... N46: =+'2025 Detail'!N59 -> -25000 | P46: =SUM(C46:E46) -> 949998.86 | Q46: =SUM(F46:H46) -> -25000 | R46: =SUM(I46:K46) -> 0 | S46: =SUM(L46:N46) -> -25000 | U46: =SUM(C46:N46) -> 899998.86 | W46: =ROUND(SUM(P46:S46)-U46,2) -> 0
B48: Ending Cash Balance | C48: =ROUND(+C43+C45+C46,2) -> 3317111 | D48: =ROUND(+D43+D45+D46,2) -> 3677069.9 | E48: =ROUND(+E43+E45+E46,2) -> 3325973.4 | F48: =ROUND(+F43+F45+F46,2) -> 2956020.3 | G48: =ROUND(+G43+G45+G46,2) -> 2520253 | H48: =ROUND(+H43+H45+H46,2) -> 2023283.3 | I48: =ROUND(+I43+I45+I46,2) -> 1726104.7 | J48: =ROUND(+J43+J45+J46,2) -> 1329558.9 | ... N48: =ROUND(+N43+N45+N46,2) -> 964110.73 | P48: =ROUND(+P43+P45+P46,0) -> 3325973 | Q48: =ROUND(+Q43+Q45+Q46,0) -> 2023283 | R48: =ROUND(+R43+R45+R46,0) -> 954186 | S48: =ROUND(+S43+S45+S46,0) -> 964111 | U48: =ROUND(+U43+U45+U46,0) -> 964111
B50: Cash In | C50: =+C8 -> 276138.86 | D50: =+D8 -> 353659.1 | E50: =+E8 -> 275252.48 | F50: =+F8 -> 212032.7 | G50: =+G8 -> 192782.4 | H50: =+H8 -> 116067.4 | I50: =+I8 -> 325181 | J50: =+J8 -> 185438.6 | ... N50: =+N8 -> 847932.6 | P50: =+P8 -> 905050.44 | Q50: =+Q8 -> 520882.5 | R50: =+R8 -> 619597.1 | S50: =+S8 -> 1546775.9 | U50: =+U8 -> 3592305.9
B51: Calculated COGS | C51: =+C10+C14 -> 237094.69 | D51: =+D10+D14 -> 373512.69 | E51: =+E10+E14 -> 223536.76 | F51: =+F10+F14 -> 187863.78 | G51: =+G10+G14 -> 191763.05 | H51: =+H10+H14 -> 197231.83 | I51: =+I10+I14 -> 187788.92 | J51: =+J10+J14 -> 186132.84 | ... N51: =+N10+N14 -> 194610 | P51: =+P10+P14 -> 834144.13 | Q51: =+Q10+Q14 -> 576858.66 | R51: =+R10+R14 -> 562447.14 | S51: =+S10+S14 -> 584581.13 | U51: =+U10+U14 -> 2558031.1
B52: Gross Margin | C52: =+C50-C51 -> 39044.174 | D52: =+D50-D51 -> -19853.588 | E52: =+E50-E51 -> 51715.722 | F52: =+F50-F51 -> 24168.919 | G52: =+G50-G51 -> 1019.3506 | H52: =+H50-H51 -> -81164.431 | I52: =+I50-I51 -> 137392.08 | J52: =+J50-J51 -> -694.24222 | ... N52: =+N50-N51 -> 653322.6 | P52: =+P50-P51 -> 70906.308 | Q52: =+Q50-Q51 -> -55976.161 | R52: =+R50-R51 -> 57149.956 | S52: =+S50-S51 -> 962194.77 | U52: =+U50-U51 -> 1034274.9
B53: GM % | C53: =+C52/C50 -> 0.14139326 | D53: =+D52/D50 -> -0.056137642 | E53: =+E52/E50 -> 0.18788467 | F53: =+F52/F50 -> 0.11398675 | G53: =+G52/G50 -> 0.005287571 | H53: =+H52/H50 -> -0.69928706 | I53: =+I52/I50 -> 0.42250955 | J53: =+J52/J50 -> -0.0037437849 | ... N53: =+N52/N50 -> 0.77048883 | P53: =+P52/P50 -> 0.078345146 | Q53: =+Q52/Q50 -> -0.10746408 | R53: =+R52/R50 -> 0.092237288 | S53: =+S52/S50 -> 0.62206476 | U53: =+U52/U50 -> 0.28791392
B55: Check | C55: =+C48-'2025 Detail'!C61 -> 0 | D55: =+D48-'2025 Detail'!D61 -> 0 | E55: =+E48-'2025 Detail'!E61 -> 0 | F55: =+F48-'2025 Detail'!F61 -> 0 | G55: =+G48-'2025 Detail'!G61 -> 0 | H55: =+H48-'2025 Detail'!H61 -> 0 | I55: =+I48-'2025 Detail'!I61 -> 0 | J55: =+J48-'2025 Detail'!J61 -> 0 | ... N55: =+N48-'2025 Detail'!N61 -> 0
B60: Plan Cash Out | C60: 493368.45 | D60: 622040 | E60: 947756.67 | F60: 607656.67 | G60: 581529.97 | H60: 632904.97 | I60: 616471.63 | J60: 694721.63 | K60: 643788.3 | L60: 560604.97 | M60: 580376.67 | N60: 623260 | P60: =SUM(C60:E60) -> 2063165.1 | Q60: =SUM(F60:H60) -> 1822091.6 | R60: =SUM(I60:K60) -> 1954981.6 | S60: =SUM(L60:N60) -> 1764241.6 | U60: =SUM(P60:S60) -> 7604479.9
B61: Actual & Forecast Cash Out | C61: =+C33-SUM(C35:C41) -> 493368.26 | D61: =+D33-SUM(D35:D41) -> 743699.71 | E61: =+E33-SUM(E35:E41) -> 626348.98 | F61: =+F33-SUM(F35:F41) -> 581985.73 | G61: =+G33-SUM(G35:G41) -> 628549.73 | H61: =+H33-SUM(H35:H41) -> 588037.13 | I61: =+I33-SUM(I35:I41) -> 622359.62 | J61: =+J33-SUM(J35:J41) -> 581984.35 | ... N61: =+N33-SUM(N35:N41) -> 528971.95 | P61: =SUM(C61:E61) -> 1863416.9 | Q61: =SUM(F61:H61) -> 1798572.6 | R61: =SUM(I61:K61) -> 1688694.6 | S61: =SUM(L61:N61) -> 1511851 | U61: =SUM(P61:S61) -> 6862535.1
B62: Delta vs Actual & Forecast | C62: =C60-C61 -> 0.19 | D62: =D60-D61 -> -121659.71 | E62: =E60-E61 -> 321407.69 | F62: =F60-F61 -> 25670.937 | G62: =G60-G61 -> -47019.763 | H62: =H60-H61 -> 44867.837 | I62: =I60-I61 -> -5887.9867 | J62: =J60-J61 -> 112737.28 | ... N62: =N60-N61 -> 94288.05 | P62: =SUM(C62:E62) -> 199748.17 | Q62: =SUM(F62:H62) -> 23519.01 | R62: =SUM(I62:K62) -> 266286.99 | S62: =SUM(L62:N62) -> 252390.66 | U62: =SUM(P62:S62) -> 741944.83
E63: =SUM(C62:E62) -> 199748.17 | H63: =SUM(F62:H62) -> 23519.01 | K63: =SUM(I62:K62) -> 266286.99 | N63: =SUM(L62:N62) -> 252390.66
B65: Plan Cash In | C65: 276138.46 | D65: 459359 | E65: 206789.93 | F65: 294789.93 | G65: 304289.93 | H65: 264089.93 | I65: 404089.93 | J65: 562006.6 | K65: 518673.27 | L65: 661173.27 | M65: 924839.93 | N65: 412339.93 | P65: =SUM(C65:E65) -> 942287.39 | Q65: =SUM(F65:H65) -> 863169.8 | R65: =SUM(I65:K65) -> 1484769.8 | S65: =SUM(L65:N65) -> 1998353.1 | U65: =SUM(P65:S65) -> 5288580.1
B66: Actual & Forecast Cash In | C66: =+C8 -> 276138.86 | D66: =+D8 -> 353659.1 | E66: =+E8 -> 275252.48 | F66: =+F8 -> 212032.7 | G66: =+G8 -> 192782.4 | H66: =+H8 -> 116067.4 | I66: =+I8 -> 325181 | J66: =+J8 -> 185438.6 | ... N66: =+N8 -> 847932.6 | P66: =SUM(C66:E66) -> 905050.44 | Q66: =SUM(F66:H66) -> 520882.5 | R66: =SUM(I66:K66) -> 619597.1 | S66: =SUM(L66:N66) -> 1546775.9 | U66: =SUM(P66:S66) -> 3592305.9
B67: Delta vs Actual & Forecast | C67: =C66-C65 -> 0.4 | D67: =D66-D65 -> -105699.9 | E67: =E66-E65 -> 68462.547 | F67: =F66-F65 -> -82757.233 | G67: =G66-G65 -> -111507.53 | H67: =H66-H65 -> -148022.53 | I67: =I66-I65 -> -78908.933 | J67: =J66-J65 -> -376568 | ... N67: =N66-N65 -> 435592.67 | P67: =SUM(C67:E67) -> -37236.953 | Q67: =SUM(F67:H67) -> -342287.3 | R67: =SUM(I67:K67) -> -865172.7 | S67: =SUM(L67:N67) -> -451577.23 | U67: =SUM(P67:S67) -> -1696274.2
E68: =SUM(C67:E67) -> -37236.953 | H68: =SUM(F67:H67) -> -342287.3 | K68: =SUM(I67:K67) -> -865172.7 | N68: =SUM(L67:N67) -> -451577.23
B70: Net Burn Plan | C70: =+C65-C60 -> -217229.99 | D70: =+D65-D60 -> -162681 | E70: =+E65-E60 -> -740966.73 | F70: =+F65-F60 -> -312866.73 | G70: =+G65-G60 -> -277240.03 | H70: =+H65-H60 -> -368815.03 | I70: =+I65-I60 -> -212381.7 | J70: =+J65-J60 -> -132715.03 | ... N70: =+N65-N60 -> -210920.07 | P70: =SUM(C70:E70) -> -1120877.7 | Q70: =SUM(F70:H70) -> -958921.8 | R70: =SUM(I70:K70) -> -470211.77 | S70: =SUM(L70:N70) -> 234111.5 | U70: =SUM(P70:S70) -> -2315899.8
B71: Net Burn Actual & Forecast | C71: =+C66-C61 -> -217229.4 | D71: =+D66-D61 -> -390040.61 | E71: =+E66-E61 -> -351096.5 | F71: =+F66-F61 -> -369953.03 | G71: =+G66-G61 -> -435767.33 | H71: =+H66-H61 -> -471969.73 | I71: =+I66-I61 -> -297178.62 | J71: =+J66-J61 -> -396545.75 | ... N71: =+N66-N61 -> 318960.65 | P71: =SUM(C71:E71) -> -958366.51 | Q71: =SUM(F71:H71) -> -1277690.1 | R71: =SUM(I71:K71) -> -1069097.5 | S71: =SUM(L71:N71) -> 34924.93 | U71: =SUM(P71:S71) -> -3270229.1
B72: Net Burn Delta | C72: =C62+C67 -> 0.59 | D72: =D71-D70 -> -227359.61 | E72: =E71-E70 -> 389870.23 | F72: =F62+F67 -> -57086.297 | G72: =G62+G67 -> -158527.3 | H72: =H62+H67 -> -103154.7 | I72: =I62+I67 -> -84796.92 | J72: =J62+J67 -> -263830.72 | K72: =K62+K67 -> -250258.08 | L72: =L62+L67 -> -318195.12 | M72: =M62+M67 -> -410872.17 | N72: =N62+N67 -> 529880.72 | P72: =SUM(C72:E72) -> 162511.21 | Q72: =SUM(F72:H72) -> -318768.29 | R72: =SUM(I72:K72) -> -598885.71 | S72: =SUM(L72:N72) -> -199186.57 | U72: =SUM(P72:S72) -> -954329.36
E73: =SUM(C72:E72) -> 162511.21 | H73: =SUM(F72:H72) -> -318768.29 | K73: =SUM(I72:K72) -> -598885.71 | N73: =SUM(L72:N72) -> -199186.57
N74: =U71 -> -3270229.1

Sheet CF Detail - Allocated
D2: SYNAPTIC CASH FLOW FORECAST | E2: 45658 | F2: =EDATE(E2,1) -> 45689 | G2: =EDATE(F2,1) -> 45717 | H2: =EDATE(G2,1) -> 45748 | I2: =EDATE(H2,1) -> 45778 | J2: =EDATE(I2,1) -> 45809 | K2: =EDATE(J2,1) -> 45839 | L2: =EDATE(K2,1) -> 45870 | M2: =EDATE(L2,1) -> 45901 | ... P2: =EDATE(O2,1) -> 45992 | R2: Q1 | S2: Q2 | T2: Q3 | U2: Q4 | W2: 2025 | Y2: Check
D3: =+Version!$C$3 -> Y2025 12 v001
D5: HLS | E5: =+#REF! -> #REF! | F5: =+#REF! -> #REF! | G5: =+#REF! -> #REF! | H5: =+#REF! -> #REF! | I5: =+#REF! -> #REF! | J5: =+#REF! -> #REF! | K5: =+#REF! -> #REF! | L5: =+#REF! -> #REF! | ... P5: =+#REF! -> #REF! | R5: =SUM(E5:G5) -> #REF! | S5: =SUM(H5:J5) -> #REF! | T5: =SUM(K5:M5) -> #REF! | U5: =SUM(N5:P5) -> #REF! | W5: =SUM(E5:P5) -> #REF! | Y5: =ROUND(SUM(R5:U5)-W5,2) -> #REF!
D6: PSS | E6: =+#REF! -> #REF! | F6: =+#REF! -> #REF! | G6: =+#REF! -> #REF! | H6: =+#REF! -> #REF! | I6: =+#REF! -> #REF! | J6: =+#REF! -> #REF! | K6: =+#REF! -> #REF! | L6: =+#REF! -> #REF! | ... P6: =+#REF! -> #REF! | R6: =SUM(E6:G6) -> #REF! | S6: =SUM(H6:J6) -> #REF! | T6: =SUM(K6:M6) -> #REF! | U6: =SUM(N6:P6) -> #REF! | W6: =SUM(E6:P6) -> #REF! | Y6: =ROUND(SUM(R6:U6)-W6,2) -> #REF!
D7: OTHER | E7: =+#REF! -> #REF! | F7: =+#REF! -> #REF! | G7: =+#REF! -> #REF! | H7: =+#REF! -> #REF! | I7: =+#REF! -> #REF! | J7: =+#REF! -> #REF! | K7: =+#REF! -> #REF! | L7: =+#REF! -> #REF! | ... P7: =+#REF! -> #REF! | R7: =SUM(E7:G7) -> #REF! | S7: =SUM(H7:J7) -> #REF! | T7: =SUM(K7:M7) -> #REF! | U7: =SUM(N7:P7) -> #REF! | W7: =SUM(E7:P7) -> #REF! | Y7: =ROUND(SUM(R7:U7)-W7,2) -> #REF!
D8: GAP | E8: =+#REF! -> #REF! | F8: =+#REF! -> #REF! | G8: =+#REF! -> #REF! | H8: =+#REF! -> #REF! | I8: =+#REF! -> #REF! | J8: =+#REF! -> #REF! | K8: =+#REF! -> #REF! | L8: =+#REF! -> #REF! | ... P8: =+#REF! -> #REF! | R8: =SUM(E8:G8) -> #REF! | S8: =SUM(H8:J8) -> #REF! | T8: =SUM(K8:M8) -> #REF! | U8: =SUM(N8:P8) -> #REF! | W8: =SUM(E8:P8) -> #REF! | Y8: =ROUND(SUM(R8:U8)-W8,2) -> #REF!
D9: Total Classic | E9: =SUM(E5:E8) -> #REF! | F9: =SUM(F5:F8) -> #REF! | G9: =SUM(G5:G8) -> #REF! | H9: =SUM(H5:H8) -> #REF! | I9: =SUM(I5:I8) -> #REF! | J9: =SUM(J5:J8) -> #REF! | K9: =SUM(K5:K8) -> #REF! | L9: =SUM(L5:L8) -> #REF! | ... P9: =SUM(P5:P8) -> #REF! | R9: =SUM(R5:R8) -> #REF! | S9: =SUM(S5:S8) -> #REF! | T9: =SUM(T5:T8) -> #REF! | U9: =SUM(U5:U8) -> #REF! | W9: =SUM(W5:W8) -> #REF! | Y9: =ROUND(SUM(R9:U9)-W9,2) -> #REF!
D11: HLS | E11: =+#REF! -> #REF! | F11: =+#REF! -> #REF! | G11: =+#REF! -> #REF! | H11: =+#REF! -> #REF! | I11: =+#REF! -> #REF! | J11: =+#REF! -> #REF! | K11: =+#REF! -> #REF! | L11: =+#REF! -> #REF! | ... P11: =+#REF! -> #REF! | R11: =SUM(E11:G11) -> #REF! | S11: =SUM(H11:J11) -> #REF! | T11: =SUM(K11:M11) -> #REF! | U11: =SUM(N11:P11) -> #REF! | W11: =SUM(E11:P11) -> #REF! | Y11: =ROUND(SUM(R11:U11)-W11,2) -> #REF!
D12: PSS | E12: =+#REF! -> #REF! | F12: =+#REF! -> #REF! | G12: =+#REF! -> #REF! | H12: =+#REF! -> #REF! | I12: =+#REF! -> #REF! | J12: =+#REF! -> #REF! | K12: =+#REF! -> #REF! | L12: =+#REF! -> #REF! | ... P12: =+#REF! -> #REF! | R12: =SUM(E12:G12) -> #REF! | S12: =SUM(H12:J12) -> #REF! | T12: =SUM(K12:M12) -> #REF! | U12: =SUM(N12:P12) -> #REF! | W12: =SUM(E12:P12) -> #REF! | Y12: =ROUND(SUM(R12:U12)-W12,2) -> #REF!
D13: OTHER | E13: =+#REF! -> #REF! | F13: =+#REF! -> #REF! | G13: =+#REF! -> #REF! | H13: =+#REF! -> #REF! | I13: =+#REF! -> #REF! | J13: =+#REF! -> #REF! | K13: =+#REF! -> #REF! | L13: =+#REF! -> #REF! | ... P13: =+#REF! -> #REF! | R13: =SUM(E13:G13) -> #REF! | S13: =SUM(H13:J13) -> #REF! | T13: =SUM(K13:M13) -> #REF! | U13: =SUM(N13:P13) -> #REF! | W13: =SUM(E13:P13) -> #REF! | Y13: =ROUND(SUM(R13:U13)-W13,2) -> #REF!
D14: GAP | E14: =+#REF! -> #REF! | F14: =+#REF! -> #REF! | G14: =+#REF! -> #REF! | H14: =+#REF! -> #REF! | I14: =+#REF! -> #REF! | J14: =+#REF! -> #REF! | K14: =+#REF! -> #REF! | L14: =+#REF! -> #REF! | ... P14: =+#REF! -> #REF! | R14: =SUM(E14:G14) -> #REF! | S14: =SUM(H14:J14) -> #REF! | T14: =SUM(K14:M14) -> #REF! | U14: =SUM(N14:P14) -> #REF! | W14: =SUM(E14:P14) -> #REF! | Y14: =ROUND(SUM(R14:U14)-W14,2) -> #REF!
D15: Total AppIQ | E15: =SUM(E11:E14) -> #REF! | F15: =SUM(F11:F14) -> #REF! | G15: =SUM(G11:G14) -> #REF! | H15: =SUM(H11:H14) -> #REF! | I15: =SUM(I11:I14) -> #REF! | J15: =SUM(J11:J14) -> #REF! | K15: =SUM(K11:K14) -> #REF! | L15: =SUM(L11:L14) -> #REF! | ... P15: =SUM(P11:P14) -> #REF! | R15: =SUM(R11:R14) -> #REF! | S15: =SUM(S11:S14) -> #REF! | T15: =SUM(T11:T14) -> #REF! | U15: =SUM(U11:U14) -> #REF! | W15: =SUM(W11:W14) -> #REF! | Y15: =ROUND(SUM(R15:U15)-W15,2) -> #REF!
D17: Total Cash Collected | E17: =+E9+E15 -> #REF! | F17: =+F9+F15 -> #REF! | G17: =+G9+G15 -> #REF! | H17: =+H9+H15 -> #REF! | I17: =+I9+I15 -> #REF! | J17: =+J9+J15 -> #REF! | K17: =+K9+K15 -> #REF! | L17: =+L9+L15 -> #REF! | ... P17: =+P9+P15 -> #REF! | R17: =+R9+R15 -> #REF! | S17: =+S9+S15 -> #REF! | T17: =+T9+T15 -> #REF! | U17: =+U9+U15 -> #REF! | W17: =+W9+W15 -> #REF! | Y17: =ROUND(SUM(R17:U17)-W17,2) -> #REF!
D19: Delivery - W2 | E19: =+'2 Employees'!C80+'3 Benefits'!C104-'5 Allocations'!C156+'5 Allocations'!C160+'5 Allocations'!C164 -> 141695.78 | F19: =+'2 Employees'!D80+'3 Benefits'!D104-'5 Allocations'!D156+'5 Allocations'!D160+'5 Allocations'!D164 -> 248351.73 | G19: =+'2 Employees'!E80+'3 Benefits'!E104-'5 Allocations'!E156+'5 Allocations'!E160+'5 Allocations'!E164 -> 130281.74 | H19: =+'2 Employees'!F80+'3 Benefits'!F104-'5 Allocations'!F156+'5 Allocations'!F160+'5 Allocations'!F164 -> 118121.43 | I19: =+'2 Employees'!G80+'3 Benefits'!G104-'5 Allocations'!G156+'5 Allocations'!G160+'5 Allocations'!G164 -> 118807.45 | J19: =+'2 Employees'!H80+'3 Benefits'!H104-'5 Allocations'!H156+'5 Allocations'!H160+'5 Allocations'!H164 -> 121137.47 | K19: =+'2 Employees'!I80+'3 Benefits'!I104-'5 Allocations'!I156+'5 Allocations'!I160+'5 Allocations'!I164 -> 117969.81 | L19: =+'2 Employees'!J80+'3 Benefits'!J104-'5 Allocations'!J156+'5 Allocations'!J160+'5 Allocations'!J164 -> 116706.81 | ... P19: =+'2 Employees'!N80+'3 Benefits'!N104-'5 Allocations'!N156+'5 Allocations'!N160+'5 Allocations'!N164 -> 118630 | R19: =SUM(E19:G19) -> 520329.26 | S19: =SUM(H19:J19) -> 358066.35 | T19: =SUM(K19:M19) -> 350794.1 | U19: =SUM(N19:P19) -> 349007.45 | W19: =SUM(E19:P19) -> 1578197.2 | Y19: =ROUND(SUM(R19:U19)-W19,2) -> 0
D20: Delivery - Contractor | E20: =+'4 Contractors'!C29-'5 Allocations'!C157+'5 Allocations'!C161+'5 Allocations'!C165 -> 82068.38 | F20: =+'4 Contractors'!D29-'5 Allocations'!D157+'5 Allocations'!D161+'5 Allocations'!D165 -> 99135.25 | G20: =+'4 Contractors'!E29-'5 Allocations'!E157+'5 Allocations'!E161+'5 Allocations'!E165 -> 81353.75 | H20: =+'4 Contractors'!F29-'5 Allocations'!F157+'5 Allocations'!F161+'5 Allocations'!F165 -> 58506.25 | I20: =+'4 Contractors'!G29-'5 Allocations'!G157+'5 Allocations'!G161+'5 Allocations'!G165 -> 61313.5 | J20: =+'4 Contractors'!H29-'5 Allocations'!H157+'5 Allocations'!H161+'5 Allocations'!H165 -> 59235.25 | K20: =+'4 Contractors'!I29-'5 Allocations'!I157+'5 Allocations'!I161+'5 Allocations'!I165 -> 48960 | L20: =+'4 Contractors'!J29-'5 Allocations'!J157+'5 Allocations'!J161+'5 Allocations'!J165 -> 49996.08 | ... P20: =+'4 Contractors'!N29-'5 Allocations'!N157+'5 Allocations'!N161+'5 Allocations'!N165 -> 57500 | R20: =SUM(E20:G20) -> 262557.38 | S20: =SUM(H20:J20) -> 179055 | T20: =SUM(K20:M20) -> 152843.08 | U20: =SUM(N20:P20) -> 190104.25 | W20: =SUM(E20:P20) -> 784559.71 | Y20: =ROUND(SUM(R20:U20)-W20,2) -> 0
D21: GTM - W2 | E21: =+'2 Employees'!C123+'3 Benefits'!C105-'5 Allocations'!C158+'5 Allocations'!C162 -> 34723.032 | F21: =+'2 Employees'!D123+'3 Benefits'!D105-'5 Allocations'!D158+'5 Allocations'!D162 -> 69494.006 | G21: =+'2 Employees'!E123+'3 Benefits'!E105-'5 Allocations'!E158+'5 Allocations'!E162 -> 34606.853 | H21: =+'2 Employees'!F123+'3 Benefits'!F105-'5 Allocations'!F158+'5 Allocations'!F162 -> 36165.669 | I21: =+'2 Employees'!G123+'3 Benefits'!G105-'5 Allocations'!G158+'5 Allocations'!G162 -> 36459.697 | J21: =+'2 Employees'!H123+'3 Benefits'!H105-'5 Allocations'!H158+'5 Allocations'!H162 -> 37458.278 | K21: =+'2 Employees'!I123+'3 Benefits'!I105-'5 Allocations'!I158+'5 Allocations'!I162 -> 36546.626 | L21: =+'2 Employees'!J123+'3 Benefits'!J105-'5 Allocations'!J158+'5 Allocations'!J162 -> 36217.587 | ... P21: =+'2 Employees'!N123+'3 Benefits'!N105-'5 Allocations'!N158+'5 Allocations'!N162 -> 36600 | R21: =SUM(E21:G21) -> 138823.89 | S21: =SUM(H21:J21) -> 110083.64 | T21: =SUM(K21:M21) -> 108244.33 | U21: =SUM(N21:P21) -> 107592 | W21: =SUM(E21:P21) -> 464743.86 | Y21: =ROUND(SUM(R21:U21)-W21,2) -> 0
D22: GTM - Contractor | E22: =+'4 Contractors'!C46-'5 Allocations'!C159+'5 Allocations'!C163 -> 12121.26 | F22: =+'4 Contractors'!D46-'5 Allocations'!D159+'5 Allocations'!D163 -> 12000 | G22: =+'4 Contractors'!E46-'5 Allocations'!E159+'5 Allocations'!E163 -> 16141.55 | H22: =+'4 Contractors'!F46-'5 Allocations'!F159+'5 Allocations'!F163 -> 12000 | I22: =+'4 Contractors'!G46-'5 Allocations'!G159+'5 Allocations'!G163 -> 12199.26 | J22: =+'4 Contractors'!H46-'5 Allocations'!H159+'5 Allocations'!H163 -> 12000 | K22: =+'4 Contractors'!I46-'5 Allocations'!I159+'5 Allocations'!I163 -> 8000 | L22: =+'4 Contractors'!J46-'5 Allocations'!J159+'5 Allocations'!J163 -> 0 | ... P22: =+'4 Contractors'!N46-'5 Allocations'!N159+'5 Allocations'!N163 -> 0 | R22: =SUM(E22:G22) -> 40262.81 | S22: =SUM(H22:J22) -> 36199.26 | T22: =SUM(K22:M22) -> 8000 | U22: =SUM(N22:P22) -> 0 | W22: =SUM(E22:P22) -> 84462.07 | Y22: =ROUND(SUM(R22:U22)-W22,2) -> 0
D23: Total Spend Classic | E23: =SUM(E19:E22) -> 270608.45 | F23: =SUM(F19:F22) -> 428980.99 | G23: =SUM(G19:G22) -> 262383.9 | H23: =SUM(H19:H22) -> 224793.35 | I23: =SUM(I19:I22) -> 228779.9 | J23: =SUM(J19:J22) -> 229831 | K23: =SUM(K19:K22) -> 211476.44 | L23: =SUM(L19:L22) -> 202920.48 | ... P23: =SUM(P19:P22) -> 212730 | R23: =SUM(R19:R22) -> 961973.34 | S23: =SUM(S19:S22) -> 683404.25 | T23: =SUM(T19:T22) -> 619881.52 | U23: =SUM(U19:U22) -> 646703.69 | W23: =SUM(W19:W22) -> 2911962.8 | Y23: =ROUND(SUM(R23:U23)-W23,2) -> 0
D25: Delivery - W2 | E25: =+'2 Employees'!C156+'3 Benefits'!C108+'5 Allocations'!C156-'5 Allocations'!C160 -> 13330.528 | F25: =+'2 Employees'!D156+'3 Benefits'!D108+'5 Allocations'!D156-'5 Allocations'!D160 -> 26025.704 | G25: =+'2 Employees'!E156+'3 Benefits'!E108+'5 Allocations'!E156-'5 Allocations'!E160 -> 9741.264 | H25: =+'2 Employees'!F156+'3 Benefits'!F108+'5 Allocations'!F156-'5 Allocations'!F160 -> 8212.104 | I25: =+'2 Employees'!G156+'3 Benefits'!G108+'5 Allocations'!G156-'5 Allocations'!G160 -> 8212.104 | J25: =+'2 Employees'!H156+'3 Benefits'!H108+'5 Allocations'!H156-'5 Allocations'!H160 -> 8212.108 | K25: =+'2 Employees'!I156+'3 Benefits'!I108+'5 Allocations'!I156-'5 Allocations'!I160 -> 8212.112 | L25: =+'2 Employees'!J156+'3 Benefits'!J108+'5 Allocations'!J156-'5 Allocations'!J160 -> 7881.952 | ... P25: =+'2 Employees'!N156+'3 Benefits'!N108+'5 Allocations'!N156-'5 Allocations'!N160 -> 7880 | R25: =SUM(E25:G25) -> 49097.496 | S25: =SUM(H25:J25) -> 24636.316 | T25: =SUM(K25:M25) -> 23802.96 | U25: =SUM(N25:P25) -> 23277.432 | W25: =SUM(E25:P25) -> 120814.2 | Y25: =ROUND(SUM(R25:U25)-W25,2) -> 0
D26: Delivery - Contractor | E26: =+'4 Contractors'!C63+'5 Allocations'!C157-'5 Allocations'!C161 -> 0 | F26: =+'4 Contractors'!D63+'5 Allocations'!D157-'5 Allocations'!D161 -> 0 | G26: =+'4 Contractors'!E63+'5 Allocations'!E157-'5 Allocations'!E161 -> 2160 | H26: =+'4 Contractors'!F63+'5 Allocations'!F157-'5 Allocations'!F161 -> 3024 | I26: =+'4 Contractors'!G63+'5 Allocations'!G157-'5 Allocations'!G161 -> 3430 | J26: =+'4 Contractors'!H63+'5 Allocations'!H157-'5 Allocations'!H161 -> 8647 | K26: =+'4 Contractors'!I63+'5 Allocations'!I157-'5 Allocations'!I161 -> 12647 | L26: =+'4 Contractors'!J63+'5 Allocations'!J157-'5 Allocations'!J161 -> 11548 | ... P26: =+'4 Contractors'!N63+'5 Allocations'!N157-'5 Allocations'!N161 -> 10600 | R26: =SUM(E26:G26) -> 2160 | S26: =SUM(H26:J26) -> 15101 | T26: =SUM(K26:M26) -> 35007 | U26: =SUM(N26:P26) -> 22192 | W26: =SUM(E26:P26) -> 74460 | Y26: =ROUND(SUM(R26:U26)-W26,2) -> 0
D27: GTM - W2 | E27: =+'5 Allocations'!C158-'5 Allocations'!C162 -> 5719.06 | F27: =+'5 Allocations'!D158-'5 Allocations'!D162 -> 3959.68 | G27: =+'5 Allocations'!E158-'5 Allocations'!E162 -> 3978.95 | H27: =+'5 Allocations'!F158-'5 Allocations'!F162 -> 3978.95 | I27: =+'5 Allocations'!G158-'5 Allocations'!G162 -> 3978.95 | J27: =+'5 Allocations'!H158-'5 Allocations'!H162 -> 3978.95 | K27: =+'5 Allocations'!I158-'5 Allocations'!I162 -> 3978.95 | L27: =+'5 Allocations'!J158-'5 Allocations'!J162 -> 3978.95 | ... P27: =+'5 Allocations'!N158-'5 Allocations'!N162 -> 4000 | R27: =SUM(E27:G27) -> 13657.69 | S27: =SUM(H27:J27) -> 11936.85 | T27: =SUM(K27:M27) -> 11936.85 | U27: =SUM(N27:P27) -> 11957.895 | W27: =SUM(E27:P27) -> 49489.285 | Y27: =ROUND(SUM(R27:U27)-W27,2) -> 0
D28: GTM - Contractor | E28: =+'4 Contractors'!C89+'5 Allocations'!C159-'5 Allocations'!C163 -> 25440.49 | F28: =+'4 Contractors'!D89+'5 Allocations'!D159-'5 Allocations'!D163 -> 54928.6 | G28: =+'4 Contractors'!E89+'5 Allocations'!E159-'5 Allocations'!E163 -> 71765.61 | H28: =+'4 Contractors'!F89+'5 Allocations'!F159-'5 Allocations'!F163 -> 75263.6 | I28: =+'4 Contractors'!G89+'5 Allocations'!G159-'5 Allocations'!G163 -> 45097.52 | J28: =+'4 Contractors'!H89+'5 Allocations'!H159-'5 Allocations'!H163 -> 28442.12 | K28: =+'4 Contractors'!I89+'5 Allocations'!I159-'5 Allocations'!I163 -> 107654.23 | L28: =+'4 Contractors'!J89+'5 Allocations'!J159-'5 Allocations'!J163 -> 19633.75 | ... P28: =+'4 Contractors'!N89+'5 Allocations'!N159-'5 Allocations'!N163 -> 46700 | R28: =SUM(E28:G28) -> 152134.7 | S28: =SUM(H28:J28) -> 148803.24 | T28: =SUM(K28:M28) -> 142676.98 | U28: =SUM(N28:P28) -> 86097.63 | W28: =SUM(E28:P28) -> 529712.55 | Y28: =ROUND(SUM(R28:U28)-W28,2) -> 0
D29: R&D - W2 | E29: =+'2 Employees'!C227+'3 Benefits'!C110-'5 Allocations'!C164 -> 23645.881 | F29: =+'2 Employees'!D227+'3 Benefits'!D110-'5 Allocations'!D164 -> 23206.142 | G29: =+'2 Employees'!E227+'3 Benefits'!E110-'5 Allocations'!E164 -> 42806.165 | H29: =+'2 Employees'!F227+'3 Benefits'!F110-'5 Allocations'!F164 -> 40594.269 | I29: =+'2 Employees'!G227+'3 Benefits'!G110-'5 Allocations'!G164 -> 35576.491 | J29: =+'2 Employees'!H227+'3 Benefits'!H110-'5 Allocations'!H164 -> 45030.208 | K29: =+'2 Employees'!I227+'3 Benefits'!I110-'5 Allocations'!I164 -> 54965.226 | L29: =+'2 Employees'!J227+'3 Benefits'!J110-'5 Allocations'!J164 -> 61914.096 | ... P29: =+'2 Employees'!N227+'3 Benefits'!N110-'5 Allocations'!N164 -> 39300 | R29: =SUM(E29:G29) -> 89658.188 | S29: =SUM(H29:J29) -> 121200.97 | T29: =SUM(K29:M29) -> 155392.55 | U29: =SUM(N29:P29) -> 116272.13 | W29: =SUM(E29:P29) -> 482523.84 | Y29: =ROUND(SUM(R29:U29)-W29,2) -> 0
D30: R&D - Contractor | E30: =+'4 Contractors'!C111-'5 Allocations'!C165 -> 43402.15 | F30: =+'4 Contractors'!D111-'5 Allocations'!D165 -> 56923.22 | G30: =+'4 Contractors'!E111-'5 Allocations'!E165 -> 49015.88 | H30: =+'4 Contractors'!F111-'5 Allocations'!F165 -> 52268.69 | I30: =+'4 Contractors'!G111-'5 Allocations'!G165 -> 58911.29 | J30: =+'4 Contractors'!H111-'5 Allocations'!H165 -> 60784 | K30: =+'4 Contractors'!I111-'5 Allocations'!I165 -> 53257.33 | L30: =+'4 Contractors'!J111-'5 Allocations'!J165 -> 49276.72 | ... P30: =+'4 Contractors'!N111-'5 Allocations'!N165 -> 21461.95 | R30: =SUM(E30:G30) -> 149341.25 | S30: =SUM(H30:J30) -> 171963.98 | T30: =SUM(K30:M30) -> 149603.14 | U30: =SUM(N30:P30) -> 143775.13 | W30: =SUM(E30:P30) -> 614683.5 | Y30: =ROUND(SUM(R30:U30)-W30,2) -> 0
D31: Total Spend AppIQ | E31: =SUM(E25:E30) -> 111538.11 | F31: =SUM(F25:F30) -> 165043.35 | G31: =SUM(G25:G30) -> 179467.87 | H31: =SUM(H25:H30) -> 183341.61 | I31: =SUM(I25:I30) -> 155206.36 | J31: =SUM(J25:J30) -> 155094.39 | K31: =SUM(K25:K30) -> 240714.85 | L31: =SUM(L25:L30) -> 154233.47 | ... P31: =SUM(P25:P30) -> 129941.95 | R31: =SUM(R25:R30) -> 456049.32 | S31: =SUM(S25:S30) -> 493642.35 | T31: =SUM(T25:T30) -> 518419.48 | U31: =SUM(U25:U30) -> 403572.22 | W31: =SUM(W25:W30) -> 1871683.4 | Y31: =ROUND(SUM(R31:U31)-W31,2) -> 0
D33: Back Office - W2 | E33: =+'2 Employees'!C280+'3 Benefits'!C113 -> 56009.581 | F33: =+'2 Employees'!D280+'3 Benefits'!D113 -> 99933.334 | G33: =+'2 Employees'!E280+'3 Benefits'!E113 -> 52560.785 | H33: =+'2 Employees'!F280+'3 Benefits'!F113 -> 52591.866 | I33: =+'2 Employees'!G280+'3 Benefits'!G113 -> 50755.491 | J33: =+'2 Employees'!H280+'3 Benefits'!H113 -> 51421.212 | K33: =+'2 Employees'!I280+'3 Benefits'!I113 -> 53980.698 | L33: =+'2 Employees'!J280+'3 Benefits'!J113 -> 50594.078 | ... P33: =+'2 Employees'!N280+'3 Benefits'!N113 -> 41150 | R33: =SUM(E33:G33) -> 208503.7 | S33: =SUM(H33:J33) -> 154768.57 | T33: =SUM(K33:M33) -> 155135.16 | U33: =SUM(N33:P33) -> 132689.16 | W33: =SUM(E33:P33) -> 651096.58 | Y33: =ROUND(SUM(R33:U33)-W33,2) -> 0
D34: Back Office - Contractor | E34: =+'4 Contractors'!C129 -> 17629.9 | F34: =+'4 Contractors'!D129 -> 21170 | G34: =+'4 Contractors'!E129 -> 29860 | H34: =+'4 Contractors'!F129 -> 26120 | I34: =+'4 Contractors'!G129 -> 26528.33 | J34: =+'4 Contractors'!H129 -> 26078.33 | K34: =+'4 Contractors'!I129 -> 26980.83 | L34: =+'4 Contractors'!J129 -> 26470.83 | ... P34: =+'4 Contractors'!N129 -> 25400 | R34: =SUM(E34:G34) -> 68659.9 | S34: =SUM(H34:J34) -> 78726.66 | T34: =SUM(K34:M34) -> 80734.99 | U34: =SUM(N34:P34) -> 77246.66 | W34: =SUM(E34:P34) -> 305368.21 | Y34: =ROUND(SUM(R34:U34)-W34,2) -> 0
D35: Total Spend Back Office | E35: =SUM(E33:E34) -> 73639.481 | F35: =SUM(F33:F34) -> 121103.33 | G35: =SUM(G33:G34) -> 82420.785 | H35: =SUM(H33:H34) -> 78711.866 | I35: =SUM(I33:I34) -> 77283.821 | J35: =SUM(J33:J34) -> 77499.542 | K35: =SUM(K33:K34) -> 80961.528 | L35: =SUM(L33:L34) -> 77064.908 | ... P35: =SUM(P33:P34) -> 66550 | R35: =SUM(R33:R34) -> 277163.6 | S35: =SUM(S33:S34) -> 233495.23 | T35: =SUM(T33:T34) -> 235870.15 | U35: =SUM(U33:U34) -> 209935.82 | W35: =SUM(W33:W34) -> 956464.79 | Y35: =ROUND(SUM(R35:U35)-W35,2) -> 0
B37: Rent | D37: Rent | E37: =+'6 Other'!C5 -> 0 | F37: =+'6 Other'!D5 -> 0 | G37: =+'6 Other'!E5 -> 0 | H37: =+'6 Other'!F5 -> 0 | I37: =+'6 Other'!G5 -> 3545.63 | J37: =+'6 Other'!H5 -> 3545.63 | K37: =+'6 Other'!I5 -> 7091.26 | L37: =+'6 Other'!J5 -> 3545.63 | ... P37: =+'6 Other'!N5 -> 3550 | R37: =SUM(E37:G37) -> 0 | S37: =SUM(H37:J37) -> 7091.26 | T37: =SUM(K37:M37) -> 14182.52 | U37: =SUM(N37:P37) -> 10641.26 | W37: =SUM(E37:P37) -> 31915.04 | Y37: =ROUND(SUM(R37:U37)-W37,2) -> 0
B38: Marketing | D38: Marketing | E38: =+'6 Other'!#REF! -> #REF! | F38: =+'6 Other'!#REF! -> #REF! | G38: =+'6 Other'!#REF! -> #REF! | H38: =+'6 Other'!#REF! -> #REF! | I38: =+'6 Other'!#REF! -> #REF! | J38: =+'6 Other'!#REF! -> #REF! | K38: =+'6 Other'!#REF! -> #REF! | L38: =+'6 Other'!#REF! -> #REF! | ... P38: =+'6 Other'!#REF! -> #REF! | R38: =SUM(E38:G38) -> #REF! | S38: =SUM(H38:J38) -> #REF! | T38: =SUM(K38:M38) -> #REF! | U38: =SUM(N38:P38) -> #REF! | W38: =SUM(E38:P38) -> #REF! | Y38: =ROUND(SUM(R38:U38)-W38,2) -> #REF!
B39: Hardware & Software | D39: Hardware & Software | E39: =+'6 Other'!C6 -> 3866.9 | F39: =+'6 Other'!D6 -> 4575.9 | G39: =+'6 Other'!E6 -> 12536.15 | H39: =+'6 Other'!F6 -> 11114.35 | I39: =+'6 Other'!G6 -> 24774.02 | J39: =+'6 Other'!H6 -> 23118.32 | K39: =+'6 Other'!I6 -> 22036.41 | L39: =+'6 Other'!J6 -> 91840.73 | ... P39: =+'6 Other'!N6 -> 12000 | R39: =SUM(E39:G39) -> 20978.95 | S39: =SUM(H39:J39) -> 59006.69 | T39: =SUM(K39:M39) -> 124166.61 | U39: =SUM(N39:P39) -> 48307.86 | W39: =SUM(E39:P39) -> 252460.11 | Y39: =ROUND(SUM(R39:U39)-W39,2) -> 0
B40: Office & Supplies | D40: Office & Supplies | E40: =+'6 Other'!C7 -> 263.76 | F40: =+'6 Other'!D7 -> 807.23 | G40: =+'6 Other'!E7 -> 556.56 | H40: =+'6 Other'!F7 -> 556 | I40: =+'6 Other'!G7 -> 354.79 | J40: =+'6 Other'!H7 -> 1130.57 | K40: =+'6 Other'!I7 -> 355.28 | L40: =+'6 Other'!J7 -> 1606.02 | ... P40: =+'6 Other'!N7 -> 500 | R40: =SUM(E40:G40) -> 1627.55 | S40: =SUM(H40:J40) -> 2041.36 | T40: =SUM(K40:M40) -> 3176.35 | U40: =SUM(N40:P40) -> 5020.86 | W40: =SUM(E40:P40) -> 11866.12 | Y40: =ROUND(SUM(R40:U40)-W40,2) -> 0
B41: Insurance | D41: Insurance | E41: =+'6 Other'!C8 -> 496.97 | F41: =+'6 Other'!D8 -> 8280.18 | G41: =+'6 Other'!E8 -> 3089.89 | H41: =+'6 Other'!F8 -> 8984.89 | I41: =+'6 Other'!G8 -> 1547.55 | J41: =+'6 Other'!H8 -> 3039.49 | K41: =+'6 Other'!I8 -> 5580.24 | L41: =+'6 Other'!J8 -> 1783.24 | ... P41: =+'6 Other'!N8 -> 2500 | R41: =SUM(E41:G41) -> 11867.04 | S41: =SUM(H41:J41) -> 13571.93 | T41: =SUM(K41:M41) -> 10402.97 | U41: =SUM(N41:P41) -> 10101.04 | W41: =SUM(E41:P41) -> 45942.98 | Y41: =ROUND(SUM(R41:U41)-W41,2) -> 0
B42: Legal Fees | D42: Legal Fees | E42: =+'6 Other'!C9 -> 10550 | F42: =+'6 Other'!D9 -> 15467.5 | G42: =+'6 Other'!E9 -> 18866 | H42: =+'6 Other'!F9 -> 28130 | I42: =+'6 Other'!G9 -> 23029.4 | J42: =+'6 Other'!H9 -> 10386.45 | K42: =+'6 Other'!I9 -> 9005.5 | L42: =+'6 Other'!J9 -> 1950.5 | ... P42: =+'6 Other'!N9 -> 11000 | R42: =SUM(E42:G42) -> 44883.5 | S42: =SUM(H42:J42) -> 61545.85 | T42: =SUM(K42:M42) -> 18957 | U42: =SUM(N42:P42) -> 21626.7 | W42: =SUM(E42:P42) -> 147013.05 | Y42: =ROUND(SUM(R42:U42)-W42,2) -> 0
B43: Accounting & Tax Fees | D43: Accounting & Tax Fees | E43: =+'6 Other'!C10 -> 0 | F43: =+'6 Other'!D10 -> 0 | G43: =+'6 Other'!E10 -> 0 | H43: =+'6 Other'!F10 -> 0 | I43: =+'6 Other'!G10 -> 22482.5 | J43: =+'6 Other'!H10 -> 287.5 | K43: =+'6 Other'!I10 -> 535 | L43: =+'6 Other'!J10 -> 0 | ... P43: =+'6 Other'!N10 -> 12500 | R43: =SUM(E43:G43) -> 0 | S43: =SUM(H43:J43) -> 22770 | T43: =SUM(K43:M43) -> 1100 | U43: =SUM(N43:P43) -> 12500 | W43: =SUM(E43:P43) -> 36370 | Y43: =ROUND(SUM(R43:U43)-W43,2) -> 0
B44: Professional Fees | D44: Professional Fees | E44: =+'6 Other'!C11 -> 0 | F44: =+'6 Other'!D11 -> 0 | G44: =+'6 Other'!E11 -> 63750 | H44: =+'6 Other'!F11 -> 0 | I44: =+'6 Other'!G11 -> 25000 | J44: =+'6 Other'!H11 -> 0 | K44: =+'6 Other'!I11 -> 0 | L44: =+'6 Other'!J11 -> 0 | ... P44: =+'6 Other'!N11 -> 35000 | R44: =SUM(E44:G44) -> 63750 | S44: =SUM(H44:J44) -> 25000 | T44: =SUM(K44:M44) -> 0 | U44: =SUM(N44:P44) -> 35000 | W44: =SUM(E44:P44) -> 123750 | Y44: =ROUND(SUM(R44:U44)-W44,2) -> 0
B45: Business Taxes, Licenses & Permits | D45: Taxes, Licenses & Permits | E45: =+'6 Other'!C12 -> 0 | F45: =+'6 Other'!D12 -> 0 | G45: =+'6 Other'!E12 -> 4036 | H45: =+'6 Other'!F12 -> 20 | I45: =+'6 Other'!G12 -> -326.17 | J45: =+'6 Other'!H12 -> 196 | K45: =+'6 Other'!I12 -> 112.92 | L45: =+'6 Other'!J12 -> 0 | ... P45: =+'6 Other'!N12 -> 250 | R45: =SUM(E45:G45) -> 4036 | S45: =SUM(H45:J45) -> -110.17 | T45: =SUM(K45:M45) -> 80.92 | U45: =SUM(N45:P45) -> 438.43 | W45: =SUM(E45:P45) -> 4445.18 | Y45: =ROUND(SUM(R45:U45)-W45,2) -> 0
B46: Travel & Meals | D46: Travel & Meals | E46: =+'6 Other'!#REF! -> #REF! | F46: =+'6 Other'!#REF! -> #REF! | G46: =+'6 Other'!#REF! -> #REF! | H46: =+'6 Other'!#REF! -> #REF! | I46: =+'6 Other'!#REF! -> #REF! | J46: =+'6 Other'!#REF! -> #REF! | K46: =+'6 Other'!#REF! -> #REF! | L46: =+'6 Other'!#REF! -> #REF! | ... P46: =+'6 Other'!#REF! -> #REF! | R46: =SUM(E46:G46) -> #REF! | S46: =SUM(H46:J46) -> #REF! | T46: =SUM(K46:M46) -> #REF! | U46: =SUM(N46:P46) -> #REF! | W46: =SUM(E46:P46) -> #REF! | Y46: =ROUND(SUM(R46:U46)-W46,2) -> #REF!
D47: Total Other Spend | E47: =SUM(E37:E46) -> #REF! | F47: =SUM(F37:F46) -> #REF! | G47: =SUM(G37:G46) -> #REF! | H47: =SUM(H37:H46) -> #REF! | I47: =SUM(I37:I46) -> #REF! | J47: =SUM(J37:J46) -> #REF! | K47: =SUM(K37:K46) -> #REF! | L47: =SUM(L37:L46) -> #REF! | ... P47: =SUM(P37:P46) -> #REF! | R47: =SUM(R37:R46) -> #REF! | S47: =SUM(S37:S46) -> #REF! | T47: =SUM(T37:T46) -> #REF! | U47: =SUM(U37:U46) -> #REF! | W47: =SUM(W37:W46) -> #REF! | Y47: =ROUND(SUM(R47:U47)-W47,2) -> #REF!
D49: Total Cash Disbursements | E49: =+E23+E31+E35+E47 -> #REF! | F49: =+F23+F31+F35+F47 -> #REF! | G49: =+G23+G31+G35+G47 -> #REF! | H49: =+H23+H31+H35+H47 -> #REF! | I49: =+I23+I31+I35+I47 -> #REF! | J49: =+J23+J31+J35+J47 -> #REF! | K49: =+K23+K31+K35+K47 -> #REF! | L49: =+L23+L31+L35+L47 -> #REF! | ... P49: =+P23+P31+P35+P47 -> #REF! | R49: =+R23+R31+R35+R47 -> #REF! | S49: =+S23+S31+S35+S47 -> #REF! | T49: =+T23+T31+T35+T47 -> #REF! | U49: =+U23+U31+U35+U47 -> #REF! | W49: =+W23+W31+W35+W47 -> #REF! | Y49: =ROUND(SUM(R49:U49)-W49,2) -> #REF!
B51: Guarenteed Payments | D51: Guarenteed Payments | E51: =+'6 Other'!C18 -> 0 | F51: =+'6 Other'!D18 -> 0 | G51: =+'6 Other'!E18 -> 0 | H51: =+'6 Other'!F18 -> 0 | I51: =+'6 Other'!G18 -> 0 | J51: =+'6 Other'!H18 -> 0 | K51: =+'6 Other'!I18 -> 0 | L51: =+'6 Other'!J18 -> 0 | ... P51: =+'6 Other'!N18 -> 0 | R51: =SUM(E51:G51) -> 0 | S51: =SUM(H51:J51) -> 0 | T51: =SUM(K51:M51) -> 0 | U51: =SUM(N51:P51) -> 0 | W51: =SUM(E51:P51) -> 0 | Y51: =ROUND(SUM(R51:U51)-W51,2) -> 0
B52: Youreka Labs Inc | D52: Youreka Labs Inc | E52: =+'6 Other'!C19 -> 0 | F52: =+'6 Other'!D19 -> 0 | G52: =+'6 Other'!E19 -> 0 | H52: =+'6 Other'!F19 -> 0 | I52: =+'6 Other'!G19 -> 0 | J52: =+'6 Other'!H19 -> 0 | K52: =+'6 Other'!I19 -> 0 | L52: =+'6 Other'!J19 -> 0 | ... P52: =+'6 Other'!N19 -> 0 | R52: =SUM(E52:G52) -> 0 | S52: =SUM(H52:J52) -> 0 | T52: =SUM(K52:M52) -> 0 | U52: =SUM(N52:P52) -> 0 | W52: =SUM(E52:P52) -> 0 | Y52: =ROUND(SUM(R52:U52)-W52,2) -> 0
B53: Brex | D53: Brex | E53: =+'6 Other'!C20 -> -5043.37 | F53: =+'6 Other'!D20 -> -5518.34 | G53: =+'6 Other'!E20 -> -4685.37 | H53: =+'6 Other'!F20 -> -3686.29 | I53: =+'6 Other'!G20 -> -2521.11 | J53: =+'6 Other'!H20 -> -957.06 | K53: =+'6 Other'!I20 -> -183.94 | L53: =+'6 Other'!J20 -> 0 | ... P53: =+'6 Other'!N20 -> 0 | R53: =SUM(E53:G53) -> -15247.08 | S53: =SUM(H53:J53) -> -7164.46 | T53: =SUM(K53:M53) -> -183.94 | U53: =SUM(N53:P53) -> 0 | W53: =SUM(E53:P53) -> -22595.48 | Y53: =ROUND(SUM(R53:U53)-W53,2) -> 0
B54: Chase Visa | D54: Chase Visa | E54: =+'6 Other'!C21 -> 0 | F54: =+'6 Other'!D21 -> -1010.7 | G54: =+'6 Other'!E21 -> 0 | H54: =+'6 Other'!F21 -> -1222.92 | I54: =+'6 Other'!G21 -> -2784.15 | J54: =+'6 Other'!H21 -> -1124.19 | K54: =+'6 Other'!I21 -> -1126.11 | L54: =+'6 Other'!J21 -> -105.74 | ... P54: =+'6 Other'!N21 -> 0 | R54: =SUM(E54:G54) -> -1010.7 | S54: =SUM(H54:J54) -> -5131.26 | T54: =SUM(K54:M54) -> -1231.85 | U54: =SUM(N54:P54) -> 0 | W54: =SUM(E54:P54) -> -7373.81 | Y54: =ROUND(SUM(R54:U54)-W54,2) -> 0
B55: Bank Fees | D55: Bank Fees | E55: =+'6 Other'!C23 -> -246.35 | F55: =+'6 Other'!D23 -> -433.54 | G55: =+'6 Other'!E23 -> -471.18 | H55: =+'6 Other'!F23 -> -346.98 | I55: =+'6 Other'!G23 -> -328.79 | J55: =+'6 Other'!H23 -> -692 | K55: =+'6 Other'!I23 -> -386.11 | L55: =+'6 Other'!J23 -> -335.21 | ... P55: =+'6 Other'!N23 -> -400 | R55: =SUM(E55:G55) -> -1151.07 | S55: =SUM(H55:J55) -> -1367.77 | T55: =SUM(K55:M55) -> -1045.49 | U55: =SUM(N55:P55) -> -1052.45 | W55: =SUM(E55:P55) -> -4616.78 | Y55: =ROUND(SUM(R55:U55)-W55,2) -> 0
B56: Interest | D56: Interest | E56: =+'6 Other'!C24 -> 7748.71 | F56: =+'6 Other'!D24 -> 8351.29 | G56: =+'6 Other'!E24 -> 8145.22 | H56: =+'6 Other'!F24 -> 6912.1 | I56: =+'6 Other'!G24 -> 5204.78 | J56: =+'6 Other'!H24 -> 3887.72 | K56: =+'6 Other'!I24 -> 3150.25 | L56: =+'6 Other'!J24 -> 2155.66 | ... P56: =+'6 Other'!N24 -> 300 | R56: =SUM(E56:G56) -> 24245.22 | S56: =SUM(H56:J56) -> 16004.6 | T56: =SUM(K56:M56) -> 6388.96 | U56: =SUM(N56:P56) -> 1225.61 | W56: =SUM(E56:P56) -> 47864.39 | Y56: =ROUND(SUM(R56:U56)-W56,2) -> 0
D58: Opening Cash Balance | E58: 3221818.9 | F58: =+E63 -> #REF! | G58: =+F63 -> #REF! | H58: =+G63 -> #REF! | I58: =+H63 -> #REF! | J58: =+I63 -> #REF! | K58: =+J63 -> #REF! | L58: =+K63 -> #REF! | M58: =+L63 -> #REF! | ... P58: =+O63 -> #REF! | R58: =+E58 -> 3221818.9 | S58: =+R63 -> #REF! | T58: =+S63 -> #REF! | U58: =+T63 -> #REF! | W58: =+R58 -> 3221818.9
D60: Net Change | E60: =E17-E49+SUM(E51:E56) -> #REF! | F60: =F17-F49+SUM(F51:F56) -> #REF! | G60: =G17-G49+SUM(G51:G56) -> #REF! | H60: =H17-H49+SUM(H51:H56) -> #REF! | I60: =I17-I49+SUM(I51:I56) -> #REF! | J60: =J17-J49+SUM(J51:J56) -> #REF! | K60: =K17-K49+SUM(K51:K56) -> #REF! | L60: =L17-L49+SUM(L51:L56) -> #REF! | ... P60: =P17-P49+SUM(P51:P56) -> #REF! | R60: =SUM(E60:G60) -> #REF! | S60: =SUM(H60:J60) -> #REF! | T60: =SUM(K60:M60) -> #REF! | U60: =SUM(N60:P60) -> #REF! | W60: =SUM(E60:P60) -> #REF! | Y60: =ROUND(SUM(R60:U60)-W60,2) -> #REF!
D61: Investment | E61: =+'6 Other'!C29 -> 199999.42 | F61: =+'6 Other'!D29 -> 749999.44 | G61: =+'6 Other'!E29 -> 0 | H61: =+'6 Other'!F29 -> 0 | I61: =+'6 Other'!G29 -> 0 | J61: =+'6 Other'!H29 -> -25000 | K61: =+'6 Other'!I29 -> 0 | L61: =+'6 Other'!J29 -> 0 | ... P61: =+'6 Other'!N29 -> -25000 | R61: =SUM(E61:G61) -> 949998.86 | S61: =SUM(H61:J61) -> -25000 | T61: =SUM(K61:M61) -> 0 | U61: =SUM(N61:P61) -> -25000 | W61: =SUM(E61:P61) -> 899998.86 | Y61: =ROUND(SUM(R61:U61)-W61,2) -> 0
D63: Ending Cash Balance | E63: =ROUND(+E58+E60+E61,0) -> #REF! | F63: =ROUND(+F58+F60+F61,0) -> #REF! | G63: =ROUND(+G58+G60+G61,0) -> #REF! | H63: =ROUND(+H58+H60+H61,0) -> #REF! | I63: =ROUND(+I58+I60+I61,0) -> #REF! | J63: =ROUND(+J58+J60+J61,0) -> #REF! | K63: =ROUND(+K58+K60+K61,0) -> #REF! | L63: =ROUND(+L58+L60+L61,0) -> #REF! | ... P63: =ROUND(+P58+P60+P61,0) -> #REF! | R63: =ROUND(+R58+R60+R61,0) -> #REF! | S63: =ROUND(+S58+S60+S61,0) -> #REF! | T63: =ROUND(+T58+T60+T61,0) -> #REF! | U63: =ROUND(+U58+U60+U61,0) -> #REF! | W63: =ROUND(+W58+W60+W61,0) -> #REF!
D65: Check | E65: =+E63-'2025 Detail'!C61 -> #REF! | F65: =+F63-'2025 Detail'!D61 -> #REF! | G65: =+G63-'2025 Detail'!E61 -> #REF! | H65: =+H63-'2025 Detail'!F61 -> #REF! | I65: =+I63-'2025 Detail'!G61 -> #REF! | J65: =+J63-'2025 Detail'!H61 -> #REF! | K65: =+K63-'2025 Detail'!I61 -> #REF! | L65: =+L63-'2025 Detail'!J61 -> #REF! | ... P65: =+P63-'2025 Detail'!N61 -> #REF!

Sheet (R) CF Summary By Dept
B2: SYNAPTIC CASH FLOW FORECAST | C2: 45658 | D2: =EDATE(C2,1) -> 45689 | E2: =EDATE(D2,1) -> 45717 | F2: =EDATE(E2,1) -> 45748 | G2: =EDATE(F2,1) -> 45778 | H2: =EDATE(G2,1) -> 45809 | I2: =EDATE(H2,1) -> 45839 | J2: =EDATE(I2,1) -> 45870 | K2: =EDATE(J2,1) -> 45901 | ... N2: =EDATE(M2,1) -> 45992 | P2: Q1 | Q2: Q2 | R2: Q3 | S2: Q4 | U2: 2025 | W2: Check
B3: =+Version!$C$3 -> Y2025 12 v001
B5: Consulting - Classic | C5: =+'2025 Detail'!C8 -> 276138.86 | D5: =+'2025 Detail'!D8 -> 303659.1 | E5: =+'2025 Detail'!E8 -> 148959.5 | F5: =+'2025 Detail'!F8 -> 175655.2 | G5: =+'2025 Detail'!G8 -> 192782.4 | H5: =+'2025 Detail'!H8 -> 75752.9 | I5: =+'2025 Detail'!I8 -> 256181 | J5: =+'2025 Detail'!J8 -> 104161 | ... N5: =+'2025 Detail'!N8 -> 335155 | P5: =SUM(C5:E5) -> 728757.46 | Q5: =SUM(F5:H5) -> 444190.5 | R5: =SUM(I5:K5) -> 447319.5 | S5: =SUM(L5:N5) -> 766915.5 | U5: =SUM(C5:N5) -> 2387183 | W5: =ROUND(SUM(P5:S5)-U5,2) -> 0
B6: Consulting - AppIQ | C6: =+'2025 Detail'!C13 -> 0 | D6: =+'2025 Detail'!D13 -> 50000 | E6: =+'2025 Detail'!E13 -> 126292.98 | F6: =+'2025 Detail'!F13 -> 36377.5 | G6: =+'2025 Detail'!G13 -> 0 | H6: =+'2025 Detail'!H13 -> 40314.5 | I6: =+'2025 Detail'!I13 -> 69000 | J6: =+'2025 Detail'!J13 -> 81277.6 | ... N6: =+'2025 Detail'!N13 -> 512777.6 | P6: =SUM(C6:E6) -> 176292.98 | Q6: =SUM(F6:H6) -> 76692 | R6: =SUM(I6:K6) -> 172277.6 | S6: =SUM(L6:N6) -> 779860.4 | U6: =SUM(C6:N6) -> 1205123 | W6: =ROUND(SUM(P6:S6)-U6,2) -> 0
B8: Total Cash Collected | C8: =SUM(C5:C6) -> 276138.86 | D8: =SUM(D5:D6) -> 353659.1 | E8: =SUM(E5:E6) -> 275252.48 | F8: =SUM(F5:F6) -> 212032.7 | G8: =SUM(G5:G6) -> 192782.4 | H8: =SUM(H5:H6) -> 116067.4 | I8: =SUM(I5:I6) -> 325181 | J8: =SUM(J5:J6) -> 185438.6 | ... N8: =SUM(N5:N6) -> 847932.6 | P8: =SUM(P5:P6) -> 905050.44 | Q8: =SUM(Q5:Q6) -> 520882.5 | R8: =SUM(R5:R6) -> 619597.1 | S8: =SUM(S5:S6) -> 1546775.9 | U8: =SUM(U5:U6) -> 3592305.9 | W8: =ROUND(SUM(P8:S8)-U8,2) -> 0
B10: Delivery | C10: =+'2025 Detail'!C17+'2025 Detail'!C18+'2025 Detail'!C23+'2025 Detail'!C24 -> 237094.69 | D10: =+'2025 Detail'!D17+'2025 Detail'!D18+'2025 Detail'!D23+'2025 Detail'!D24 -> 373512.69 | E10: =+'2025 Detail'!E17+'2025 Detail'!E18+'2025 Detail'!E23+'2025 Detail'!E24 -> 223536.76 | F10: =+'2025 Detail'!F17+'2025 Detail'!F18+'2025 Detail'!F23+'2025 Detail'!F24 -> 187863.78 | G10: =+'2025 Detail'!G17+'2025 Detail'!G18+'2025 Detail'!G23+'2025 Detail'!G24 -> 191763.05 | H10: =+'2025 Detail'!H17+'2025 Detail'!H18+'2025 Detail'!H23+'2025 Detail'!H24 -> 197231.83 | I10: =+'2025 Detail'!I17+'2025 Detail'!I18+'2025 Detail'!I23+'2025 Detail'!I24 -> 187788.92 | J10: =+'2025 Detail'!J17+'2025 Detail'!J18+'2025 Detail'!J23+'2025 Detail'!J24 -> 186132.84 | ... N10: =+'2025 Detail'!N17+'2025 Detail'!N18+'2025 Detail'!N23+'2025 Detail'!N24 -> 194610 | P10: =SUM(C10:E10) -> 834144.13 | Q10: =SUM(F10:H10) -> 576858.66 | R10: =SUM(I10:K10) -> 562447.14 | S10: =SUM(L10:N10) -> 584581.13 | U10: =SUM(C10:N10) -> 2558031.1 | W10: =ROUND(SUM(P10:S10)-U10,2) -> 0
B11: GTM | C11: =+'2025 Detail'!C19+'2025 Detail'!C20+'2025 Detail'!C25+'2025 Detail'!C26 -> 78003.842 | D11: =+'2025 Detail'!D19+'2025 Detail'!D20+'2025 Detail'!D25+'2025 Detail'!D26 -> 140382.29 | E11: =+'2025 Detail'!E19+'2025 Detail'!E20+'2025 Detail'!E25+'2025 Detail'!E26 -> 126492.96 | F11: =+'2025 Detail'!F19+'2025 Detail'!F20+'2025 Detail'!F25+'2025 Detail'!F26 -> 161548.09 | G11: =+'2025 Detail'!G19+'2025 Detail'!G20+'2025 Detail'!G25+'2025 Detail'!G26 -> 144154.06 | H11: =+'2025 Detail'!H19+'2025 Detail'!H20+'2025 Detail'!H25+'2025 Detail'!H26 -> 128723.2 | I11: =+'2025 Detail'!I19+'2025 Detail'!I20+'2025 Detail'!I25+'2025 Detail'!I26 -> 192250.88 | J11: =+'2025 Detail'!J19+'2025 Detail'!J20+'2025 Detail'!J25+'2025 Detail'!J26 -> 87570.004 | ... N11: =+'2025 Detail'!N19+'2025 Detail'!N20+'2025 Detail'!N25+'2025 Detail'!N26 -> 121150 | P11: =SUM(C11:E11) -> 344879.09 | Q11: =SUM(F11:H11) -> 434425.35 | R11: =SUM(I11:K11) -> 354262.14 | S11: =SUM(L11:N11) -> 271117.28 | U11: =SUM(C11:N11) -> 1404683.9 | W11: =ROUND(SUM(P11:S11)-U11,2) -> 0
B12: R&D | C12: =+'2025 Detail'!C27+'2025 Detail'!C28 -> 67048.031 | D12: =+'2025 Detail'!D27+'2025 Detail'!D28 -> 80129.362 | E12: =+'2025 Detail'!E27+'2025 Detail'!E28 -> 91822.045 | F12: =+'2025 Detail'!F27+'2025 Detail'!F28 -> 92862.959 | G12: =+'2025 Detail'!G27+'2025 Detail'!G28 -> 94487.781 | H12: =+'2025 Detail'!H27+'2025 Detail'!H28 -> 105814.21 | I12: =+'2025 Detail'!I27+'2025 Detail'!I28 -> 108222.56 | J12: =+'2025 Detail'!J27+'2025 Detail'!J28 -> 111190.82 | ... N12: =+'2025 Detail'!N27+'2025 Detail'!N28 -> 60761.95 | P12: =SUM(C12:E12) -> 238999.44 | Q12: =SUM(F12:H12) -> 293164.95 | R12: =SUM(I12:K12) -> 304995.69 | S12: =SUM(L12:N12) -> 260047.26 | U12: =SUM(C12:N12) -> 1097207.3 | W12: =ROUND(SUM(P12:S12)-U12,2) -> 0
B13: Back Office | C13: =+'2025 Detail'!C31+'2025 Detail'!C32 -> 73639.481 | D13: =+'2025 Detail'!D31+'2025 Detail'!D32 -> 121103.33 | E13: =+'2025 Detail'!E31+'2025 Detail'!E32 -> 82420.785 | F13: =+'2025 Detail'!F31+'2025 Detail'!F32 -> 78711.866 | G13: =+'2025 Detail'!G31+'2025 Detail'!G32 -> 77283.821 | H13: =+'2025 Detail'!H31+'2025 Detail'!H32 -> 77499.542 | I13: =+'2025 Detail'!I31+'2025 Detail'!I32 -> 80961.528 | J13: =+'2025 Detail'!J31+'2025 Detail'!J32 -> 77064.908 | ... N13: =+'2025 Detail'!N31+'2025 Detail'!N32 -> 66550 | P13: =SUM(C13:E13) -> 277163.6 | Q13: =SUM(F13:H13) -> 233495.23 | R13: =SUM(I13:K13) -> 235870.15 | S13: =SUM(L13:N13) -> 209935.82 | U13: =SUM(C13:N13) -> 956464.79 | W13: =ROUND(SUM(P13:S13)-U13,2) -> 0
B14: Total Department Spend | C14: =SUM(C10:C13) -> 455786.04 | D14: =SUM(D10:D13) -> 715127.67 | E14: =SUM(E10:E13) -> 524272.55 | F14: =SUM(F10:F13) -> 520986.7 | G14: =SUM(G10:G13) -> 507688.71 | H14: =SUM(H10:H13) -> 509268.78 | I14: =SUM(I10:I13) -> 569223.89 | J14: =SUM(J10:J13) -> 461958.57 | ... N14: =SUM(N10:N13) -> 443071.95 | P14: =SUM(P10:P13) -> 1695186.3 | Q14: =SUM(Q10:Q13) -> 1537944.2 | R14: =SUM(R10:R13) -> 1457575.1 | S14: =SUM(S10:S13) -> 1325681.5 | U14: =SUM(U10:U13) -> 6016387 | W14: =ROUND(SUM(P14:S14)-U14,2) -> 0
B16: Rent | C16: =+'2025 Detail'!C35 -> 0 | D16: =+'2025 Detail'!D35 -> 0 | E16: =+'2025 Detail'!E35 -> 0 | F16: =+'2025 Detail'!F35 -> 0 | G16: =+'2025 Detail'!G35 -> 3545.63 | H16: =+'2025 Detail'!H35 -> 3545.63 | I16: =+'2025 Detail'!I35 -> 7091.26 | J16: =+'2025 Detail'!J35 -> 3545.63 | ... N16: =+'2025 Detail'!N35 -> 3550 | P16: =SUM(C16:E16) -> 0 | Q16: =SUM(F16:H16) -> 7091.26 | R16: =SUM(I16:K16) -> 14182.52 | S16: =SUM(L16:N16) -> 10641.26 | U16: =SUM(C16:N16) -> 31915.04 | W16: =ROUND(SUM(P16:S16)-U16,2) -> 0
B17: Hardware & Software | C17: =+'2025 Detail'!C36 -> 3866.9 | D17: =+'2025 Detail'!D36 -> 4575.9 | E17: =+'2025 Detail'!E36 -> 12536.15 | F17: =+'2025 Detail'!F36 -> 11114.35 | G17: =+'2025 Detail'!G36 -> 24774.02 | H17: =+'2025 Detail'!H36 -> 23118.32 | I17: =+'2025 Detail'!I36 -> 22036.41 | J17: =+'2025 Detail'!J36 -> 91840.73 | ... N17: =+'2025 Detail'!N36 -> 12000 | P17: =SUM(C17:E17) -> 20978.95 | Q17: =SUM(F17:H17) -> 59006.69 | R17: =SUM(I17:K17) -> 124166.61 | S17: =SUM(L17:N17) -> 48307.86 | U17: =SUM(C17:N17) -> 252460.11 | W17: =ROUND(SUM(P17:S17)-U17,2) -> 0
B18: Office & Supplies | C18: =+'2025 Detail'!C37 -> 263.76 | D18: =+'2025 Detail'!D37 -> 807.23 | E18: =+'2025 Detail'!E37 -> 556.56 | F18: =+'2025 Detail'!F37 -> 556 | G18: =+'2025 Detail'!G37 -> 354.79 | H18: =+'2025 Detail'!H37 -> 1130.57 | I18: =+'2025 Detail'!I37 -> 355.28 | J18: =+'2025 Detail'!J37 -> 1606.02 | ... N18: =+'2025 Detail'!N37 -> 500 | P18: =SUM(C18:E18) -> 1627.55 | Q18: =SUM(F18:H18) -> 2041.36 | R18: =SUM(I18:K18) -> 3176.35 | S18: =SUM(L18:N18) -> 5020.86 | U18: =SUM(C18:N18) -> 11866.12 | W18: =ROUND(SUM(P18:S18)-U18,2) -> 0
B19: Insurance | C19: =+'2025 Detail'!C38 -> 496.97 | D19: =+'2025 Detail'!D38 -> 8280.18 | E19: =+'2025 Detail'!E38 -> 3089.89 | F19: =+'2025 Detail'!F38 -> 8984.89 | G19: =+'2025 Detail'!G38 -> 1547.55 | H19: =+'2025 Detail'!H38 -> 3039.49 | I19: =+'2025 Detail'!I38 -> 5580.24 | J19: =+'2025 Detail'!J38 -> 1783.24 | ... N19: =+'2025 Detail'!N38 -> 2500 | P19: =SUM(C19:E19) -> 11867.04 | Q19: =SUM(F19:H19) -> 13571.93 | R19: =SUM(I19:K19) -> 10402.97 | S19: =SUM(L19:N19) -> 10101.04 | U19: =SUM(C19:N19) -> 45942.98 | W19: =ROUND(SUM(P19:S19)-U19,2) -> 0
B20: Legal Fees | C20: =+'2025 Detail'!C39 -> 10550 | D20: =+'2025 Detail'!D39 -> 15467.5 | E20: =+'2025 Detail'!E39 -> 18866 | F20: =+'2025 Detail'!F39 -> 28130 | G20: =+'2025 Detail'!G39 -> 23029.4 | H20: =+'2025 Detail'!H39 -> 10386.45 | I20: =+'2025 Detail'!I39 -> 9005.5 | J20: =+'2025 Detail'!J39 -> 1950.5 | ... N20: =+'2025 Detail'!N39 -> 11000 | P20: =SUM(C20:E20) -> 44883.5 | Q20: =SUM(F20:H20) -> 61545.85 | R20: =SUM(I20:K20) -> 18957 | S20: =SUM(L20:N20) -> 21626.7 | U20: =SUM(C20:N20) -> 147013.05 | W20: =ROUND(SUM(P20:S20)-U20,2) -> 0
B21: Accounting & Tax Fees | C21: =+'2025 Detail'!C40 -> 0 | D21: =+'2025 Detail'!D40 -> 0 | E21: =+'2025 Detail'!E40 -> 0 | F21: =+'2025 Detail'!F40 -> 0 | G21: =+'2025 Detail'!G40 -> 22482.5 | H21: =+'2025 Detail'!H40 -> 287.5 | I21: =+'2025 Detail'!I40 -> 535 | J21: =+'2025 Detail'!J40 -> 0 | ... N21: =+'2025 Detail'!N40 -> 12500 | P21: =SUM(C21:E21) -> 0 | Q21: =SUM(F21:H21) -> 22770 | R21: =SUM(I21:K21) -> 1100 | S21: =SUM(L21:N21) -> 12500 | U21: =SUM(C21:N21) -> 36370 | W21: =ROUND(SUM(P21:S21)-U21,2) -> 0
B22: Professional Fees | C22: =+'2025 Detail'!C41 -> 0 | D22: =+'2025 Detail'!D41 -> 0 | E22: =+'2025 Detail'!E41 -> 63750 | F22: =+'2025 Detail'!F41 -> 0 | G22: =+'2025 Detail'!G41 -> 25000 | H22: =+'2025 Detail'!H41 -> 0 | I22: =+'2025 Detail'!I41 -> 0 | J22: =+'2025 Detail'!J41 -> 0 | ... N22: =+'2025 Detail'!N41 -> 35000 | P22: =SUM(C22:E22) -> 63750 | Q22: =SUM(F22:H22) -> 25000 | R22: =SUM(I22:K22) -> 0 | S22: =SUM(L22:N22) -> 35000 | U22: =SUM(C22:N22) -> 123750 | W22: =ROUND(SUM(P22:S22)-U22,2) -> 0
B23: Taxes, Licenses & Permits | C23: =+'2025 Detail'!C42 -> 0 | D23: =+'2025 Detail'!D42 -> 0 | E23: =+'2025 Detail'!E42 -> 4036 | F23: =+'2025 Detail'!F42 -> 20 | G23: =+'2025 Detail'!G42 -> -326.17 | H23: =+'2025 Detail'!H42 -> 196 | I23: =+'2025 Detail'!I42 -> 112.92 | J23: =+'2025 Detail'!J42 -> 0 | ... N23: =+'2025 Detail'!N42 -> 250 | P23: =SUM(C23:E23) -> 4036 | Q23: =SUM(F23:H23) -> -110.17 | R23: =SUM(I23:K23) -> 80.92 | S23: =SUM(L23:N23) -> 438.43 | U23: =SUM(C23:N23) -> 4445.18 | W23: =ROUND(SUM(P23:S23)-U23,2) -> 0
B24: Travel & Meals | C24: =+'2025 Detail'!C43 -> 24863.58 | D24: =+'2025 Detail'!D43 -> 829.94 | E24: =+'2025 Detail'!E43 -> 2230.5 | F24: =+'2025 Detail'!F43 -> 13849.7 | G24: =+'2025 Detail'!G43 -> 20024.03 | H24: =+'2025 Detail'!H43 -> 38178.86 | I24: =+'2025 Detail'!I43 -> 9873.21 | J24: =+'2025 Detail'!J43 -> 21014.37 | ... N24: =+'2025 Detail'!N43 -> 8500 | P24: =SUM(C24:E24) -> 27924.02 | Q24: =SUM(F24:H24) -> 72052.59 | R24: =SUM(I24:K24) -> 62980.77 | S24: =SUM(L24:N24) -> 42706.5 | U24: =SUM(C24:N24) -> 205663.88 | W24: =ROUND(SUM(P24:S24)-U24,2) -> 0
B25: Total Other Spend | C25: =SUM(C16:C24) -> 40041.21 | D25: =SUM(D16:D24) -> 29960.75 | E25: =SUM(E16:E24) -> 105065.1 | F25: =SUM(F16:F24) -> 62654.94 | G25: =SUM(G16:G24) -> 120431.75 | H25: =SUM(H16:H24) -> 79882.82 | I25: =SUM(I16:I24) -> 54589.82 | J25: =SUM(J16:J24) -> 121740.49 | ... N25: =SUM(N16:N24) -> 85800 | P25: =SUM(P16:P24) -> 175067.06 | Q25: =SUM(Q16:Q24) -> 262969.51 | R25: =SUM(R16:R24) -> 235047.14 | S25: =SUM(S16:S24) -> 186342.65 | U25: =SUM(U16:U24) -> 859426.36 | W25: =ROUND(SUM(P25:S25)-U25,2) -> 0
B27: Total Cash Disbursements | C27: =+C14+C25 -> 495827.25 | D27: =+D14+D25 -> 745088.42 | E27: =+E14+E25 -> 629337.65 | F27: =+F14+F25 -> 583641.64 | G27: =+G14+G25 -> 628120.46 | H27: =+H14+H25 -> 589151.6 | I27: =+I14+I25 -> 623813.71 | J27: =+J14+J25 -> 583699.06 | ... N27: =+N14+N25 -> 528871.95 | P27: =+P14+P25 -> 1870253.3 | Q27: =+Q14+Q25 -> 1800913.7 | R27: =+R14+R25 -> 1692622.3 | S27: =+S14+S25 -> 1512024.1 | U27: =+U14+U25 -> 6875813.4 | W27: =ROUND(SUM(P27:S27)-U27,2) -> 0
B29: Guarenteed Payments | C29: =+'2025 Detail'!C48 -> 0 | D29: =+'2025 Detail'!D48 -> 0 | E29: =+'2025 Detail'!E48 -> 0 | F29: =+'2025 Detail'!F48 -> 0 | G29: =+'2025 Detail'!G48 -> 0 | H29: =+'2025 Detail'!H48 -> 0 | I29: =+'2025 Detail'!I48 -> 0 | J29: =+'2025 Detail'!J48 -> 0 | ... N29: =+'2025 Detail'!N48 -> 0 | P29: =SUM(C29:E29) -> 0 | Q29: =SUM(F29:H29) -> 0 | R29: =SUM(I29:K29) -> 0 | S29: =SUM(L29:N29) -> 0 | U29: =SUM(C29:N29) -> 0 | W29: =ROUND(SUM(P29:S29)-U29,2) -> 0
B30: Youreka Labs Inc | C30: =+'2025 Detail'!C49 -> 0 | D30: =+'2025 Detail'!D49 -> 0 | E30: =+'2025 Detail'!E49 -> 0 | F30: =+'2025 Detail'!F49 -> 0 | G30: =+'2025 Detail'!G49 -> 0 | H30: =+'2025 Detail'!H49 -> 0 | I30: =+'2025 Detail'!I49 -> 0 | J30: =+'2025 Detail'!J49 -> 0 | ... N30: =+'2025 Detail'!N49 -> 0 | P30: =SUM(C30:E30) -> 0 | Q30: =SUM(F30:H30) -> 0 | R30: =SUM(I30:K30) -> 0 | S30: =SUM(L30:N30) -> 0 | U30: =SUM(C30:N30) -> 0 | W30: =ROUND(SUM(P30:S30)-U30,2) -> 0
B31: Brex | C31: =+'2025 Detail'!C50 -> -5043.37 | D31: =+'2025 Detail'!D50 -> -5518.34 | E31: =+'2025 Detail'!E50 -> -4685.37 | F31: =+'2025 Detail'!F50 -> -3686.29 | G31: =+'2025 Detail'!G50 -> -2521.11 | H31: =+'2025 Detail'!H50 -> -957.06 | I31: =+'2025 Detail'!I50 -> -183.94 | J31: =+'2025 Detail'!J50 -> 0 | ... N31: =+'2025 Detail'!N50 -> 0 | P31: =SUM(C31:E31) -> -15247.08 | Q31: =SUM(F31:H31) -> -7164.46 | R31: =SUM(I31:K31) -> -183.94 | S31: =SUM(L31:N31) -> 0 | U31: =SUM(C31:N31) -> -22595.48 | W31: =ROUND(SUM(P31:S31)-U31,2) -> 0
B32: Chase Visa | C32: =+'2025 Detail'!C51 -> 0 | D32: =+'2025 Detail'!D51 -> -1010.7 | E32: =+'2025 Detail'!E51 -> 0 | F32: =+'2025 Detail'!F51 -> -1222.92 | G32: =+'2025 Detail'!G51 -> -2784.15 | H32: =+'2025 Detail'!H51 -> -1124.19 | I32: =+'2025 Detail'!I51 -> -1126.11 | J32: =+'2025 Detail'!J51 -> -105.74 | ... N32: =+'2025 Detail'!N51 -> 0 | P32: =SUM(C32:E32) -> -1010.7 | Q32: =SUM(F32:H32) -> -5131.26 | R32: =SUM(I32:K32) -> -1231.85 | S32: =SUM(L32:N32) -> 0 | U32: =SUM(C32:N32) -> -7373.81 | W32: =ROUND(SUM(P32:S32)-U32,2) -> 0
B33: Bank Fees | C33: =+'2025 Detail'!C53 -> -246.35 | D33: =+'2025 Detail'!D53 -> -433.54 | E33: =+'2025 Detail'!E53 -> -471.18 | F33: =+'2025 Detail'!F53 -> -346.98 | G33: =+'2025 Detail'!G53 -> -328.79 | H33: =+'2025 Detail'!H53 -> -692 | I33: =+'2025 Detail'!I53 -> -386.11 | J33: =+'2025 Detail'!J53 -> -335.21 | ... N33: =+'2025 Detail'!N53 -> -400 | P33: =SUM(C33:E33) -> -1151.07 | Q33: =SUM(F33:H33) -> -1367.77 | R33: =SUM(I33:K33) -> -1045.49 | S33: =SUM(L33:N33) -> -1052.45 | U33: =SUM(C33:N33) -> -4616.78 | W33: =ROUND(SUM(P33:S33)-U33,2) -> 0
B34: Interest | C34: =+'2025 Detail'!C54 -> 7748.71 | D34: =+'2025 Detail'!D54 -> 8351.29 | E34: =+'2025 Detail'!E54 -> 8145.22 | F34: =+'2025 Detail'!F54 -> 6912.1 | G34: =+'2025 Detail'!G54 -> 5204.78 | H34: =+'2025 Detail'!H54 -> 3887.72 | I34: =+'2025 Detail'!I54 -> 3150.25 | J34: =+'2025 Detail'!J54 -> 2155.66 | ... N34: =+'2025 Detail'!N54 -> 300 | P34: =SUM(C34:E34) -> 24245.22 | Q34: =SUM(F34:H34) -> 16004.6 | R34: =SUM(I34:K34) -> 6388.96 | S34: =SUM(L34:N34) -> 1225.61 | U34: =SUM(C34:N34) -> 47864.39 | W34: =ROUND(SUM(P34:S34)-U34,2) -> 0
B36: Opening Cash Balance | C36: =+'2025 Detail'!C56 -> 3334341 | D36: =+C41 -> 3317111 | E36: =+D41 -> 3677069.9 | F36: =+E41 -> 3325973.4 | G36: =+F41 -> 2956020.3 | H36: =+G41 -> 2520253 | I36: =+H41 -> 2023283.3 | J36: =+I41 -> 1726104.7 | K36: =+J41 -> 1329558.9 | ... N36: =+M41 -> 670150.08 | P36: =+C36 -> 3334341 | Q36: =+P41 -> 3325973 | R36: =+Q41 -> 2023283 | S36: =+R41 -> 954186 | U36: =+P36 -> 3334341
B38: Net Change | C38: =C8-C27+SUM(C29:C34) -> -217229.4 | D38: =D8-D27+SUM(D29:D34) -> -390040.61 | E38: =E8-E27+SUM(E29:E34) -> -351096.5 | F38: =F8-F27+SUM(F29:F34) -> -369953.03 | G38: =G8-G27+SUM(G29:G34) -> -435767.33 | H38: =H8-H27+SUM(H29:H34) -> -471969.73 | I38: =I8-I27+SUM(I29:I34) -> -297178.62 | J38: =J8-J27+SUM(J29:J34) -> -396545.75 | ... N38: =N8-N27+SUM(N29:N34) -> 318960.65 | P38: =SUM(C38:E38) -> -958366.51 | Q38: =SUM(F38:H38) -> -1277690.1 | R38: =SUM(I38:K38) -> -1069097.5 | S38: =SUM(L38:N38) -> 34924.93 | U38: =SUM(C38:N38) -> -3270229.1 | W38: =ROUND(SUM(P38:S38)-U38,2) -> 0
B39: Investment | C39: =+'2025 Detail'!C59 -> 199999.42 | D39: =+'2025 Detail'!D59 -> 749999.44 | E39: =+'2025 Detail'!E59 -> 0 | F39: =+'2025 Detail'!F59 -> 0 | G39: =+'2025 Detail'!G59 -> 0 | H39: =+'2025 Detail'!H59 -> -25000 | I39: =+'2025 Detail'!I59 -> 0 | J39: =+'2025 Detail'!J59 -> 0 | ... N39: =+'2025 Detail'!N59 -> -25000 | P39: =SUM(C39:E39) -> 949998.86 | Q39: =SUM(F39:H39) -> -25000 | R39: =SUM(I39:K39) -> 0 | S39: =SUM(L39:N39) -> -25000 | U39: =SUM(C39:N39) -> 899998.86 | W39: =ROUND(SUM(P39:S39)-U39,2) -> 0
B41: Ending Cash Balance | C41: =ROUND(+C36+C38+C39,2) -> 3317111 | D41: =ROUND(+D36+D38+D39,2) -> 3677069.9 | E41: =ROUND(+E36+E38+E39,2) -> 3325973.4 | F41: =ROUND(+F36+F38+F39,2) -> 2956020.3 | G41: =ROUND(+G36+G38+G39,2) -> 2520253 | H41: =ROUND(+H36+H38+H39,2) -> 2023283.3 | I41: =ROUND(+I36+I38+I39,2) -> 1726104.7 | J41: =ROUND(+J36+J38+J39,2) -> 1329558.9 | ... N41: =ROUND(+N36+N38+N39,2) -> 964110.73 | P41: =ROUND(+P36+P38+P39,0) -> 3325973 | Q41: =ROUND(+Q36+Q38+Q39,0) -> 2023283 | R41: =ROUND(+R36+R38+R39,0) -> 954186 | S41: =ROUND(+S36+S38+S39,0) -> 964111 | U41: =ROUND(+U36+U38+U39,0) -> 964111
B43: Cash In | C43: =+C8 -> 276138.86 | D43: =+D8 -> 353659.1 | E43: =+E8 -> 275252.48 | F43: =+F8 -> 212032.7 | G43: =+G8 -> 192782.4 | H43: =+H8 -> 116067.4 | I43: =+I8 -> 325181 | J43: =+J8 -> 185438.6 | ... N43: =+N8 -> 847932.6 | P43: =+P8 -> 905050.44 | Q43: =+Q8 -> 520882.5 | R43: =+R8 -> 619597.1 | S43: =+S8 -> 1546775.9 | U43: =+U8 -> 3592305.9
B44: Calculated COGS | C44: =+C10 -> 237094.69 | D44: =+D10 -> 373512.69 | E44: =+E10 -> 223536.76 | F44: =+F10 -> 187863.78 | G44: =+G10 -> 191763.05 | H44: =+H10 -> 197231.83 | I44: =+I10 -> 187788.92 | J44: =+J10 -> 186132.84 | ... N44: =+N10 -> 194610 | P44: =+P10 -> 834144.13 | Q44: =+Q10 -> 576858.66 | R44: =+R10 -> 562447.14 | S44: =+S10 -> 584581.13 | U44: =+U10 -> 2558031.1
B45: Gross Margin | C45: =+C43-C44 -> 39044.174 | D45: =+D43-D44 -> -19853.588 | E45: =+E43-E44 -> 51715.722 | F45: =+F43-F44 -> 24168.919 | G45: =+G43-G44 -> 1019.3506 | H45: =+H43-H44 -> -81164.431 | I45: =+I43-I44 -> 137392.08 | J45: =+J43-J44 -> -694.24222 | ... N45: =+N43-N44 -> 653322.6 | P45: =+P43-P44 -> 70906.308 | Q45: =+Q43-Q44 -> -55976.161 | R45: =+R43-R44 -> 57149.956 | S45: =+S43-S44 -> 962194.77 | U45: =+U43-U44 -> 1034274.9
B46: GM % | C46: =+C45/C43 -> 0.14139326 | D46: =+D45/D43 -> -0.056137642 | E46: =+E45/E43 -> 0.18788467 | F46: =+F45/F43 -> 0.11398675 | G46: =+G45/G43 -> 0.005287571 | H46: =+H45/H43 -> -0.69928706 | I46: =+I45/I43 -> 0.42250955 | J46: =+J45/J43 -> -0.0037437849 | ... N46: =+N45/N43 -> 0.77048883 | P46: =+P45/P43 -> 0.078345146 | Q46: =+Q45/Q43 -> -0.10746408 | R46: =+R45/R43 -> 0.092237288 | S46: =+S45/S43 -> 0.62206476 | U46: =+U45/U43 -> 0.28791392
B48: Check | C48: =+C41-'2025 Detail'!C61 -> 0 | D48: =+D41-'2025 Detail'!D61 -> 0 | E48: =+E41-'2025 Detail'!E61 -> 0 | F48: =+F41-'2025 Detail'!F61 -> 0 | G48: =+G41-'2025 Detail'!G61 -> 0 | H48: =+H41-'2025 Detail'!H61 -> 0 | I48: =+I41-'2025 Detail'!I61 -> 0 | J48: =+J41-'2025 Detail'!J61 -> 0 | ... N48: =+N41-'2025 Detail'!N61 -> 0

Sheet 2025 Detail
B2: SYNAPTIC CASH FLOW FORECAST | C2: 45658 | D2: =EDATE(C2,1) -> 45689 | E2: =EDATE(D2,1) -> 45717 | F2: =EDATE(E2,1) -> 45748 | G2: =EDATE(F2,1) -> 45778 | H2: =EDATE(G2,1) -> 45809 | I2: =EDATE(H2,1) -> 45839 | J2: =EDATE(I2,1) -> 45870 | K2: =EDATE(J2,1) -> 45901 | ... N2: =EDATE(M2,1) -> 45992 | P2: Q1 | Q2: Q2 | R2: Q3 | S2: Q4 | U2: 2025 | W2: Check
B3: =+Version!$C$3 -> Y2025 12 v001
B5: HLS | C5: =+'1 Collections'!E29 -> 80791.9 | D5: =+'1 Collections'!F29 -> 26087.5 | E5: =+'1 Collections'!G29 -> 37975 | F5: =+'1 Collections'!H29 -> 30025 | G5: =+'1 Collections'!I29 -> 24950 | H5: =+'1 Collections'!J29 -> 13706.25 | I5: =+'1 Collections'!K29 -> 15950 | J5: =+'1 Collections'!L29 -> 5192.5 | ... N5: =+'1 Collections'!P29 -> 1930 | P5: =SUM(C5:E5) -> 144854.4 | Q5: =SUM(F5:H5) -> 68681.25 | R5: =SUM(I5:K5) -> 28510 | S5: =SUM(L5:N5) -> 6540 | U5: =SUM(C5:N5) -> 248585.65 | W5: =ROUND(SUM(P5:S5)-U5,2) -> 0
B6: PSS | C6: =+'1 Collections'!E30 -> 162319.6 | D6: =+'1 Collections'!F30 -> 101637.6 | E6: =+'1 Collections'!G30 -> 110984.5 | F6: =+'1 Collections'!H30 -> 145135.2 | G6: =+'1 Collections'!I30 -> 165203.6 | H6: =+'1 Collections'!J30 -> 39277.6 | I6: =+'1 Collections'!K30 -> 166597.6 | J6: =+'1 Collections'!L30 -> 57512 | ... N6: =+'1 Collections'!P30 -> 138214 | P6: =SUM(C6:E6) -> 374941.7 | Q6: =SUM(F6:H6) -> 349616.4 | R6: =SUM(I6:K6) -> 281609.6 | S6: =SUM(L6:N6) -> 534745 | U6: =SUM(C6:N6) -> 1540912.7 | W6: =ROUND(SUM(P6:S6)-U6,2) -> 0
B7: ENT | C7: =+'1 Collections'!E31 -> 33027.36 | D7: =+'1 Collections'!F31 -> 175934 | E7: =+'1 Collections'!G31 -> 0 | F7: =+'1 Collections'!H31 -> 495 | G7: =+'1 Collections'!I31 -> 2628.8 | H7: =+'1 Collections'!J31 -> 22769.05 | I7: =+'1 Collections'!K31 -> 73633.4 | J7: =+'1 Collections'!L31 -> 41456.5 | ... N7: =+'1 Collections'!P31 -> 195011 | P7: =SUM(C7:E7) -> 208961.36 | Q7: =SUM(F7:H7) -> 25892.85 | R7: =SUM(I7:K7) -> 137199.9 | S7: =SUM(L7:N7) -> 225630.5 | U7: =SUM(C7:N7) -> 597684.61 | W7: =ROUND(SUM(P7:S7)-U7,2) -> 0
B8: Total Classic | C8: =SUM(C5:C7) -> 276138.86 | D8: =SUM(D5:D7) -> 303659.1 | E8: =SUM(E5:E7) -> 148959.5 | F8: =SUM(F5:F7) -> 175655.2 | G8: =SUM(G5:G7) -> 192782.4 | H8: =SUM(H5:H7) -> 75752.9 | I8: =SUM(I5:I7) -> 256181 | J8: =SUM(J5:J7) -> 104161 | ... N8: =SUM(N5:N7) -> 335155 | P8: =SUM(P5:P7) -> 728757.46 | Q8: =SUM(Q5:Q7) -> 444190.5 | R8: =SUM(R5:R7) -> 447319.5 | S8: =SUM(S5:S7) -> 766915.5 | U8: =SUM(U5:U7) -> 2387183 | W8: =ROUND(SUM(P8:S8)-U8,2) -> 0
B10: HLS | C10: =+'1 Collections'!E34 -> 0 | D10: =+'1 Collections'!F34 -> 50000 | E10: =+'1 Collections'!G34 -> 126292.98 | F10: =+'1 Collections'!H34 -> 11377.5 | G10: =+'1 Collections'!I34 -> 0 | H10: =+'1 Collections'!J34 -> 30327.5 | I10: =+'1 Collections'!K34 -> 0 | J10: =+'1 Collections'!L34 -> 0 | ... N10: =+'1 Collections'!P34 -> 203000 | P10: =SUM(C10:E10) -> 176292.98 | Q10: =SUM(F10:H10) -> 41705 | R10: =SUM(I10:K10) -> 0 | S10: =SUM(L10:N10) -> 306250 | U10: =SUM(C10:N10) -> 524247.98 | W10: =ROUND(SUM(P10:S10)-U10,2) -> 0
B11: PSS | C11: =+'1 Collections'!E35 -> 0 | D11: =+'1 Collections'!F35 -> 0 | E11: =+'1 Collections'!G35 -> 0 | F11: =+'1 Collections'!H35 -> 0 | G11: =+'1 Collections'!I35 -> 0 | H11: =+'1 Collections'!J35 -> 9987 | I11: =+'1 Collections'!K35 -> 0 | J11: =+'1 Collections'!L35 -> 39277.6 | ... N11: =+'1 Collections'!P35 -> 269777.6 | P11: =SUM(C11:E11) -> 0 | Q11: =SUM(F11:H11) -> 9987 | R11: =SUM(I11:K11) -> 39277.6 | S11: =SUM(L11:N11) -> 387610.4 | U11: =SUM(C11:N11) -> 436875 | W11: =ROUND(SUM(P11:S11)-U11,2) -> 0
B12: ENT | C12: =+'1 Collections'!E36 -> 0 | D12: =+'1 Collections'!F36 -> 0 | E12: =+'1 Collections'!G36 -> 0 | F12: =+'1 Collections'!H36 -> 25000 | G12: =+'1 Collections'!I36 -> 0 | H12: =+'1 Collections'!J36 -> 0 | I12: =+'1 Collections'!K36 -> 69000 | J12: =+'1 Collections'!L36 -> 42000 | ... N12: =+'1 Collections'!P36 -> 40000 | P12: =SUM(C12:E12) -> 0 | Q12: =SUM(F12:H12) -> 25000 | R12: =SUM(I12:K12) -> 133000 | S12: =SUM(L12:N12) -> 86000 | U12: =SUM(C12:N12) -> 244000 | W12: =ROUND(SUM(P12:S12)-U12,2) -> 0
B13: Total AppIQ | C13: =SUM(C10:C12) -> 0 | D13: =SUM(D10:D12) -> 50000 | E13: =SUM(E10:E12) -> 126292.98 | F13: =SUM(F10:F12) -> 36377.5 | G13: =SUM(G10:G12) -> 0 | H13: =SUM(H10:H12) -> 40314.5 | I13: =SUM(I10:I12) -> 69000 | J13: =SUM(J10:J12) -> 81277.6 | ... N13: =SUM(N10:N12) -> 512777.6 | P13: =SUM(P10:P12) -> 176292.98 | Q13: =SUM(Q10:Q12) -> 76692 | R13: =SUM(R10:R12) -> 172277.6 | S13: =SUM(S10:S12) -> 779860.4 | U13: =SUM(U10:U12) -> 1205123 | W13: =ROUND(SUM(P13:S13)-U13,2) -> 0
B15: Total Cash Collected | C15: =+C8+C13 -> 276138.86 | D15: =+D8+D13 -> 353659.1 | E15: =+E8+E13 -> 275252.48 | F15: =+F8+F13 -> 212032.7 | G15: =+G8+G13 -> 192782.4 | H15: =+H8+H13 -> 116067.4 | I15: =+I8+I13 -> 325181 | J15: =+J8+J13 -> 185438.6 | ... N15: =+N8+N13 -> 847932.6 | P15: =+P8+P13 -> 905050.44 | Q15: =+Q8+Q13 -> 520882.5 | R15: =+R8+R13 -> 619597.1 | S15: =+S8+S13 -> 1546775.9 | U15: =+U8+U13 -> 3592305.9 | W15: =ROUND(SUM(P15:S15)-U15,2) -> 0
B17: Delivery - W2 | C17: =+'2 Employees'!C80+'3 Benefits'!C104 -> 155026.31 | D17: =+'2 Employees'!D80+'3 Benefits'!D104 -> 274377.44 | E17: =+'2 Employees'!E80+'3 Benefits'!E104 -> 140023.01 | F17: =+'2 Employees'!F80+'3 Benefits'!F104 -> 126333.53 | G17: =+'2 Employees'!G80+'3 Benefits'!G104 -> 127019.55 | H17: =+'2 Employees'!H80+'3 Benefits'!H104 -> 129349.58 | I17: =+'2 Employees'!I80+'3 Benefits'!I104 -> 126181.92 | J17: =+'2 Employees'!J80+'3 Benefits'!J104 -> 124588.76 | ... N17: =+'2 Employees'!N80+'3 Benefits'!N104 -> 126510 | P17: =SUM(C17:E17) -> 569426.75 | Q17: =SUM(F17:H17) -> 382702.66 | R17: =SUM(I17:K17) -> 374597.06 | S17: =SUM(L17:N17) -> 372284.88 | U17: =SUM(C17:N17) -> 1699011.4 | W17: =ROUND(SUM(P17:S17)-U17,2) -> 0
B18: Delivery - Contractor | C18: =+'4 Contractors'!C29+'4 Contractors'!C142 -> 82068.38 | D18: =+'4 Contractors'!D29+'4 Contractors'!D142 -> 99135.25 | E18: =+'4 Contractors'!E29+'4 Contractors'!E142 -> 81353.75 | F18: =+'4 Contractors'!F29+'4 Contractors'!F142 -> 58506.25 | G18: =+'4 Contractors'!G29+'4 Contractors'!G142 -> 61313.5 | H18: =+'4 Contractors'!H29+'4 Contractors'!H142 -> 59235.25 | I18: =+'4 Contractors'!I29+'4 Contractors'!I142 -> 48960 | J18: =+'4 Contractors'!J29+'4 Contractors'!J142 -> 49996.08 | ... N18: =+'4 Contractors'!N29+'4 Contractors'!N142 -> 57500 | P18: =SUM(C18:E18) -> 262557.38 | Q18: =SUM(F18:H18) -> 179055 | R18: =SUM(I18:K18) -> 152843.08 | S18: =SUM(L18:N18) -> 190104.25 | U18: =SUM(C18:N18) -> 784559.71 | W18: =ROUND(SUM(P18:S18)-U18,2) -> 0
B19: GTM - W2 | C19: =+'2 Employees'!C123+'3 Benefits'!C105 -> 40442.092 | D19: =+'2 Employees'!D123+'3 Benefits'!D105 -> 73453.686 | E19: =+'2 Employees'!E123+'3 Benefits'!E105 -> 38585.803 | F19: =+'2 Employees'!F123+'3 Benefits'!F105 -> 40144.619 | G19: =+'2 Employees'!G123+'3 Benefits'!G105 -> 40438.647 | H19: =+'2 Employees'!H123+'3 Benefits'!H105 -> 41437.228 | I19: =+'2 Employees'!I123+'3 Benefits'!I105 -> 40525.576 | J19: =+'2 Employees'!J123+'3 Benefits'!J105 -> 40196.537 | ... N19: =+'2 Employees'!N123+'3 Benefits'!N105 -> 40600 | P19: =SUM(C19:E19) -> 152481.58 | Q19: =SUM(F19:H19) -> 122020.49 | R19: =SUM(I19:K19) -> 120181.18 | S19: =SUM(L19:N19) -> 119549.89 | U19: =SUM(C19:N19) -> 514233.15 | W19: =ROUND(SUM(P19:S19)-U19,2) -> 0
B20: GTM - Contractor | C20: =+'4 Contractors'!C46 -> 12121.26 | D20: =+'4 Contractors'!D46 -> 12000 | E20: =+'4 Contractors'!E46 -> 16141.55 | F20: =+'4 Contractors'!F46 -> 12000 | G20: =+'4 Contractors'!G46 -> 12199.26 | H20: =+'4 Contractors'!H46 -> 12000 | I20: =+'4 Contractors'!I46 -> 8000 | J20: =+'4 Contractors'!J46 -> 0 | ... N20: =+'4 Contractors'!N46 -> 0 | P20: =SUM(C20:E20) -> 40262.81 | Q20: =SUM(F20:H20) -> 36199.26 | R20: =SUM(I20:K20) -> 8000 | S20: =SUM(L20:N20) -> 0 | U20: =SUM(C20:N20) -> 84462.07 | W20: =ROUND(SUM(P20:S20)-U20,2) -> 0
B21: Total Spend Classic | C21: =SUM(C17:C20) -> 289658.04 | D21: =SUM(D17:D20) -> 458966.37 | E21: =SUM(E17:E20) -> 276104.11 | F21: =SUM(F17:F20) -> 236984.4 | G21: =SUM(G17:G20) -> 240970.96 | H21: =SUM(H17:H20) -> 242022.06 | I21: =SUM(I17:I20) -> 223667.5 | J21: =SUM(J17:J20) -> 214781.38 | ... N21: =SUM(N17:N20) -> 224610 | P21: =SUM(P17:P20) -> 1024728.5 | Q21: =SUM(Q17:Q20) -> 719977.41 | R21: =SUM(R17:R20) -> 655621.33 | S21: =SUM(S17:S20) -> 681939.02 | U21: =SUM(U17:U20) -> 3082266.3 | W21: =ROUND(SUM(P21:S21)-U21,2) -> 0
B23: Delivery - W2 | C23: =+'2 Employees'!C156+'3 Benefits'!C108 -> 0 | D23: =+'2 Employees'!D156+'3 Benefits'!D108 -> 0 | E23: =+'2 Employees'!E156+'3 Benefits'!E108 -> 0 | F23: =+'2 Employees'!F156+'3 Benefits'!F108 -> 0 | G23: =+'2 Employees'!G156+'3 Benefits'!G108 -> 0 | H23: =+'2 Employees'!H156+'3 Benefits'!H108 -> 0 | I23: =+'2 Employees'!I156+'3 Benefits'!I108 -> 0 | J23: =+'2 Employees'!J156+'3 Benefits'!J108 -> 0 | ... N23: =+'2 Employees'!N156+'3 Benefits'!N108 -> 0 | P23: =SUM(C23:E23) -> 0 | Q23: =SUM(F23:H23) -> 0 | R23: =SUM(I23:K23) -> 0 | S23: =SUM(L23:N23) -> 0 | U23: =SUM(C23:N23) -> 0 | W23: =ROUND(SUM(P23:S23)-U23,2) -> 0
B24: Delivery - Contractor | C24: =+'4 Contractors'!C63 -> 0 | D24: =+'4 Contractors'!D63 -> 0 | E24: =+'4 Contractors'!E63 -> 2160 | F24: =+'4 Contractors'!F63 -> 3024 | G24: =+'4 Contractors'!G63 -> 3430 | H24: =+'4 Contractors'!H63 -> 8647 | I24: =+'4 Contractors'!I63 -> 12647 | J24: =+'4 Contractors'!J63 -> 11548 | ... N24: =+'4 Contractors'!N63 -> 10600 | P24: =SUM(C24:E24) -> 2160 | Q24: =SUM(F24:H24) -> 15101 | R24: =SUM(I24:K24) -> 35007 | S24: =SUM(L24:N24) -> 22192 | U24: =SUM(C24:N24) -> 74460 | W24: =ROUND(SUM(P24:S24)-U24,2) -> 0
B25: GTM - W2 | C25: =+'2 Employees'!C189+'3 Benefits'!C109 -> 0 | D25: =+'2 Employees'!D189+'3 Benefits'!D109 -> 0 | E25: =+'2 Employees'!E189+'3 Benefits'!E109 -> 0 | F25: =+'2 Employees'!F189+'3 Benefits'!F109 -> 34139.876 | G25: =+'2 Employees'!G189+'3 Benefits'!G109 -> 46418.631 | H25: =+'2 Employees'!H189+'3 Benefits'!H109 -> 46843.852 | I25: =+'2 Employees'!I189+'3 Benefits'!I109 -> 36071.078 | J25: =+'2 Employees'!J189+'3 Benefits'!J109 -> 27739.718 | ... N25: =+'2 Employees'!N189+'3 Benefits'!N109 -> 33850 | P25: =SUM(C25:E25) -> 0 | Q25: =SUM(F25:H25) -> 127402.36 | R25: =SUM(I25:K25) -> 83403.975 | S25: =SUM(L25:N25) -> 65469.754 | U25: =SUM(C25:N25) -> 276276.09 | W25: =ROUND(SUM(P25:S25)-U25,2) -> 0
B26: GTM - Contractor | C26: =+'4 Contractors'!C89 -> 25440.49 | D26: =+'4 Contractors'!D89 -> 54928.6 | E26: =+'4 Contractors'!E89 -> 71765.61 | F26: =+'4 Contractors'!F89 -> 75263.6 | G26: =+'4 Contractors'!G89 -> 45097.52 | H26: =+'4 Contractors'!H89 -> 28442.12 | I26: =+'4 Contractors'!I89 -> 107654.23 | J26: =+'4 Contractors'!J89 -> 19633.75 | ... N26: =+'4 Contractors'!N89 -> 46700 | P26: =SUM(C26:E26) -> 152134.7 | Q26: =SUM(F26:H26) -> 148803.24 | R26: =SUM(I26:K26) -> 142676.98 | S26: =SUM(L26:N26) -> 86097.63 | U26: =SUM(C26:N26) -> 529712.55 | W26: =ROUND(SUM(P26:S26)-U26,2) -> 0
B27: R&D - W2 | C27: =+'2 Employees'!C227+'3 Benefits'!C110 -> 23645.881 | D27: =+'2 Employees'!D227+'3 Benefits'!D110 -> 23206.142 | E27: =+'2 Employees'!E227+'3 Benefits'!E110 -> 42806.165 | F27: =+'2 Employees'!F227+'3 Benefits'!F110 -> 40594.269 | G27: =+'2 Employees'!G227+'3 Benefits'!G110 -> 35576.491 | H27: =+'2 Employees'!H227+'3 Benefits'!H110 -> 45030.208 | I27: =+'2 Employees'!I227+'3 Benefits'!I110 -> 54965.226 | J27: =+'2 Employees'!J227+'3 Benefits'!J110 -> 61914.096 | ... N27: =+'2 Employees'!N227+'3 Benefits'!N110 -> 39300 | P27: =SUM(C27:E27) -> 89658.188 | Q27: =SUM(F27:H27) -> 121200.97 | R27: =SUM(I27:K27) -> 155392.55 | S27: =SUM(L27:N27) -> 116272.13 | U27: =SUM(C27:N27) -> 482523.84 | W27: =ROUND(SUM(P27:S27)-U27,2) -> 0
B28: R&D - Contractor | C28: =+'4 Contractors'!C111 -> 43402.15 | D28: =+'4 Contractors'!D111 -> 56923.22 | E28: =+'4 Contractors'!E111 -> 49015.88 | F28: =+'4 Contractors'!F111 -> 52268.69 | G28: =+'4 Contractors'!G111 -> 58911.29 | H28: =+'4 Contractors'!H111 -> 60784 | I28: =+'4 Contractors'!I111 -> 53257.33 | J28: =+'4 Contractors'!J111 -> 49276.72 | ... N28: =+'4 Contractors'!N111 -> 21461.95 | P28: =SUM(C28:E28) -> 149341.25 | Q28: =SUM(F28:H28) -> 171963.98 | R28: =SUM(I28:K28) -> 149603.14 | S28: =SUM(L28:N28) -> 143775.13 | U28: =SUM(C28:N28) -> 614683.5 | W28: =ROUND(SUM(P28:S28)-U28,2) -> 0
B29: Total Spend AppIQ | C29: =SUM(C23:C28) -> 92488.521 | D29: =SUM(D23:D28) -> 135057.96 | E29: =SUM(E23:E28) -> 165747.65 | F29: =SUM(F23:F28) -> 205290.43 | G29: =SUM(G23:G28) -> 189433.93 | H29: =SUM(H23:H28) -> 189747.18 | I29: =SUM(I23:I28) -> 264594.86 | J29: =SUM(J23:J28) -> 170112.28 | ... N29: =SUM(N23:N28) -> 151911.95 | P29: =SUM(P23:P28) -> 393294.14 | Q29: =SUM(Q23:Q28) -> 584471.55 | R29: =SUM(R23:R28) -> 566083.65 | S29: =SUM(S23:S28) -> 433806.64 | U29: =SUM(U23:U28) -> 1977656 | W29: =ROUND(SUM(P29:S29)-U29,2) -> 0
B31: Back Office - W2 | C31: =+'2 Employees'!C280+'3 Benefits'!C113 -> 56009.581 | D31: =+'2 Employees'!D280+'3 Benefits'!D113 -> 99933.334 | E31: =+'2 Employees'!E280+'3 Benefits'!E113 -> 52560.785 | F31: =+'2 Employees'!F280+'3 Benefits'!F113 -> 52591.866 | G31: =+'2 Employees'!G280+'3 Benefits'!G113 -> 50755.491 | H31: =+'2 Employees'!H280+'3 Benefits'!H113 -> 51421.212 | I31: =+'2 Employees'!I280+'3 Benefits'!I113 -> 53980.698 | J31: =+'2 Employees'!J280+'3 Benefits'!J113 -> 50594.078 | ... N31: =+'2 Employees'!N280+'3 Benefits'!N113 -> 41150 | P31: =SUM(C31:E31) -> 208503.7 | Q31: =SUM(F31:H31) -> 154768.57 | R31: =SUM(I31:K31) -> 155135.16 | S31: =SUM(L31:N31) -> 132689.16 | U31: =SUM(C31:N31) -> 651096.58 | W31: =ROUND(SUM(P31:S31)-U31,2) -> 0
B32: Back Office - Contractor | C32: =+'4 Contractors'!C129 -> 17629.9 | D32: =+'4 Contractors'!D129 -> 21170 | E32: =+'4 Contractors'!E129 -> 29860 | F32: =+'4 Contractors'!F129 -> 26120 | G32: =+'4 Contractors'!G129 -> 26528.33 | H32: =+'4 Contractors'!H129 -> 26078.33 | I32: =+'4 Contractors'!I129 -> 26980.83 | J32: =+'4 Contractors'!J129 -> 26470.83 | ... N32: =+'4 Contractors'!N129 -> 25400 | P32: =SUM(C32:E32) -> 68659.9 | Q32: =SUM(F32:H32) -> 78726.66 | R32: =SUM(I32:K32) -> 80734.99 | S32: =SUM(L32:N32) -> 77246.66 | U32: =SUM(C32:N32) -> 305368.21 | W32: =ROUND(SUM(P32:S32)-U32,2) -> 0
B33: Total Spend Back Office | C33: =SUM(C31:C32) -> 73639.481 | D33: =SUM(D31:D32) -> 121103.33 | E33: =SUM(E31:E32) -> 82420.785 | F33: =SUM(F31:F32) -> 78711.866 | G33: =SUM(G31:G32) -> 77283.821 | H33: =SUM(H31:H32) -> 77499.542 | I33: =SUM(I31:I32) -> 80961.528 | J33: =SUM(J31:J32) -> 77064.908 | ... N33: =SUM(N31:N32) -> 66550 | P33: =SUM(P31:P32) -> 277163.6 | Q33: =SUM(Q31:Q32) -> 233495.23 | R33: =SUM(R31:R32) -> 235870.15 | S33: =SUM(S31:S32) -> 209935.82 | U33: =SUM(U31:U32) -> 956464.79 | W33: =ROUND(SUM(P33:S33)-U33,2) -> 0
B35: Rent | C35: =+'6 Other'!C5 -> 0 | D35: =+'6 Other'!D5 -> 0 | E35: =+'6 Other'!E5 -> 0 | F35: =+'6 Other'!F5 -> 0 | G35: =+'6 Other'!G5 -> 3545.63 | H35: =+'6 Other'!H5 -> 3545.63 | I35: =+'6 Other'!I5 -> 7091.26 | J35: =+'6 Other'!J5 -> 3545.63 | ... N35: =+'6 Other'!N5 -> 3550 | P35: =SUM(C35:E35) -> 0 | Q35: =SUM(F35:H35) -> 7091.26 | R35: =SUM(I35:K35) -> 14182.52 | S35: =SUM(L35:N35) -> 10641.26 | U35: =SUM(C35:N35) -> 31915.04 | W35: =ROUND(SUM(P35:S35)-U35,2) -> 0
B36: Hardware & Software | C36: =+'6 Other'!C6 -> 3866.9 | D36: =+'6 Other'!D6 -> 4575.9 | E36: =+'6 Other'!E6 -> 12536.15 | F36: =+'6 Other'!F6 -> 11114.35 | G36: =+'6 Other'!G6 -> 24774.02 | H36: =+'6 Other'!H6 -> 23118.32 | I36: =+'6 Other'!I6 -> 22036.41 | J36: =+'6 Other'!J6 -> 91840.73 | ... N36: =+'6 Other'!N6 -> 12000 | P36: =SUM(C36:E36) -> 20978.95 | Q36: =SUM(F36:H36) -> 59006.69 | R36: =SUM(I36:K36) -> 124166.61 | S36: =SUM(L36:N36) -> 48307.86 | U36: =SUM(C36:N36) -> 252460.11 | W36: =ROUND(SUM(P36:S36)-U36,2) -> 0
B37: Office & Supplies | C37: =+'6 Other'!C7 -> 263.76 | D37: =+'6 Other'!D7 -> 807.23 | E37: =+'6 Other'!E7 -> 556.56 | F37: =+'6 Other'!F7 -> 556 | G37: =+'6 Other'!G7 -> 354.79 | H37: =+'6 Other'!H7 -> 1130.57 | I37: =+'6 Other'!I7 -> 355.28 | J37: =+'6 Other'!J7 -> 1606.02 | ... N37: =+'6 Other'!N7 -> 500 | P37: =SUM(C37:E37) -> 1627.55 | Q37: =SUM(F37:H37) -> 2041.36 | R37: =SUM(I37:K37) -> 3176.35 | S37: =SUM(L37:N37) -> 5020.86 | U37: =SUM(C37:N37) -> 11866.12 | W37: =ROUND(SUM(P37:S37)-U37,2) -> 0
B38: Insurance | C38: =+'6 Other'!C8 -> 496.97 | D38: =+'6 Other'!D8 -> 8280.18 | E38: =+'6 Other'!E8 -> 3089.89 | F38: =+'6 Other'!F8 -> 8984.89 | G38: =+'6 Other'!G8 -> 1547.55 | H38: =+'6 Other'!H8 -> 3039.49 | I38: =+'6 Other'!I8 -> 5580.24 | J38: =+'6 Other'!J8 -> 1783.24 | ... N38: =+'6 Other'!N8 -> 2500 | P38: =SUM(C38:E38) -> 11867.04 | Q38: =SUM(F38:H38) -> 13571.93 | R38: =SUM(I38:K38) -> 10402.97 | S38: =SUM(L38:N38) -> 10101.04 | U38: =SUM(C38:N38) -> 45942.98 | W38: =ROUND(SUM(P38:S38)-U38,2) -> 0
B39: Legal Fees | C39: =+'6 Other'!C9 -> 10550 | D39: =+'6 Other'!D9 -> 15467.5 | E39: =+'6 Other'!E9 -> 18866 | F39: =+'6 Other'!F9 -> 28130 | G39: =+'6 Other'!G9 -> 23029.4 | H39: =+'6 Other'!H9 -> 10386.45 | I39: =+'6 Other'!I9 -> 9005.5 | J39: =+'6 Other'!J9 -> 1950.5 | ... N39: =+'6 Other'!N9 -> 11000 | P39: =SUM(C39:E39) -> 44883.5 | Q39: =SUM(F39:H39) -> 61545.85 | R39: =SUM(I39:K39) -> 18957 | S39: =SUM(L39:N39) -> 21626.7 | U39: =SUM(C39:N39) -> 147013.05 | W39: =ROUND(SUM(P39:S39)-U39,2) -> 0
B40: Accounting & Tax Fees | C40: =+'6 Other'!C10 -> 0 | D40: =+'6 Other'!D10 -> 0 | E40: =+'6 Other'!E10 -> 0 | F40: =+'6 Other'!F10 -> 0 | G40: =+'6 Other'!G10 -> 22482.5 | H40: =+'6 Other'!H10 -> 287.5 | I40: =+'6 Other'!I10 -> 535 | J40: =+'6 Other'!J10 -> 0 | ... N40: =+'6 Other'!N10 -> 12500 | P40: =SUM(C40:E40) -> 0 | Q40: =SUM(F40:H40) -> 22770 | R40: =SUM(I40:K40) -> 1100 | S40: =SUM(L40:N40) -> 12500 | U40: =SUM(C40:N40) -> 36370 | W40: =ROUND(SUM(P40:S40)-U40,2) -> 0
B41: Professional Fees | C41: =+'6 Other'!C11 -> 0 | D41: =+'6 Other'!D11 -> 0 | E41: =+'6 Other'!E11 -> 63750 | F41: =+'6 Other'!F11 -> 0 | G41: =+'6 Other'!G11 -> 25000 | H41: =+'6 Other'!H11 -> 0 | I41: =+'6 Other'!I11 -> 0 | J41: =+'6 Other'!J11 -> 0 | ... N41: =+'6 Other'!N11 -> 35000 | P41: =SUM(C41:E41) -> 63750 | Q41: =SUM(F41:H41) -> 25000 | R41: =SUM(I41:K41) -> 0 | S41: =SUM(L41:N41) -> 35000 | U41: =SUM(C41:N41) -> 123750 | W41: =ROUND(SUM(P41:S41)-U41,2) -> 0
B42: Taxes, Licenses & Permits | C42: =+'6 Other'!C12 -> 0 | D42: =+'6 Other'!D12 -> 0 | E42: =+'6 Other'!E12 -> 4036 | F42: =+'6 Other'!F12 -> 20 | G42: =+'6 Other'!G12 -> -326.17 | H42: =+'6 Other'!H12 -> 196 | I42: =+'6 Other'!I12 -> 112.92 | J42: =+'6 Other'!J12 -> 0 | ... N42: =+'6 Other'!N12 -> 250 | P42: =SUM(C42:E42) -> 4036 | Q42: =SUM(F42:H42) -> -110.17 | R42: =SUM(I42:K42) -> 80.92 | S42: =SUM(L42:N42) -> 438.43 | U42: =SUM(C42:N42) -> 4445.18 | W42: =ROUND(SUM(P42:S42)-U42,2) -> 0
B43: Travel & Meals | C43: =SUM('6 Other'!C13:C13) -> 24863.58 | D43: =SUM('6 Other'!D13:D13) -> 829.94 | E43: =SUM('6 Other'!E13:E13) -> 2230.5 | F43: =SUM('6 Other'!F13:F13) -> 13849.7 | G43: =SUM('6 Other'!G13:G13) -> 20024.03 | H43: =SUM('6 Other'!H13:H13) -> 38178.86 | I43: =SUM('6 Other'!I13:I13) -> 9873.21 | J43: =SUM('6 Other'!J13:J13) -> 21014.37 | K43: =SUM('6 Other'!K13:K13) -> 32093.19 | L43: =+'6 Other'!L13 -> 21464.5 | M43: =+'6 Other'!M13 -> 12742 | N43: =+'6 Other'!N13 -> 8500 | P43: =SUM(C43:E43) -> 27924.02 | Q43: =SUM(F43:H43) -> 72052.59 | R43: =SUM(I43:K43) -> 62980.77 | S43: =SUM(L43:N43) -> 42706.5 | U43: =SUM(C43:N43) -> 205663.88 | W43: =ROUND(SUM(P43:S43)-U43,2) -> 0
B44: Total Other Spend | C44: =SUM(C35:C43) -> 40041.21 | D44: =SUM(D35:D43) -> 29960.75 | E44: =SUM(E35:E43) -> 105065.1 | F44: =SUM(F35:F43) -> 62654.94 | G44: =SUM(G35:G43) -> 120431.75 | H44: =SUM(H35:H43) -> 79882.82 | I44: =SUM(I35:I43) -> 54589.82 | J44: =SUM(J35:J43) -> 121740.49 | ... N44: =SUM(N35:N43) -> 85800 | P44: =SUM(P35:P43) -> 175067.06 | Q44: =SUM(Q35:Q43) -> 262969.51 | R44: =SUM(R35:R43) -> 235047.14 | S44: =SUM(S35:S43) -> 186342.65 | U44: =SUM(U35:U43) -> 859426.36 | W44: =ROUND(SUM(P44:S44)-U44,2) -> 0
B46: Total Cash Disbursements | C46: =+C21+C29+C33+C44 -> 495827.25 | D46: =+D21+D29+D33+D44 -> 745088.42 | E46: =+E21+E29+E33+E44 -> 629337.65 | F46: =+F21+F29+F33+F44 -> 583641.64 | G46: =+G21+G29+G33+G44 -> 628120.46 | H46: =+H21+H29+H33+H44 -> 589151.6 | I46: =+I21+I29+I33+I44 -> 623813.71 | J46: =+J21+J29+J33+J44 -> 583699.06 | ... N46: =+N21+N29+N33+N44 -> 528871.95 | P46: =+P21+P29+P33+P44 -> 1870253.3 | Q46: =+Q21+Q29+Q33+Q44 -> 1800913.7 | R46: =+R21+R29+R33+R44 -> 1692622.3 | S46: =+S21+S29+S33+S44 -> 1512024.1 | U46: =+U21+U29+U33+U44 -> 6875813.4 | W46: =ROUND(SUM(P46:S46)-U46,2) -> 0
B48: Guarenteed Payments | C48: =+'6 Other'!C18 -> 0 | D48: =+'6 Other'!D18 -> 0 | E48: =+'6 Other'!E18 -> 0 | F48: =+'6 Other'!F18 -> 0 | G48: =+'6 Other'!G18 -> 0 | H48: =+'6 Other'!H18 -> 0 | I48: =+'6 Other'!I18 -> 0 | J48: =+'6 Other'!J18 -> 0 | ... N48: =+'6 Other'!N18 -> 0 | P48: =SUM(C48:E48) -> 0 | Q48: =SUM(F48:H48) -> 0 | R48: =SUM(I48:K48) -> 0 | S48: =SUM(L48:N48) -> 0 | U48: =SUM(C48:N48) -> 0 | W48: =ROUND(SUM(P48:S48)-U48,2) -> 0
B49: Youreka Labs Inc | C49: =+'6 Other'!C19 -> 0 | D49: =+'6 Other'!D19 -> 0 | E49: =+'6 Other'!E19 -> 0 | F49: =+'6 Other'!F19 -> 0 | G49: =+'6 Other'!G19 -> 0 | H49: =+'6 Other'!H19 -> 0 | I49: =+'6 Other'!I19 -> 0 | J49: =+'6 Other'!J19 -> 0 | ... N49: =+'6 Other'!N19 -> 0 | P49: =SUM(C49:E49) -> 0 | Q49: =SUM(F49:H49) -> 0 | R49: =SUM(I49:K49) -> 0 | S49: =SUM(L49:N49) -> 0 | U49: =SUM(C49:N49) -> 0 | W49: =ROUND(SUM(P49:S49)-U49,2) -> 0
B50: Brex | C50: =+'6 Other'!C20 -> -5043.37 | D50: =+'6 Other'!D20 -> -5518.34 | E50: =+'6 Other'!E20 -> -4685.37 | F50: =+'6 Other'!F20 -> -3686.29 | G50: =+'6 Other'!G20 -> -2521.11 | H50: =+'6 Other'!H20 -> -957.06 | I50: =+'6 Other'!I20 -> -183.94 | J50: =+'6 Other'!J20 -> 0 | ... N50: =+'6 Other'!N20 -> 0 | P50: =SUM(C50:E50) -> -15247.08 | Q50: =SUM(F50:H50) -> -7164.46 | R50: =SUM(I50:K50) -> -183.94 | S50: =SUM(L50:N50) -> 0 | U50: =SUM(C50:N50) -> -22595.48 | W50: =ROUND(SUM(P50:S50)-U50,2) -> 0
B51: Chase Visa | C51: =+'6 Other'!C21 -> 0 | D51: =+'6 Other'!D21 -> -1010.7 | E51: =+'6 Other'!E21 -> 0 | F51: =+'6 Other'!F21 -> -1222.92 | G51: =+'6 Other'!G21 -> -2784.15 | H51: =+'6 Other'!H21 -> -1124.19 | I51: =+'6 Other'!I21 -> -1126.11 | J51: =+'6 Other'!J21 -> -105.74 | ... N51: =+'6 Other'!N21 -> 0 | P51: =SUM(C51:E51) -> -1010.7 | Q51: =SUM(F51:H51) -> -5131.26 | R51: =SUM(I51:K51) -> -1231.85 | S51: =SUM(L51:N51) -> 0 | U51: =SUM(C51:N51) -> -7373.81 | W51: =ROUND(SUM(P51:S51)-U51,2) -> 0
B52: Ramp | C52: =+'6 Other'!C22 -> 0 | D52: =+'6 Other'!D22 -> 0 | E52: =+'6 Other'!E22 -> 0 | F52: =+'6 Other'!F22 -> 0 | G52: =+'6 Other'!G22 -> 0 | H52: =+'6 Other'!H22 -> 0 | I52: =+'6 Other'!I22 -> 0 | J52: =+'6 Other'!J22 -> 0 | ... N52: =+'6 Other'!N22 -> 0 | P52: =SUM(C52:E52) -> 0 | Q52: =SUM(F52:H52) -> 0 | R52: =SUM(I52:K52) -> 0 | S52: =SUM(L52:N52) -> 0 | U52: =SUM(C52:N52) -> 0 | W52: =ROUND(SUM(P52:S52)-U52,2) -> 0
B53: Bank Fees | C53: =+'6 Other'!C23 -> -246.35 | D53: =+'6 Other'!D23 -> -433.54 | E53: =+'6 Other'!E23 -> -471.18 | F53: =+'6 Other'!F23 -> -346.98 | G53: =+'6 Other'!G23 -> -328.79 | H53: =+'6 Other'!H23 -> -692 | I53: =+'6 Other'!I23 -> -386.11 | J53: =+'6 Other'!J23 -> -335.21 | ... N53: =+'6 Other'!N23 -> -400 | P53: =SUM(C53:E53) -> -1151.07 | Q53: =SUM(F53:H53) -> -1367.77 | R53: =SUM(I53:K53) -> -1045.49 | S53: =SUM(L53:N53) -> -1052.45 | U53: =SUM(C53:N53) -> -4616.78 | W53: =ROUND(SUM(P53:S53)-U53,2) -> 0
B54: Interest | C54: =+'6 Other'!C24 -> 7748.71 | D54: =+'6 Other'!D24 -> 8351.29 | E54: =+'6 Other'!E24 -> 8145.22 | F54: =+'6 Other'!F24 -> 6912.1 | G54: =+'6 Other'!G24 -> 5204.78 | H54: =+'6 Other'!H24 -> 3887.72 | I54: =+'6 Other'!I24 -> 3150.25 | J54: =+'6 Other'!J24 -> 2155.66 | ... N54: =+'6 Other'!N24 -> 300 | P54: =SUM(C54:E54) -> 24245.22 | Q54: =SUM(F54:H54) -> 16004.6 | R54: =SUM(I54:K54) -> 6388.96 | S54: =SUM(L54:N54) -> 1225.61 | U54: =SUM(C54:N54) -> 47864.39 | W54: =ROUND(SUM(P54:S54)-U54,2) -> 0
B56: Opening Cash Balance | C56: 3334341 | D56: =+C61 -> 3317111 | E56: =+D61 -> 3677069.9 | F56: =+E61 -> 3325973.4 | G56: =+F61 -> 2956020.3 | H56: =+G61 -> 2520253 | I56: =+H61 -> 2023283.3 | J56: =+I61 -> 1726104.7 | K56: =+J61 -> 1329558.9 | ... N56: =+M61 -> 670150.08 | P56: =+C56 -> 3334341 | Q56: =+P61 -> 3325973 | R56: =+Q61 -> 2023283 | S56: =+R61 -> 954186 | U56: =+P56 -> 3334341
B58: Net Change | C58: =C15-C46+SUM(C48:C54) -> -217229.4 | D58: =D15-D46+SUM(D48:D54) -> -390040.61 | E58: =E15-E46+SUM(E48:E54) -> -351096.5 | F58: =F15-F46+SUM(F48:F54) -> -369953.03 | G58: =G15-G46+SUM(G48:G54) -> -435767.33 | H58: =H15-H46+SUM(H48:H54) -> -471969.73 | I58: =I15-I46+SUM(I48:I54) -> -297178.62 | J58: =J15-J46+SUM(J48:J54) -> -396545.75 | ... N58: =N15-N46+SUM(N48:N54) -> 318960.65 | P58: =SUM(C58:E58) -> -958366.51 | Q58: =SUM(F58:H58) -> -1277690.1 | R58: =SUM(I58:K58) -> -1069097.5 | S58: =SUM(L58:N58) -> 34924.93 | U58: =SUM(C58:N58) -> -3270229.1 | W58: =ROUND(SUM(P58:S58)-U58,2) -> 0
B59: Investment | C59: =+'6 Other'!C29 -> 199999.42 | D59: =+'6 Other'!D29 -> 749999.44 | E59: =+'6 Other'!E29 -> 0 | F59: =+'6 Other'!F29 -> 0 | G59: =+'6 Other'!G29 -> 0 | H59: =+'6 Other'!H29 -> -25000 | I59: =+'6 Other'!I29 -> 0 | J59: =+'6 Other'!J29 -> 0 | ... N59: =+'6 Other'!N29 -> -25000 | P59: =SUM(C59:E59) -> 949998.86 | Q59: =SUM(F59:H59) -> -25000 | R59: =SUM(I59:K59) -> 0 | S59: =SUM(L59:N59) -> -25000 | U59: =SUM(C59:N59) -> 899998.86 | W59: =ROUND(SUM(P59:S59)-U59,2) -> 0
B61: Ending Cash Balance | C61: =ROUND(+C56+C58+C59,2) -> 3317111 | D61: =ROUND(+D56+D58+D59,2) -> 3677069.9 | E61: =ROUND(+E56+E58+E59,2) -> 3325973.4 | F61: =ROUND(+F56+F58+F59,2) -> 2956020.3 | G61: =ROUND(+G56+G58+G59,2) -> 2520253 | H61: =ROUND(+H56+H58+H59,2) -> 2023283.3 | I61: =ROUND(+I56+I58+I59,2) -> 1726104.7 | J61: =ROUND(+J56+J58+J59,2) -> 1329558.9 | ... N61: =ROUND(+N56+N58+N59,2) -> 964110.73 | P61: =ROUND(+P56+P58+P59,0) -> 3325973 | Q61: =ROUND(+Q56+Q58+Q59,0) -> 2023283 | R61: =ROUND(+R56+R58+R59,0) -> 954186 | S61: =ROUND(+S56+S58+S59,0) -> 964111 | U61: =ROUND(+U56+U58+U59,0) -> 964111
B63: Cash In | C63: =+C15 -> 276138.86 | D63: =+D15 -> 353659.1 | E63: =+E15 -> 275252.48 | F63: =+F15 -> 212032.7 | G63: =+G15 -> 192782.4 | H63: =+H15 -> 116067.4 | I63: =+I15 -> 325181 | J63: =+J15 -> 185438.6 | ... N63: =+N15 -> 847932.6 | P63: =+P15 -> 905050.44 | Q63: =+Q15 -> 520882.5 | R63: =+R15 -> 619597.1 | S63: =+S15 -> 1546775.9 | U63: =+U15 -> 3592305.9
B64: Calculated COGS | C64: =SUM(C17:C18,C23:C24) -> 237094.69 | D64: =SUM(D17:D18,D23:D24) -> 373512.69 | E64: =SUM(E17:E18,E23:E24) -> 223536.76 | F64: =SUM(F17:F18,F23:F24) -> 187863.78 | G64: =SUM(G17:G18,G23:G24) -> 191763.05 | H64: =SUM(H17:H18,H23:H24) -> 197231.83 | I64: =SUM(I17:I18,I23:I24) -> 187788.92 | J64: =SUM(J17:J18,J23:J24) -> 186132.84 | ... N64: =SUM(N17:N18,N23:N24) -> 194610 | P64: =SUM(P17:P18,P23:P24) -> 834144.13 | Q64: =SUM(Q17:Q18,Q23:Q24) -> 576858.66 | R64: =SUM(R17:R18,R23:R24) -> 562447.14 | S64: =SUM(S17:S18,S23:S24) -> 584581.13 | U64: =SUM(U17:U18,U23:U24) -> 2558031.1
B65: Gross Margin | C65: =+C63-C64 -> 39044.174 | D65: =+D63-D64 -> -19853.588 | E65: =+E63-E64 -> 51715.722 | F65: =+F63-F64 -> 24168.919 | G65: =+G63-G64 -> 1019.3506 | H65: =+H63-H64 -> -81164.431 | I65: =+I63-I64 -> 137392.08 | J65: =+J63-J64 -> -694.24222 | ... N65: =+N63-N64 -> 653322.6 | P65: =+P63-P64 -> 70906.308 | Q65: =+Q63-Q64 -> -55976.161 | R65: =+R63-R64 -> 57149.956 | S65: =+S63-S64 -> 962194.77 | U65: =+U63-U64 -> 1034274.9
B66: GM % | C66: =+C65/C63 -> 0.14139326 | D66: =+D65/D63 -> -0.056137642 | E66: =+E65/E63 -> 0.18788467 | F66: =+F65/F63 -> 0.11398675 | G66: =+G65/G63 -> 0.005287571 | H66: =+H65/H63 -> -0.69928706 | I66: =+I65/I63 -> 0.42250955 | J66: =+J65/J63 -> -0.0037437849 | ... N66: =+N65/N63 -> 0.77048883 | P66: =+P65/P63 -> 0.078345146 | Q66: =+Q65/Q63 -> -0.10746408 | R66: =+R65/R63 -> 0.092237288 | S66: =+S65/S63 -> 0.62206476 | U66: =+U65/U63 -> 0.28791392
B69: M&T Operating | C69: =+'2025 CF Basic'!E57 -> 500000 | D69: =+'2025 CF Basic'!F57 -> 500798.3 | E69: =+'2025 CF Basic'!G57 -> 500000 | F69: =+'2025 CF Basic'!H57 -> 500000 | G69: =+'2025 CF Basic'!I57 -> 498031.75 | H69: =+'2025 CF Basic'!J57 -> 498031.75 | I69: =+'2025 CF Basic'!K57 -> 500000 | J69: =+'2025 CF Basic'!L57 -> 500000 | ... M69: =+'2025 CF Basic'!O57 -> 503545.63
