Workbook

Sheet Assumptions
A1: STRATEGIC PATH FINANCIAL MODEL - KEY ASSUMPTIONS
A2: All blue cells are editable inputs
A4: SERVICES BUSINESS ASSUMPTIONS
A5: Current Annual Revenue | B5: 4000000 | C5: $ - Salesforce consulting
A6: Current Headcount | B6: 25 | C6: FTEs
A7: Revenue per Head | B7: =B5/B6 | C7: $ per FTE
A8: Gross Margin % | B8: 0.45 | C8: % - typical for services
A9: SG&A % of Revenue | B9: 0.25 | C9: % - overhead
A10: EBITDA Margin % | B10: =B8-B9 | C10: % - operating margin
A11: Annual Growth (Optimized) | B11: 0.05 | C11: % - modest growth focus
A12: Annual Growth (Lean) | B12: -0.05 | C12: % - declining with underinvestment
A13: Sale Multiple (Revenue) | B13: 2.5 | C13: x - conservative for $4M business
A14: Sale Multiple (EBITDA) | B14: 12 | C14: x - IT consulting range
A15: Cash at Close % | B15: 0.6 | C15: % - typical deal structure
A16: Earnout Period (Years) | B16: 2 | C16: Years
A18: PRODUCT BUSINESS ASSUMPTIONS (HELM)
A19: Seed Round Size | B19: 3000000 | C19: $ - typical AI seed
A20: Series A Size | B20: 10000000 | C20: $ - target Series A
A21: Monthly Burn (Product) | B21: 200000 | C21: $ per month
A22: Founder Ownership Post-Seed | B22: 0.7 | C22: % - after seed dilution
A23: Founder Ownership Post-A | B23: 0.5 | C23: % - after Series A
A24: Y1 Product Revenue | B24: 500000 | C24: $ - early customers
A25: Y2 Product Revenue | B25: 3000000 | C25: $ - scaling
A26: Y3 Product Revenue | B26: 12000000 | C26: $ - growth
A27: Product Revenue Multiple | B27: 15 | C27: x - AI SaaS multiple
A28: PMF Probability (Well-Funded) | B28: 0.6 | C28: % - success rate
A29: PMF Probability (Underfunded) | B29: 0.3 | C29: % - lean success rate
A31: SCENARIO PROBABILITIES
A32: Helm Succeeds (Well-Funded) | B32: 0.6 | C32: %
A33: Helm Struggles | B33: 0.25 | C33: %
A34: Pivot/Different Opportunity | B34: 0.15 | C34: %
A35: Total | B35: =SUM(B32:B34) | C35: Must = 100%

Sheet Path 1 - Lean
A1: PATH 1: LEAN
A2: Services: lean, cash flow positive | Product: lean, modest investment
A4: SERVICES PROJECTION
B5: Year 0 | C5: Year 1 | D5: Year 2 | E5: Year 3
A6: Revenue | B6: =Assumptions!B5 | C6: =B6*(1+Assumptions!$B$12) | D6: =C6*(1+Assumptions!$B$12) | E6: =D6*(1+Assumptions!$B$12)
A7: Gross Profit | B7: =B6*Assumptions!$B$8 | C7: =C6*Assumptions!$B$8 | D7: =D6*Assumptions!$B$8 | E7: =E6*Assumptions!$B$8
A8: SG&A | B8: =B6*Assumptions!$B$9 | C8: =C6*Assumptions!$B$9 | D8: =D6*Assumptions!$B$9 | E8: =E6*Assumptions!$B$9
A9: EBITDA | B9: =B7-B8 | C9: =C7-C8 | D9: =D7-D8 | E9: =E7-E8
A10: EBITDA Margin | B10: =IF(B6=0,0,B9/B6) | C10: =IF(C6=0,0,C9/C6) | D10: =IF(D6=0,0,D9/D6) | E10: =IF(E6=0,0,E9/E6)
A12: PRODUCT INVESTMENT
B13: Year 0 | C13: Year 1 | D13: Year 2 | E13: Year 3
A14: Product Investment | B14: 0 | C14: =MIN(C9*0.75, 300000) | D14: =MIN(D9*0.75, 350000) | E14: =MIN(E9*0.75, 300000)
A15: Product Revenue | B15: 0 | C15: 100000 | D15: 300000 | E15: 800000
A16: Net Product Cash Flow | B16: 0 | C16: =C15-C14 | D16: =D15-D14 | E16: =E15-E14
A18: COMBINED CASH FLOW
B19: Year 0 | C19: Year 1 | D19: Year 2 | E19: Year 3
A20: Services EBITDA | B20: =B9 | C20: =C9 | D20: =D9 | E20: =E9
A21: Product Investment | B21: =B14 | C21: =C14 | D21: =D14 | E21: =E14
A22: Net Cash Flow | B22: =B20-B21 | C22: =C20-C21 | D22: =D20-D21 | E22: =E20-E21
A23: Cumulative Cash | B23: =B22 | C23: =B23+C22 | D23: =C23+D22 | E23: =D23+E22
A26: YEAR 3 VALUATION
A27: Services Value (Revenue x) | B27: =E6*Assumptions!B13
A28: Product Value (Revenue x) | B28: =E15*8
A29: Total Enterprise Value | B29: =B27+B28
A30: Founder Ownership | B30: 0.85
A31: Founder Equity Value | B31: =B29*B30

Sheet Path 2 - Liquidate
A1: PATH 2: LIQUIDATE SERVICES
A2: Sell services for ~$8-12M, invest aggressively in product
A4: SERVICES SALE
A5: Current Revenue | B5: =Assumptions!B5
A6: Revenue Multiple | B6: =Assumptions!B13
A7: Implied Sale Price | B7: =B5*B6
A8: Transaction Costs (5%) | B8: =B7*0.05
A9: Net Proceeds | B9: =B7-B8
A10: Cash at Close | B10: =B9*Assumptions!B15
A11: Earnout (deferred) | B11: =B9-B10
A13: PRODUCT INVESTMENT
B14: Year 0 | C14: Year 1 | D14: Year 2 | E14: Year 3
A15: Available Capital | B15: =B10 | C15: =B15-C16 | D15: =C15+Assumptions!B19-D16 | E15: =D15-E16
A16: Product Investment (Burn) | B16: 0 | C16: =Assumptions!B21*12 | D16: =Assumptions!B21*12 | E16: =Assumptions!B21*12
A17: Product Revenue | B17: 0 | C17: =Assumptions!B24 | D17: =Assumptions!B25 | E17: =Assumptions!B26
A18: Net Cash Position | B18: =B15 | C18: =B15-C16+C17 | D18: =C18+Assumptions!B19-D16+D17 | E18: =D18-E16+E17
A21: YEAR 3 VALUATION (SUCCESS CASE)
A22: Product Revenue (Y3) | B22: =E17
A23: Product Multiple | B23: =Assumptions!B27
A24: Product Value | B24: =B22*B23
A25: Founder Ownership Post-A | B25: =Assumptions!B23
A26: Founder Equity Value | B26: =B24*B25

Sheet Path 3 - Growth Both
A1: PATH 3: GROWTH BOTH
A2: New services leader + VC for product
A4: SERVICES (WITH NEW LEADER)
B5: Year 0 | C5: Year 1 | D5: Year 2 | E5: Year 3
A6: Revenue | B6: =Assumptions!B5 | C6: =B6*(1+Assumptions!$B$11) | D6: =C6*(1+Assumptions!$B$11) | E6: =D6*(1+Assumptions!$B$11)
A7: Leader Investment | B7: 0 | C7: 150000 | D7: 0 | E7: 0
A8: Working Capital Needs | B8: 0 | C8: 100000 | D8: 50000 | E8: 0
A9: EBITDA | B9: =B6*Assumptions!$B$10 | C9: =C6*Assumptions!$B$10-C7-C8 | D9: =D6*Assumptions!$B$10-D8 | E9: =E6*Assumptions!$B$10
A10: Services Value (Y3) | E10: =E6*Assumptions!B13
A13: PRODUCT (WITH VC)
B14: Year 0 | C14: Year 1 | D14: Year 2 | E14: Year 3
A15: VC Raise (Seed) | B15: 0 | C15: =Assumptions!B19 | D15: 0 | E15: 0
A16: VC Raise (Series A) | B16: 0 | C16: 0 | D16: =Assumptions!B20 | E16: 0
A17: Product Burn | B17: 0 | C17: =Assumptions!B21*12 | D17: =Assumptions!B21*12 | E17: =Assumptions!B21*12
A18: Product Revenue | B18: 0 | C18: =Assumptions!B24 | D18: =Assumptions!B25 | E18: =Assumptions!B26
A19: Product Value (Y3) | E19: =E18*Assumptions!B27
A22: COMBINED VALUATION (Y3)
A23: Services Value | B23: =E10
A24: Product Value | B24: =E19
A25: Total Enterprise Value | B25: =B23+B24
A26: Services Ownership | B26: 1
A27: Product Ownership Post-A | B27: =Assumptions!B23
A28: Founder Value (Services) | B28: =B23*B26
A29: Founder Value (Product) | B29: =B24*B27
A30: Total Founder Value | B30: =B28+B29

Sheet Path 4 - Strategic Leverage
A1: PATH 4: STRATEGIC LEVERAGE (RECOMMENDED)
A2: Use services as bridge, maintain optionality, then transition
A4: PHASE 1: STRATEGIC BRIDGE (MONTHS 1-12)
A5: Services Revenue | B5: =Assumptions!B5
A6: Optimized EBITDA Margin | B6: 0.2
A7: Services EBITDA | B7: =B5*B6
A8: Product Investment (from services) | B8: =B7*0.7
A9: Remaining Cash Cushion | B9: =B7-B8
A11: PHASE 2: DECISION POINT (MONTH 12-18)
A12: Decision Trigger | B12: Services Action | C12: Product Action | D12: Raise | E12: Expected Outcome
A13: Strong PMF (3+ paying customers) | B13: Sell quickly | C13: Accelerate | D13: Seed $3M | E13: High upside
A14: Moderate PMF (1-2 customers) | B14: Maintain | C14: Continue | D14: Small seed $1M | E14: Moderate upside
A15: Weak PMF (no customers) | B15: Preserve/Sell | C15: Pivot or stop | D15: None | E15: Preserve value
A17: 3-YEAR PROJECTION (BASE CASE: STRONG PMF)
B18: Year 0 | C18: Year 1 | D18: Year 2 | E18: Year 3
A19: Services Revenue | B19: =Assumptions!B5 | C19: =B19 | D19: 0 | E19: 0
A20: Services EBITDA | B20: =B19*0.2 | C20: =C19*0.2 | D20: 0 | E20: 0
A21: Services Sale (Y1) | B21: 0 | C21: =Assumptions!B5*Assumptions!B13*0.95 | D21: 0 | E21: 0
A22: Product Investment | B22: 0 | C22: =B8 | D22: =Assumptions!B21*12 | E22: =Assumptions!B21*12
A23: Seed Raise (Y2) | B23: 0 | C23: 0 | D23: =Assumptions!B19 | E23: 0
A24: Series A (Y3) | B24: 0 | C24: 0 | D24: 0 | E24: =Assumptions!B20
A25: Product Revenue | B25: 0 | C25: 200000 | D25: =Assumptions!B25 | E25: =Assumptions!B26
A28: YEAR 3 VALUATION
A29: Services Sale Proceeds (Y1) | B29: =C21
A30: Product Value (Y3) | B30: =E25*Assumptions!B27
A31: Total Value Created | B31: =B29+B30
A32: Product Ownership Post-A | B32: =Assumptions!B23
A33: Founder Value (Services) | B33: =B29
A34: Founder Value (Product) | B34: =B30*B32
A35: Total Founder Value | B35: =B33+B34

Sheet EV Comparison
A1: EXPECTED VALUE COMPARISON
A2: E(V) = Probability x Value across scenarios
A4: SCENARIO PROBABILITIES
A5: Helm Succeeds | B5: =Assumptions!B32
A6: Helm Struggles | B6: =Assumptions!B33
A7: Pivot/Other | B7: =Assumptions!B34
A9: FOUNDER EQUITY VALUE BY PATH AND SCENARIO ($M)
A10: Path | B10: Success | C10: Struggles | D10: Pivot | E10: Expected Value
A11: Path 1: Lean | B11: 25 | C11: 4 | D11: 12 | E11: =B11*$B$5+C11*$B$6+D11*$B$7
A12: Path 2: Liquidate | B12: 50 | C12: 0 | D12: 3 | E12: =B12*$B$5+C12*$B$6+D12*$B$7
A13: Path 3: Growth Both | B13: 45 | C13: 10 | D13: 18 | E13: =B13*$B$5+C13*$B$6+D13*$B$7
A14: Path 4: Strategic Leverage | B14: 55 | C14: 10 | D14: 15 | E14: =B14*$B$5+C14*$B$6+D14*$B$7
A16: RANKING BY EXPECTED VALUE
A17: 1. Strategic Leverage | B17: =E14
A18: 2. Growth Both | B18: =E13
A19: 3. Liquidate | B19: =E12
A20: 4. Lean | B20: =E11
A22: KEY INSIGHTS
A23: 1. Strategic Leverage wins by preserving optionality while making progress
A24: 2. Liquidate has highest upside but highest downside (total loss if product fails)
A25: 3. Lean underperforms due to market timing risk - too slow for 18-24mo window
A26: 4. Growth Both viable but adds complexity for marginal EV gain
