Workbook

Sheet Path1_Lean
B2: Path 1: LEAN - Minimal Investment, Self-Funded
B4: ASSUMPTIONS
B5: Services starting revenue ($M) | C5: 4
B6: Services annual decline | C6: -0.05
B7: Services EBITDA margin | C7: 0.12
B8: Product investment/year ($M) | C8: 0.35
B9: Services EV multiple | C9: 2.5
B10: Product EV multiple (if successful) | C10: 10
B12: GROWTH PLAN
C13: 2025 | D13: 2026 | E13: 2027 | F13: 2028 | G13: 2029
B14: Services Revenue ($M) | C14: =C5 | D14: =C14*(1+$C$6) | E14: =D14*(1+$C$6) | F14: =E14*(1+$C$6) | G14: =F14*(1+$C$6)
B15: Services EBITDA ($M) | C15: =C14*$C$7 | D15: =D14*$C$7 | E15: =E14*$C$7 | F15: =F14*$C$7 | G15: =G14*$C$7
B16: Product Investment ($M) | C16: =-$C$8 | D16: =-$C$8 | E16: =-$C$8 | F16: =-$C$8 | G16: =-$C$8
B17: Net Cash Flow ($M) | C17: =C15+C16 | D17: =D15+D16 | E17: =E15+E16 | F17: =F15+F16 | G17: =G15+G16
B19: Product Revenue ($M) | C19: 0.05 | D19: 0.15 | E19: 0.4 | F19: 0.8 | G19: 1.5
B21: EV CALCULATION
B22: Services EV ($M) | C22: =C14*$C$9 | D22: =D14*$C$9 | E22: =E14*$C$9 | F22: =F14*$C$9 | G22: =G14*$C$9
B23: Product EV ($M) | C23: =C19*$C$10 | D23: =D19*$C$10 | E23: =E19*$C$10 | F23: =F19*$C$10 | G23: =G19*$C$10
B24: Total EV ($M) | C24: =C22+C23 | D24: =D22+D23 | E24: =E22+E23 | F24: =F22+F23 | G24: =G22+G23

Sheet Path2_Liquidate
B2: Path 2: LIQUIDATE - Sell Services, All-In on Product
B4: ASSUMPTIONS
B5: Services sale price ($M) | C5: 10
B6: Net after tax/earnout ($M) | C6: 7
B7: Product burn rate/year ($M) | C7: 2.5
B8: Product EV multiple | C8: 10
B9: Sale completed (year) | C9: 2025
B11: CASH POSITION
C12: 2025 | D12: 2026 | E12: 2027 | F12: 2028 | G12: 2029
B13: Starting Cash ($M) | C13: =$C$6 | D13: =C15 | E13: =D15 | F13: =E15 | G13: =F15
B14: Product Burn ($M) | C14: =-$C$7 | D14: =-$C$7 | E14: =-$C$7 | F14: =-$C$7 | G14: =-$C$7
B15: Ending Cash ($M) | C15: =C13+C14 | D15: =D13+D14 | E15: =E13+E14 | F15: =F13+F14 | G15: =G13+G14
B17: PRODUCT GROWTH
B18: Product Revenue ($M) | C18: 0.2 | D18: 1 | E18: 5 | F18: 15 | G18: 40
B19: YoY Growth | C19: N/A | D19: =(D18-C18)/C18 | E19: =(E18-D18)/D18 | F19: =(F18-E18)/E18 | G19: =(G18-F18)/F18
B21: EV CALCULATION
B22: Product EV ($M) | C22: =C18*$C$8 | D22: =D18*$C$8 | E22: =E18*$C$8 | F22: =F18*$C$8 | G22: =G18*$C$8
B23: Cash Position ($M) | C23: =C15 | D23: =D15 | E23: =E15 | F23: =F15 | G23: =G15
B24: Total EV ($M) | C24: =C22+MAX(0,C23) | D24: =D22+MAX(0,D23) | E24: =E22+MAX(0,E23) | F24: =F22+MAX(0,F23) | G24: =G22+MAX(0,G23)

Sheet Path3_GrowthBoth
B2: Path 3: GROWTH BOTH - Dual Business Strategy
B4: ASSUMPTIONS
B5: Services starting revenue ($M) | C5: 4
B6: Services annual growth | C6: 0.3
B7: Services EV multiple | C7: 3
B8: Product EV multiple | C8: 10
B9: VC funding (Year 1, $M) | C9: 3
B11: GROWTH PLAN
C12: 2025 | D12: 2026 | E12: 2027 | F12: 2028 | G12: 2029
B13: Services Revenue ($M) | C13: 4.275 | D13: 5.56 | E13: 7.22 | F13: 9.39 | G13: 11.74
B14: Product Revenue ($M) | C14: 0 | D14: 1 | E14: 5 | F14: 25 | G14: 100
B15: Total Revenue ($M) | C15: =C13+C14 | D15: =D13+D14 | E15: =E13+E14 | F15: =F13+F14 | G15: =G13+G14
B17: EV CALCULATION
B18: Services EV ($M) | C18: =C13*$C$7 | D18: =D13*$C$7 | E18: =E13*$C$7 | F18: =F13*$C$7 | G18: =G13*$C$7
B19: Product EV ($M) | C19: =C14*$C$8 | D19: =D14*$C$8 | E19: =E14*$C$8 | F19: =F14*$C$8 | G19: =G14*$C$8
B20: Total EV ($M) | C20: =C18+C19 | D20: =D18+D19 | E20: =E18+E19 | F20: =F18+F19 | G20: =G18+G19

Sheet Path4_Strategic
B2: Path 4: STRATEGIC LEVERAGE - Bridge to Product (RECOMMENDED)
B4: ASSUMPTIONS
B5: Services starting revenue ($M) | C5: 4
B6: Services EBITDA margin (optimized) | C6: 0.2
B7: Services sale price (Year 2, $M) | C7: 10
B8: Net after sale ($M) | C8: 7
B9: Seed funding (Year 2, $M) | C9: 3
B10: Series A (Year 3, $M) | C10: 10
B11: Product EV multiple | C11: 10
B13: PHASE 1: STRATEGIC EXTRACTION (Y1)
C14: 2025 | D14: 2026 | E14: 2027 | F14: 2028 | G14: 2029
B15: Services Revenue ($M) | C15: 4 | D15: 3.5 | E15: 0 | F15: 0 | G15: 0
B16: Services Cash Gen ($M) | C16: =C15*$C$6 | D16: =$C$8 | E16: 0 | F16: 0 | G16: 0
B17: Product Investment ($M) | C17: -0.5 | D17: -2 | E17: -3 | F17: -4 | G17: -5
B18: External Capital ($M) | C18: 0 | D18: =$C$9 | E18: =$C$10 | F18: 0 | G18: 0
B20: PRODUCT GROWTH
B21: Product Revenue ($M) | C21: 0.2 | D21: 2 | E21: 10 | F21: 35 | G21: 100
B23: EV CALCULATION
B24: Services EV ($M) | C24: =C15*2.5 | D24: 0 | E24: 0 | F24: 0 | G24: 0
B25: Product EV ($M) | C25: =C21*$C$11 | D25: =D21*$C$11 | E25: =E21*$C$11 | F25: =F21*$C$11 | G25: =G21*$C$11
B26: Total EV ($M) | C26: =C24+C25 | D26: =D24+D25 | E26: =E24+E25 | F26: =F24+F25 | G26: =G24+G25

Sheet Summary_Comparison
B2: SCENARIO COMPARISON & RISK-ADJUSTED EXPECTED VALUE ANALYSIS
B4: YEAR 3 (2027) EV COMPARISON
B5: Scenario | C5: Services EV | D5: Product EV | E5: Total EV | F5: Risk Level | G5: Success Prob
B6: Path 1: Lean | C6: =Path1_Lean!E22 | D6: =Path1_Lean!E23 | E6: =Path1_Lean!E24 | F6: HIGH | G6: 0.3
B7: Path 2: Liquidate | C7: 0 | D7: =Path2_Liquidate!E22 | E7: =Path2_Liquidate!E24 | F7: MED-HIGH | G7: 0.5
B8: Path 3: Growth Both | C8: =Path3_GrowthBoth!E18 | D8: =Path3_GrowthBoth!E19 | E8: =Path3_GrowthBoth!E20 | F8: HIGH | G8: 0.4
B9: Path 4: Strategic | C9: =Path4_Strategic!E24 | D9: =Path4_Strategic!E25 | E9: =Path4_Strategic!E26 | F9: MEDIUM | G9: 0.6
B12: RISK-ADJUSTED EXPECTED VALUE ANALYSIS
B13: Scenario Probabilities
B14: Product Succeeds (PMF achieved) | C14: 0.6
B15: Product Struggles (slow growth) | C15: 0.25
B16: Product Pivots (different direction) | C16: 0.15
B18: EXPECTED VALUE BY OUTCOME (Year 5 - 2029)
B19: Scenario | C19: Success EV | D19: Struggle EV | E19: Pivot EV | F19: Expected Value
B20: Path 1: Lean | C20: 20 | D20: 12 | E20: 8 | F20: =C20*$C$14+D20*$C$15+E20*$C$16
B21: Path 2: Liquidate | C21: 45 | D21: 15 | E21: 5 | F21: =C21*$C$14+D21*$C$15+E21*$C$16
B22: Path 3: Growth Both | C22: 60 | D22: 25 | E22: 15 | F22: =C22*$C$14+D22*$C$15+E22*$C$16
B23: Path 4: Strategic | C23: 70 | D23: 30 | E23: 15 | F23: =C23*$C$14+D23*$C$15+E23*$C$16
B26: SENSITIVITY: EV BY SUCCESS PROBABILITY
B27: Success Probability | C27: 0.4 | D27: 0.5 | E27: 0.6 | F27: 0.7 | G27: 0.8
B28: Path 1: Lean | C28: 14.3 | D28: 15.25 | E28: 16.2 | F28: 17.15 | G28: 18.1
B29: Path 2: Liquidate | C29: 24.75 | D29: 28.125 | E29: 31.5 | F29: 34.875 | G29: 38.25
B30: Path 3: Growth Both | C30: 36.75 | D30: 40.625 | E30: 44.5 | F30: 48.375 | G30: 52.25
B31: Path 4: Strategic | C31: 42.625 | D31: 47.1875 | E31: 51.75 | F31: 56.3125 | G31: 60.875
B34: KEY TAKEAWAYS
B35: 1. Strategic Leverage (Path 4) has highest Expected Value at $45.3M
B36: 2. Path 4 maintains optionality - performs well even in downside scenarios
B37: 3. Liquidate (Path 2) is high-risk high-reward - best if success prob > 70%
B38: 4. Lean (Path 1) underperforms across all scenarios due to underfunding
B39: 5. At 60% success probability, Path 4 leads by ~$5M in Expected Value
