Workbook

Sheet Path1_Lean
A1: PATH 1: LEAN BOOTSTRAP - No External Dilution
A3: STARTING POSITION
B4: Founder ownership | C4: 1
B5: Services revenue ($M) | C5: 4
B6: Services EBITDA margin | C6: 0.15
B7: Annual cash for product ($M) | C7: 0.3
A9: CAPITAL STRUCTURE
B10: No external funding - 100% self-funded from services cash flow
B11: Founder retains 100% ownership throughout
A13: 3-YEAR EXIT SCENARIOS
B14: Scenario | C14: Probability | D14: Enterprise Value | E14: Founder % | F14: Founder Value
B15: Product gains traction | C15: 0.25 | D15: 30 | E15: =C4 | F15: =D15*E15
B16: Modest services growth | C16: 0.5 | D16: 14 | E16: =C4 | F16: =D16*E16
B17: Business stagnates | C17: 0.25 | D17: 8 | E17: =C4 | F17: =D17*E17
A19: SUMMARY
B20: Expected Enterprise Value | C20: =SUMPRODUCT(C15:C17,D15:D17)
B21: Expected Founder Value | C21: =SUMPRODUCT(C15:C17,F15:F17)
B22: Final Founder Ownership | C22: =C4
B23: Total Dilution | C23: =1-C22

Sheet Path2_Liquidate
A1: PATH 2: LIQUIDATE - Sell Services, All-In Product
A3: STARTING POSITION
B4: Founder ownership | C4: 1
B5: Services sale price ($M) | C5: 10
B6: Founder take from sale ($M) | C6: 8 | D6: (after advisors, legal, escrow)
A8: FUNDING ROUNDS - 2025/2026 MARKET
B9: Round | C9: Timing | D9: Pre-Money | E9: Raise | F9: Post-Money | G9: Dilution
B10: ESOP Pool (pre-seed) | C10: Day 1 | D10: - | E10: 0.12 | F10: - | G10: =E10
B11: Seed Round | C11: Month 2-3 | D11: 7 | E11: 2.5 | F11: =D11+E11 | G11: =E11/F11
B12: Series A | C12: Month 14-16 | D12: 22 | E12: 8 | F12: =D12+E12 | G12: =E12/F12
B13: Note: Lower seed valuation due to raising without customer validation
A15: OWNERSHIP WATERFALL
B16: Event | C16: Before | D16: Dilution | E16: After
B17: Starting | C17: =C4 | D17: 0 | E17: =C17
B18: After ESOP | C18: =E17 | D18: =G10 | E18: =C18*(1-D18)
B19: After Seed | C19: =E18 | D19: =G11 | E19: =C19*(1-D19)
B20: After Series A | C20: =E19 | D20: =G12 | E20: =C20*(1-D20)
A22: 3-YEAR EXIT SCENARIOS
B23: Scenario | C23: Probability | D23: Product EV | E23: Founder % | F23: From Product | G23: + Services = Total
B24: Helm hits $10M+ ARR | C24: 0.35 | D24: 100 | E24: =E20 | F24: =D24*E24 | G24: =F24+C6
B25: Helm at $3-5M ARR | C25: 0.3 | D25: 35 | E25: =E20 | F25: =D25*E25 | G25: =F25+C6
B26: Helm struggles (<$1M ARR) | C26: 0.25 | D26: 8 | E26: =E20 | F26: =D26*E26 | G26: =F26+C6
B27: Helm shuts down | C27: 0.1 | D27: 0 | E27: =E20 | F27: =D27*E27 | G27: =F27+C6
A29: SUMMARY
B30: Expected Enterprise Value | C30: =SUMPRODUCT(C24:C27,D24:D27)
B31: Expected Founder Value (Product) | C31: =SUMPRODUCT(C24:C27,F24:F27)
B32: Expected Founder Value (Total) | C32: =SUMPRODUCT(C24:C27,G24:G27)
B33: Final Founder Ownership | C33: =E20
B34: Total Dilution | C34: =1-C33
B35: Total Capital Raised | C35: =E11+E12

Sheet Path3_GrowthBoth
A1: PATH 3: GROWTH BOTH - Dual Business Strategy
A3: STARTING POSITION
B4: Founder ownership | C4: 1
B5: Services Y1 revenue ($M) | C5: 4.5
B6: Services Y3 value (3x rev @ $8M) | C6: 24
B7: Services leadership hire ($M/yr) | C7: 0.25
A9: FUNDING ROUNDS - PRODUCT ENTITY
B10: Round | C10: Timing | D10: Pre-Money | E10: Raise | F10: Post-Money | G10: Dilution
B11: ESOP Pool | C11: At Seed | D11: - | E11: 0.12 | F11: - | G11: =E11
B12: Seed Round | C12: Month 4-6 | D12: 8 | E12: 3 | F12: =D12+E12 | G12: =E12/F12
B13: Series A | C13: Month 18 | D13: 25 | E13: 8 | F13: =D13+E13 | G13: =E13/F13
B14: Note: VCs typically discount services-heavy companies by 20-30%
A16: OWNERSHIP WATERFALL (PRODUCT)
B17: Event | C17: Before | D17: Dilution | E17: After
B18: Starting | C18: =C4 | D18: 0 | E18: =C18
B19: After ESOP | C19: =E18 | D19: =G11 | E19: =C19*(1-D19)
B20: After Seed | C20: =E19 | D20: =G12 | E20: =C20*(1-D20)
B21: After Series A | C21: =E20 | D21: =G13 | E21: =C21*(1-D21)
A23: 3-YEAR EXIT SCENARIOS
B24: Scenario | C24: Prob | D24: Product EV | E24: Services EV | F24: Founder Prod | G24: Total Founder
B25: Both succeed | C25: 0.3 | D25: 70 | E25: =C6 | F25: =D25*E21 | G25: =F25+E25
B26: Product moderate | C26: 0.35 | D26: 25 | E26: =C6 | F26: =D26*E21 | G26: =F26+E26
B27: Focus dilution hurts both | C27: 0.25 | D27: 10 | E27: 15 | F27: =D27*E21 | G27: =F27+E27
B28: Product fails, services OK | C28: 0.1 | D28: 0 | E28: 18 | F28: =D28*E21 | G28: =F28+E28
A30: SUMMARY
B31: Expected Enterprise Value (Combined) | C31: =SUMPRODUCT(C25:C28,D25:D28)+SUMPRODUCT(C25:C28,E25:E28)
B32: Expected Founder Value | C32: =SUMPRODUCT(C25:C28,G25:G28)
B33: Final Founder % (Product) | C33: =E21
B34: Total Dilution (Product) | C34: =1-C33
B35: Total Capital Raised | C35: =E12+E13

Sheet Path4_Strategic
A1: PATH 4: STRATEGIC LEVERAGE (RECOMMENDED)
A3: STARTING POSITION
B4: Founder ownership | C4: 1
B5: Services revenue ($M) | C5: 4
B6: Services EBITDA (optimized to 20%) | C6: 0.8
B7: Services sale price (Month 12, $M) | C7: 10
B8: Founder take from services ($M) | C8: 8
A10: FUNDING ROUNDS - VALIDATED APPROACH
B11: Round | C11: Timing | D11: Pre-Money | E11: Raise | F11: Post-Money | G11: Dilution
B12: ESOP Pool | C12: At Seed | D12: - | E12: 0.1 | F12: - | G12: =E12
B13: Seed (with design partners) | C13: Month 12-14 | D13: 12 | E13: 3 | F13: =D13+E13 | G13: =E13/F13
B14: Series A (with ARR traction) | C14: Month 24-30 | D14: 35 | E14: 10 | F14: =D14+E14 | G14: =E14/F14
B15: Key: 70%+ higher seed valuation due to design partner validation
A17: OWNERSHIP WATERFALL
B18: Event | C18: Before | D18: Dilution | E18: After
B19: Starting | C19: =C4 | D19: 0 | E19: =C19
B20: After ESOP | C20: =E19 | D20: =G12 | E20: =C20*(1-D20)
B21: After Seed | C21: =E20 | D21: =G13 | E21: =C21*(1-D21)
B22: After Series A | C22: =E21 | D22: =G14 | E22: =C22*(1-D22)
A24: 3-YEAR EXIT SCENARIOS
B25: Scenario | C25: Prob | D25: Product EV | E25: Founder Prod | F25: Services $ | G25: Total Founder
B26: Helm hits $10M+ ARR | C26: 0.5 | D26: 100 | E26: =D26*E22 | F26: =C8 | G26: =E26+F26
B27: Helm at $3-5M ARR | C27: 0.3 | D27: 40 | E27: =D27*E22 | F27: =C8 | G27: =E27+F27
B28: Helm pivots/struggles | C28: 0.15 | D28: 10 | E28: =D28*E22 | F28: =C8 | G28: =E28+F28
B29: Wind down (services $ preserved) | C29: 0.05 | D29: 0 | E29: =D29*E22 | F29: =C8 | G29: =E29+F29
A31: SUMMARY
B32: Expected Enterprise Value | C32: =SUMPRODUCT(C26:C29,D26:D29)
B33: Expected Founder Value | C33: =SUMPRODUCT(C26:C29,G26:G29)
B34: Final Founder % (Product) | C34: =E22
B35: Total Dilution (Product) | C35: =1-C34
B36: Total Capital Raised | C36: =E13+E14
B37: Guaranteed Floor (Services) | C37: =C8

Sheet Summary_Comparison
A1: DILUTION-ADJUSTED COMPARISON
A3: FOUNDER VALUE ANALYSIS
B4: Metric | C4: Lean | D4: Liquidate | E4: Growth Both | F4: Strategic
B5: Expected Founder Value | C5: =Path1_Lean!C21 | D5: =Path2_Liquidate!C32 | E5: =Path3_GrowthBoth!C32 | F5: =Path4_Strategic!C33
B6: Final Founder % | C6: =Path1_Lean!C22 | D6: =Path2_Liquidate!C33 | E6: =Path3_GrowthBoth!C33 | F6: =Path4_Strategic!C34
B7: Total Dilution | C7: =1-C6 | D7: =1-D6 | E7: =1-E6 | F7: =1-F6
B8: Capital Raised | C8: 0 | D8: =Path2_Liquidate!C35 | E8: =Path3_GrowthBoth!C35 | F8: =Path4_Strategic!C36
A10: DOWNSIDE PROTECTION
B11: Worst Case (Founder $) | C11: =Path1_Lean!F17 | D11: =Path2_Liquidate!G27 | E11: =Path3_GrowthBoth!G28 | F11: =Path4_Strategic!G29
B12: Best Case (Founder $) | C12: =Path1_Lean!F15 | D12: =Path2_Liquidate!G24 | E12: =Path3_GrowthBoth!G25 | F12: =Path4_Strategic!G26
B13: Upside/Downside Ratio | C13: =C12/C11 | D13: =D12/D11 | E13: =E12/E11 | F13: =F12/F11
A15: RANKING
B16: Rank by Founder Value | C16: =RANK(C5,$C$5:$F$5,0) | D16: =RANK(D5,$C$5:$F$5,0) | E16: =RANK(E5,$C$5:$F$5,0) | F16: =RANK(F5,$C$5:$F$5,0)
B17: Rank by Downside Protection | C17: =RANK(C11,$C$11:$F$11,0) | D17: =RANK(D11,$C$11:$F$11,0) | E17: =RANK(E11,$C$11:$F$11,0) | F17: =RANK(F11,$C$11:$F$11,0)
B19: WINNER | F19: STRATEGIC
A21: KEY INSIGHTS
B22: 1. Strategic Leverage has BOTH highest EV and best downside protection
B23: 2. Validation-first approach yields 70%+ better seed valuations
B24: 3. $8M services floor means founder never walks away empty
B25: 4. Same $13M raised, but at better terms = less dilution
A27: FUNDING ASSUMPTIONS (2025/2026 Market)
B28: Seed without traction: $6-8M pre-money
B29: Seed with design partners: $10-14M pre-money
B30: Series A (B2B SaaS): $20-40M pre-money
B31: Standard ESOP: 10-15% pre-financing
B32: Services multiple: 2.5-3.5x revenue
