Workbook
Name _: #REF!
Name __: #REF!
Name ___: {"'1-TheatreBkgs'!$A$1:$L$102"}
Name ______________________________j4: {"Inc_standard",#N/A,TRUE,"Inc"}
Name ______________________________j5: {"'A'!$A$1:$AH$71","'TOC'!$J$29"}
Name ______________________________j6: {"'A'!$A$1:$AH$71","'TOC'!$J$29"}
Name ______________________________j8: {#N/A,"SCENARIO2",FALSE,"DirRpts_Sum";#N/A,"SCENARIO2",FALSE,"Exp_Adjmts";#N/A,#N/A,FALSE,"Advtg_Sum"}
Name ______________________________t9: {#N/A,"SCENARIO2",FALSE,"DirRpts_Sum";#N/A,"SCENARIO2",FALSE,"Exp_Adjmts";#N/A,#N/A,FALSE,"Advtg_Sum"}
Name _____________________________DCF1: #REF!
Name ____________________________j4: {"Inc_standard",#N/A,TRUE,"Inc"}
Name ____________________________j5: {"'A'!$A$1:$AH$71","'TOC'!$J$29"}
Name ____________________________j6: {"'A'!$A$1:$AH$71","'TOC'!$J$29"}
Name ____________________________j8: {#N/A,"SCENARIO2",FALSE,"DirRpts_Sum";#N/A,"SCENARIO2",FALSE,"Exp_Adjmts";#N/A,#N/A,FALSE,"Advtg_Sum"}
Name ____________________________t9: {#N/A,"SCENARIO2",FALSE,"DirRpts_Sum";#N/A,"SCENARIO2",FALSE,"Exp_Adjmts";#N/A,#N/A,FALSE,"Advtg_Sum"}
Name ____________________________ww2: {#N/A,#N/A,FALSE,"Admin";#N/A,#N/A,FALSE,"Other"}
Name ___________________________DCF1: #REF!
Name __________________________DCF1: #REF!
Name __________________________j4: {"Inc_standard",#N/A,TRUE,"Inc"}
Name __________________________j5: {"'A'!$A$1:$AH$71","'TOC'!$J$29"}
Name __________________________j6: {"'A'!$A$1:$AH$71","'TOC'!$J$29"}
Name __________________________j8: {#N/A,"SCENARIO2",FALSE,"DirRpts_Sum";#N/A,"SCENARIO2",FALSE,"Exp_Adjmts";#N/A,#N/A,FALSE,"Advtg_Sum"}
Name __________________________t9: {#N/A,"SCENARIO2",FALSE,"DirRpts_Sum";#N/A,"SCENARIO2",FALSE,"Exp_Adjmts";#N/A,#N/A,FALSE,"Advtg_Sum"}
Name _________________________DCF1: #REF!
Name _________________________j4: {"Inc_standard",#N/A,TRUE,"Inc"}
Name _________________________j5: {"'A'!$A$1:$AH$71","'TOC'!$J$29"}
Name _________________________j6: {"'A'!$A$1:$AH$71","'TOC'!$J$29"}
Name _________________________j8: {#N/A,"SCENARIO2",FALSE,"DirRpts_Sum";#N/A,"SCENARIO2",FALSE,"Exp_Adjmts";#N/A,#N/A,FALSE,"Advtg_Sum"}
Name _________________________t9: {#N/A,"SCENARIO2",FALSE,"DirRpts_Sum";#N/A,"SCENARIO2",FALSE,"Exp_Adjmts";#N/A,#N/A,FALSE,"Advtg_Sum"}
Name ________________________DCF1: #REF!
Name _______________________DCF1: #REF!
Name _______________________j4: {"Inc_standard",#N/A,TRUE,"Inc"}
Name _______________________j5: {"'A'!$A$1:$AH$71","'TOC'!$J$29"}
Name _______________________j6: {"'A'!$A$1:$AH$71","'TOC'!$J$29"}
Name _______________________j8: {#N/A,"SCENARIO2",FALSE,"DirRpts_Sum";#N/A,"SCENARIO2",FALSE,"Exp_Adjmts";#N/A,#N/A,FALSE,"Advtg_Sum"}
Name _______________________t9: {#N/A,"SCENARIO2",FALSE,"DirRpts_Sum";#N/A,"SCENARIO2",FALSE,"Exp_Adjmts";#N/A,#N/A,FALSE,"Advtg_Sum"}
Name ______________________DCF1: #REF!
Name ______________________j4: {"Inc_standard",#N/A,TRUE,"Inc"}
Name ______________________j5: {"'A'!$A$1:$AH$71","'TOC'!$J$29"}
Name ______________________j6: {"'A'!$A$1:$AH$71","'TOC'!$J$29"}
Name ______________________j8: {#N/A,"SCENARIO2",FALSE,"DirRpts_Sum";#N/A,"SCENARIO2",FALSE,"Exp_Adjmts";#N/A,#N/A,FALSE,"Advtg_Sum"}
Name ______________________t9: {#N/A,"SCENARIO2",FALSE,"DirRpts_Sum";#N/A,"SCENARIO2",FALSE,"Exp_Adjmts";#N/A,#N/A,FALSE,"Advtg_Sum"}
Name _____________________DCF1: #REF!
Name _____________________PRN2: {"adj95mult",#N/A,FALSE,"COMPCO";"adj95est",#N/A,FALSE,"COMPCO"}
Name _____________________T123456: {"COUNT",#N/A,FALSE,"AB"}
Name _____________________T12347: {"COUNT",#N/A,FALSE,"AB"}
Name ____________________DCF1: #REF!
Name ____________________j4: {"Inc_standard",#N/A,TRUE,"Inc"}
Name ____________________j5: {"'A'!$A$1:$AH$71","'TOC'!$J$29"}
Name ____________________j6: {"'A'!$A$1:$AH$71","'TOC'!$J$29"}
Name ____________________j8: {#N/A,"SCENARIO2",FALSE,"DirRpts_Sum";#N/A,"SCENARIO2",FALSE,"Exp_Adjmts";#N/A,#N/A,FALSE,"Advtg_Sum"}
Name ____________________PRN2: {"adj95mult",#N/A,FALSE,"COMPCO";"adj95est",#N/A,FALSE,"COMPCO"}
Name ____________________t9: {#N/A,"SCENARIO2",FALSE,"DirRpts_Sum";#N/A,"SCENARIO2",FALSE,"Exp_Adjmts";#N/A,#N/A,FALSE,"Advtg_Sum"}
Name ___________________DCF1: #REF!
Name ___________________PRN2: {"adj95mult",#N/A,FALSE,"COMPCO";"adj95est",#N/A,FALSE,"COMPCO"}
Name __________________DCF1: #REF!
Name __________________PRN2: {"adj95mult",#N/A,FALSE,"COMPCO";"adj95est",#N/A,FALSE,"COMPCO"}
Name __________________T123456: {"COUNT",#N/A,FALSE,"AB"}
Name __________________T12347: {"COUNT",#N/A,FALSE,"AB"}
Name _________________DCF1: #REF!
Name _________________j4: {"Inc_standard",#N/A,TRUE,"Inc"}

Sheet Inputs
B2: Current Month: | C2: 46022

Sheet Cover Page
C17: =TEXT(Inputs!C2,"Mmmm yyyy")&" - Monthly Reporting Pack" -> December 2025 - Monthly Reporting Pack
F19: Confidential

Sheet Narrative
B2: Dispatch | Monthly Operating Narrative
B3: =TEXT(Inputs!C2,"Mmmm yyyy") -> December 2025

Sheet Exec Summary
C2: Dispatch Business Unit | M2: Youreka Business Unit | W2: Consolidated Company
C3: =Inputs!$C$2 -> 46022 | E3: Actual vs Plan | I3: Year over Year | M3: =Inputs!$C$2 -> 46022 | O3: Actual vs Plan | S3: Year over Year | W3: =Inputs!$C$2 -> 46022 | Y3: Actual vs Plan | AC3: Year over Year
C4: Actual | E4: =YEAR(Inputs!$C$2)&" Plan" -> 2025 Plan | F4: Diff($) | G4: Diff (%) | I4: =YEAR(EOMONTH(Inputs!$C$2,-12))&" Actual" -> 2024 Actual | J4: Diff($) | K4: Diff (%) | M4: Actual | O4: =YEAR(Inputs!$C$2)&" Plan" -> 2025 Plan | P4: Diff($) | Q4: Diff (%) | S4: =YEAR(EOMONTH(Inputs!$C$2,-12))&" Actual" -> 2024 Actual | T4: Diff($) | U4: Diff (%) | W4: Actual | Y4: =YEAR(Inputs!$C$2)&" Plan" -> 2025 Plan | Z4: Diff($) | AA4: Diff (%) | AC4: =YEAR(EOMONTH(Inputs!$C$2,-12))&" Actual" -> 2024 Actual | AD4: Diff($) | AE4: Diff (%)
B5: Revenue
B6: Recurring | C6: ='1a. Dispatch Functional P&L'!E11 -> 1121015.8 | E6: ='1a. Dispatch Functional P&L'!F11 -> 1200544.9 | F6: =IFERROR(C6-E6,"N/A") -> -79529.093 | G6: =IFERROR(C6/E6-1,"N/A") -> -0.066244161 | I6: ='1a. Dispatch Functional P&L'!P11 -> 1070609 | J6: =IFERROR(C6-I6,"N/A") -> 50406.84 | K6: =IFERROR(C6/I6-1,"N/A") -> 0.047082398 | M6: ='1b. Youreka Functional P&L'!E11 -> 993864.86 | O6: ='1b. Youreka Functional P&L'!F11 -> 1080660.7 | P6: =IFERROR(M6-O6,"N/A") -> -86795.881 | Q6: =IFERROR(M6/O6-1,"N/A") -> -0.080317418 | S6: ='1b. Youreka Functional P&L'!P11 -> 865103.75 | T6: =IFERROR(M6-S6,"N/A") -> 128761.11 | U6: =IFERROR(M6/S6-1,"N/A") -> 0.14883892 | W6: =C6+M6 -> 2114880.7 | Y6: =IFERROR(E6+O6,"N/A") -> 2281205.7 | Z6: =IFERROR(W6-Y6,"N/A") -> -166324.97 | AA6: =IFERROR(W6/Y6-1,"N/A") -> -0.072910994 | AC6: =I6+S6 -> 1935712.8 | AD6: =IFERROR(W6-AC6,"N/A") -> 179167.95 | AE6: =IFERROR(W6/AC6-1,"N/A") -> 0.092559162
B7: Non-recurring | C7: ='1a. Dispatch Functional P&L'!E15 -> 26500 | E7: ='1a. Dispatch Functional P&L'!F15 -> 28666.667 | F7: =IFERROR(C7-E7,"N/A") -> -2166.6667 | G7: =IFERROR(C7/E7-1,"N/A") -> -0.075581395 | I7: ='1a. Dispatch Functional P&L'!P15 -> 31999 | J7: =IFERROR(C7-I7,"N/A") -> -5499 | K7: =IFERROR(C7/I7-1,"N/A") -> -0.17184912 | M7: ='1b. Youreka Functional P&L'!E15 -> 22500 | O7: ='1b. Youreka Functional P&L'!F15 -> 10583.333 | P7: =IFERROR(M7-O7,"N/A") -> 11916.667 | Q7: =IFERROR(M7/O7-1,"N/A") -> 1.1259843 | S7: ='1b. Youreka Functional P&L'!P15 -> 37019.05 | T7: =IFERROR(M7-S7,"N/A") -> -14519.05 | U7: =IFERROR(M7/S7-1,"N/A") -> -0.39220482 | W7: =C7+M7 -> 49000 | Y7: =IFERROR(E7+O7,"N/A") -> 39250 | Z7: =IFERROR(W7-Y7,"N/A") -> 9750 | AA7: =IFERROR(W7/Y7-1,"N/A") -> 0.24840764 | AC7: =I7+S7 -> 69018.05 | AD7: =IFERROR(W7-AC7,"N/A") -> -20018.05 | AE7: =IFERROR(W7/AC7-1,"N/A") -> -0.29004079
B8: Total | C8: =SUM(C6:C7) -> 1147515.8 | E8: ='1a. Dispatch Functional P&L'!F16 -> 1229211.6 | F8: =IFERROR(C8-E8,"N/A") -> -81695.759 | G8: =IFERROR(C8/E8-1,"N/A") -> -0.066461917 | I8: =SUM(I6:I7) -> 1102608 | J8: =IFERROR(C8-I8,"N/A") -> 44907.84 | K8: =IFERROR(C8/I8-1,"N/A") -> 0.040728745 | M8: =SUM(M6:M7) -> 1016364.9 | O8: ='1b. Youreka Functional P&L'!F16 -> 1091244.1 | P8: =IFERROR(M8-O8,"N/A") -> -74879.214 | Q8: =IFERROR(M8/O8-1,"N/A") -> -0.068618209 | S8: =SUM(S6:S7) -> 902122.8 | T8: =IFERROR(M8-S8,"N/A") -> 114242.06 | U8: =IFERROR(M8/S8-1,"N/A") -> 0.12663693 | W8: =SUM(W6:W7) -> 2163880.7 | Y8: =IFERROR(E8+O8,"N/A") -> 2320455.7 | Z8: =IFERROR(W8-Y8,"N/A") -> -156574.97 | AA8: =IFERROR(W8/Y8-1,"N/A") -> -0.067475959 | AC8: =SUM(AC6:AC7) -> 2004730.8 | AD8: =IFERROR(W8-AC8,"N/A") -> 159149.9 | AE8: =IFERROR(W8/AC8-1,"N/A") -> 0.079387167
B9: % Reccurring Revenue | C9: =C6/C8 -> 0.97690664 | E9: =IFERROR(E6/E8,"N/A") -> 0.97667882 | I9: =I6/I8 -> 0.97097881 | M9: =M6/M8 -> 0.97786228 | O9: =IFERROR(O6/O8,"N/A") -> 0.99030159 | S9: =S6/S8 -> 0.95896451 | W9: =W6/W8 -> 0.9773555 | Y9: =IFERROR(Y6/Y8,"N/A") -> 0.98308522 | AC9: =AC6/AC8 -> 0.96557241
B11: Gross Profit ($) | C11: ='1a. Dispatch Functional P&L'!E32 -> 936897.54 | E11: ='1a. Dispatch Functional P&L'!F32 -> 1034875.5 | F11: =IFERROR(C11-E11,"N/A") -> -97977.98 | G11: =IFERROR(C11/E11-1,"N/A") -> -0.094676102 | I11: ='1a. Dispatch Functional P&L'!P32 -> 911795.62 | J11: =IFERROR(C11-I11,"N/A") -> 25101.92 | K11: =IFERROR(C11/I11-1,"N/A") -> 0.027530205 | M11: ='1b. Youreka Functional P&L'!E32 -> 763128.94 | O11: ='1b. Youreka Functional P&L'!F32 -> 834901.58 | P11: =IFERROR(M11-O11,"N/A") -> -71772.644 | Q11: =IFERROR(M11/O11-1,"N/A") -> -0.085965394 | S11: ='1b. Youreka Functional P&L'!P32 -> 669606.17 | T11: =IFERROR(M11-S11,"N/A") -> 93522.77 | U11: =IFERROR(M11/S11-1,"N/A") -> 0.13966832 | W11: =C11+M11 -> 1700026.5 | Y11: =IFERROR(E11+O11,"N/A") -> 1869777.1 | Z11: =IFERROR(W11-Y11,"N/A") -> -169750.62 | AA11: =IFERROR(W11/Y11-1,"N/A") -> -0.090786556 | AC11: =I11+S11 -> 1581401.8 | AD11: =IFERROR(W11-AC11,"N/A") -> 118624.69 | AE11: =IFERROR(W11/AC11-1,"N/A") -> 0.075012366
B12: Gross Profit (%) | C12: =C11/C8 -> 0.81645717 | E12: =IFERROR(E11/E8,"N/A") -> 0.84190184 | G12: =C12-E12 -> -0.025444677 | I12: =I11/I8 -> 0.82694449 | K12: =C12-I12 -> -0.010487324 | M12: =M11/M8 -> 0.75084152 | O12: =IFERROR(O11/O8,"N/A") -> 0.76509152 | Q12: =M12-O12 -> -0.014249993 | S12: =S11/S8 -> 0.74225612 | U12: =M12-S12 -> 0.0085854028 | W12: =W11/W8 -> 0.7856378 | Y12: =Y11/Y8 -> 0.80578014 | AA12: =W12-Y12 -> -0.02014234 | AC12: =AC11/AC8 -> 0.78883498 | AE12: =W12-AC12 -> -0.003197181
B14: EBITDA ($) | C14: ='1a. Dispatch Functional P&L'!E84 -> 246778.48 | E14: ='1a. Dispatch Functional P&L'!F84 -> 98053.145 | F14: =IFERROR(C14-E14,"N/A") -> 148725.34 | G14: =IFERROR(C14/E14-1,"N/A") -> 1.5167829 | I14: ='1a. Dispatch Functional P&L'!P84 -> 11013.611 | J14: =IFERROR(C14-I14,"N/A") -> 235764.87 | K14: =IFERROR(C14/I14-1,"N/A") -> 21.406682 | M14: ='1b. Youreka Functional P&L'!E84 -> 355001.73 | O14: ='1b. Youreka Functional P&L'!F84 -> 266928.82 | P14: =IFERROR(M14-O14,"N/A") -> 88072.914 | Q14: =IFERROR(M14/O14-1,"N/A") -> 0.32994907 | S14: ='1b. Youreka Functional P&L'!P84 -> 133318.06 | T14: =IFERROR(M14-S14,"N/A") -> 221683.67 | U14: =IFERROR(M14/S14-1,"N/A") -> 1.662818 | W14: =C14+M14 -> 601780.21 | Y14: =IFERROR(E14+O14,"N/A") -> 364981.96 | Z14: =IFERROR(W14-Y14,"N/A") -> 236798.25 | AA14: =IFERROR(W14/Y14-1,"N/A") -> 0.64879439 | AC14: =I14+S14 -> 144331.67 | AD14: =IFERROR(W14-AC14,"N/A") -> 457448.54 | AE14: =IFERROR(W14/AC14-1,"N/A") -> 3.1694259
B15: EBITDA (%) | C15: =C14/C8 -> 0.21505453 | E15: =IFERROR(E14/E8,"N/A") -> 0.079769134 | I15: =I14/I8 -> 0.0099886912 | M15: =M14/M8 -> 0.34928572 | O15: =IFERROR(O14/O8,"N/A") -> 0.24460964 | S15: =S14/S8 -> 0.14778261 | W15: =W14/W8 -> 0.2781023 | Y15: =Y14/Y8 -> 0.15728892 | AC15: =AC14/AC8 -> 0.071995537
B17: Cash Balance | C17: ='Dispatch BS-Monthly'!Q8 -> 47713.25 | E17: =INDEX('Dispatch CF-Monthly'!$AI$66:$AU$66,MATCH($C$3,'Dispatch CF-Monthly'!$AI$5:$AU$5,0)) -> -3532586.7 | F17: =IFERROR(C17-E17,"N/A") -> 3580299.9 | G17: =IFERROR(C17/E17-1,"N/A") -> -1.0135066 | I17: ='3. Balance Sheet'!I9 -> 489889.18 | J17: =IFERROR(C17-I17,"N/A") -> -442175.93 | K17: =IFERROR(C17/I17-1,"N/A") -> -0.90260399 | M17: ='Youreka BS-Monthly'!Q8 -> 46955.58 | O17: =INDEX('Youreka CF-Monthly'!$AI$66:$AU$66,MATCH($C$3,'Youreka CF-Monthly'!$AI$5:$AU$5,0)) -> 4059401.8 | P17: =IFERROR(M17-O17,"N/A") -> -4012446.2 | Q17: =IFERROR(M17/O17-1,"N/A") -> -0.98843288 | S17: ='3. Balance Sheet'!I9 -> 489889.18 | T17: =IFERROR(M17-S17,"N/A") -> -442933.6 | U17: =IFERROR(M17/S17-1,"N/A") -> -0.90415061 | W17: =C17+M17 -> 94668.83 | Y17: =IFERROR(E17+O17,"N/A") -> 526815.12 | Z17: =IFERROR(W17-Y17,"N/A") -> -432146.29 | AA17: =IFERROR(W17/Y17-1,"N/A") -> -0.82029971 | AC17: =I17+S17 -> 979778.36 | AD17: =IFERROR(W17-AC17,"N/A") -> -885109.53 | AE17: =IFERROR(W17/AC17-1,"N/A") -> -0.9033773
B18: Debt Balance | C18: ='Dispatch BS-Monthly'!Q49 -> 53483000 | E18: =INDEX('Dispatch BS-Monthly'!$AI$49:$AU$49,MATCH(C3,'Dispatch BS-Monthly'!$AI$5:$AU$5,0)) -> 48325271 | F18: =IFERROR(C18-E18,"N/A") -> 5157729 | G18: =IFERROR(C18/E18-1,"N/A") -> 0.10672944 | I18: ='3. Balance Sheet'!I50 -> 52158000 | J18: =IFERROR(C18-I18,"N/A") -> 1325000 | K18: =IFERROR(C18/I18-1,"N/A") -> 0.025403581 | W18: =C18+M18 -> 53483000 | Y18: =IFERROR(E18+O18,"N/A") -> 48325271 | Z18: =IFERROR(W18-Y18,"N/A") -> 5157729 | AA18: =IFERROR(W18/Y18-1,"N/A") -> 0.10672944 | AC18: =I18+S18 -> 52158000 | AD18: =IFERROR(W18-AC18,"N/A") -> 1325000 | AE18: =IFERROR(W18/AC18-1,"N/A") -> 0.025403581
B20: Enterprise collections | C20: ='Dispatch Payments'!F16 -> 215777.79 | E20: List | M20: ='Youreka Payments'!E19 -> 761145 | O20: List | W20: =M20+C20 -> 976922.79
B22: Live ARR3 | C22: =INDEX('6. Snowball'!$L$51:$W$51,MATCH(C$3,'6. Snowball'!$L$8:$W$8,0)) -> 13452190 | E22: =INDEX('6. Snowball'!$AH$51:$AS$51,MATCH(C$3,'6. Snowball'!$AH$8:$AS$8,0)) -> 14406539 | F22: =IFERROR(C22-E22,"N/A") -> -954349.4 | G22: =IFERROR(C22/E22-1,"N/A") -> -0.066244181 | I22: =I6*12 -> 12847308 | J22: =IFERROR(C22-I22,"N/A") -> 604881.79 | K22: =IFERROR(C22/I22-1,"N/A") -> 0.047082376 | M22: {=INDEX('6. Snowball'!$L$81:$W$81,MATCH(M$3,'6. Snowball'!$L$8:$W$8,0))} -> 11797002 | O22: =INDEX('6. Snowball'!$AH$81:$AS$81,MATCH(M$3,'6. Snowball'!$AH$8:$AS$8,0)) -> 12967929 | P22: =IFERROR(M22-O22,"N/A") -> -1170927 | Q22: =IFERROR(M22/O22-1,"N/A") -> -0.090294061 | S22: =S6*12 -> 10381245 | T22: =IFERROR(M22-S22,"N/A") -> 1415756.9 | U22: =IFERROR(M22/S22-1,"N/A") -> 0.13637641 | W22: =M22+C22 -> 25249192 | Y22: =IFERROR(E22+O22,"N/A") -> 27374468 | Z22: =IFERROR(W22-Y22,"N/A") -> -2125276.4 | AA22: =IFERROR(W22/Y22-1,"N/A") -> -0.077637174 | AC22: =I22+S22 -> 23228553 | AD22: =IFERROR(W22-AC22,"N/A") -> 2020638.7 | AE22: =IFERROR(W22/AC22-1,"N/A") -> 0.086989435
B24: CARR 1 | C24: 13817790 | E24: 15076015 | F24: =IFERROR(C24-E24,"N/A") -> -1258225.2 | G24: =IFERROR(C24/E24-1,"N/A") -> -0.083458742 | I24: 13599013 | J24: =IFERROR(C24-I24,"N/A") -> 218776.54 | K24: =IFERROR(C24/I24-1,"N/A") -> 0.016087678 | M24: 11868188 | O24: 13943297 | P24: =IFERROR(M24-O24,"N/A") -> -2075108.6 | Q24: =IFERROR(M24/O24-1,"N/A") -> -0.14882481 | S24: 11974733 | T24: =IFERROR(M24-S24,"N/A") -> -106544.44 | U24: =IFERROR(M24/S24-1,"N/A") -> -0.0088974382 | W24: =M24+C24 -> 25685978 | Y24: =IFERROR(E24+O24,"N/A") -> 29019312 | Z24: =IFERROR(W24-Y24,"N/A") -> -3333333.8 | AA24: =IFERROR(W24/Y24-1,"N/A") -> -0.11486605 | AC24: =I24+S24 -> 25573746 | AD24: =IFERROR(W24-AC24,"N/A") -> 112232.1 | AE24: =IFERROR(W24/AC24-1,"N/A") -> 0.0043885669
B25: Max ARR 2 | C25: 13971474 | I25: 13812253 | J25: =IFERROR(C25-I25,"N/A") -> 159221.58 | K25: =IFERROR(C25/I25-1,"N/A") -> 0.011527561 | M25: TBD | S25: TBD | T25: =IFERROR(M25-S25,"N/A") -> N/A | U25: =IFERROR(M25/S25-1,"N/A") -> N/A | W25: =IFERROR(M25+C25,"N/A") -> N/A | AC25: =IFERROR(S25+I25,"N/A") -> N/A | AD25: =IFERROR(W25-AC25,"N/A") -> N/A | AE25: =IFERROR(W25/AC25-1,"N/A") -> N/A
B28: 1 Contracted ARR scheduled to go live in the next 12 months
B29: 2 Includes all contractual step ups, regardless of timing, and assumes 100% renewal rate

Sheet 1. Consolidated Functional P&L
C1: Dispatch | Monthly Profit & Loss (Functional View)
E4: Current Month | J4: Year-to-Date | O4: Year-over-Year
U5: Current Month | X5: YTD | AA5: YoY
C6: Revenue | E6: =Inputs!C2 -> 46022 | F6: Budget | G6: Difference | H6: % Difference | J6: =E6 -> 46022 | K6: Budget | L6: Difference | M6: % Difference | O6: =J6 -> 46022 | P6: =EOMONTH(E6,-12) -> 45657 | Q6: Difference | R6: % Difference | U6: Checks | X6: Checks | AA6: Checks
C7: Recurring Revenue
C8: Recurring Enterprise License Revenue | E8: ='1a. Dispatch Functional P&L'!E8+'1b. Youreka Functional P&L'!E8 -> 1886430.2 | F8: ='1a. Dispatch Functional P&L'!F8+'1b. Youreka Functional P&L'!F8 -> 2054472.9 | G8: =IFERROR(E8-F8,"N/A") -> -168042.7 | H8: =IFERROR((E8/F8-1),"N/A") -> -0.081793584 | J8: ='1a. Dispatch Functional P&L'!J8+'1b. Youreka Functional P&L'!J8 -> 22220506 | K8: ='1a. Dispatch Functional P&L'!K8+'1b. Youreka Functional P&L'!K8 -> 23068278 | L8: =IFERROR(J8-K8,"N/A") -> -847772.07 | M8: =IFERROR((J8/K8-1),"N/A") -> -0.036750557 | O8: ='1a. Dispatch Functional P&L'!O8+'1b. Youreka Functional P&L'!O8 -> 1886430.2 | P8: ='1a. Dispatch Functional P&L'!P8+'1b. Youreka Functional P&L'!P8 -> 1736049.1 | Q8: =O8-P8 -> 150381.11 | R8: =IFERROR((O8/P8-1),"N/A") -> 0.086622615
C9: Recurring Services Revenue | E9: ='1a. Dispatch Functional P&L'!E9+'1b. Youreka Functional P&L'!E9 -> 132806.87 | F9: ='1a. Dispatch Functional P&L'!F9+'1b. Youreka Functional P&L'!F9 -> 118739.5 | G9: =IFERROR(E9-F9,"N/A") -> 14067.368 | H9: =IFERROR((E9/F9-1),"N/A") -> 0.11847252 | J9: ='1a. Dispatch Functional P&L'!J9+'1b. Youreka Functional P&L'!J9 -> 1534400.6 | K9: ='1a. Dispatch Functional P&L'!K9+'1b. Youreka Functional P&L'!K9 -> 1423624 | L9: =IFERROR(J9-K9,"N/A") -> 110776.62 | M9: =IFERROR((J9/K9-1),"N/A") -> 0.077813115 | O9: ='1a. Dispatch Functional P&L'!O9+'1b. Youreka Functional P&L'!O9 -> 132806.87 | P9: ='1a. Dispatch Functional P&L'!P9+'1b. Youreka Functional P&L'!P9 -> 107855.4 | Q9: =O9-P9 -> 24951.47 | R9: =IFERROR((O9/P9-1),"N/A") -> 0.23134187
C10: Recurring Service Provider (SMB) Revenue | E10: ='1a. Dispatch Functional P&L'!E10+'1b. Youreka Functional P&L'!E10 -> 95643.67 | F10: ='1a. Dispatch Functional P&L'!F10+'1b. Youreka Functional P&L'!F10 -> 107993.31 | G10: =IFERROR(E10-F10,"N/A") -> -12349.642 | H10: =IFERROR((E10/F10-1),"N/A") -> -0.11435562 | J10: ='1a. Dispatch Functional P&L'!J10+'1b. Youreka Functional P&L'!J10 -> 1158666.8 | K10: ='1a. Dispatch Functional P&L'!K10+'1b. Youreka Functional P&L'!K10 -> 1217243.8 | L10: =IFERROR(J10-K10,"N/A") -> -58577.008 | M10: =IFERROR((J10/K10-1),"N/A") -> -0.048122658 | O10: ='1a. Dispatch Functional P&L'!O10+'1b. Youreka Functional P&L'!O10 -> 95643.67 | P10: ='1a. Dispatch Functional P&L'!P10+'1b. Youreka Functional P&L'!P10 -> 91808.3 | Q10: =O10-P10 -> 3835.37 | R10: =IFERROR((O10/P10-1),"N/A") -> 0.041775853
C11: Total Recurring Revenue | E11: ='1a. Dispatch Functional P&L'!E11+'1b. Youreka Functional P&L'!E11 -> 2114880.7 | F11: ='1a. Dispatch Functional P&L'!F11+'1b. Youreka Functional P&L'!F11 -> 2281205.7 | G11: =IFERROR(E11-F11,"N/A") -> -166324.97 | H11: =IFERROR((E11/F11-1),"N/A") -> -0.072910994 | J11: ='1a. Dispatch Functional P&L'!J11+'1b. Youreka Functional P&L'!J11 -> 24913573 | K11: ='1a. Dispatch Functional P&L'!K11+'1b. Youreka Functional P&L'!K11 -> 25709146 | L11: =IFERROR(J11-K11,"N/A") -> -795572.46 | M11: =IFERROR((J11/K11-1),"N/A") -> -0.030945115 | O11: ='1a. Dispatch Functional P&L'!O11+'1b. Youreka Functional P&L'!O11 -> 2114880.7 | P11: ='1a. Dispatch Functional P&L'!P11+'1b. Youreka Functional P&L'!P11 -> 1935712.8 | Q11: =O11-P11 -> 179167.95 | R11: =IFERROR((O11/P11-1),"N/A") -> 0.092559162 | U11: =SUM(E8:E10)-E11 -> 0 | V11: =SUM(F8:F10)-F11 -> 0 | X11: =SUM(J8:J10)-J11 -> 0 | Y11: =SUM(K8:K10)-K11 -> 0 | AA11: =SUM(O8:O10)-O11 -> 0 | AB11: =SUM(P8:P10)-P11 -> 0
C12: Non-Recurring Revenue
C13: Non-Recurring Professional Services Revenue | E13: ='1a. Dispatch Functional P&L'!E13+'1b. Youreka Functional P&L'!E13 -> 49000 | F13: ='1a. Dispatch Functional P&L'!F13+'1b. Youreka Functional P&L'!F13 -> 39250 | G13: =IFERROR(E13-F13,"N/A") -> 9750 | H13: =IFERROR((E13/F13-1),"N/A") -> 0.24840764 | J13: ='1a. Dispatch Functional P&L'!J13+'1b. Youreka Functional P&L'!J13 -> 772519.96 | K13: ='1a. Dispatch Functional P&L'!K13+'1b. Youreka Functional P&L'!K13 -> 506416.67 | L13: =IFERROR(J13-K13,"N/A") -> 266103.29 | M13: =IFERROR((J13/K13-1),"N/A") -> 0.52546314 | O13: ='1a. Dispatch Functional P&L'!O13+'1b. Youreka Functional P&L'!O13 -> 49000 | P13: ='1a. Dispatch Functional P&L'!P13+'1b. Youreka Functional P&L'!P13 -> 69018.05 | Q13: =O13-P13 -> -20018.05 | R13: =IFERROR((O13/P13-1),"N/A") -> -0.29004079
C14: Other Non-Recurring Revenue | E14: ='1a. Dispatch Functional P&L'!E14+'1b. Youreka Functional P&L'!E14 -> 0 | F14: ='1a. Dispatch Functional P&L'!F14+'1b. Youreka Functional P&L'!F14 -> 0 | G14: =IFERROR(E14-F14,"N/A") -> 0 | H14: =IFERROR((E14/F14-1),"N/A") -> N/A | J14: ='1a. Dispatch Functional P&L'!J14+'1b. Youreka Functional P&L'!J14 -> 0 | K14: ='1a. Dispatch Functional P&L'!K14+'1b. Youreka Functional P&L'!K14 -> 0 | L14: =IFERROR(J14-K14,"N/A") -> 0 | M14: =IFERROR((J14/K14-1),"N/A") -> N/A | O14: ='1a. Dispatch Functional P&L'!O14+'1b. Youreka Functional P&L'!O14 -> 0 | P14: ='1a. Dispatch Functional P&L'!P14+'1b. Youreka Functional P&L'!P14 -> 0 | Q14: =O14-P14 -> 0 | R14: =IFERROR((O14/P14-1),"N/A") -> N/A
C15: Total Non-Recurring Revenue | E15: ='1a. Dispatch Functional P&L'!E15+'1b. Youreka Functional P&L'!E15 -> 49000 | F15: ='1a. Dispatch Functional P&L'!F15+'1b. Youreka Functional P&L'!F15 -> 39250 | G15: =IFERROR(E15-F15,"N/A") -> 9750 | H15: =IFERROR((E15/F15-1),"N/A") -> 0.24840764 | J15: ='1a. Dispatch Functional P&L'!J15+'1b. Youreka Functional P&L'!J15 -> 772519.96 | K15: ='1a. Dispatch Functional P&L'!K15+'1b. Youreka Functional P&L'!K15 -> 506416.67 | L15: =IFERROR(J15-K15,"N/A") -> 266103.29 | M15: =IFERROR((J15/K15-1),"N/A") -> 0.52546314 | O15: ='1a. Dispatch Functional P&L'!O15+'1b. Youreka Functional P&L'!O15 -> 49000 | P15: ='1a. Dispatch Functional P&L'!P15+'1b. Youreka Functional P&L'!P15 -> 69018.05 | Q15: =O15-P15 -> -20018.05 | R15: =IFERROR((O15/P15-1),"N/A") -> -0.29004079 | U15: =SUM(E13:E14)-E15 -> 0 | V15: =SUM(F13:F14)-F15 -> 0 | X15: =SUM(J13:J14)-J15 -> 0 | Y15: =SUM(K13:K14)-K15 -> 0 | AA15: =SUM(O13:O14)-O15 -> 0 | AB15: =SUM(P13:P14)-P15 -> 0
C16: Total Revenue | E16: ='1a. Dispatch Functional P&L'!E16+'1b. Youreka Functional P&L'!E16 -> 2163880.7 | F16: ='1a. Dispatch Functional P&L'!F16+'1b. Youreka Functional P&L'!F16 -> 2320455.7 | G16: =IFERROR(E16-F16,"N/A") -> -156574.97 | H16: =IFERROR((E16/F16-1),"N/A") -> -0.067475959 | J16: ='1a. Dispatch Functional P&L'!J16+'1b. Youreka Functional P&L'!J16 -> 25686093 | K16: ='1a. Dispatch Functional P&L'!K16+'1b. Youreka Functional P&L'!K16 -> 26215562 | L16: =IFERROR(J16-K16,"N/A") -> -529469.17 | M16: =IFERROR((J16/K16-1),"N/A") -> -0.02019675 | O16: ='1a. Dispatch Functional P&L'!O16+'1b. Youreka Functional P&L'!O16 -> 2163880.7 | P16: ='1a. Dispatch Functional P&L'!P16+'1b. Youreka Functional P&L'!P16 -> 2004730.8 | Q16: =O16-P16 -> 159149.9 | R16: =IFERROR((O16/P16-1),"N/A") -> 0.079387167 | U16: =E11+E15-E16 -> 0 | V16: =F11+F15-F16 -> 0 | X16: =J11+J15-J16 -> 0 | Y16: =K11+K15-K16 -> 0 | AA16: =O11+O15-O16 -> 0 | AB16: =P11+P15-P16 -> 0
C17: % Reccurring Revenue | E17: =E11/E16 -> 0.9773555 | F17: =F11/F16 -> 0.98308522 | G17: =IFERROR(E17-F17,"N/A") -> -0.0057297204 | J17: =J11/J16 -> 0.96992458 | K17: =K11/K16 -> 0.98068259 | L17: =IFERROR(J17-K17,"N/A") -> -0.010758011 | O17: =O11/O16 -> 0.9773555 | P17: =P11/P16 -> 0.96557241 | Q17: =O17-P17 -> 0.011783088 | U17: =E11/E16-E17 -> 0 | V17: =F11/F16-F17 -> 0 | X17: =J11/J16-J17 -> 0 | Y17: =K11/K16-K17 -> 0 | AA17: =O11/O16-O17 -> 0 | AB17: =P11/P16-P17 -> 0
C19: Recurring Cost of Sales - Functional
C20: Cost of Sales (Functional) - Direct Compensation (R) | E20: ='1a. Dispatch Functional P&L'!E20+'1b. Youreka Functional P&L'!E20 -> 133217.39 | F20: ='1a. Dispatch Functional P&L'!F20+'1b. Youreka Functional P&L'!F20 -> 123599.11 | G20: =IFERROR(E20-F20,"N/A") -> 9618.2846 | H20: =IFERROR((E20/F20-1),"N/A") -> 0.0778184 | J20: ='1a. Dispatch Functional P&L'!J20+'1b. Youreka Functional P&L'!J20 -> 1575570.4 | K20: ='1a. Dispatch Functional P&L'!K20+'1b. Youreka Functional P&L'!K20 -> 1505275.3 | L20: =IFERROR(J20-K20,"N/A") -> 70295.077 | M20: =IFERROR((J20/K20-1),"N/A") -> 0.04669915 | O20: ='1a. Dispatch Functional P&L'!O20+'1b. Youreka Functional P&L'!O20 -> 133217.39 | P20: ='1a. Dispatch Functional P&L'!P20+'1b. Youreka Functional P&L'!P20 -> 131756.49 | Q20: =O20-P20 -> 1460.9 | R20: =IFERROR((O20/P20-1),"N/A") -> 0.011087879
C21: Cost of Sales (Functional) - Hosting & Infrastructure | E21: ='1a. Dispatch Functional P&L'!E21+'1b. Youreka Functional P&L'!E21 -> 159319.81 | F21: ='1a. Dispatch Functional P&L'!F21+'1b. Youreka Functional P&L'!F21 -> 169122.85 | G21: =IFERROR(E21-F21,"N/A") -> -9803.0355 | H21: =IFERROR((E21/F21-1),"N/A") -> -0.057963994 | J21: ='1a. Dispatch Functional P&L'!J21+'1b. Youreka Functional P&L'!J21 -> 1869794.5 | K21: ='1a. Dispatch Functional P&L'!K21+'1b. Youreka Functional P&L'!K21 -> 1958808.1 | L21: =IFERROR(J21-K21,"N/A") -> -89013.559 | M21: =IFERROR((J21/K21-1),"N/A") -> -0.045442716 | O21: ='1a. Dispatch Functional P&L'!O21+'1b. Youreka Functional P&L'!O21 -> 159319.81 | P21: ='1a. Dispatch Functional P&L'!P21+'1b. Youreka Functional P&L'!P21 -> 145877.6 | Q21: =O21-P21 -> 13442.21 | R21: =IFERROR((O21/P21-1),"N/A") -> 0.092147184
C22: Cost of Sales (Functional) - Software & Subscriptions | E22: ='1a. Dispatch Functional P&L'!E22+'1b. Youreka Functional P&L'!E22 -> 60407.04 | F22: ='1a. Dispatch Functional P&L'!F22+'1b. Youreka Functional P&L'!F22 -> 60127.688 | G22: =IFERROR(E22-F22,"N/A") -> 279.3525 | H22: =IFERROR((E22/F22-1),"N/A") -> 0.0046459878 | J22: ='1a. Dispatch Functional P&L'!J22+'1b. Youreka Functional P&L'!J22 -> 736470.03 | K22: ='1a. Dispatch Functional P&L'!K22+'1b. Youreka Functional P&L'!K22 -> 751768.25 | L22: =IFERROR(J22-K22,"N/A") -> -15298.22 | M22: =IFERROR((J22/K22-1),"N/A") -> -0.020349649 | O22: ='1a. Dispatch Functional P&L'!O22+'1b. Youreka Functional P&L'!O22 -> 60407.04 | P22: ='1a. Dispatch Functional P&L'!P22+'1b. Youreka Functional P&L'!P22 -> 58677.8 | Q22: =O22-P22 -> 1729.24 | R22: =IFERROR((O22/P22-1),"N/A") -> 0.029470089
C23: Total Recurring Cost of Sales - Functional | E23: ='1a. Dispatch Functional P&L'!E23+'1b. Youreka Functional P&L'!E23 -> 352944.24 | F23: ='1a. Dispatch Functional P&L'!F23+'1b. Youreka Functional P&L'!F23 -> 352849.64 | G23: =IFERROR(E23-F23,"N/A") -> 94.601564 | H23: =IFERROR((E23/F23-1),"N/A") -> 0.0002681073 | J23: ='1a. Dispatch Functional P&L'!J23+'1b. Youreka Functional P&L'!J23 -> 4181834.9 | K23: ='1a. Dispatch Functional P&L'!K23+'1b. Youreka Functional P&L'!K23 -> 4215851.6 | L23: =IFERROR(J23-K23,"N/A") -> -34016.702 | M23: =IFERROR((J23/K23-1),"N/A") -> -0.0080687618 | O23: ='1a. Dispatch Functional P&L'!O23+'1b. Youreka Functional P&L'!O23 -> 352944.24 | P23: ='1a. Dispatch Functional P&L'!P23+'1b. Youreka Functional P&L'!P23 -> 336311.89 | Q23: =O23-P23 -> 16632.35 | R23: =IFERROR((O23/P23-1),"N/A") -> 0.049455135 | U23: =SUM(E20:E22)-E23 -> 0 | V23: =SUM(F20:F22)-F23 -> 0 | X23: =SUM(J20:J22)-J23 -> 0 | Y23: =SUM(K20:K22)-K23 -> 0 | AA23: =SUM(O20:O22)-O23 -> 0 | AB23: =SUM(P20:P22)-P23 -> 0
C24: Non-recurring Cost of Sales - Functional
C25: Cost of Sales (Functional) - Consultants & Contractors | E25: ='1a. Dispatch Functional P&L'!E25+'1b. Youreka Functional P&L'!E25 -> 10632.75 | F25: ='1a. Dispatch Functional P&L'!F25+'1b. Youreka Functional P&L'!F25 -> 0 | G25: =IFERROR(E25-F25,"N/A") -> 10632.75 | H25: =IFERROR((E25/F25-1),"N/A") -> N/A | J25: ='1a. Dispatch Functional P&L'!J25+'1b. Youreka Functional P&L'!J25 -> 51263.75 | K25: ='1a. Dispatch Functional P&L'!K25+'1b. Youreka Functional P&L'!K25 -> 0 | L25: =IFERROR(J25-K25,"N/A") -> 51263.75 | M25: =IFERROR((J25/K25-1),"N/A") -> N/A | O25: ='1a. Dispatch Functional P&L'!O25+'1b. Youreka Functional P&L'!O25 -> 10632.75 | P25: ='1a. Dispatch Functional P&L'!P25+'1b. Youreka Functional P&L'!P25 -> 0 | Q25: =O25-P25 -> 10632.75 | R25: =IFERROR((O25/P25-1),"N/A") -> N/A
C26: Cost of Sales (Functional) - Direct Compensation (NR) | E26: ='1a. Dispatch Functional P&L'!E26+'1b. Youreka Functional P&L'!E26 -> 100277.24 | F26: ='1a. Dispatch Functional P&L'!F26+'1b. Youreka Functional P&L'!F26 -> 97828.941 | G26: =IFERROR(E26-F26,"N/A") -> 2448.2991 | H26: =IFERROR((E26/F26-1),"N/A") -> 0.025026327 | J26: ='1a. Dispatch Functional P&L'!J26+'1b. Youreka Functional P&L'!J26 -> 1192046.8 | K26: ='1a. Dispatch Functional P&L'!K26+'1b. Youreka Functional P&L'!K26 -> 1162277.6 | L26: =IFERROR(J26-K26,"N/A") -> 29769.212 | M26: =IFERROR((J26/K26-1),"N/A") -> 0.025612825 | O26: ='1a. Dispatch Functional P&L'!O26+'1b. Youreka Functional P&L'!O26 -> 100277.24 | P26: ='1a. Dispatch Functional P&L'!P26+'1b. Youreka Functional P&L'!P26 -> 87017.13 | Q26: =O26-P26 -> 13260.11 | R26: =IFERROR((O26/P26-1),"N/A") -> 0.15238505
C27: Total Non-recurring Cost of Sales - Functional | E27: ='1a. Dispatch Functional P&L'!E27+'1b. Youreka Functional P&L'!E27 -> 110909.99 | F27: ='1a. Dispatch Functional P&L'!F27+'1b. Youreka Functional P&L'!F27 -> 97828.941 | G27: =IFERROR(E27-F27,"N/A") -> 13081.049 | H27: =IFERROR((E27/F27-1),"N/A") -> 0.13371349 | J27: ='1a. Dispatch Functional P&L'!J27+'1b. Youreka Functional P&L'!J27 -> 1243310.6 | K27: ='1a. Dispatch Functional P&L'!K27+'1b. Youreka Functional P&L'!K27 -> 1162277.6 | L27: =IFERROR(J27-K27,"N/A") -> 81032.962 | M27: =IFERROR((J27/K27-1),"N/A") -> 0.069719112 | O27: ='1a. Dispatch Functional P&L'!O27+'1b. Youreka Functional P&L'!O27 -> 110909.99 | P27: ='1a. Dispatch Functional P&L'!P27+'1b. Youreka Functional P&L'!P27 -> 87017.13 | Q27: =O27-P27 -> 23892.86 | R27: =IFERROR((O27/P27-1),"N/A") -> 0.27457651 | U27: =E27-E26-E25 -> 0 | V27: =F27-F26 -> 0 | X27: =J27-J26-J25 -> 0 | Y27: =K27-K26 -> 0 | AA27: =O27-O26-O25 -> 0 | AB27: =P27-P26 -> 0
C28: Total Cost of Sales - Functional | E28: ='1a. Dispatch Functional P&L'!E28+'1b. Youreka Functional P&L'!E28 -> 463854.23 | F28: ='1a. Dispatch Functional P&L'!F28+'1b. Youreka Functional P&L'!F28 -> 450678.58 | G28: =IFERROR(E28-F28,"N/A") -> 13175.651 | H28: =IFERROR((E28/F28-1),"N/A") -> 0.029235138 | J28: ='1a. Dispatch Functional P&L'!J28+'1b. Youreka Functional P&L'!J28 -> 5425145.5 | K28: ='1a. Dispatch Functional P&L'!K28+'1b. Youreka Functional P&L'!K28 -> 5378129.2 | L28: =IFERROR(J28-K28,"N/A") -> 47016.26 | M28: =IFERROR((J28/K28-1),"N/A") -> 0.0087421217 | O28: ='1a. Dispatch Functional P&L'!O28+'1b. Youreka Functional P&L'!O28 -> 463854.23 | P28: ='1a. Dispatch Functional P&L'!P28+'1b. Youreka Functional P&L'!P28 -> 423329.02 | Q28: =O28-P28 -> 40525.21 | R28: =IFERROR((O28/P28-1),"N/A") -> 0.095729818 | U28: =E28-E27-E23 -> 0 | V28: =F28-F27-F23 -> 0 | X28: =J28-J27-J23 -> 0 | Y28: =K28-K27-K23 -> 0 | AA28: =O28-O27-O23 -> 0 | AB28: =P28-P27-P23 -> 0
C29: Gross Profit - Functional
C30: Recurring Gross Profit - Functional | E30: ='1a. Dispatch Functional P&L'!E30+'1b. Youreka Functional P&L'!E30 -> 1761936.5 | F30: ='1a. Dispatch Functional P&L'!F30+'1b. Youreka Functional P&L'!F30 -> 1928356 | G30: =IFERROR(E30-F30,"N/A") -> -166419.58 | H30: =IFERROR((E30/F30-1),"N/A") -> -0.08630127 | J30: ='1a. Dispatch Functional P&L'!J30+'1b. Youreka Functional P&L'!J30 -> 20731738 | K30: ='1a. Dispatch Functional P&L'!K30+'1b. Youreka Functional P&L'!K30 -> 21493294 | L30: =IFERROR(J30-K30,"N/A") -> -761555.76 | M30: =IFERROR((J30/K30-1),"N/A") -> -0.035432249 | O30: ='1a. Dispatch Functional P&L'!O30+'1b. Youreka Functional P&L'!O30 -> 1761936.5 | P30: ='1a. Dispatch Functional P&L'!P30+'1b. Youreka Functional P&L'!P30 -> 1599400.9 | Q30: =O30-P30 -> 162535.6 | R30: =IFERROR((O30/P30-1),"N/A") -> 0.1016228
C31: Non-recurring Gross Profit - Functional | E31: ='1a. Dispatch Functional P&L'!E31+'1b. Youreka Functional P&L'!E31 -> -61909.99 | F31: ='1a. Dispatch Functional P&L'!F31+'1b. Youreka Functional P&L'!F31 -> -58578.941 | G31: =IFERROR(E31-F31,"N/A") -> -3331.0491 | H31: =IFERROR((E31/F31-1),"N/A") -> 0.056864276 | J31: ='1a. Dispatch Functional P&L'!J31+'1b. Youreka Functional P&L'!J31 -> -470790.61 | K31: ='1a. Dispatch Functional P&L'!K31+'1b. Youreka Functional P&L'!K31 -> -655860.94 | L31: =IFERROR(J31-K31,"N/A") -> 185070.33 | M31: =IFERROR((J31/K31-1),"N/A") -> -0.28217922 | O31: ='1a. Dispatch Functional P&L'!O31+'1b. Youreka Functional P&L'!O31 -> -61909.99 | P31: ='1a. Dispatch Functional P&L'!P31+'1b. Youreka Functional P&L'!P31 -> -17999.08 | Q31: =O31-P31 -> -43910.91 | R31: =IFERROR((O31/P31-1),"N/A") -> 2.4396197
C32: Total Gross Profit - Functional | E32: ='1a. Dispatch Functional P&L'!E32+'1b. Youreka Functional P&L'!E32 -> 1700026.5 | F32: ='1a. Dispatch Functional P&L'!F32+'1b. Youreka Functional P&L'!F32 -> 1869777.1 | G32: =IFERROR(E32-F32,"N/A") -> -169750.62 | H32: =IFERROR((E32/F32-1),"N/A") -> -0.090786556 | J32: ='1a. Dispatch Functional P&L'!J32+'1b. Youreka Functional P&L'!J32 -> 20260948 | K32: ='1a. Dispatch Functional P&L'!K32+'1b. Youreka Functional P&L'!K32 -> 20837433 | L32: =IFERROR(J32-K32,"N/A") -> -576485.43 | M32: =IFERROR((J32/K32-1),"N/A") -> -0.027665856 | O32: ='1a. Dispatch Functional P&L'!O32+'1b. Youreka Functional P&L'!O32 -> 1700026.5 | P32: ='1a. Dispatch Functional P&L'!P32+'1b. Youreka Functional P&L'!P32 -> 1581401.8 | Q32: =O32-P32 -> 118624.69 | R32: =IFERROR((O32/P32-1),"N/A") -> 0.075012366 | U32: =E16-E28-E32 -> 0 | V32: =F16-F28-F32 -> 0 | X32: =J16-J28-J32 -> 0 | Y32: =K16-K28-K32 -> 0 | AA32: =O16-O28-O32 -> 0 | AB32: =P16-P28-P32 -> 0
C33: Recurring Gross Profit Margin % - Functional | E33: =E30/E11 -> 0.83311388 | F33: =F30/F11 -> 0.84532318 | G33: =IFERROR(E33-F33,"N/A") -> -0.012209303 | J33: =J30/J11 -> 0.83214632 | K33: =K30/K11 -> 0.83601744 | L33: =IFERROR(J33-K33,"N/A") -> -0.003871115 | O33: =O30/O11 -> 0.83311388 | P33: =P30/P11 -> 0.8262594 | Q33: =O33-P33 -> 0.0068544748
C34: Non-recurring Gross Profit Margin % - Functional | E34: =E31/E15 -> -1.2634692 | F34: =F31/F15 -> -1.4924571 | G34: =IFERROR(E34-F34,"N/A") -> 0.22898791 | J34: =J31/J15 -> -0.60942194 | K34: =K31/K15 -> -1.2951014 | L34: =IFERROR(J34-K34,"N/A") -> 0.68567948 | O34: =O31/O15 -> -1.2634692 | P34: =P31/P15 -> -0.26078801 | Q34: =O34-P34 -> -1.0026812
C35: Total Gross Profit Margin % - Functional | E35: =E32/E16 -> 0.7856378 | F35: =F32/F16 -> 0.80578014 | G35: =IFERROR(E35-F35,"N/A") -> -0.02014234 | J35: =J32/J16 -> 0.78879056 | K35: =K32/K16 -> 0.79484975 | L35: =IFERROR(J35-K35,"N/A") -> -0.0060591929 | O35: =O32/O16 -> 0.7856378 | P35: =P32/P16 -> 0.78883498 | Q35: =O35-P35 -> -0.003197181 | U35: =E32/E16-E35 -> 0 | V35: =F32/F16-F35 -> 0 | X35: =J32/J16-J35 -> 0 | Y35: =K32/K16-K35 -> 0 | AA35: =O32/O16-O35 -> 0 | AB35: =P32/P16-P35 -> 0
C37: Functional Operating Expenses
C38: Product & Engineering Expense - Functional | E38: ='1a. Dispatch Functional P&L'!E38+'1b. Youreka Functional P&L'!E38 -> 442397.33 | F38: ='1a. Dispatch Functional P&L'!F38+'1b. Youreka Functional P&L'!F38 -> 584826.18 | G38: =IFERROR(E38-F38,"N/A") -> -142428.85 | H38: =IFERROR((E38/F38-1),"N/A") -> -0.24354048 | J38: ='1a. Dispatch Functional P&L'!J38+'1b. Youreka Functional P&L'!J38 -> 6306078.5 | K38: ='1a. Dispatch Functional P&L'!K38+'1b. Youreka Functional P&L'!K38 -> 7248588.7 | L38: =IFERROR(J38-K38,"N/A") -> -942510.15 | M38: =IFERROR((J38/K38-1),"N/A") -> -0.13002671 | O38: ='1a. Dispatch Functional P&L'!O38+'1b. Youreka Functional P&L'!O38 -> 442397.33 | P38: ='1a. Dispatch Functional P&L'!P38+'1b. Youreka Functional P&L'!P38 -> 599255.53 | Q38: =O38-P38 -> -156858.2 | R38: =IFERROR((O38/P38-1),"N/A") -> -0.26175511
C39: General & Administrative Expense - Functional | E39: ='1a. Dispatch Functional P&L'!E39+'1b. Youreka Functional P&L'!E39 -> 242107.56 | F39: ='1a. Dispatch Functional P&L'!F39+'1b. Youreka Functional P&L'!F39 -> 373135.83 | G39: =IFERROR(E39-F39,"N/A") -> -131028.27 | H39: =IFERROR((E39/F39-1),"N/A") -> -0.35115434 | J39: ='1a. Dispatch Functional P&L'!J39+'1b. Youreka Functional P&L'!J39 -> 4183787.8 | K39: ='1a. Dispatch Functional P&L'!K39+'1b. Youreka Functional P&L'!K39 -> 4608003 | L39: =IFERROR(J39-K39,"N/A") -> -424215.24 | M39: =IFERROR((J39/K39-1),"N/A") -> -0.092060538 | O39: ='1a. Dispatch Functional P&L'!O39+'1b. Youreka Functional P&L'!O39 -> 242107.56 | P39: ='1a. Dispatch Functional P&L'!P39+'1b. Youreka Functional P&L'!P39 -> 317762.27 | Q39: =O39-P39 -> -75654.71 | R39: =IFERROR((O39/P39-1),"N/A") -> -0.23808588
C40: Human Resources - Functional | E40: ='1a. Dispatch Functional P&L'!E40+'1b. Youreka Functional P&L'!E40 -> 6591.59 | F40: ='1a. Dispatch Functional P&L'!F40+'1b. Youreka Functional P&L'!F40 -> 11424.583 | G40: =IFERROR(E40-F40,"N/A") -> -4832.9933 | H40: =IFERROR((E40/F40-1),"N/A") -> -0.42303454 | J40: ='1a. Dispatch Functional P&L'!J40+'1b. Youreka Functional P&L'!J40 -> 82432.71 | K40: ='1a. Dispatch Functional P&L'!K40+'1b. Youreka Functional P&L'!K40 -> 116671 | L40: =IFERROR(J40-K40,"N/A") -> -34238.29 | M40: =IFERROR((J40/K40-1),"N/A") -> -0.29346016 | O40: ='1a. Dispatch Functional P&L'!O40+'1b. Youreka Functional P&L'!O40 -> 6591.59 | P40: ='1a. Dispatch Functional P&L'!P40+'1b. Youreka Functional P&L'!P40 -> 7263.65 | Q40: =O40-P40 -> -672.06 | R40: =IFERROR((O40/P40-1),"N/A") -> -0.092523731
C41: Sales Expense - Functional | E41: ='1a. Dispatch Functional P&L'!E41+'1b. Youreka Functional P&L'!E41 -> 346036.59 | F41: ='1a. Dispatch Functional P&L'!F41+'1b. Youreka Functional P&L'!F41 -> 446168.36 | G41: =IFERROR(E41-F41,"N/A") -> -100131.77 | H41: =IFERROR((E41/F41-1),"N/A") -> -0.22442598 | J41: ='1a. Dispatch Functional P&L'!J41+'1b. Youreka Functional P&L'!J41 -> 4626641.5 | K41: ='1a. Dispatch Functional P&L'!K41+'1b. Youreka Functional P&L'!K41 -> 5479382.1 | L41: =IFERROR(J41-K41,"N/A") -> -852740.65 | M41: =IFERROR((J41/K41-1),"N/A") -> -0.15562715 | O41: ='1a. Dispatch Functional P&L'!O41+'1b. Youreka Functional P&L'!O41 -> 346036.59 | P41: ='1a. Dispatch Functional P&L'!P41+'1b. Youreka Functional P&L'!P41 -> 429493.92 | Q41: =O41-P41 -> -83457.33 | R41: =IFERROR((O41/P41-1),"N/A") -> -0.19431551
C42: Marketing Expense - Functional | E42: ='1a. Dispatch Functional P&L'!E42+'1b. Youreka Functional P&L'!E42 -> 61113.21 | F42: ='1a. Dispatch Functional P&L'!F42+'1b. Youreka Functional P&L'!F42 -> 89240.191 | G42: =IFERROR(E42-F42,"N/A") -> -28126.981 | H42: =IFERROR((E42/F42-1),"N/A") -> -0.31518289 | J42: ='1a. Dispatch Functional P&L'!J42+'1b. Youreka Functional P&L'!J42 -> 1041226 | K42: ='1a. Dispatch Functional P&L'!K42+'1b. Youreka Functional P&L'!K42 -> 1245318.9 | L42: =IFERROR(J42-K42,"N/A") -> -204092.84 | M42: =IFERROR((J42/K42-1),"N/A") -> -0.16388802 | O42: ='1a. Dispatch Functional P&L'!O42+'1b. Youreka Functional P&L'!O42 -> 61113.21 | P42: ='1a. Dispatch Functional P&L'!P42+'1b. Youreka Functional P&L'!P42 -> 83294.76 | Q42: =O42-P42 -> -22181.55 | R42: =IFERROR((O42/P42-1),"N/A") -> -0.26630187
C43: Other Functional Operating Expense (incl. D&A) | E43: ='1a. Dispatch Functional P&L'!E43+'1b. Youreka Functional P&L'!E43 -> 1251110.2 | F43: ='1a. Dispatch Functional P&L'!F43+'1b. Youreka Functional P&L'!F43 -> 1241003.5 | G43: =IFERROR(E43-F43,"N/A") -> 10106.684 | H43: =IFERROR((E43/F43-1),"N/A") -> 0.0081439607 | J43: ='1a. Dispatch Functional P&L'!J43+'1b. Youreka Functional P&L'!J43 -> 14975224 | K43: ='1a. Dispatch Functional P&L'!K43+'1b. Youreka Functional P&L'!K43 -> 15092042 | L43: =IFERROR(J43-K43,"N/A") -> -116817.92 | M43: =IFERROR((J43/K43-1),"N/A") -> -0.0077403657 | O43: ='1a. Dispatch Functional P&L'!O43+'1b. Youreka Functional P&L'!O43 -> 1251110.2 | P43: ='1a. Dispatch Functional P&L'!P43+'1b. Youreka Functional P&L'!P43 -> 1304209.1 | Q43: =O43-P43 -> -53098.95 | R43: =IFERROR((O43/P43-1),"N/A") -> -0.040713524
C44: Total - Functional Operating Expenses | E44: ='1a. Dispatch Functional P&L'!E44+'1b. Youreka Functional P&L'!E44 -> 2349356.5 | F44: ='1a. Dispatch Functional P&L'!F44+'1b. Youreka Functional P&L'!F44 -> 2745798.7 | G44: =IFERROR(E44-F44,"N/A") -> -396442.18 | H44: =IFERROR((E44/F44-1),"N/A") -> -0.14438137 | J44: ='1a. Dispatch Functional P&L'!J44+'1b. Youreka Functional P&L'!J44 -> 31215391 | K44: ='1a. Dispatch Functional P&L'!K44+'1b. Youreka Functional P&L'!K44 -> 33790006 | L44: =IFERROR(J44-K44,"N/A") -> -2574615.1 | M44: =IFERROR((J44/K44-1),"N/A") -> -0.076194574 | O44: ='1a. Dispatch Functional P&L'!O44+'1b. Youreka Functional P&L'!O44 -> 2349356.5 | P44: ='1a. Dispatch Functional P&L'!P44+'1b. Youreka Functional P&L'!P44 -> 2741279.3 | Q44: =O44-P44 -> -391922.8 | R44: =IFERROR((O44/P44-1),"N/A") -> -0.14297077 | U44: =SUM(E38:E43)-E44 -> 0 | V44: =SUM(F38:F43)-F44 -> 0 | X44: =SUM(J38:J43)-J44 -> 0 | Y44: =SUM(K38:K43)-K44 -> 0 | AA44: =SUM(O38:O43)-O44 -> 0 | AB44: =SUM(P38:P43)-P44 -> 0
C45: w/o Depreciation, Amoritization, or Bad Debt | E45: ='1a. Dispatch Functional P&L'!E45+'1b. Youreka Functional P&L'!E45 -> 1098246.3 | F45: ='1a. Dispatch Functional P&L'!F45+'1b. Youreka Functional P&L'!F45 -> 1504795.1 | G45: =IFERROR(E45-F45,"N/A") -> -406548.86 | H45: =IFERROR((E45/F45-1),"N/A") -> -0.27016891 | J45: ='1a. Dispatch Functional P&L'!J45+'1b. Youreka Functional P&L'!J45 -> 16240167 | K45: ='1a. Dispatch Functional P&L'!K45+'1b. Youreka Functional P&L'!K45 -> 18897964 | L45: =IFERROR(J45-K45,"N/A") -> -2657797.2 | M45: =IFERROR((J45/K45-1),"N/A") -> -0.14063934 | O45: ='1a. Dispatch Functional P&L'!O45+'1b. Youreka Functional P&L'!O45 -> 1098246.3 | P45: ='1a. Dispatch Functional P&L'!P45+'1b. Youreka Functional P&L'!P45 -> 1437070.1 | Q45: =O45-P45 -> -338823.85 | R45: =IFERROR((O45/P45-1),"N/A") -> -0.23577405 | U45: =E44-SUM(E79:E81)-E45 -> -0.01097497 | V45: =F44-SUM(F79:F81)-F45 -> 0 | X45: =J44-SUM(J79:J81)-J45 -> -0.13169963 | Y45: =K44-SUM(K80:K81)-K45 -> 0 | AA45: =O44-SUM(O79:O81)-O45 -> -0.01097497 | AB45: =P44-SUM(P79:P81)-P45 -> -0.010974969
C47: Operating Margin | E47: ='1a. Dispatch Functional P&L'!E47+'1b. Youreka Functional P&L'!E47 -> -649329.99 | F47: ='1a. Dispatch Functional P&L'!F47+'1b. Youreka Functional P&L'!F47 -> -876021.55 | G47: =IFERROR(E47-F47,"N/A") -> 226691.56 | H47: =IFERROR((E47/F47-1),"N/A") -> -0.25877395 | J47: ='1a. Dispatch Functional P&L'!J47+'1b. Youreka Functional P&L'!J47 -> -10954443 | K47: ='1a. Dispatch Functional P&L'!K47+'1b. Youreka Functional P&L'!K47 -> -12952573 | L47: =IFERROR(J47-K47,"N/A") -> 1998129.7 | M47: =IFERROR((J47/K47-1),"N/A") -> -0.15426508 | O47: ='1a. Dispatch Functional P&L'!O47+'1b. Youreka Functional P&L'!O47 -> -649329.99 | P47: ='1a. Dispatch Functional P&L'!P47+'1b. Youreka Functional P&L'!P47 -> -1159877.5 | Q47: =O47-P47 -> 510547.49 | R47: =IFERROR((O47/P47-1),"N/A") -> -0.44017364 | U47: =E32-E44-E47 -> 0 | V47: =F32-F44-F47 -> 0 | X47: =J32-J44-J47 -> 0 | Y47: =K32-K44-K47 -> 0 | AA47: =O32-O44-O47 -> 0 | AB47: =P32-P44-P47 -> 0
C48: Operating Margin % | E48: =E47/E16 -> -0.30007661 | F48: =F47/F16 -> -0.37752134 | G48: =IFERROR(E48-F48,"N/A") -> 0.077444732 | J48: =J47/J16 -> -0.42647369 | K48: =K47/K16 -> -0.49407952 | L48: =IFERROR(J48-K48,"N/A") -> 0.067605835 | O48: =O47/O16 -> -0.30007661 | P48: =P47/P16 -> -0.57857019 | Q48: =O48-P48 -> 0.27849358 | U48: =E47/E16-E48 -> 0 | V48: =F47/F16-F48 -> 0 | X48: =J47/J16-J48 -> 0 | Y48: =K47/K16-K48 -> 0 | AA48: =O47/O16-O48 -> 0 | AB48: =P47/P16-P48 -> 0
C49: Operating Margin Check (F-N) | E49: =E47-'2a. Dispatch Natural P&L'!E58-'2b. Youreka Natural P&L'!E58 -> 0.01097497 | F49: =F47-'2a. Dispatch Natural P&L'!F58-'2b. Youreka Natural P&L'!F58 -> 0 | J49: =J47-'2a. Dispatch Natural P&L'!J58-'2b. Youreka Natural P&L'!J58 -> 0.13169964 | K49: =K47-'2a. Dispatch Natural P&L'!K58-'2b. Youreka Natural P&L'!K58 -> 0 | O49: =O47-'2a. Dispatch Natural P&L'!O58-'2b. Youreka Natural P&L'!O58 -> 0.01097497 | P49: =P47-'2a. Dispatch Natural P&L'!P58-'2b. Youreka Natural P&L'!P58 -> 0.010974969
C51: Non-Operating Expenses / (Income)
C52: Interest Expense | E52: ='1a. Dispatch Functional P&L'!E52+'1b. Youreka Functional P&L'!E52 -> 556137.34 | F52: ='1a. Dispatch Functional P&L'!F52+'1b. Youreka Functional P&L'!F52 -> 529320.93 | G52: =IFERROR(E52-F52,"N/A") -> 26816.411 | H52: =IFERROR((E52/F52-1),"N/A") -> 0.050661913 | J52: ='1a. Dispatch Functional P&L'!J52+'1b. Youreka Functional P&L'!J52 -> 6770607 | K52: ='1a. Dispatch Functional P&L'!K52+'1b. Youreka Functional P&L'!K52 -> 6033984.6 | L52: =IFERROR(J52-K52,"N/A") -> 736622.41 | M52: =IFERROR((J52/K52-1),"N/A") -> 0.12207893 | O52: ='1a. Dispatch Functional P&L'!O52+'1b. Youreka Functional P&L'!O52 -> 556137.34 | P52: ='1a. Dispatch Functional P&L'!P52+'1b. Youreka Functional P&L'!P52 -> 557496.68 | Q52: =O52-P52 -> -1359.34 | R52: =IFERROR((O52/P52-1),"N/A") -> -0.0024382925
C53: Interest Income | E53: ='1a. Dispatch Functional P&L'!E53+'1b. Youreka Functional P&L'!E53 -> 0 | F53: ='1a. Dispatch Functional P&L'!F53+'1b. Youreka Functional P&L'!F53 -> 0 | G53: =IFERROR(E53-F53,"N/A") -> 0 | H53: =IFERROR((E53/F53-1),"N/A") -> N/A | J53: ='1a. Dispatch Functional P&L'!J53+'1b. Youreka Functional P&L'!J53 -> 0 | K53: ='1a. Dispatch Functional P&L'!K53+'1b. Youreka Functional P&L'!K53 -> 0 | L53: =IFERROR(J53-K53,"N/A") -> 0 | M53: =IFERROR((J53/K53-1),"N/A") -> N/A | O53: ='1a. Dispatch Functional P&L'!O53+'1b. Youreka Functional P&L'!O53 -> 0 | P53: ='1a. Dispatch Functional P&L'!P53+'1b. Youreka Functional P&L'!P53 -> 0 | Q53: =O53-P53 -> 0 | R53: =IFERROR((O53/P53-1),"N/A") -> N/A
C54: Other Expense / (Income) | E54: ='1a. Dispatch Functional P&L'!E54+'1b. Youreka Functional P&L'!E54 -> 8363.91 | F54: ='1a. Dispatch Functional P&L'!F54+'1b. Youreka Functional P&L'!F54 -> 12729.167 | G54: =IFERROR(E54-F54,"N/A") -> -4365.2567 | H54: =IFERROR((E54/F54-1),"N/A") -> -0.34293342 | J54: ='1a. Dispatch Functional P&L'!J54+'1b. Youreka Functional P&L'!J54 -> -139480.41 | K54: ='1a. Dispatch Functional P&L'!K54+'1b. Youreka Functional P&L'!K54 -> 244375 | L54: =IFERROR(J54-K54,"N/A") -> -383855.41 | M54: =IFERROR((J54/K54-1),"N/A") -> -1.5707638 | O54: ='1a. Dispatch Functional P&L'!O54+'1b. Youreka Functional P&L'!O54 -> 8363.91 | P54: ='1a. Dispatch Functional P&L'!P54+'1b. Youreka Functional P&L'!P54 -> 2546.53 | Q54: =O54-P54 -> 5817.38 | R54: =IFERROR((O54/P54-1),"N/A") -> 2.2844341
C55: Stock-Based Compensation | E55: ='1a. Dispatch Functional P&L'!E55+'1b. Youreka Functional P&L'!E55 -> 0 | F55: ='1a. Dispatch Functional P&L'!F55+'1b. Youreka Functional P&L'!F55 -> 0 | G55: =IFERROR(E55-F55,"N/A") -> 0 | H55: =IFERROR((E55/F55-1),"N/A") -> N/A | J55: ='1a. Dispatch Functional P&L'!J55+'1b. Youreka Functional P&L'!J55 -> 0 | K55: ='1a. Dispatch Functional P&L'!K55+'1b. Youreka Functional P&L'!K55 -> 0 | L55: =IFERROR(J55-K55,"N/A") -> 0 | M55: =IFERROR((J55/K55-1),"N/A") -> N/A | O55: ='1a. Dispatch Functional P&L'!O55+'1b. Youreka Functional P&L'!O55 -> 0 | P55: ='1a. Dispatch Functional P&L'!P55+'1b. Youreka Functional P&L'!P55 -> 217081.7 | Q55: =O55-P55 -> -217081.7 | R55: =IFERROR((O55/P55-1),"N/A") -> -1
C56: Acquisition-Related Costs | E56: ='1a. Dispatch Functional P&L'!E56+'1b. Youreka Functional P&L'!E56 -> 0 | F56: ='1a. Dispatch Functional P&L'!F56+'1b. Youreka Functional P&L'!F56 -> 0 | G56: =IFERROR(E56-F56,"N/A") -> 0 | H56: =IFERROR((E56/F56-1),"N/A") -> N/A | J56: ='1a. Dispatch Functional P&L'!J56+'1b. Youreka Functional P&L'!J56 -> 4857 | K56: ='1a. Dispatch Functional P&L'!K56+'1b. Youreka Functional P&L'!K56 -> 0 | L56: =IFERROR(J56-K56,"N/A") -> 4857 | M56: =IFERROR((J56/K56-1),"N/A") -> N/A | O56: ='1a. Dispatch Functional P&L'!O56+'1b. Youreka Functional P&L'!O56 -> 0 | P56: ='1a. Dispatch Functional P&L'!P56+'1b. Youreka Functional P&L'!P56 -> 218532.97 | Q56: =O56-P56 -> -218532.97 | R56: =IFERROR((O56/P56-1),"N/A") -> -1
C57: Deferred Revenue - Purchase Accounting Haircut | E57: ='1a. Dispatch Functional P&L'!E57+'1b. Youreka Functional P&L'!E57 -> 0 | F57: ='1a. Dispatch Functional P&L'!F57+'1b. Youreka Functional P&L'!F57 -> 0 | G57: =IFERROR(E57-F57,"N/A") -> 0 | H57: =IFERROR((E57/F57-1),"N/A") -> N/A | J57: ='1a. Dispatch Functional P&L'!J57+'1b. Youreka Functional P&L'!J57 -> 0 | K57: ='1a. Dispatch Functional P&L'!K57+'1b. Youreka Functional P&L'!K57 -> 0 | L57: =IFERROR(J57-K57,"N/A") -> 0 | M57: =IFERROR((J57/K57-1),"N/A") -> N/A | O57: ='1a. Dispatch Functional P&L'!O57+'1b. Youreka Functional P&L'!O57 -> 0 | P57: ='1a. Dispatch Functional P&L'!P57+'1b. Youreka Functional P&L'!P57 -> 0 | Q57: =O57-P57 -> 0 | R57: =IFERROR((O57/P57-1),"N/A") -> N/A
C58: Restructuring Fees and Expenses / Severance | E58: ='1a. Dispatch Functional P&L'!E58+'1b. Youreka Functional P&L'!E58 -> 0 | F58: ='1a. Dispatch Functional P&L'!F58+'1b. Youreka Functional P&L'!F58 -> 0 | G58: =IFERROR(E58-F58,"N/A") -> 0 | H58: =IFERROR((E58/F58-1),"N/A") -> N/A | J58: ='1a. Dispatch Functional P&L'!J58+'1b. Youreka Functional P&L'!J58 -> 280586.49 | K58: ='1a. Dispatch Functional P&L'!K58+'1b. Youreka Functional P&L'!K58 -> 0 | L58: =IFERROR(J58-K58,"N/A") -> 280586.49 | M58: =IFERROR((J58/K58-1),"N/A") -> N/A | O58: ='1a. Dispatch Functional P&L'!O58+'1b. Youreka Functional P&L'!O58 -> 0 | P58: ='1a. Dispatch Functional P&L'!P58+'1b. Youreka Functional P&L'!P58 -> 0 | Q58: =O58-P58 -> 0 | R58: =IFERROR((O58/P58-1),"N/A") -> N/A
C59: VEP & VCG Expenses | E59: ='1a. Dispatch Functional P&L'!E59+'1b. Youreka Functional P&L'!E59 -> 5145.89 | F59: ='1a. Dispatch Functional P&L'!F59+'1b. Youreka Functional P&L'!F59 -> 29333.333 | G59: =IFERROR(E59-F59,"N/A") -> -24187.443 | H59: =IFERROR((E59/F59-1),"N/A") -> -0.82457193 | J59: ='1a. Dispatch Functional P&L'!J59+'1b. Youreka Functional P&L'!J59 -> 123836.42 | K59: ='1a. Dispatch Functional P&L'!K59+'1b. Youreka Functional P&L'!K59 -> 352000 | L59: =IFERROR(J59-K59,"N/A") -> -228163.58 | M59: =IFERROR((J59/K59-1),"N/A") -> -0.64819199 | O59: ='1a. Dispatch Functional P&L'!O59+'1b. Youreka Functional P&L'!O59 -> 5145.89 | P59: ='1a. Dispatch Functional P&L'!P59+'1b. Youreka Functional P&L'!P59 -> 4202.57 | Q59: =O59-P59 -> 943.32 | R59: =IFERROR((O59/P59-1),"N/A") -> 0.22446265
C60: Total - Non-Operating Expenses / (Income) | E60: ='1a. Dispatch Functional P&L'!E60+'1b. Youreka Functional P&L'!E60 -> 569647.14 | F60: ='1a. Dispatch Functional P&L'!F60+'1b. Youreka Functional P&L'!F60 -> 571383.43 | G60: =IFERROR(E60-F60,"N/A") -> -1736.2889 | H60: =IFERROR((E60/F60-1),"N/A") -> -0.0030387457 | J60: ='1a. Dispatch Functional P&L'!J60+'1b. Youreka Functional P&L'!J60 -> 7040406.5 | K60: ='1a. Dispatch Functional P&L'!K60+'1b. Youreka Functional P&L'!K60 -> 6630359.6 | L60: =IFERROR(J60-K60,"N/A") -> 410046.91 | M60: =IFERROR((J60/K60-1),"N/A") -> 0.061843842 | O60: ='1a. Dispatch Functional P&L'!O60+'1b. Youreka Functional P&L'!O60 -> 569647.14 | P60: ='1a. Dispatch Functional P&L'!P60+'1b. Youreka Functional P&L'!P60 -> 999860.45 | Q60: =O60-P60 -> -430213.31 | R60: =IFERROR((O60/P60-1),"N/A") -> -0.43027335 | U60: =SUM(E52:E59)-E60 -> 0 | V60: =SUM(F52:F59)-F60 -> 0 | X60: =SUM(J52:J59)-J60 -> 0 | Y60: =SUM(K52:K59)-K60 -> 0 | AA60: =SUM(O52:O59)-O60 -> 0 | AB60: =SUM(P52:P59)-P60 -> 0
C62: Pre-Tax Income | E62: ='1a. Dispatch Functional P&L'!E62+'1b. Youreka Functional P&L'!E62 -> -1218977.1 | F62: ='1a. Dispatch Functional P&L'!F62+'1b. Youreka Functional P&L'!F62 -> -1447405 | G62: =IFERROR(E62-F62,"N/A") -> 228427.84 | H62: =IFERROR((E62/F62-1),"N/A") -> -0.15781889 | J62: ='1a. Dispatch Functional P&L'!J62+'1b. Youreka Functional P&L'!J62 -> -17994849 | K62: ='1a. Dispatch Functional P&L'!K62+'1b. Youreka Functional P&L'!K62 -> -19582932 | L62: =IFERROR(J62-K62,"N/A") -> 1588082.8 | M62: =IFERROR((J62/K62-1),"N/A") -> -0.081095249 | O62: ='1a. Dispatch Functional P&L'!O62+'1b. Youreka Functional P&L'!O62 -> -1218977.1 | P62: ='1a. Dispatch Functional P&L'!P62+'1b. Youreka Functional P&L'!P62 -> -2159737.9 | Q62: =O62-P62 -> 940760.8 | R62: =IFERROR((O62/P62-1),"N/A") -> -0.43559026 | U62: =E47-E60-E62 -> 0 | V62: =F47-F60-F62 -> 0 | X62: =J47-J60-J62 -> 0 | Y62: =K47-K60-K62 -> 0 | AA62: =O47-O60-O62 -> 0 | AB62: =P47-P60-P62 -> 0
C63: Provision for Income Taxes | E63: ='1a. Dispatch Functional P&L'!E63+'1b. Youreka Functional P&L'!E63 -> 0 | F63: ='1a. Dispatch Functional P&L'!F63+'1b. Youreka Functional P&L'!F63 -> 0 | G63: =IFERROR(E63-F63,"N/A") -> 0 | H63: =IFERROR((E63/F63-1),"N/A") -> N/A | J63: ='1a. Dispatch Functional P&L'!J63+'1b. Youreka Functional P&L'!J63 -> 0 | K63: ='1a. Dispatch Functional P&L'!K63+'1b. Youreka Functional P&L'!K63 -> 0 | L63: =IFERROR(J63-K63,"N/A") -> 0 | M63: =IFERROR((J63/K63-1),"N/A") -> N/A | O63: ='1a. Dispatch Functional P&L'!O63+'1b. Youreka Functional P&L'!O63 -> 0 | P63: ='1a. Dispatch Functional P&L'!P63+'1b. Youreka Functional P&L'!P63 -> 0 | Q63: =O63-P63 -> 0 | R63: =IFERROR((O63/P63-1),"N/A") -> N/A
C64: Implied Tax Rate | E64: ='1a. Dispatch Functional P&L'!E64+'1b. Youreka Functional P&L'!E64 -> 0 | F64: ='1a. Dispatch Functional P&L'!F64+'1b. Youreka Functional P&L'!F64 -> 0 | G64: =IFERROR(E64-F64,"N/A") -> 0 | J64: ='1a. Dispatch Functional P&L'!J64+'1b. Youreka Functional P&L'!J64 -> 0 | K64: ='1a. Dispatch Functional P&L'!K64+'1b. Youreka Functional P&L'!K64 -> 0 | L64: =IFERROR(J64-K64,"N/A") -> 0 | O64: ='1a. Dispatch Functional P&L'!O64+'1b. Youreka Functional P&L'!O64 -> 0 | P64: ='1a. Dispatch Functional P&L'!P64+'1b. Youreka Functional P&L'!P64 -> 0 | Q64: =O64-P64 -> 0
F65: {=INDEX('Dispatch Monthly Func P&L'!$AI64:$AT64,MATCH(EOMONTH(Inputs!$C$2,0),'Dispatch Monthly Func P&L'!$AI$5:$AT$5,0))} -> 0
C66: Net Income | E66: ='1a. Dispatch Functional P&L'!E66+'1b. Youreka Functional P&L'!E66 -> -1218977.1 | F66: ='1a. Dispatch Functional P&L'!F66+'1b. Youreka Functional P&L'!F66 -> -1447405 | G66: =IFERROR(E66-F66,"N/A") -> 228427.84 | H66: =IFERROR((E66/F66-1),"N/A") -> -0.15781889 | J66: ='1a. Dispatch Functional P&L'!J66+'1b. Youreka Functional P&L'!J66 -> -17994849 | K66: ='1a. Dispatch Functional P&L'!K66+'1b. Youreka Functional P&L'!K66 -> -19582932 | L66: =IFERROR(J66-K66,"N/A") -> 1588082.8 | M66: =IFERROR((J66/K66-1),"N/A") -> -0.081095249 | O66: ='1a. Dispatch Functional P&L'!O66+'1b. Youreka Functional P&L'!O66 -> -1218977.1 | P66: ='1a. Dispatch Functional P&L'!P66+'1b. Youreka Functional P&L'!P66 -> -2159737.9 | Q66: =O66-P66 -> 940760.8 | R66: =IFERROR((O66/P66-1),"N/A") -> -0.43559026 | U66: =E62-E63-E66 -> 0 | V66: =F62-F63-F66 -> 0 | X66: =J62-J63-J66 -> 0 | Y66: =K62-K63-K66 -> 0 | AA66: =O62-O63-O66 -> 0 | AB66: =P62-P63-P66 -> 0
C67: Net Income (% of Revenue) | E67: =E66/E16 -> -0.56332917 | F67: =F66/F16 -> -0.62375894 | G67: =IFERROR(E67-F67,"N/A") -> 0.060429766 | J67: =J66/J16 -> -0.70056778 | K67: =K66/K16 -> -0.74699645 | L67: =IFERROR(J67-K67,"N/A") -> 0.046428671 | O67: =O66/O16 -> -0.56332917 | P67: =P66/P16 -> -1.0773207 | Q67: =O67-P67 -> 0.51399149 | U67: =E66/E16-E67 -> 0 | V67: =F66/F16-F67 -> 0 | X67: =J66/J16-J67 -> 0 | Y67: =K66/K16-K67 -> 0 | AA67: =O66/O16-O67 -> 0 | AB67: =P66/P16-P67 -> 0
C69: EBITDA Addbacks
C70: Interest Expense | E70: ='1a. Dispatch Functional P&L'!E70+'1b. Youreka Functional P&L'!E70 -> 556137.34 | F70: ='1a. Dispatch Functional P&L'!F70+'1b. Youreka Functional P&L'!F70 -> 529320.93 | G70: =IFERROR(E70-F70,"N/A") -> 26816.411 | H70: =IFERROR((E70/F70-1),"N/A") -> 0.050661913 | J70: ='1a. Dispatch Functional P&L'!J70+'1b. Youreka Functional P&L'!J70 -> 6770607 | K70: ='1a. Dispatch Functional P&L'!K70+'1b. Youreka Functional P&L'!K70 -> 6033984.6 | L70: =IFERROR(J70-K70,"N/A") -> 736622.41 | M70: =IFERROR((J70/K70-1),"N/A") -> 0.12207893 | O70: ='1a. Dispatch Functional P&L'!O70+'1b. Youreka Functional P&L'!O70 -> 556137.34 | P70: ='1a. Dispatch Functional P&L'!P70+'1b. Youreka Functional P&L'!P70 -> 557496.68 | Q70: =O70-P70 -> -1359.34 | R70: =IFERROR((O70/P70-1),"N/A") -> -0.0024382925
C71: Interest Income | E71: ='1a. Dispatch Functional P&L'!E71+'1b. Youreka Functional P&L'!E71 -> 0 | F71: ='1a. Dispatch Functional P&L'!F71+'1b. Youreka Functional P&L'!F71 -> 0 | G71: =IFERROR(E71-F71,"N/A") -> 0 | H71: =IFERROR((E71/F71-1),"N/A") -> N/A | J71: ='1a. Dispatch Functional P&L'!J71+'1b. Youreka Functional P&L'!J71 -> 0 | K71: ='1a. Dispatch Functional P&L'!K71+'1b. Youreka Functional P&L'!K71 -> 0 | L71: =IFERROR(J71-K71,"N/A") -> 0 | M71: =IFERROR((J71/K71-1),"N/A") -> N/A | O71: ='1a. Dispatch Functional P&L'!O71+'1b. Youreka Functional P&L'!O71 -> 0 | P71: ='1a. Dispatch Functional P&L'!P71+'1b. Youreka Functional P&L'!P71 -> 0 | Q71: =O71-P71 -> 0 | R71: =IFERROR((O71/P71-1),"N/A") -> N/A
C72: Other Expense / Income | E72: ='1a. Dispatch Functional P&L'!E72+'1b. Youreka Functional P&L'!E72 -> 8363.91 | F72: ='1a. Dispatch Functional P&L'!F72+'1b. Youreka Functional P&L'!F72 -> 12729.167 | G72: =IFERROR(E72-F72,"N/A") -> -4365.2567 | H72: =IFERROR((E72/F72-1),"N/A") -> -0.34293342 | J72: ='1a. Dispatch Functional P&L'!J72+'1b. Youreka Functional P&L'!J72 -> -139480.41 | K72: ='1a. Dispatch Functional P&L'!K72+'1b. Youreka Functional P&L'!K72 -> 244375 | L72: =IFERROR(J72-K72,"N/A") -> -383855.41 | M72: =IFERROR((J72/K72-1),"N/A") -> -1.5707638 | O72: ='1a. Dispatch Functional P&L'!O72+'1b. Youreka Functional P&L'!O72 -> 8363.91 | P72: ='1a. Dispatch Functional P&L'!P72+'1b. Youreka Functional P&L'!P72 -> 2546.53 | Q72: =O72-P72 -> 5817.38 | R72: =IFERROR((O72/P72-1),"N/A") -> 2.2844341
C73: Stock-Based Compensation | E73: ='1a. Dispatch Functional P&L'!E73+'1b. Youreka Functional P&L'!E73 -> 0 | F73: ='1a. Dispatch Functional P&L'!F73+'1b. Youreka Functional P&L'!F73 -> 0 | G73: =IFERROR(E73-F73,"N/A") -> 0 | H73: =IFERROR((E73/F73-1),"N/A") -> N/A | J73: ='1a. Dispatch Functional P&L'!J73+'1b. Youreka Functional P&L'!J73 -> 0 | K73: ='1a. Dispatch Functional P&L'!K73+'1b. Youreka Functional P&L'!K73 -> 0 | L73: =IFERROR(J73-K73,"N/A") -> 0 | M73: =IFERROR((J73/K73-1),"N/A") -> N/A | O73: ='1a. Dispatch Functional P&L'!O73+'1b. Youreka Functional P&L'!O73 -> 0 | P73: ='1a. Dispatch Functional P&L'!P73+'1b. Youreka Functional P&L'!P73 -> 217081.7 | Q73: =O73-P73 -> -217081.7 | R73: =IFERROR((O73/P73-1),"N/A") -> -1
C74: Acquisition-Related Costs | E74: ='1a. Dispatch Functional P&L'!E74+'1b. Youreka Functional P&L'!E74 -> 0 | F74: ='1a. Dispatch Functional P&L'!F74+'1b. Youreka Functional P&L'!F74 -> 0 | G74: =IFERROR(E74-F74,"N/A") -> 0 | H74: =IFERROR((E74/F74-1),"N/A") -> N/A | J74: ='1a. Dispatch Functional P&L'!J74+'1b. Youreka Functional P&L'!J74 -> 4857 | K74: ='1a. Dispatch Functional P&L'!K74+'1b. Youreka Functional P&L'!K74 -> 0 | L74: =IFERROR(J74-K74,"N/A") -> 4857 | M74: =IFERROR((J74/K74-1),"N/A") -> N/A | O74: ='1a. Dispatch Functional P&L'!O74+'1b. Youreka Functional P&L'!O74 -> 0 | P74: ='1a. Dispatch Functional P&L'!P74+'1b. Youreka Functional P&L'!P74 -> 218532.97 | Q74: =O74-P74 -> -218532.97 | R74: =IFERROR((O74/P74-1),"N/A") -> -1
C75: Deferred Revenue - Purchase Accounting Haircut | E75: ='1a. Dispatch Functional P&L'!E75+'1b. Youreka Functional P&L'!E75 -> 0 | F75: ='1a. Dispatch Functional P&L'!F75+'1b. Youreka Functional P&L'!F75 -> 0 | G75: =IFERROR(E75-F75,"N/A") -> 0 | H75: =IFERROR((E75/F75-1),"N/A") -> N/A | J75: ='1a. Dispatch Functional P&L'!J75+'1b. Youreka Functional P&L'!J75 -> 0 | K75: ='1a. Dispatch Functional P&L'!K75+'1b. Youreka Functional P&L'!K75 -> 0 | L75: =IFERROR(J75-K75,"N/A") -> 0 | M75: =IFERROR((J75/K75-1),"N/A") -> N/A | O75: ='1a. Dispatch Functional P&L'!O75+'1b. Youreka Functional P&L'!O75 -> 0 | P75: ='1a. Dispatch Functional P&L'!P75+'1b. Youreka Functional P&L'!P75 -> 0 | Q75: =O75-P75 -> 0 | R75: =IFERROR((O75/P75-1),"N/A") -> N/A
C76: Restructuring Fees and Expenses / Severance | E76: ='1a. Dispatch Functional P&L'!E76+'1b. Youreka Functional P&L'!E76 -> 0 | F76: ='1a. Dispatch Functional P&L'!F76+'1b. Youreka Functional P&L'!F76 -> 0 | G76: =IFERROR(E76-F76,"N/A") -> 0 | H76: =IFERROR((E76/F76-1),"N/A") -> N/A | J76: ='1a. Dispatch Functional P&L'!J76+'1b. Youreka Functional P&L'!J76 -> 280586.49 | K76: ='1a. Dispatch Functional P&L'!K76+'1b. Youreka Functional P&L'!K76 -> 0 | L76: =IFERROR(J76-K76,"N/A") -> 280586.49 | M76: =IFERROR((J76/K76-1),"N/A") -> N/A | O76: ='1a. Dispatch Functional P&L'!O76+'1b. Youreka Functional P&L'!O76 -> 0 | P76: ='1a. Dispatch Functional P&L'!P76+'1b. Youreka Functional P&L'!P76 -> 0 | Q76: =O76-P76 -> 0 | R76: =IFERROR((O76/P76-1),"N/A") -> N/A
C77: VEP & VCG Expenses | E77: ='1a. Dispatch Functional P&L'!E77+'1b. Youreka Functional P&L'!E77 -> 5145.89 | F77: ='1a. Dispatch Functional P&L'!F77+'1b. Youreka Functional P&L'!F77 -> 29333.333 | G77: =IFERROR(E77-F77,"N/A") -> -24187.443 | H77: =IFERROR((E77/F77-1),"N/A") -> -0.82457193 | J77: ='1a. Dispatch Functional P&L'!J77+'1b. Youreka Functional P&L'!J77 -> 123836.42 | K77: ='1a. Dispatch Functional P&L'!K77+'1b. Youreka Functional P&L'!K77 -> 352000 | L77: =IFERROR(J77-K77,"N/A") -> -228163.58 | M77: =IFERROR((J77/K77-1),"N/A") -> -0.64819199 | O77: ='1a. Dispatch Functional P&L'!O77+'1b. Youreka Functional P&L'!O77 -> 5145.89 | P77: ='1a. Dispatch Functional P&L'!P77+'1b. Youreka Functional P&L'!P77 -> 4202.57 | Q77: =O77-P77 -> 943.32 | R77: =IFERROR((O77/P77-1),"N/A") -> 0.22446265
C78: Provision for Income Taxes | E78: ='1a. Dispatch Functional P&L'!E78+'1b. Youreka Functional P&L'!E78 -> 0 | F78: ='1a. Dispatch Functional P&L'!F78+'1b. Youreka Functional P&L'!F78 -> 0 | G78: =IFERROR(E78-F78,"N/A") -> 0 | H78: =IFERROR((E78/F78-1),"N/A") -> N/A | J78: ='1a. Dispatch Functional P&L'!J78+'1b. Youreka Functional P&L'!J78 -> 0 | K78: ='1a. Dispatch Functional P&L'!K78+'1b. Youreka Functional P&L'!K78 -> 0 | L78: =IFERROR(J78-K78,"N/A") -> 0 | M78: =IFERROR((J78/K78-1),"N/A") -> N/A | O78: ='1a. Dispatch Functional P&L'!O78+'1b. Youreka Functional P&L'!O78 -> 0 | P78: ='1a. Dispatch Functional P&L'!P78+'1b. Youreka Functional P&L'!P78 -> 0 | Q78: =O78-P78 -> 0 | R78: =IFERROR((O78/P78-1),"N/A") -> N/A
C79: Bad Debt Expense | E79: ='1a. Dispatch Functional P&L'!E79+'1b. Youreka Functional P&L'!E79 -> 9000 | F79: ='1a. Dispatch Functional P&L'!F79+'1b. Youreka Functional P&L'!F79 -> 0 | G79: =IFERROR(E79-F79,"N/A") -> 9000 | H79: =IFERROR((E79/F79-1),"N/A") -> N/A | J79: ='1a. Dispatch Functional P&L'!J79+'1b. Youreka Functional P&L'!J79 -> 74466.59 | K79: ='1a. Dispatch Functional P&L'!K79+'1b. Youreka Functional P&L'!K79 -> 200000 | L79: =IFERROR(J79-K79,"N/A") -> -125533.41 | M79: =IFERROR((J79/K79-1),"N/A") -> -0.62766705 | O79: ='1a. Dispatch Functional P&L'!O79+'1b. Youreka Functional P&L'!O79 -> 9000 | P79: ='1a. Dispatch Functional P&L'!P79+'1b. Youreka Functional P&L'!P79 -> 63277.83 | Q79: =O79-P79 -> -54277.83 | R79: =IFERROR((O79/P79-1),"N/A") -> -0.85777009
C80: Depreciation | E80: ='1a. Dispatch Functional P&L'!E80+'1b. Youreka Functional P&L'!E80 -> 2227.11 | F80: ='1a. Dispatch Functional P&L'!F80+'1b. Youreka Functional P&L'!F80 -> 1120.3488 | G80: =IFERROR(E80-F80,"N/A") -> 1106.7612 | H80: =IFERROR((E80/F80-1),"N/A") -> 0.98787208 | J80: ='1a. Dispatch Functional P&L'!J80+'1b. Youreka Functional P&L'!J80 -> 22160.6 | K80: ='1a. Dispatch Functional P&L'!K80+'1b. Youreka Functional P&L'!K80 -> 13444.185 | L80: =IFERROR(J80-K80,"N/A") -> 8716.415 | M80: =IFERROR((J80/K80-1),"N/A") -> 0.6483409 | O80: ='1a. Dispatch Functional P&L'!O80+'1b. Youreka Functional P&L'!O80 -> 2227.11 | P80: ='1a. Dispatch Functional P&L'!P80+'1b. Youreka Functional P&L'!P80 -> 1048.23 | Q80: =O80-P80 -> 1178.88 | R80: =IFERROR((O80/P80-1),"N/A") -> 1.1246387
C81: Amortization | E81: ='1a. Dispatch Functional P&L'!E81+'1b. Youreka Functional P&L'!E81 -> 1239883.1 | F81: ='1a. Dispatch Functional P&L'!F81+'1b. Youreka Functional P&L'!F81 -> 1239883.2 | G81: =IFERROR(E81-F81,"N/A") -> -0.0665 | H81: =IFERROR((E81/F81-1),"N/A") -> -5.3634086e-08 | J81: ='1a. Dispatch Functional P&L'!J81+'1b. Youreka Functional P&L'!J81 -> 14878597 | K81: ='1a. Dispatch Functional P&L'!K81+'1b. Youreka Functional P&L'!K81 -> 14878598 | L81: =IFERROR(J81-K81,"N/A") -> -0.798 | M81: =IFERROR((J81/K81-1),"N/A") -> -5.3634086e-08 | O81: ='1a. Dispatch Functional P&L'!O81+'1b. Youreka Functional P&L'!O81 -> 1239883.1 | P81: ='1a. Dispatch Functional P&L'!P81+'1b. Youreka Functional P&L'!P81 -> 1239883.1 | Q81: =O81-P81 -> 0 | R81: =IFERROR((O81/P81-1),"N/A") -> 0
C82: Total - EBITDA Addbacks | E82: ='1a. Dispatch Functional P&L'!E82+'1b. Youreka Functional P&L'!E82 -> 1820757.3 | F82: ='1a. Dispatch Functional P&L'!F82+'1b. Youreka Functional P&L'!F82 -> 1812386.9 | G82: =IFERROR(E82-F82,"N/A") -> 8370.4058 | H82: =IFERROR((E82/F82-1),"N/A") -> 0.004618443 | J82: ='1a. Dispatch Functional P&L'!J82+'1b. Youreka Functional P&L'!J82 -> 22015631 | K82: ='1a. Dispatch Functional P&L'!K82+'1b. Youreka Functional P&L'!K82 -> 21722402 | L82: =IFERROR(J82-K82,"N/A") -> 293229.12 | M82: =IFERROR((J82/K82-1),"N/A") -> 0.013498927 | O82: ='1a. Dispatch Functional P&L'!O82+'1b. Youreka Functional P&L'!O82 -> 1820757.3 | P82: ='1a. Dispatch Functional P&L'!P82+'1b. Youreka Functional P&L'!P82 -> 2304069.6 | Q82: =O82-P82 -> -483312.26 | R82: =IFERROR((O82/P82-1),"N/A") -> -0.20976461 | U82: =SUM(E70:E81)-E82 -> 0 | V82: =SUM(F70:F81)-F82 -> 0 | X82: =SUM(J70:J81)-J82 -> 0 | Y82: =SUM(K70:K81)-K82 -> 0 | AA82: =SUM(O70:O81)-O82 -> 0 | AB82: =SUM(P70:P81)-P82 -> 0
F83: {=INDEX('Dispatch Monthly Func P&L'!$AI82:$AT82,MATCH(EOMONTH(Inputs!$C$2,0),'Dispatch Monthly Func P&L'!$AI$5:$AT$5,0))} -> 0
C84: EBITDA | E84: ='1a. Dispatch Functional P&L'!E84+'1b. Youreka Functional P&L'!E84 -> 601780.21 | F84: ='1a. Dispatch Functional P&L'!F84+'1b. Youreka Functional P&L'!F84 -> 364981.96 | G84: =IFERROR(E84-F84,"N/A") -> 236798.25 | H84: =IFERROR((E84/F84-1),"N/A") -> 0.64879439 | J84: ='1a. Dispatch Functional P&L'!J84+'1b. Youreka Functional P&L'!J84 -> 4020781.4 | K84: ='1a. Dispatch Functional P&L'!K84+'1b. Youreka Functional P&L'!K84 -> 2139469.5 | L84: =IFERROR(J84-K84,"N/A") -> 1881311.9 | M84: =IFERROR((J84/K84-1),"N/A") -> 0.87933566 | O84: ='1a. Dispatch Functional P&L'!O84+'1b. Youreka Functional P&L'!O84 -> 601780.21 | P84: ='1a. Dispatch Functional P&L'!P84+'1b. Youreka Functional P&L'!P84 -> 144331.67 | Q84: =O84-P84 -> 457448.54 | R84: =IFERROR((O84/P84-1),"N/A") -> 3.1694259 | U84: =E66+E82-E84 -> 0 | V84: =F66+F82-F84 -> 0 | X84: =J66+J82-J84 -> 0 | Y84: =K66+K82-K84 -> -4.6566129e-09 | AA84: =O66+O82-O84 -> 0 | AB84: =P66+P82-P84 -> 2.3283064e-10
C85: EBITDA Margin % | E85: =E84/E16 -> 0.2781023 | F85: =F84/F16 -> 0.15728892 | G85: =IFERROR(E85-F85,"N/A") -> 0.12081339 | J85: =J84/J16 -> 0.15653534 | K85: =K84/K16 -> 0.081610668 | L85: =IFERROR(J85-K85,"N/A") -> 0.074924676 | O85: =O84/O16 -> 0.2781023 | P85: =P84/P16 -> 0.071995537 | U85: =E84/E16-E85 -> 0 | V85: =F84/F16-F85 -> 0 | X85: =J84/J16-J85 -> 0 | Y85: =K84/K16-K85 -> 0 | AA85: =O84/O16-O85 -> 0 | AB85: =P84/P16-P85 -> 0
C86: EBITDA Check (F-N) | E86: =E84-'2a. Dispatch Natural P&L'!E94-'2b. Youreka Natural P&L'!E94 -> 0.01097497 | F86: =F84-'2a. Dispatch Natural P&L'!F94-'2b. Youreka Natural P&L'!F94 -> 0 | J86: =J84-'2a. Dispatch Natural P&L'!J94-'2b. Youreka Natural P&L'!J94 -> 0.13169964 | K86: =K84-'2a. Dispatch Natural P&L'!K94-'2b. Youreka Natural P&L'!K94 -> 0 | O86: =O84-'2a. Dispatch Natural P&L'!O94-'2b. Youreka Natural P&L'!O94 -> 0.01097497 | P86: =P84-'2a. Dispatch Natural P&L'!P94-'2b. Youreka Natural P&L'!P94 -> 0.01097497
C88: Capitalized Software Costs | E88: ='1a. Dispatch Functional P&L'!E88+'1b. Youreka Functional P&L'!E88 -> 0 | F88: ='1a. Dispatch Functional P&L'!F88+'1b. Youreka Functional P&L'!F88 -> 0 | G88: =IFERROR(E88-F88,"N/A") -> 0 | H88: =IFERROR((E88/F88-1),"N/A") -> N/A | J88: ='1a. Dispatch Functional P&L'!J88+'1b. Youreka Functional P&L'!J88 -> 0 | K88: ='1a. Dispatch Functional P&L'!K88+'1b. Youreka Functional P&L'!K88 -> 0 | L88: =IFERROR(J88-K88,"N/A") -> 0 | M88: =IFERROR((J88/K88-1),"N/A") -> N/A | O88: ='1a. Dispatch Functional P&L'!O88+'1b. Youreka Functional P&L'!O88 -> 0 | P88: ='1a. Dispatch Functional P&L'!P88+'1b. Youreka Functional P&L'!P88 -> 0 | Q88: =O88-P88 -> 0 | R88: =IFERROR((O88/P88-1),"N/A") -> N/A
C90: EBITDAC | E90: ='1a. Dispatch Functional P&L'!E90+'1b. Youreka Functional P&L'!E90 -> 601780.21 | F90: ='1a. Dispatch Functional P&L'!F90+'1b. Youreka Functional P&L'!F90 -> 364981.96 | G90: =IFERROR(E90-F90,"N/A") -> 236798.25 | H90: =IFERROR((E90/F90-1),"N/A") -> 0.64879439 | J90: ='1a. Dispatch Functional P&L'!J90+'1b. Youreka Functional P&L'!J90 -> 4020781.4 | K90: ='1a. Dispatch Functional P&L'!K90+'1b. Youreka Functional P&L'!K90 -> 2139469.5 | L90: =IFERROR(J90-K90,"N/A") -> 1881311.9 | M90: =IFERROR((J90/K90-1),"N/A") -> 0.87933566 | O90: ='1a. Dispatch Functional P&L'!O90+'1b. Youreka Functional P&L'!O90 -> 601780.21 | P90: ='1a. Dispatch Functional P&L'!P90+'1b. Youreka Functional P&L'!P90 -> 144331.67 | Q90: =O90-P90 -> 457448.54 | R90: =IFERROR((O90/P90-1),"N/A") -> 3.1694259 | U90: =E84-E88-E90 -> 0 | V90: =F84-F88-F90 -> 0 | X90: =J84-J88-J90 -> 0 | Y90: =K84-K88-K90 -> 0 | AA90: =O84-O88-O90 -> 0 | AB90: =P84-P88-P90 -> 0
C91: EBITDAC Margin % | E91: =E90/E16 -> 0.2781023 | F91: =F90/F16 -> 0.15728892 | G91: =IFERROR(E91-F91,"N/A") -> 0.12081339 | J91: =J90/J16 -> 0.15653534 | K91: =K90/K16 -> 0.081610668 | L91: =IFERROR(J91-K91,"N/A") -> 0.074924676 | O91: =O90/O16 -> 0.2781023 | P91: =P90/P16 -> 0.071995537 | Q91: =O91-P91 -> 0.20610677 | U91: =E90/E16-E91 -> 0 | V91: =F90/F16-F91 -> 0 | X91: =J90/J16-J91 -> 0 | Y91: =K90/K16-K91 -> 0 | AA91: =O90/O16-O91 -> 0 | AB91: =P90/P16-P91 -> 0
C93: Compensation by Function
C94: COS Compensation | E94: ='1a. Dispatch Functional P&L'!E94+'1b. Youreka Functional P&L'!E94 -> 233494.63 | F94: ='1a. Dispatch Functional P&L'!F94+'1b. Youreka Functional P&L'!F94 -> 221428.05 | G94: =IFERROR(E94-F94,"N/A") -> 12066.584 | H94: =IFERROR((E94/F94-1),"N/A") -> 0.054494378 | J94: ='1a. Dispatch Functional P&L'!J94+'1b. Youreka Functional P&L'!J94 -> 2767617.2 | K94: ='1a. Dispatch Functional P&L'!K94+'1b. Youreka Functional P&L'!K94 -> 2667552.9 | L94: =IFERROR(J94-K94,"N/A") -> 100064.29 | M94: =IFERROR((J94/K94-1),"N/A") -> 0.037511642 | O94: ='1a. Dispatch Functional P&L'!O94+'1b. Youreka Functional P&L'!O94 -> 233494.63 | P94: ='1a. Dispatch Functional P&L'!P94+'1b. Youreka Functional P&L'!P94 -> 218773.62 | Q94: =O94-P94 -> 14721.01 | R94: =IFERROR((O94/P94-1),"N/A") -> 0.06728878
C95: Product & Engineering Compensation | E95: ='1a. Dispatch Functional P&L'!E95+'1b. Youreka Functional P&L'!E95 -> 418737.45 | F95: ='1a. Dispatch Functional P&L'!F95+'1b. Youreka Functional P&L'!F95 -> 565387.5 | G95: =IFERROR(E95-F95,"N/A") -> -146650.05 | H95: =IFERROR((E95/F95-1),"N/A") -> -0.25937972 | J95: ='1a. Dispatch Functional P&L'!J95+'1b. Youreka Functional P&L'!J95 -> 6037977.2 | K95: ='1a. Dispatch Functional P&L'!K95+'1b. Youreka Functional P&L'!K95 -> 7013148.1 | L95: =IFERROR(J95-K95,"N/A") -> -975170.89 | M95: =IFERROR((J95/K95-1),"N/A") -> -0.13904895 | O95: ='1a. Dispatch Functional P&L'!O95+'1b. Youreka Functional P&L'!O95 -> 418737.45 | P95: ='1a. Dispatch Functional P&L'!P95+'1b. Youreka Functional P&L'!P95 -> 579536.03 | Q95: =O95-P95 -> -160798.58 | R95: =IFERROR((O95/P95-1),"N/A") -> -0.27746089
C96: General & Administrative Compensation | E96: ='1a. Dispatch Functional P&L'!E96+'1b. Youreka Functional P&L'!E96 -> 168302 | F96: ='1a. Dispatch Functional P&L'!F96+'1b. Youreka Functional P&L'!F96 -> 201759.63 | G96: =IFERROR(E96-F96,"N/A") -> -33457.632 | H96: =IFERROR((E96/F96-1),"N/A") -> -0.16582917 | J96: ='1a. Dispatch Functional P&L'!J96+'1b. Youreka Functional P&L'!J96 -> 2212060.7 | K96: ='1a. Dispatch Functional P&L'!K96+'1b. Youreka Functional P&L'!K96 -> 2430199.5 | L96: =IFERROR(J96-K96,"N/A") -> -218138.77 | M96: =IFERROR((J96/K96-1),"N/A") -> -0.089761671 | O96: ='1a. Dispatch Functional P&L'!O96+'1b. Youreka Functional P&L'!O96 -> 168302 | P96: ='1a. Dispatch Functional P&L'!P96+'1b. Youreka Functional P&L'!P96 -> 188022.19 | Q96: =O96-P96 -> -19720.19 | R96: =IFERROR((O96/P96-1),"N/A") -> -0.10488225
C97: Sales Compensation | E97: ='1a. Dispatch Functional P&L'!E97+'1b. Youreka Functional P&L'!E97 -> 323375.29 | F97: ='1a. Dispatch Functional P&L'!F97+'1b. Youreka Functional P&L'!F97 -> 421604.68 | G97: =IFERROR(E97-F97,"N/A") -> -98229.389 | H97: =IFERROR((E97/F97-1),"N/A") -> -0.23298932 | J97: ='1a. Dispatch Functional P&L'!J97+'1b. Youreka Functional P&L'!J97 -> 4353929.4 | K97: ='1a. Dispatch Functional P&L'!K97+'1b. Youreka Functional P&L'!K97 -> 5181789.7 | L97: =IFERROR(J97-K97,"N/A") -> -827860.33 | M97: =IFERROR((J97/K97-1),"N/A") -> -0.1597634 | O97: ='1a. Dispatch Functional P&L'!O97+'1b. Youreka Functional P&L'!O97 -> 323375.29 | P97: ='1a. Dispatch Functional P&L'!P97+'1b. Youreka Functional P&L'!P97 -> 406207.73 | Q97: =O97-P97 -> -82832.44 | R97: =IFERROR((O97/P97-1),"N/A") -> -0.20391645
C98: Marketing Compensation | E98: ='1a. Dispatch Functional P&L'!E98+'1b. Youreka Functional P&L'!E98 -> 46322.67 | F98: ='1a. Dispatch Functional P&L'!F98+'1b. Youreka Functional P&L'!F98 -> 56090.191 | G98: =IFERROR(E98-F98,"N/A") -> -9767.5208 | H98: =IFERROR((E98/F98-1),"N/A") -> -0.17413955 | J98: ='1a. Dispatch Functional P&L'!J98+'1b. Youreka Functional P&L'!J98 -> 699812.46 | K98: ='1a. Dispatch Functional P&L'!K98+'1b. Youreka Functional P&L'!K98 -> 706468.86 | L98: =IFERROR(J98-K98,"N/A") -> -6656.4044 | M98: =IFERROR((J98/K98-1),"N/A") -> -0.0094220775 | O98: ='1a. Dispatch Functional P&L'!O98+'1b. Youreka Functional P&L'!O98 -> 46322.67 | P98: ='1a. Dispatch Functional P&L'!P98+'1b. Youreka Functional P&L'!P98 -> 64248.56 | Q98: =O98-P98 -> -17925.89 | R98: =IFERROR((O98/P98-1),"N/A") -> -0.27900843
C99: Payroll Fees | E99: ='1a. Dispatch Functional P&L'!E99+'1b. Youreka Functional P&L'!E99 -> 4142.49 | F99: ='1a. Dispatch Functional P&L'!F99+'1b. Youreka Functional P&L'!F99 -> 4095 | G99: =IFERROR(E99-F99,"N/A") -> 47.49 | H99: =IFERROR((E99/F99-1),"N/A") -> 0.01159707 | J99: ='1a. Dispatch Functional P&L'!J99+'1b. Youreka Functional P&L'!J99 -> 51081.67 | K99: ='1a. Dispatch Functional P&L'!K99+'1b. Youreka Functional P&L'!K99 -> 50580 | L99: =IFERROR(J99-K99,"N/A") -> 501.67 | M99: =IFERROR((J99/K99-1),"N/A") -> 0.0099183472 | O99: ='1a. Dispatch Functional P&L'!O99+'1b. Youreka Functional P&L'!O99 -> 4142.49 | P99: ='1a. Dispatch Functional P&L'!P99+'1b. Youreka Functional P&L'!P99 -> 4167.8 | Q99: =O99-P99 -> -25.31 | R99: =IFERROR((O99/P99-1),"N/A") -> -0.0060727482
C100: Total - Compensation | E100: ='1a. Dispatch Functional P&L'!E100+'1b. Youreka Functional P&L'!E100 -> 1194374.5 | F100: ='1a. Dispatch Functional P&L'!F100+'1b. Youreka Functional P&L'!F100 -> 1470365 | G100: =IFERROR(E100-F100,"N/A") -> -275990.52 | H100: =IFERROR((E100/F100-1),"N/A") -> -0.18770204 | J100: ='1a. Dispatch Functional P&L'!J100+'1b. Youreka Functional P&L'!J100 -> 16122479 | K100: ='1a. Dispatch Functional P&L'!K100+'1b. Youreka Functional P&L'!K100 -> 18049739 | L100: =IFERROR(J100-K100,"N/A") -> -1927260.4 | M100: =IFERROR((J100/K100-1),"N/A") -> -0.10677498 | O100: ='1a. Dispatch Functional P&L'!O100+'1b. Youreka Functional P&L'!O100 -> 1194374.5 | P100: ='1a. Dispatch Functional P&L'!P100+'1b. Youreka Functional P&L'!P100 -> 1460955.9 | Q100: =O100-P100 -> -266581.4 | R100: =IFERROR((O100/P100-1),"N/A") -> -0.18247053 | U100: =SUM(E94:E99)-E100 -> 0 | V100: =SUM(F94:F99)-F100 -> 0 | X100: =SUM(J94:J99)-J100 -> 0 | Y100: =SUM(K94:K99)-K100 -> 0 | AA100: =SUM(O94:O99)-O100 -> 0 | AB100: =SUM(P94:P99)-P100 -> 0
E103: =E100-'Dispatch Monthly Func P&L'!$Q99-'Youreka Monthly Func P&L'!$Q99 -> 0 | J103: =J100-'Dispatch Monthly Func P&L'!$X99-'Youreka Monthly Func P&L'!$X99 -> 0 | P103: =P100-'Dispatch Monthly Func P&L'!$BM99-'Youreka Monthly Func P&L'!$BM99 -> 0

Sheet 1a. Dispatch Functional P&L
C1: Dispatch | Monthly Profit & Loss (Functional View)
E4: Current Month | J4: Year-to-Date | O4: Year-over-Year
U5: Current Month | X5: YTD | AA5: YoY
C6: Revenue | E6: =Inputs!C2 -> 46022 | F6: Budget | G6: Difference | H6: % Difference | J6: =E6 -> 46022 | K6: Budget | L6: Difference | M6: % Difference | O6: =J6 -> 46022 | P6: =EOMONTH(E6,-12) -> 45657 | Q6: Difference | R6: % Difference | U6: Checks | X6: Checks | AA6: Checks
C7: Recurring Revenue
C8: Recurring Enterprise License Revenue | E8: ='Dispatch Monthly Func P&L'!Q7 -> 1025372.2 | F8: =INDEX('Dispatch Monthly Func P&L'!$AI7:$AT7,MATCH(EOMONTH(Inputs!$C$2,0),'Dispatch Monthly Func P&L'!$AI$5:$AT$5,0)) -> 1092551.6 | G8: =IFERROR(E8-F8,"N/A") -> -67179.451 | H8: =IFERROR((E8/F8-1),"N/A") -> -0.061488582 | J8: ='Dispatch Monthly Func P&L'!X7 -> 12038585 | K8: ='Dispatch Monthly Func P&L'!AV7 -> 12122794 | L8: =IFERROR(J8-K8,"N/A") -> -84208.692 | M8: =IFERROR((J8/K8-1),"N/A") -> -0.0069463105 | O8: =E8 -> 1025372.2 | P8: ='Dispatch Monthly Func P&L'!$BM7 -> 978384.06 | Q8: =O8-P8 -> 46988.12 | R8: =IFERROR((O8/P8-1),"N/A") -> 0.048026253
C9: Recurring Services Revenue | E9: ='Dispatch Monthly Func P&L'!Q8 -> 0 | F9: =INDEX('Dispatch Monthly Func P&L'!$AI8:$AT8,MATCH(EOMONTH(Inputs!$C$2,0),'Dispatch Monthly Func P&L'!$AI$5:$AT$5,0)) -> 0 | G9: =IFERROR(E9-F9,"N/A") -> 0 | H9: =IFERROR((E9/F9-1),"N/A") -> N/A | J9: ='Dispatch Monthly Func P&L'!X8 -> 0 | K9: ='Dispatch Monthly Func P&L'!AV8 -> 0 | L9: =IFERROR(J9-K9,"N/A") -> 0 | M9: =IFERROR((J9/K9-1),"N/A") -> N/A | O9: =E9 -> 0 | P9: ='Dispatch Monthly Func P&L'!$BM8 -> 416.65 | Q9: =O9-P9 -> -416.65 | R9: =IFERROR((O9/P9-1),"N/A") -> -1
C10: Recurring Service Provider (SMB) Revenue | E10: ='Dispatch Monthly Func P&L'!Q9 -> 95643.67 | F10: =INDEX('Dispatch Monthly Func P&L'!$AI9:$AT9,MATCH(EOMONTH(Inputs!$C$2,0),'Dispatch Monthly Func P&L'!$AI$5:$AT$5,0)) -> 107993.31 | G10: =IFERROR(E10-F10,"N/A") -> -12349.642 | H10: =IFERROR((E10/F10-1),"N/A") -> -0.11435562 | J10: ='Dispatch Monthly Func P&L'!X9 -> 1158666.8 | K10: ='Dispatch Monthly Func P&L'!AV9 -> 1217243.8 | L10: =IFERROR(J10-K10,"N/A") -> -58577.008 | M10: =IFERROR((J10/K10-1),"N/A") -> -0.048122658 | O10: =E10 -> 95643.67 | P10: ='Dispatch Monthly Func P&L'!$BM9 -> 91808.3 | Q10: =O10-P10 -> 3835.37 | R10: =IFERROR((O10/P10-1),"N/A") -> 0.041775853
C11: Total Recurring Revenue | E11: ='Dispatch Monthly Func P&L'!Q10 -> 1121015.8 | F11: =INDEX('Dispatch Monthly Func P&L'!$AI10:$AT10,MATCH(EOMONTH(Inputs!$C$2,0),'Dispatch Monthly Func P&L'!$AI$5:$AT$5,0)) -> 1200544.9 | G11: =IFERROR(E11-F11,"N/A") -> -79529.093 | H11: =IFERROR((E11/F11-1),"N/A") -> -0.066244161 | J11: ='Dispatch Monthly Func P&L'!X10 -> 13197252 | K11: ='Dispatch Monthly Func P&L'!AV10 -> 13340038 | L11: =IFERROR(J11-K11,"N/A") -> -142785.7 | M11: =IFERROR((J11/K11-1),"N/A") -> -0.010703545 | O11: =E11 -> 1121015.8 | P11: ='Dispatch Monthly Func P&L'!$BM10 -> 1070609 | Q11: =O11-P11 -> 50406.84 | R11: =IFERROR((O11/P11-1),"N/A") -> 0.047082398 | U11: =SUM(E8:E10)-E11 -> 0 | V11: =SUM(F8:F10)-F11 -> 0 | X11: =SUM(J8:J10)-J11 -> 0 | Y11: =SUM(K8:K10)-K11 -> 0 | AA11: =SUM(O8:O10)-O11 -> 0 | AB11: =SUM(P8:P10)-P11 -> 0
C12: Non-Recurring Revenue
C13: Non-Recurring Professional Services Revenue | E13: ='Dispatch Monthly Func P&L'!Q12 -> 26500 | F13: =INDEX('Dispatch Monthly Func P&L'!$AI12:$AT12,MATCH(EOMONTH(Inputs!$C$2,0),'Dispatch Monthly Func P&L'!$AI$5:$AT$5,0)) -> 28666.667 | G13: =IFERROR(E13-F13,"N/A") -> -2166.6667 | H13: =IFERROR((E13/F13-1),"N/A") -> -0.075581395 | J13: ='Dispatch Monthly Func P&L'!X12 -> 480250 | K13: ='Dispatch Monthly Func P&L'!AV12 -> 250041.67 | L13: =IFERROR(J13-K13,"N/A") -> 230208.33 | M13: =IFERROR((J13/K13-1),"N/A") -> 0.92067989 | O13: =E13 -> 26500 | P13: ='Dispatch Monthly Func P&L'!$BM12 -> 31999 | Q13: =O13-P13 -> -5499 | R13: =IFERROR((O13/P13-1),"N/A") -> -0.17184912
C14: Other Non-Recurring Revenue | E14: ='Dispatch Monthly Func P&L'!Q13 -> 0 | F14: =INDEX('Dispatch Monthly Func P&L'!$AI13:$AT13,MATCH(EOMONTH(Inputs!$C$2,0),'Dispatch Monthly Func P&L'!$AI$5:$AT$5,0)) -> 0 | G14: =IFERROR(E14-F14,"N/A") -> 0 | H14: =IFERROR((E14/F14-1),"N/A") -> N/A | J14: ='Dispatch Monthly Func P&L'!X13 -> 0 | K14: ='Dispatch Monthly Func P&L'!AV13 -> 0 | L14: =IFERROR(J14-K14,"N/A") -> 0 | M14: =IFERROR((J14/K14-1),"N/A") -> N/A | O14: =E14 -> 0 | P14: ='Dispatch Monthly Func P&L'!$BM13 -> 0 | Q14: =O14-P14 -> 0 | R14: =IFERROR((O14/P14-1),"N/A") -> N/A
C15: Total Non-Recurring Revenue | E15: ='Dispatch Monthly Func P&L'!Q14 -> 26500 | F15: =INDEX('Dispatch Monthly Func P&L'!$AI14:$AT14,MATCH(EOMONTH(Inputs!$C$2,0),'Dispatch Monthly Func P&L'!$AI$5:$AT$5,0)) -> 28666.667 | G15: =IFERROR(E15-F15,"N/A") -> -2166.6667 | H15: =IFERROR((E15/F15-1),"N/A") -> -0.075581395 | J15: ='Dispatch Monthly Func P&L'!X14 -> 480250 | K15: ='Dispatch Monthly Func P&L'!AV14 -> 250041.67 | L15: =IFERROR(J15-K15,"N/A") -> 230208.33 | M15: =IFERROR((J15/K15-1),"N/A") -> 0.92067989 | O15: =E15 -> 26500 | P15: ='Dispatch Monthly Func P&L'!$BM14 -> 31999 | Q15: =O15-P15 -> -5499 | R15: =IFERROR((O15/P15-1),"N/A") -> -0.17184912 | U15: =SUM(E13:E14)-E15 -> 0 | V15: =SUM(F13:F14)-F15 -> 0 | X15: =SUM(J13:J14)-J15 -> 0 | Y15: =SUM(K13:K14)-K15 -> 0 | AA15: =SUM(O13:O14)-O15 -> 0 | AB15: =SUM(P13:P14)-P15 -> 0
C16: Total Revenue | E16: ='Dispatch Monthly Func P&L'!Q15 -> 1147515.8 | F16: =INDEX('Dispatch Monthly Func P&L'!$AI15:$AT15,MATCH(EOMONTH(Inputs!$C$2,0),'Dispatch Monthly Func P&L'!$AI$5:$AT$5,0)) -> 1229211.6 | G16: =IFERROR(E16-F16,"N/A") -> -81695.759 | H16: =IFERROR((E16/F16-1),"N/A") -> -0.066461917 | J16: ='Dispatch Monthly Func P&L'!X15 -> 13677502 | K16: ='Dispatch Monthly Func P&L'!AV15 -> 13590080 | L16: =IFERROR(J16-K16,"N/A") -> 87422.634 | M16: =IFERROR((J16/K16-1),"N/A") -> 0.0064328272 | O16: =E16 -> 1147515.8 | P16: ='Dispatch Monthly Func P&L'!$BM15 -> 1102608 | Q16: =O16-P16 -> 44907.84 | R16: =IFERROR((O16/P16-1),"N/A") -> 0.040728745 | U16: =E11+E15-E16 -> 0 | V16: =F11+F15-F16 -> 0 | X16: =J11+J15-J16 -> 0 | Y16: =K11+K15-K16 -> 0 | AA16: =O11+O15-O16 -> 0 | AB16: =P11+P15-P16 -> 0
C17: % Reccurring Revenue | E17: ='Dispatch Monthly Func P&L'!Q16 -> 0.97690664 | F17: =INDEX('Dispatch Monthly Func P&L'!$AI16:$AT16,MATCH(EOMONTH(Inputs!$C$2,0),'Dispatch Monthly Func P&L'!$AI$5:$AT$5,0)) -> 0.97667882 | G17: =IFERROR(E17-F17,"N/A") -> 0.00022781825 | J17: ='Dispatch Monthly Func P&L'!X16 -> 0.96488759 | K17: ='Dispatch Monthly Func P&L'!AV16 -> 0.98160116 | L17: =IFERROR(J17-K17,"N/A") -> -0.016713568 | O17: =E17 -> 0.97690664 | P17: ='Dispatch Monthly Func P&L'!$BM16 -> 0.97097881 | Q17: =O17-P17 -> 0.0059278302 | U17: =E11/E16-E17 -> 0 | V17: =F11/F16-F17 -> 0 | X17: =J11/J16-J17 -> 0 | Y17: =K11/K16-K17 -> 0 | AA17: =O11/O16-O17 -> 0 | AB17: =P11/P16-P17 -> 0
C19: Recurring Cost of Sales - Functional
C20: Cost of Sales (Functional) - Direct Compensation (R) | E20: ='Dispatch Monthly Func P&L'!Q19 -> 71518.56 | F20: =INDEX('Dispatch Monthly Func P&L'!$AI19:$AT19,MATCH(EOMONTH(Inputs!$C$2,0),'Dispatch Monthly Func P&L'!$AI$5:$AT$5,0)) -> 60391.046 | G20: =IFERROR(E20-F20,"N/A") -> 11127.514 | H20: =IFERROR((E20/F20-1),"N/A") -> 0.18425769 | J20: ='Dispatch Monthly Func P&L'!X19 -> 818939.73 | K20: ='Dispatch Monthly Func P&L'!AV19 -> 749729.86 | L20: =IFERROR(J20-K20,"N/A") -> 69209.87 | M20: =IFERROR((J20/K20-1),"N/A") -> 0.092313077 | O20: =E20 -> 71518.56 | P20: ='Dispatch Monthly Func P&L'!$BM19 -> 71244.07 | Q20: =O20-P20 -> 274.49 | R20: =IFERROR((O20/P20-1),"N/A") -> 0.0038528119
C21: Cost of Sales (Functional) - Hosting & Infrastructure | E21: ='Dispatch Monthly Func P&L'!Q20 -> 30965.26 | F21: =INDEX('Dispatch Monthly Func P&L'!$AI20:$AT20,MATCH(EOMONTH(Inputs!$C$2,0),'Dispatch Monthly Func P&L'!$AI$5:$AT$5,0)) -> 30367 | G21: =IFERROR(E21-F21,"N/A") -> 598.26 | H21: =IFERROR((E21/F21-1),"N/A") -> 0.019700991 | J21: ='Dispatch Monthly Func P&L'!X20 -> 384144.89 | K21: ='Dispatch Monthly Func P&L'!AV20 -> 383084 | L21: =IFERROR(J21-K21,"N/A") -> 1060.89 | M21: =IFERROR((J21/K21-1),"N/A") -> 0.0027693404 | O21: =E21 -> 30965.26 | P21: ='Dispatch Monthly Func P&L'!$BM20 -> 26023.77 | Q21: =O21-P21 -> 4941.49 | R21: =IFERROR((O21/P21-1),"N/A") -> 0.18988371
C22: Cost of Sales (Functional) - Software & Subscriptions | E22: ='Dispatch Monthly Func P&L'!Q21 -> 48760.04 | F22: =INDEX('Dispatch Monthly Func P&L'!$AI21:$AT21,MATCH(EOMONTH(Inputs!$C$2,0),'Dispatch Monthly Func P&L'!$AI$5:$AT$5,0)) -> 46922.188 | G22: =IFERROR(E22-F22,"N/A") -> 1837.8525 | H22: =IFERROR((E22/F22-1),"N/A") -> 0.039168091 | J22: ='Dispatch Monthly Func P&L'!X21 -> 584922.5 | K22: ='Dispatch Monthly Func P&L'!AV21 -> 593302.25 | L22: =IFERROR(J22-K22,"N/A") -> -8379.75 | M22: =IFERROR((J22/K22-1),"N/A") -> -0.014123914 | O22: =E22 -> 48760.04 | P22: ='Dispatch Monthly Func P&L'!$BM21 -> 45472.75 | Q22: =O22-P22 -> 3287.29 | R22: =IFERROR((O22/P22-1),"N/A") -> 0.072291427
C23: Total Recurring Cost of Sales - Functional | E23: ='Dispatch Monthly Func P&L'!Q22 -> 151243.86 | F23: =INDEX('Dispatch Monthly Func P&L'!$AI22:$AT22,MATCH(EOMONTH(Inputs!$C$2,0),'Dispatch Monthly Func P&L'!$AI$5:$AT$5,0)) -> 137680.23 | G23: =IFERROR(E23-F23,"N/A") -> 13563.627 | H23: =IFERROR((E23/F23-1),"N/A") -> 0.098515427 | J23: ='Dispatch Monthly Func P&L'!X22 -> 1788007.1 | K23: ='Dispatch Monthly Func P&L'!AV22 -> 1726116.1 | L23: =IFERROR(J23-K23,"N/A") -> 61891.01 | M23: =IFERROR((J23/K23-1),"N/A") -> 0.035855647 | O23: =E23 -> 151243.86 | P23: ='Dispatch Monthly Func P&L'!$BM22 -> 142740.59 | Q23: =O23-P23 -> 8503.27 | R23: =IFERROR((O23/P23-1),"N/A") -> 0.059571493 | U23: =SUM(E20:E22)-E23 -> 0 | V23: =SUM(F20:F22)-F23 -> 0 | X23: =SUM(J20:J22)-J23 -> 0 | Y23: =SUM(K20:K22)-K23 -> 0 | AA23: =SUM(O20:O22)-O23 -> 0 | AB23: =SUM(P20:P22)-P23 -> 0
C24: Non-recurring Cost of Sales - Functional
C25: Cost of Sales (Functional) - Consultants & Contractors | E25: ='Dispatch Monthly Func P&L'!Q24 -> 0 | F25: =INDEX('Dispatch Monthly Func P&L'!$AI24:$AT24,MATCH(EOMONTH(Inputs!$C$2,0),'Dispatch Monthly Func P&L'!$AI$5:$AT$5,0)) -> 0 | G25: =IFERROR(E25-F25,"N/A") -> 0 | H25: =IFERROR((E25/F25-1),"N/A") -> N/A | J25: ='Dispatch Monthly Func P&L'!X24 -> 0 | K25: ='Dispatch Monthly Func P&L'!AV24 -> 0 | L25: =IFERROR(J25-K25,"N/A") -> 0 | M25: =IFERROR((J25/K25-1),"N/A") -> N/A | O25: =E25 -> 0 | P25: ='Dispatch Monthly Func P&L'!$BM24 -> 0 | Q25: =O25-P25 -> 0 | R25: =IFERROR((O25/P25-1),"N/A") -> N/A
C26: Cost of Sales (Functional) - Direct Compensation (NR) | E26: ='Dispatch Monthly Func P&L'!Q25 -> 59374.45 | F26: =INDEX('Dispatch Monthly Func P&L'!$AI25:$AT25,MATCH(EOMONTH(Inputs!$C$2,0),'Dispatch Monthly Func P&L'!$AI$5:$AT$5,0)) -> 56655.856 | G26: =IFERROR(E26-F26,"N/A") -> 2718.594 | H26: =IFERROR((E26/F26-1),"N/A") -> 0.047984342 | J26: ='Dispatch Monthly Func P&L'!X25 -> 694660.55 | K26: ='Dispatch Monthly Func P&L'!AV25 -> 673118.5 | L26: =IFERROR(J26-K26,"N/A") -> 21542.046 | M26: =IFERROR((J26/K26-1),"N/A") -> 0.032003349 | O26: =E26 -> 59374.45 | P26: ='Dispatch Monthly Func P&L'!$BM25 -> 48071.8 | Q26: =O26-P26 -> 11302.65 | R26: =IFERROR((O26/P26-1),"N/A") -> 0.23512017
C27: Total Non-recurring Cost of Sales - Functional | E27: ='Dispatch Monthly Func P&L'!Q26 -> 59374.45 | F27: =INDEX('Dispatch Monthly Func P&L'!$AI26:$AT26,MATCH(EOMONTH(Inputs!$C$2,0),'Dispatch Monthly Func P&L'!$AI$5:$AT$5,0)) -> 56655.856 | G27: =IFERROR(E27-F27,"N/A") -> 2718.594 | H27: =IFERROR((E27/F27-1),"N/A") -> 0.047984342 | J27: ='Dispatch Monthly Func P&L'!X26 -> 694660.55 | K27: ='Dispatch Monthly Func P&L'!AV26 -> 673118.5 | L27: =IFERROR(J27-K27,"N/A") -> 21542.046 | M27: =IFERROR((J27/K27-1),"N/A") -> 0.032003349 | O27: =E27 -> 59374.45 | P27: ='Dispatch Monthly Func P&L'!$BM26 -> 48071.8 | Q27: =O27-P27 -> 11302.65 | R27: =IFERROR((O27/P27-1),"N/A") -> 0.23512017 | U27: =E27-E26 -> 0 | V27: =F27-F26 -> 0 | X27: =J27-J26 -> 0 | Y27: =K27-K26 -> 0 | AA27: =O27-O26 -> 0 | AB27: =P27-P26 -> 0
C28: Total Cost of Sales - Functional | E28: ='Dispatch Monthly Func P&L'!Q27 -> 210618.31 | F28: =INDEX('Dispatch Monthly Func P&L'!$AI27:$AT27,MATCH(EOMONTH(Inputs!$C$2,0),'Dispatch Monthly Func P&L'!$AI$5:$AT$5,0)) -> 194336.09 | G28: =IFERROR(E28-F28,"N/A") -> 16282.221 | H28: =IFERROR((E28/F28-1),"N/A") -> 0.083783825 | J28: ='Dispatch Monthly Func P&L'!X27 -> 2482667.7 | K28: ='Dispatch Monthly Func P&L'!AV27 -> 2399234.6 | L28: =IFERROR(J28-K28,"N/A") -> 83433.057 | M28: =IFERROR((J28/K28-1),"N/A") -> 0.034774864 | O28: =E28 -> 210618.31 | P28: ='Dispatch Monthly Func P&L'!$BM27 -> 190812.39 | Q28: =O28-P28 -> 19805.92 | R28: =IFERROR((O28/P28-1),"N/A") -> 0.10379787 | U28: =E28-E27-E23 -> 0 | V28: =F28-F27-F23 -> 0 | X28: =J28-J27-J23 -> 0 | Y28: =K28-K27-K23 -> 0 | AA28: =O28-O27-O23 -> 0 | AB28: =P28-P27-P23 -> 0
C29: Gross Profit - Functional
C30: Recurring Gross Profit - Functional | E30: ='Dispatch Monthly Func P&L'!Q29 -> 969771.99 | F30: =INDEX('Dispatch Monthly Func P&L'!$AI29:$AT29,MATCH(EOMONTH(Inputs!$C$2,0),'Dispatch Monthly Func P&L'!$AI$5:$AT$5,0)) -> 1062864.7 | G30: =IFERROR(E30-F30,"N/A") -> -93092.72 | H30: =IFERROR((E30/F30-1),"N/A") -> -0.087586613 | J30: ='Dispatch Monthly Func P&L'!X29 -> 11409245 | K30: ='Dispatch Monthly Func P&L'!AV29 -> 11613922 | L30: =IFERROR(J30-K30,"N/A") -> -204676.71 | M30: =IFERROR((J30/K30-1),"N/A") -> -0.017623393 | O30: =E30 -> 969771.99 | P30: ='Dispatch Monthly Func P&L'!$BM29 -> 927868.42 | Q30: =O30-P30 -> 41903.57 | R30: =IFERROR((O30/P30-1),"N/A") -> 0.045161112
C31: Non-recurring Gross Profit - Functional | E31: ='Dispatch Monthly Func P&L'!Q30 -> -32874.45 | F31: =INDEX('Dispatch Monthly Func P&L'!$AI30:$AT30,MATCH(EOMONTH(Inputs!$C$2,0),'Dispatch Monthly Func P&L'!$AI$5:$AT$5,0)) -> -27989.189 | G31: =IFERROR(E31-F31,"N/A") -> -4885.2606 | H31: =IFERROR((E31/F31-1),"N/A") -> 0.17454098 | J31: ='Dispatch Monthly Func P&L'!X30 -> -214410.55 | K31: ='Dispatch Monthly Func P&L'!AV30 -> -423076.84 | L31: =IFERROR(J31-K31,"N/A") -> 208666.29 | M31: =IFERROR((J31/K31-1),"N/A") -> -0.49321132 | O31: =E31 -> -32874.45 | P31: ='Dispatch Monthly Func P&L'!$BM30 -> -16072.8 | Q31: =O31-P31 -> -16801.65 | R31: =IFERROR((O31/P31-1),"N/A") -> 1.0453468
C32: Total Gross Profit - Functional | E32: ='Dispatch Monthly Func P&L'!Q31 -> 936897.54 | F32: =INDEX('Dispatch Monthly Func P&L'!$AI31:$AT31,MATCH(EOMONTH(Inputs!$C$2,0),'Dispatch Monthly Func P&L'!$AI$5:$AT$5,0)) -> 1034875.5 | G32: =IFERROR(E32-F32,"N/A") -> -97977.98 | H32: =IFERROR((E32/F32-1),"N/A") -> -0.094676102 | J32: ='Dispatch Monthly Func P&L'!X31 -> 11194835 | K32: ='Dispatch Monthly Func P&L'!AV31 -> 11190845 | L32: =IFERROR(J32-K32,"N/A") -> 3989.5771 | M32: =IFERROR((J32/K32-1),"N/A") -> 0.00035650365 | O32: =E32 -> 936897.54 | P32: ='Dispatch Monthly Func P&L'!$BM31 -> 911795.62 | Q32: =O32-P32 -> 25101.92 | R32: =IFERROR((O32/P32-1),"N/A") -> 0.027530205 | U32: =E16-E28-E32 -> 0 | V32: =F16-F28-F32 -> 0 | X32: =J16-J28-J32 -> 0 | Y32: =K16-K28-K32 -> 0 | AA32: =O16-O28-O32 -> 0 | AB32: =P16-P28-P32 -> 0
C33: Recurring Gross Profit Margin % - Functional | E33: ='Dispatch Monthly Func P&L'!Q32 -> 0.86508321 | F33: =INDEX('Dispatch Monthly Func P&L'!$AI32:$AT32,MATCH(EOMONTH(Inputs!$C$2,0),'Dispatch Monthly Func P&L'!$AI$5:$AT$5,0)) -> 0.88531855 | G33: =IFERROR(E33-F33,"N/A") -> -0.020235341 | J33: ='Dispatch Monthly Func P&L'!X32 -> 0.86451671 | K33: ='Dispatch Monthly Func P&L'!AV32 -> 0.87060636 | L33: =IFERROR(J33-K33,"N/A") -> -0.0060896443 | O33: =E33 -> 0.86508321 | P33: ='Dispatch Monthly Func P&L'!$BM32 -> 0.86667346 | Q33: =O33-P33 -> -0.0015902546
C34: Non-recurring Gross Profit Margin % - Functional | E34: ='Dispatch Monthly Func P&L'!Q33 -> -1.2405453 | F34: =INDEX('Dispatch Monthly Func P&L'!$AI33:$AT33,MATCH(EOMONTH(Inputs!$C$2,0),'Dispatch Monthly Func P&L'!$AI$5:$AT$5,0)) -> -0.97636707 | G34: =IFERROR(E34-F34,"N/A") -> -0.26417821 | J34: ='Dispatch Monthly Func P&L'!X33 -> -0.44645612 | K34: ='Dispatch Monthly Func P&L'!AV33 -> -1.6920253 | L34: =IFERROR(J34-K34,"N/A") -> 1.2455692 | O34: =E34 -> -1.2405453 | P34: ='Dispatch Monthly Func P&L'!$BM33 -> -0.5022907 | Q34: =O34-P34 -> -0.73825459
C35: Total Gross Profit Margin % - Functional | E35: ='Dispatch Monthly Func P&L'!Q34 -> 0.81645717 | F35: =INDEX('Dispatch Monthly Func P&L'!$AI34:$AT34,MATCH(EOMONTH(Inputs!$C$2,0),'Dispatch Monthly Func P&L'!$AI$5:$AT$5,0)) -> 0.84190184 | G35: =IFERROR(E35-F35,"N/A") -> -0.025444677 | J35: ='Dispatch Monthly Func P&L'!X34 -> 0.8184853 | K35: ='Dispatch Monthly Func P&L'!AV34 -> 0.82345691 | L35: =IFERROR(J35-K35,"N/A") -> -0.0049716091 | O35: =E35 -> 0.81645717 | P35: ='Dispatch Monthly Func P&L'!$BM34 -> 0.82694449 | Q35: =O35-P35 -> -0.010487324 | U35: =E32/E16-E35 -> 0 | V35: =F32/F16-F35 -> 0 | X35: =J32/J16-J35 -> 0 | Y35: =K32/K16-K35 -> 0 | AA35: =O32/O16-O35 -> 0 | AB35: =P32/P16-P35 -> 0
C37: Functional Operating Expenses
C38: Product & Engineering Expense - Functional | E38: ='Dispatch Monthly Func P&L'!Q37 -> 295887.01 | F38: =INDEX('Dispatch Monthly Func P&L'!$AI37:$AT37,MATCH(EOMONTH(Inputs!$C$2,0),'Dispatch Monthly Func P&L'!$AI$5:$AT$5,0)) -> 373734.97 | G38: =IFERROR(E38-F38,"N/A") -> -77847.964 | H38: =IFERROR((E38/F38-1),"N/A") -> -0.20829724 | J38: ='Dispatch Monthly Func P&L'!X37 -> 4142020.4 | K38: ='Dispatch Monthly Func P&L'!AV37 -> 4680914.8 | L38: =IFERROR(J38-K38,"N/A") -> -538894.45 | M38: =IFERROR((J38/K38-1),"N/A") -> -0.11512588 | O38: =E38 -> 295887.01 | P38: ='Dispatch Monthly Func P&L'!$BM37 -> 389441.73 | Q38: =O38-P38 -> -93554.72 | R38: =IFERROR((O38/P38-1),"N/A") -> -0.24022777
C39: General & Administrative Expense - Functional | E39: ='Dispatch Monthly Func P&L'!Q38 -> 183958.68 | F39: =INDEX('Dispatch Monthly Func P&L'!$AI38:$AT38,MATCH(EOMONTH(Inputs!$C$2,0),'Dispatch Monthly Func P&L'!$AI$5:$AT$5,0)) -> 274754.18 | G39: =IFERROR(E39-F39,"N/A") -> -90795.498 | H39: =IFERROR((E39/F39-1),"N/A") -> -0.33046084 | J39: ='Dispatch Monthly Func P&L'!X38 -> 3235849.6 | K39: ='Dispatch Monthly Func P&L'!AV38 -> 3437916.3 | L39: =IFERROR(J39-K39,"N/A") -> -202066.69 | M39: =IFERROR((J39/K39-1),"N/A") -> -0.058775919 | O39: =E39 -> 183958.68 | P39: ='Dispatch Monthly Func P&L'!$BM38 -> 242492.84 | Q39: =O39-P39 -> -58534.16 | R39: =IFERROR((O39/P39-1),"N/A") -> -0.24138511
C40: Human Resources - Functional | E40: ='Dispatch Monthly Func P&L'!Q39 -> 6091.76 | F40: =INDEX('Dispatch Monthly Func P&L'!$AI39:$AT39,MATCH(EOMONTH(Inputs!$C$2,0),'Dispatch Monthly Func P&L'!$AI$5:$AT$5,0)) -> 8841.25 | G40: =IFERROR(E40-F40,"N/A") -> -2749.49 | H40: =IFERROR((E40/F40-1),"N/A") -> -0.31098431 | J40: ='Dispatch Monthly Func P&L'!X39 -> 77250.29 | K40: ='Dispatch Monthly Func P&L'!AV39 -> 93546 | L40: =IFERROR(J40-K40,"N/A") -> -16295.71 | M40: =IFERROR((J40/K40-1),"N/A") -> -0.17419997 | O40: =E40 -> 6091.76 | P40: ='Dispatch Monthly Func P&L'!$BM39 -> 6273.72 | Q40: =O40-P40 -> -181.96 | R40: =IFERROR((O40/P40-1),"N/A") -> -0.029003526
C41: Sales Expense - Functional | E41: ='Dispatch Monthly Func P&L'!Q40 -> 170948.6 | F41: =INDEX('Dispatch Monthly Func P&L'!$AI40:$AT40,MATCH(EOMONTH(Inputs!$C$2,0),'Dispatch Monthly Func P&L'!$AI$5:$AT$5,0)) -> 231405.92 | G41: =IFERROR(E41-F41,"N/A") -> -60457.321 | H41: =IFERROR((E41/F41-1),"N/A") -> -0.26126091 | J41: ='Dispatch Monthly Func P&L'!X40 -> 2228482.5 | K41: ='Dispatch Monthly Func P&L'!AV40 -> 2861633 | L41: =IFERROR(J41-K41,"N/A") -> -633150.46 | M41: =IFERROR((J41/K41-1),"N/A") -> -0.22125495 | O41: =E41 -> 170948.6 | P41: ='Dispatch Monthly Func P&L'!$BM40 -> 218757.79 | Q41: =O41-P41 -> -47809.19 | R41: =IFERROR((O41/P41-1),"N/A") -> -0.21854851
C42: Marketing Expense - Functional | E42: ='Dispatch Monthly Func P&L'!Q41 -> 33233.02 | F42: =INDEX('Dispatch Monthly Func P&L'!$AI41:$AT41,MATCH(EOMONTH(Inputs!$C$2,0),'Dispatch Monthly Func P&L'!$AI$5:$AT$5,0)) -> 48086.053 | G42: =IFERROR(E42-F42,"N/A") -> -14853.033 | H42: =IFERROR((E42/F42-1),"N/A") -> -0.30888442 | J42: ='Dispatch Monthly Func P&L'!X41 -> 474025.87 | K42: ='Dispatch Monthly Func P&L'!AV41 -> 698421.14 | L42: =IFERROR(J42-K42,"N/A") -> -224395.27 | M42: =IFERROR((J42/K42-1),"N/A") -> -0.32128934 | O42: =E42 -> 33233.02 | P42: ='Dispatch Monthly Func P&L'!$BM41 -> 43815.94 | Q42: =O42-P42 -> -10582.92 | R42: =IFERROR((O42/P42-1),"N/A") -> -0.24153128
C43: Other Functional Operating Expense (incl. D&A) | E43: ='Dispatch Monthly Func P&L'!Q42 -> 428302.12 | F43: =INDEX('Dispatch Monthly Func P&L'!$AI42:$AT42,MATCH(EOMONTH(Inputs!$C$2,0),'Dispatch Monthly Func P&L'!$AI$5:$AT$5,0)) -> 427276.51 | G43: =IFERROR(E43-F43,"N/A") -> 1025.6078 | H43: =IFERROR((E43/F43-1),"N/A") -> 0.0024003374 | J43: ='Dispatch Monthly Func P&L'!X42 -> 5193547.6 | K43: ='Dispatch Monthly Func P&L'!AV42 -> 5227318.1 | L43: =IFERROR(J43-K43,"N/A") -> -33770.577 | M43: =IFERROR((J43/K43-1),"N/A") -> -0.006460402 | O43: =E43 -> 428302.12 | P43: ='Dispatch Monthly Func P&L'!$BM42 -> 490022.21 | Q43: =O43-P43 -> -61720.09 | R43: =IFERROR((O43/P43-1),"N/A") -> -0.12595366
C44: Total - Functional Operating Expenses | E44: ='Dispatch Monthly Func P&L'!Q43 -> 1118421.2 | F44: =INDEX('Dispatch Monthly Func P&L'!$AI43:$AT43,MATCH(EOMONTH(Inputs!$C$2,0),'Dispatch Monthly Func P&L'!$AI$5:$AT$5,0)) -> 1364098.9 | G44: =IFERROR(E44-F44,"N/A") -> -245677.7 | H44: =IFERROR((E44/F44-1),"N/A") -> -0.18010256 | J44: ='Dispatch Monthly Func P&L'!X43 -> 15351176 | K44: ='Dispatch Monthly Func P&L'!AV43 -> 16999749 | L44: =IFERROR(J44-K44,"N/A") -> -1648573.2 | M44: =IFERROR((J44/K44-1),"N/A") -> -0.096976321 | O44: =E44 -> 1118421.2 | P44: ='Dispatch Monthly Func P&L'!$BM43 -> 1390804.2 | Q44: =O44-P44 -> -272383.04 | R44: =IFERROR((O44/P44-1),"N/A") -> -0.19584571 | U44: =SUM(E38:E43)-E44 -> 0 | V44: =SUM(F38:F43)-F44 -> 0 | X44: =SUM(J38:J43)-J44 -> 0 | Y44: =SUM(K38:K43)-K44 -> 0 | AA44: =SUM(O38:O43)-O44 -> 0 | AB44: =SUM(P38:P43)-P44 -> 0
C45: w/o Depreciation, Amoritization, or Bad Debt | E45: ='Dispatch Monthly Func P&L'!Q44 -> 690119.07 | F45: =INDEX('Dispatch Monthly Func P&L'!$AI44:$AT44,MATCH(EOMONTH(Inputs!$C$2,0),'Dispatch Monthly Func P&L'!$AI$5:$AT$5,0)) -> 936822.38 | G45: =IFERROR(E45-F45,"N/A") -> -246703.31 | H45: =IFERROR((E45/F45-1),"N/A") -> -0.26334053 | J45: ='Dispatch Monthly Func P&L'!X44 -> 10157629 | K45: ='Dispatch Monthly Func P&L'!AV44 -> 11872431 | L45: =IFERROR(J45-K45,"N/A") -> -1714802.6 | M45: =IFERROR((J45/K45-1),"N/A") -> -0.14443567 | O45: =E45 -> 690119.07 | P45: ='Dispatch Monthly Func P&L'!$BM44 -> 900782.02 | Q45: =O45-P45 -> -210662.95 | R45: =IFERROR((O45/P45-1),"N/A") -> -0.23386674 | U45: =E44-SUM(E79:E81)-E45 -> -0.010974969 | V45: =F44-SUM(F79:F81)-F45 -> 0 | X45: =J44-SUM(J79:J81)-J45 -> -0.13169963 | Y45: =K44-SUM(K79:K81)-K45 -> -100000 | AA45: =O44-SUM(O79:O81)-O45 -> -0.010974969 | AB45: =P44-SUM(P79:P81)-P45 -> -0.010974969
F46: =INDEX('Dispatch Monthly Func P&L'!$AI45:$AT45,MATCH(EOMONTH(Inputs!$C$2,0),'Dispatch Monthly Func P&L'!$AI$5:$AT$5,0)) -> 0
C47: Operating Margin | E47: ='Dispatch Monthly Func P&L'!Q46 -> -181523.65 | F47: =INDEX('Dispatch Monthly Func P&L'!$AI46:$AT46,MATCH(EOMONTH(Inputs!$C$2,0),'Dispatch Monthly Func P&L'!$AI$5:$AT$5,0)) -> -329223.37 | G47: =IFERROR(E47-F47,"N/A") -> 147699.72 | H47: =IFERROR((E47/F47-1),"N/A") -> -0.44863072 | J47: ='Dispatch Monthly Func P&L'!X46 -> -4156341.7 | K47: ='Dispatch Monthly Func P&L'!AV46 -> -5808904.4 | L47: =IFERROR(J47-K47,"N/A") -> 1652562.7 | M47: =IFERROR((J47/K47-1),"N/A") -> -0.28448785 | O47: =E47 -> -181523.65 | P47: ='Dispatch Monthly Func P&L'!$BM46 -> -479008.61 | Q47: =O47-P47 -> 297484.96 | R47: =IFERROR((O47/P47-1),"N/A") -> -0.62104303 | U47: =E32-E44-E47 -> 0 | V47: =F32-F44-F47 -> 0 | X47: =J32-J44-J47 -> 0 | Y47: =K32-K44-K47 -> 0 | AA47: =O32-O44-O47 -> 0 | AB47: =P32-P44-P47 -> 0
C48: Operating Margin % | E48: ='Dispatch Monthly Func P&L'!Q47 -> -0.15818836 | F48: =INDEX('Dispatch Monthly Func P&L'!$AI47:$AT47,MATCH(EOMONTH(Inputs!$C$2,0),'Dispatch Monthly Func P&L'!$AI$5:$AT$5,0)) -> -0.26783295 | G48: =IFERROR(E48-F48,"N/A") -> 0.10964459 | J48: ='Dispatch Monthly Func P&L'!X47 -> -0.30388163 | K48: ='Dispatch Monthly Func P&L'!AV47 -> -0.42743711 | L48: =IFERROR(J48-K48,"N/A") -> 0.12355548 | O48: =E48 -> -0.15818836 | P48: ='Dispatch Monthly Func P&L'!$BM47 -> -0.43443237 | Q48: =O48-P48 -> 0.27624401 | U48: =E47/E16-E48 -> 0 | V48: =F47/F16-F48 -> 0 | X48: =J47/J16-J48 -> 0 | Y48: =K47/K16-K48 -> 0 | AA48: =O47/O16-O48 -> 0 | AB48: =P47/P16-P48 -> 0
C49: Operating Margin Check (F-N) | E49: =E47-'2a. Dispatch Natural P&L'!E58 -> 0.01097497 | F49: =F47-'2a. Dispatch Natural P&L'!F58 -> 0 | J49: =J47-'2a. Dispatch Natural P&L'!J58 -> 0.13169964 | K49: ='Dispatch Monthly Func P&L'!AV48 -> 0.014308303 | O49: =E49 -> 0.01097497 | P49: =P47-'2a. Dispatch Natural P&L'!P58 -> 0.010974969
C51: Non-Operating Expenses / (Income)
C52: Interest Expense | E52: ='Dispatch Monthly Func P&L'!Q51 -> 556137.34 | F52: =INDEX('Dispatch Monthly Func P&L'!$AI51:$AT51,MATCH(EOMONTH(Inputs!$C$2,0),'Dispatch Monthly Func P&L'!$AI$5:$AT$5,0)) -> 529320.93 | G52: =IFERROR(E52-F52,"N/A") -> 26816.411 | H52: =IFERROR((E52/F52-1),"N/A") -> 0.050661913 | J52: ='Dispatch Monthly Func P&L'!X51 -> 6770607 | K52: ='Dispatch Monthly Func P&L'!AV51 -> 6033984.6 | L52: =IFERROR(J52-K52,"N/A") -> 736622.41 | M52: =IFERROR((J52/K52-1),"N/A") -> 0.12207893 | O52: =E52 -> 556137.34 | P52: ='Dispatch Monthly Func P&L'!$BM51 -> 557496.68 | Q52: =O52-P52 -> -1359.34 | R52: =IFERROR((O52/P52-1),"N/A") -> -0.0024382925
C53: Interest Income | E53: ='Dispatch Monthly Func P&L'!Q52 -> 0 | F53: =INDEX('Dispatch Monthly Func P&L'!$AI52:$AT52,MATCH(EOMONTH(Inputs!$C$2,0),'Dispatch Monthly Func P&L'!$AI$5:$AT$5,0)) -> 0 | G53: =IFERROR(E53-F53,"N/A") -> 0 | H53: =IFERROR((E53/F53-1),"N/A") -> N/A | J53: ='Dispatch Monthly Func P&L'!X52 -> 0 | K53: ='Dispatch Monthly Func P&L'!AV52 -> 0 | L53: =IFERROR(J53-K53,"N/A") -> 0 | M53: =IFERROR((J53/K53-1),"N/A") -> N/A | O53: =E53 -> 0 | P53: ='Dispatch Monthly Func P&L'!$BM52 -> 0 | Q53: =O53-P53 -> 0 | R53: =IFERROR((O53/P53-1),"N/A") -> N/A
C54: Other Expense / (Income) | E54: ='Dispatch Monthly Func P&L'!Q53 -> 8363.91 | F54: =INDEX('Dispatch Monthly Func P&L'!$AI53:$AT53,MATCH(EOMONTH(Inputs!$C$2,0),'Dispatch Monthly Func P&L'!$AI$5:$AT$5,0)) -> 12729.167 | G54: =IFERROR(E54-F54,"N/A") -> -4365.2567 | H54: =IFERROR((E54/F54-1),"N/A") -> -0.34293342 | J54: ='Dispatch Monthly Func P&L'!X53 -> -139558.44 | K54: ='Dispatch Monthly Func P&L'!AV53 -> 244375 | L54: =IFERROR(J54-K54,"N/A") -> -383933.44 | M54: =IFERROR((J54/K54-1),"N/A") -> -1.5710831 | O54: =E54 -> 8363.91 | P54: ='Dispatch Monthly Func P&L'!$BM53 -> 3977.37 | Q54: =O54-P54 -> 4386.54 | R54: =IFERROR((O54/P54-1),"N/A") -> 1.1028745
C55: Stock-Based Compensation | E55: ='Dispatch Monthly Func P&L'!Q54 -> 0 | F55: =INDEX('Dispatch Monthly Func P&L'!$AI54:$AT54,MATCH(EOMONTH(Inputs!$C$2,0),'Dispatch Monthly Func P&L'!$AI$5:$AT$5,0)) -> 0 | G55: =IFERROR(E55-F55,"N/A") -> 0 | H55: =IFERROR((E55/F55-1),"N/A") -> N/A | J55: ='Dispatch Monthly Func P&L'!X54 -> 0 | K55: ='Dispatch Monthly Func P&L'!AV54 -> 0 | L55: =IFERROR(J55-K55,"N/A") -> 0 | M55: =IFERROR((J55/K55-1),"N/A") -> N/A | O55: =E55 -> 0 | P55: ='Dispatch Monthly Func P&L'!$BM54 -> 217081.7 | Q55: =O55-P55 -> -217081.7 | R55: =IFERROR((O55/P55-1),"N/A") -> -1
C56: Acquisition-Related Costs | E56: ='Dispatch Monthly Func P&L'!Q55 -> 0 | F56: =INDEX('Dispatch Monthly Func P&L'!$AI55:$AT55,MATCH(EOMONTH(Inputs!$C$2,0),'Dispatch Monthly Func P&L'!$AI$5:$AT$5,0)) -> 0 | G56: =IFERROR(E56-F56,"N/A") -> 0 | H56: =IFERROR((E56/F56-1),"N/A") -> N/A | J56: ='Dispatch Monthly Func P&L'!X55 -> 4857 | K56: ='Dispatch Monthly Func P&L'!AV55 -> 0 | L56: =IFERROR(J56-K56,"N/A") -> 4857 | M56: =IFERROR((J56/K56-1),"N/A") -> N/A | O56: =E56 -> 0 | P56: ='Dispatch Monthly Func P&L'!$BM55 -> 218532.97 | Q56: =O56-P56 -> -218532.97 | R56: =IFERROR((O56/P56-1),"N/A") -> -1
C57: Deferred Revenue - Purchase Accounting Haircut | E57: ='Dispatch Monthly Func P&L'!Q56 -> 0 | F57: =INDEX('Dispatch Monthly Func P&L'!$AI56:$AT56,MATCH(EOMONTH(Inputs!$C$2,0),'Dispatch Monthly Func P&L'!$AI$5:$AT$5,0)) -> 0 | G57: =IFERROR(E57-F57,"N/A") -> 0 | H57: =IFERROR((E57/F57-1),"N/A") -> N/A | J57: ='Dispatch Monthly Func P&L'!X56 -> 0 | K57: ='Dispatch Monthly Func P&L'!AV56 -> 0 | L57: =IFERROR(J57-K57,"N/A") -> 0 | M57: =IFERROR((J57/K57-1),"N/A") -> N/A | O57: =E57 -> 0 | P57: ='Dispatch Monthly Func P&L'!$BM56 -> 0 | Q57: =O57-P57 -> 0 | R57: =IFERROR((O57/P57-1),"N/A") -> N/A
C58: Restructuring Fees and Expenses / Severance | E58: ='Dispatch Monthly Func P&L'!Q57 -> 0 | F58: =INDEX('Dispatch Monthly Func P&L'!$AI57:$AT57,MATCH(EOMONTH(Inputs!$C$2,0),'Dispatch Monthly Func P&L'!$AI$5:$AT$5,0)) -> 0 | G58: =IFERROR(E58-F58,"N/A") -> 0 | H58: =IFERROR((E58/F58-1),"N/A") -> N/A | J58: ='Dispatch Monthly Func P&L'!X57 -> 241203.21 | K58: ='Dispatch Monthly Func P&L'!AV57 -> 0 | L58: =IFERROR(J58-K58,"N/A") -> 241203.21 | M58: =IFERROR((J58/K58-1),"N/A") -> N/A | O58: =E58 -> 0 | P58: ='Dispatch Monthly Func P&L'!$BM57 -> 0 | Q58: =O58-P58 -> 0 | R58: =IFERROR((O58/P58-1),"N/A") -> N/A
C59: VEP & VCG Expenses | E59: ='Dispatch Monthly Func P&L'!Q58 -> 5145.89 | F59: =INDEX('Dispatch Monthly Func P&L'!$AI58:$AT58,MATCH(EOMONTH(Inputs!$C$2,0),'Dispatch Monthly Func P&L'!$AI$5:$AT$5,0)) -> 29333.333 | G59: =IFERROR(E59-F59,"N/A") -> -24187.443 | H59: =IFERROR((E59/F59-1),"N/A") -> -0.82457193 | J59: ='Dispatch Monthly Func P&L'!X58 -> 123836.42 | K59: ='Dispatch Monthly Func P&L'!AV58 -> 352000 | L59: =IFERROR(J59-K59,"N/A") -> -228163.58 | M59: =IFERROR((J59/K59-1),"N/A") -> -0.64819199 | O59: =E59 -> 5145.89 | P59: ='Dispatch Monthly Func P&L'!$BM58 -> 4202.57 | Q59: =O59-P59 -> 943.32 | R59: =IFERROR((O59/P59-1),"N/A") -> 0.22446265
C60: Total - Non-Operating Expenses / (Income) | E60: ='Dispatch Monthly Func P&L'!Q59 -> 569647.14 | F60: =INDEX('Dispatch Monthly Func P&L'!$AI59:$AT59,MATCH(EOMONTH(Inputs!$C$2,0),'Dispatch Monthly Func P&L'!$AI$5:$AT$5,0)) -> 571383.43 | G60: =IFERROR(E60-F60,"N/A") -> -1736.2889 | H60: =IFERROR((E60/F60-1),"N/A") -> -0.0030387457 | J60: ='Dispatch Monthly Func P&L'!X59 -> 7000945.2 | K60: ='Dispatch Monthly Func P&L'!AV59 -> 6630359.6 | L60: =IFERROR(J60-K60,"N/A") -> 370585.6 | M60: =IFERROR((J60/K60-1),"N/A") -> 0.055892233 | O60: =E60 -> 569647.14 | P60: ='Dispatch Monthly Func P&L'!$BM59 -> 1001291.3 | Q60: =O60-P60 -> -431644.15 | R60: =IFERROR((O60/P60-1),"N/A") -> -0.43108749 | U60: =SUM(E52:E59)-E60 -> 0 | V60: =SUM(F52:F59)-F60 -> 0 | X60: =SUM(J52:J59)-J60 -> 0 | Y60: =SUM(K52:K59)-K60 -> 0 | AA60: =SUM(O52:O59)-O60 -> 0 | AB60: =SUM(P52:P59)-P60 -> 0
F61: =INDEX('Dispatch Monthly Func P&L'!$AI60:$AT60,MATCH(EOMONTH(Inputs!$C$2,0),'Dispatch Monthly Func P&L'!$AI$5:$AT$5,0)) -> 0
C62: Pre-Tax Income | E62: ='Dispatch Monthly Func P&L'!Q61 -> -751170.79 | F62: =INDEX('Dispatch Monthly Func P&L'!$AI61:$AT61,MATCH(EOMONTH(Inputs!$C$2,0),'Dispatch Monthly Func P&L'!$AI$5:$AT$5,0)) -> -900606.8 | G62: =IFERROR(E62-F62,"N/A") -> 149436.01 | H62: =IFERROR((E62/F62-1),"N/A") -> -0.16592813 | J62: ='Dispatch Monthly Func P&L'!X61 -> -11157287 | K62: ='Dispatch Monthly Func P&L'!AV61 -> -12439264 | L62: =IFERROR(J62-K62,"N/A") -> 1281977.1 | M62: =IFERROR((J62/K62-1),"N/A") -> -0.10305892 | O62: =E62 -> -751170.79 | P62: ='Dispatch Monthly Func P&L'!$BM61 -> -1480299.9 | Q62: =O62-P62 -> 729129.11 | R62: =IFERROR((O62/P62-1),"N/A") -> -0.492555 | U62: =E47-E60-E62 -> 0 | V62: =F47-F60-F62 -> 0 | X62: =J47-J60-J62 -> 0 | Y62: =K47-K60-K62 -> 0 | AA62: =O47-O60-O62 -> 0 | AB62: =P47-P60-P62 -> 0
C63: Provision for Income Taxes | E63: ='Dispatch Monthly Func P&L'!Q62 -> 0 | F63: =INDEX('Dispatch Monthly Func P&L'!$AI62:$AT62,MATCH(EOMONTH(Inputs!$C$2,0),'Dispatch Monthly Func P&L'!$AI$5:$AT$5,0)) -> 0 | G63: =IFERROR(E63-F63,"N/A") -> 0 | H63: =IFERROR((E63/F63-1),"N/A") -> N/A | J63: ='Dispatch Monthly Func P&L'!X62 -> 0 | K63: ='Dispatch Monthly Func P&L'!AV62 -> 0 | L63: =IFERROR(J63-K63,"N/A") -> 0 | M63: =IFERROR((J63/K63-1),"N/A") -> N/A | O63: =E63 -> 0 | P63: ='Dispatch Monthly Func P&L'!$BM62 -> 0 | Q63: =O63-P63 -> 0 | R63: =IFERROR((O63/P63-1),"N/A") -> N/A
C64: Implied Tax Rate | E64: ='Dispatch Monthly Func P&L'!Q63 -> 0 | F64: =INDEX('Dispatch Monthly Func P&L'!$AI63:$AT63,MATCH(EOMONTH(Inputs!$C$2,0),'Dispatch Monthly Func P&L'!$AI$5:$AT$5,0)) -> 0 | G64: =IFERROR(E64-F64,"N/A") -> 0 | J64: ='Dispatch Monthly Func P&L'!X63 -> 0 | K64: ='Dispatch Monthly Func P&L'!AV63 -> 0 | L64: =IFERROR(J64-K64,"N/A") -> 0 | O64: =E64 -> 0 | P64: ='Dispatch Monthly Func P&L'!$BM63 -> 0 | Q64: =O64-P64 -> 0
C66: Net Income | E66: ='Dispatch Monthly Func P&L'!Q65 -> -751170.79 | F66: =INDEX('Dispatch Monthly Func P&L'!$AI65:$AT65,MATCH(EOMONTH(Inputs!$C$2,0),'Dispatch Monthly Func P&L'!$AI$5:$AT$5,0)) -> -900606.8 | G66: =IFERROR(E66-F66,"N/A") -> 149436.01 | H66: =IFERROR((E66/F66-1),"N/A") -> -0.16592813 | J66: ='Dispatch Monthly Func P&L'!X65 -> -11157287 | K66: ='Dispatch Monthly Func P&L'!AV65 -> -12439264 | L66: =IFERROR(J66-K66,"N/A") -> 1281977.1 | M66: =IFERROR((J66/K66-1),"N/A") -> -0.10305892 | O66: =E66 -> -751170.79 | P66: ='Dispatch Monthly Func P&L'!$BM65 -> -1480299.9 | Q66: =O66-P66 -> 729129.11 | R66: =IFERROR((O66/P66-1),"N/A") -> -0.492555 | U66: =E62-E63-E66 -> 0 | V66: =F62-F63-F66 -> 0 | X66: =J62-J63-J66 -> 0 | Y66: =K62-K63-K66 -> 0 | AA66: =O62-O63-O66 -> 0 | AB66: =P62-P63-P66 -> 0
C67: Net Income (% of Revenue) | E67: ='Dispatch Monthly Func P&L'!Q66 -> -0.65460603 | F67: =INDEX('Dispatch Monthly Func P&L'!$AI66:$AT66,MATCH(EOMONTH(Inputs!$C$2,0),'Dispatch Monthly Func P&L'!$AI$5:$AT$5,0)) -> -0.73267027 | G67: =IFERROR(E67-F67,"N/A") -> 0.07806424 | J67: ='Dispatch Monthly Func P&L'!X66 -> -0.81574009 | K67: ='Dispatch Monthly Func P&L'!AV66 -> -0.91531944 | L67: =IFERROR(J67-K67,"N/A") -> 0.099579349 | O67: =E67 -> -0.65460603 | P67: ='Dispatch Monthly Func P&L'!$BM66 -> -1.3425441 | Q67: =O67-P67 -> 0.68793809 | U67: =E66/E16-E67 -> 0 | V67: =F66/F16-F67 -> 0 | X67: =J66/J16-J67 -> 0 | Y67: =K66/K16-K67 -> 0 | AA67: =O66/O16-O67 -> 0 | AB67: =P66/P16-P67 -> 0
C69: EBITDA Addbacks
C70: Interest Expense | E70: ='Dispatch Monthly Func P&L'!Q69 -> 556137.34 | F70: =INDEX('Dispatch Monthly Func P&L'!$AI69:$AT69,MATCH(EOMONTH(Inputs!$C$2,0),'Dispatch Monthly Func P&L'!$AI$5:$AT$5,0)) -> 529320.93 | G70: =IFERROR(E70-F70,"N/A") -> 26816.411 | H70: =IFERROR((E70/F70-1),"N/A") -> 0.050661913 | J70: ='Dispatch Monthly Func P&L'!X69 -> 6770607 | K70: ='Dispatch Monthly Func P&L'!AV69 -> 6033984.6 | L70: =IFERROR(J70-K70,"N/A") -> 736622.41 | M70: =IFERROR((J70/K70-1),"N/A") -> 0.12207893 | O70: =E70 -> 556137.34 | P70: ='Dispatch Monthly Func P&L'!$BM69 -> 557496.68 | Q70: =O70-P70 -> -1359.34 | R70: =IFERROR((O70/P70-1),"N/A") -> -0.0024382925
C71: Interest Income | E71: ='Dispatch Monthly Func P&L'!Q70 -> 0 | F71: =INDEX('Dispatch Monthly Func P&L'!$AI70:$AT70,MATCH(EOMONTH(Inputs!$C$2,0),'Dispatch Monthly Func P&L'!$AI$5:$AT$5,0)) -> 0 | G71: =IFERROR(E71-F71,"N/A") -> 0 | H71: =IFERROR((E71/F71-1),"N/A") -> N/A | J71: ='Dispatch Monthly Func P&L'!X70 -> 0 | K71: ='Dispatch Monthly Func P&L'!AV70 -> 0 | L71: =IFERROR(J71-K71,"N/A") -> 0 | M71: =IFERROR((J71/K71-1),"N/A") -> N/A | O71: =E71 -> 0 | P71: ='Dispatch Monthly Func P&L'!$BM70 -> 0 | Q71: =O71-P71 -> 0 | R71: =IFERROR((O71/P71-1),"N/A") -> N/A
C72: Other Expense / Income | E72: ='Dispatch Monthly Func P&L'!Q71 -> 8363.91 | F72: =INDEX('Dispatch Monthly Func P&L'!$AI71:$AT71,MATCH(EOMONTH(Inputs!$C$2,0),'Dispatch Monthly Func P&L'!$AI$5:$AT$5,0)) -> 12729.167 | G72: =IFERROR(E72-F72,"N/A") -> -4365.2567 | H72: =IFERROR((E72/F72-1),"N/A") -> -0.34293342 | J72: ='Dispatch Monthly Func P&L'!X71 -> -139558.44 | K72: ='Dispatch Monthly Func P&L'!AV71 -> 244375 | L72: =IFERROR(J72-K72,"N/A") -> -383933.44 | M72: =IFERROR((J72/K72-1),"N/A") -> -1.5710831 | O72: =E72 -> 8363.91 | P72: ='Dispatch Monthly Func P&L'!$BM71 -> 3977.37 | Q72: =O72-P72 -> 4386.54 | R72: =IFERROR((O72/P72-1),"N/A") -> 1.1028745
C73: Stock-Based Compensation | E73: ='Dispatch Monthly Func P&L'!Q72 -> 0 | F73: =INDEX('Dispatch Monthly Func P&L'!$AI72:$AT72,MATCH(EOMONTH(Inputs!$C$2,0),'Dispatch Monthly Func P&L'!$AI$5:$AT$5,0)) -> 0 | G73: =IFERROR(E73-F73,"N/A") -> 0 | H73: =IFERROR((E73/F73-1),"N/A") -> N/A | J73: ='Dispatch Monthly Func P&L'!X72 -> 0 | K73: ='Dispatch Monthly Func P&L'!AV72 -> 0 | L73: =IFERROR(J73-K73,"N/A") -> 0 | M73: =IFERROR((J73/K73-1),"N/A") -> N/A | O73: =E73 -> 0 | P73: ='Dispatch Monthly Func P&L'!$BM72 -> 217081.7 | Q73: =O73-P73 -> -217081.7 | R73: =IFERROR((O73/P73-1),"N/A") -> -1
C74: Acquisition-Related Costs | E74: ='Dispatch Monthly Func P&L'!Q73 -> 0 | F74: =INDEX('Dispatch Monthly Func P&L'!$AI73:$AT73,MATCH(EOMONTH(Inputs!$C$2,0),'Dispatch Monthly Func P&L'!$AI$5:$AT$5,0)) -> 0 | G74: =IFERROR(E74-F74,"N/A") -> 0 | H74: =IFERROR((E74/F74-1),"N/A") -> N/A | J74: ='Dispatch Monthly Func P&L'!X73 -> 4857 | K74: ='Dispatch Monthly Func P&L'!AV73 -> 0 | L74: =IFERROR(J74-K74,"N/A") -> 4857 | M74: =IFERROR((J74/K74-1),"N/A") -> N/A | O74: =E74 -> 0 | P74: ='Dispatch Monthly Func P&L'!$BM73 -> 218532.97 | Q74: =O74-P74 -> -218532.97 | R74: =IFERROR((O74/P74-1),"N/A") -> -1
C75: Deferred Revenue - Purchase Accounting Haircut | E75: ='Dispatch Monthly Func P&L'!Q74 -> 0 | F75: =INDEX('Dispatch Monthly Func P&L'!$AI74:$AT74,MATCH(EOMONTH(Inputs!$C$2,0),'Dispatch Monthly Func P&L'!$AI$5:$AT$5,0)) -> 0 | G75: =IFERROR(E75-F75,"N/A") -> 0 | H75: =IFERROR((E75/F75-1),"N/A") -> N/A | J75: ='Dispatch Monthly Func P&L'!X74 -> 0 | K75: ='Dispatch Monthly Func P&L'!AV74 -> 0 | L75: =IFERROR(J75-K75,"N/A") -> 0 | M75: =IFERROR((J75/K75-1),"N/A") -> N/A | O75: =E75 -> 0 | P75: ='Dispatch Monthly Func P&L'!$BM74 -> 0 | Q75: =O75-P75 -> 0 | R75: =IFERROR((O75/P75-1),"N/A") -> N/A
C76: Restructuring Fees and Expenses / Severance | E76: ='Dispatch Monthly Func P&L'!Q75 -> 0 | F76: =INDEX('Dispatch Monthly Func P&L'!$AI75:$AT75,MATCH(EOMONTH(Inputs!$C$2,0),'Dispatch Monthly Func P&L'!$AI$5:$AT$5,0)) -> 0 | G76: =IFERROR(E76-F76,"N/A") -> 0 | H76: =IFERROR((E76/F76-1),"N/A") -> N/A | J76: ='Dispatch Monthly Func P&L'!X75 -> 241203.21 | K76: ='Dispatch Monthly Func P&L'!AV75 -> 0 | L76: =IFERROR(J76-K76,"N/A") -> 241203.21 | M76: =IFERROR((J76/K76-1),"N/A") -> N/A | O76: =E76 -> 0 | P76: ='Dispatch Monthly Func P&L'!$BM75 -> 0 | Q76: =O76-P76 -> 0 | R76: =IFERROR((O76/P76-1),"N/A") -> N/A
C77: VEP & VCG Expenses | E77: ='Dispatch Monthly Func P&L'!Q76 -> 5145.89 | F77: =INDEX('Dispatch Monthly Func P&L'!$AI76:$AT76,MATCH(EOMONTH(Inputs!$C$2,0),'Dispatch Monthly Func P&L'!$AI$5:$AT$5,0)) -> 29333.333 | G77: =IFERROR(E77-F77,"N/A") -> -24187.443 | H77: =IFERROR((E77/F77-1),"N/A") -> -0.82457193 | J77: ='Dispatch Monthly Func P&L'!X76 -> 123836.42 | K77: ='Dispatch Monthly Func P&L'!AV76 -> 352000 | L77: =IFERROR(J77-K77,"N/A") -> -228163.58 | M77: =IFERROR((J77/K77-1),"N/A") -> -0.64819199 | O77: =E77 -> 5145.89 | P77: ='Dispatch Monthly Func P&L'!$BM76 -> 4202.57 | Q77: =O77-P77 -> 943.32 | R77: =IFERROR((O77/P77-1),"N/A") -> 0.22446265
C78: Provision for Income Taxes | E78: ='Dispatch Monthly Func P&L'!Q77 -> 0 | F78: =INDEX('Dispatch Monthly Func P&L'!$AI77:$AT77,MATCH(EOMONTH(Inputs!$C$2,0),'Dispatch Monthly Func P&L'!$AI$5:$AT$5,0)) -> 0 | G78: =IFERROR(E78-F78,"N/A") -> 0 | H78: =IFERROR((E78/F78-1),"N/A") -> N/A | J78: ='Dispatch Monthly Func P&L'!X77 -> 0 | K78: ='Dispatch Monthly Func P&L'!AV77 -> 0 | L78: =IFERROR(J78-K78,"N/A") -> 0 | M78: =IFERROR((J78/K78-1),"N/A") -> N/A | O78: =E78 -> 0 | P78: ='Dispatch Monthly Func P&L'!$BM77 -> 0 | Q78: =O78-P78 -> 0 | R78: =IFERROR((O78/P78-1),"N/A") -> N/A
C79: Bad Debt Expense | E79: ='Dispatch Monthly Func P&L'!Q78 -> 0 | F79: =INDEX('Dispatch Monthly Func P&L'!$AI78:$AT78,MATCH(EOMONTH(Inputs!$C$2,0),'Dispatch Monthly Func P&L'!$AI$5:$AT$5,0)) -> 0 | G79: =IFERROR(E79-F79,"N/A") -> 0 | H79: =IFERROR((E79/F79-1),"N/A") -> N/A | J79: ='Dispatch Monthly Func P&L'!X78 -> 58000 | K79: ='Dispatch Monthly Func P&L'!AV78 -> 100000 | L79: =IFERROR(J79-K79,"N/A") -> -42000 | M79: =IFERROR((J79/K79-1),"N/A") -> -0.42 | O79: =E79 -> 0 | P79: ='Dispatch Monthly Func P&L'!$BM78 -> 62817.83 | Q79: =O79-P79 -> -62817.83 | R79: =IFERROR((O79/P79-1),"N/A") -> -1
C80: Depreciation | E80: ='Dispatch Monthly Func P&L'!Q79 -> 1935.37 | F80: =INDEX('Dispatch Monthly Func P&L'!$AI79:$AT79,MATCH(EOMONTH(Inputs!$C$2,0),'Dispatch Monthly Func P&L'!$AI$5:$AT$5,0)) -> 909.75125 | G80: =IFERROR(E80-F80,"N/A") -> 1025.6187 | H80: =IFERROR((E80/F80-1),"N/A") -> 1.1273617 | J80: ='Dispatch Monthly Func P&L'!X79 -> 19146.57 | K80: ='Dispatch Monthly Func P&L'!AV79 -> 10917.015 | L80: =IFERROR(J80-K80,"N/A") -> 8229.555 | M80: =IFERROR((J80/K80-1),"N/A") -> 0.75382831 | O80: =E80 -> 1935.37 | P80: ='Dispatch Monthly Func P&L'!$BM79 -> 837.63 | Q80: =O80-P80 -> 1097.74 | R80: =IFERROR((O80/P80-1),"N/A") -> 1.3105309
C81: Amortization | E81: ='Dispatch Monthly Func P&L'!Q80 -> 426366.76 | F81: =INDEX('Dispatch Monthly Func P&L'!$AI80:$AT80,MATCH(EOMONTH(Inputs!$C$2,0),'Dispatch Monthly Func P&L'!$AI$5:$AT$5,0)) -> 426366.76 | G81: =IFERROR(E81-F81,"N/A") -> 0 | H81: =IFERROR((E81/F81-1),"N/A") -> 0 | J81: ='Dispatch Monthly Func P&L'!X80 -> 5116401.1 | K81: ='Dispatch Monthly Func P&L'!AV80 -> 5116401.1 | L81: =IFERROR(J81-K81,"N/A") -> 0 | M81: =IFERROR((J81/K81-1),"N/A") -> 0 | O81: =E81 -> 426366.76 | P81: ='Dispatch Monthly Func P&L'!$BM80 -> 426366.76 | Q81: =O81-P81 -> 0 | R81: =IFERROR((O81/P81-1),"N/A") -> 0
C82: Total - EBITDA Addbacks | E82: ='Dispatch Monthly Func P&L'!Q81 -> 997949.27 | F82: =INDEX('Dispatch Monthly Func P&L'!$AI81:$AT81,MATCH(EOMONTH(Inputs!$C$2,0),'Dispatch Monthly Func P&L'!$AI$5:$AT$5,0)) -> 998659.94 | G82: =IFERROR(E82-F82,"N/A") -> -710.67017 | H82: =IFERROR((E82/F82-1),"N/A") -> -0.00071162378 | J82: ='Dispatch Monthly Func P&L'!X81 -> 12194493 | K82: ='Dispatch Monthly Func P&L'!AV81 -> 11857678 | L82: =IFERROR(J82-K82,"N/A") -> 336815.16 | M82: =IFERROR((J82/K82-1),"N/A") -> 0.028404816 | O82: =E82 -> 997949.27 | P82: ='Dispatch Monthly Func P&L'!$BM81 -> 1491313.5 | Q82: =O82-P82 -> -493364.24 | R82: =IFERROR((O82/P82-1),"N/A") -> -0.3308253 | U82: =SUM(E70:E81)-E82 -> 0 | V82: =SUM(F70:F81)-F82 -> 0 | X82: =SUM(J70:J81)-J82 -> 0 | Y82: =SUM(K70:K81)-K82 -> 0 | AA82: =SUM(O70:O81)-O82 -> 0 | AB82: =SUM(P70:P81)-P82 -> 0
F83: =INDEX('Dispatch Monthly Func P&L'!$AI82:$AT82,MATCH(EOMONTH(Inputs!$C$2,0),'Dispatch Monthly Func P&L'!$AI$5:$AT$5,0)) -> 0
C84: EBITDA | E84: ='Dispatch Monthly Func P&L'!Q83 -> 246778.48 | F84: =INDEX('Dispatch Monthly Func P&L'!$AI83:$AT83,MATCH(EOMONTH(Inputs!$C$2,0),'Dispatch Monthly Func P&L'!$AI$5:$AT$5,0)) -> 98053.145 | G84: =IFERROR(E84-F84,"N/A") -> 148725.34 | H84: =IFERROR((E84/F84-1),"N/A") -> 1.5167829 | J84: ='Dispatch Monthly Func P&L'!X83 -> 1037206 | K84: ='Dispatch Monthly Func P&L'!AV83 -> -581586.27 | L84: =IFERROR(J84-K84,"N/A") -> 1618792.3 | M84: =IFERROR((J84/K84-1),"N/A") -> -2.7834087 | O84: =E84 -> 246778.48 | P84: ='Dispatch Monthly Func P&L'!$BM83 -> 11013.611 | Q84: =O84-P84 -> 235764.87 | R84: =IFERROR((O84/P84-1),"N/A") -> 21.406682 | U84: =E66+E82-E84 -> 0 | V84: =F66+F82-F84 -> 0 | X84: =J66+J82-J84 -> 0 | Y84: =K66+K82-K84 -> -2.6775524e-09 | AA84: =O66+O82-O84 -> 0 | AB84: =P66+P82-P84 -> 0
C85: EBITDA Margin % | E85: ='Dispatch Monthly Func P&L'!Q84 -> 0.21505453 | F85: =INDEX('Dispatch Monthly Func P&L'!$AI84:$AT84,MATCH(EOMONTH(Inputs!$C$2,0),'Dispatch Monthly Func P&L'!$AI$5:$AT$5,0)) -> 0.079769134 | G85: =IFERROR(E85-F85,"N/A") -> 0.1352854 | J85: ='Dispatch Monthly Func P&L'!X84 -> 0.075832999 | K85: ='Dispatch Monthly Func P&L'!AV84 -> -0.042794912 | L85: =IFERROR(J85-K85,"N/A") -> 0.11862791 | O85: =E85 -> 0.21505453 | P85: ='Dispatch Monthly Func P&L'!$BM84 -> 0.0099886912 | U85: =E84/E16-E85 -> 0 | V85: =F84/F16-F85 -> 0 | X85: =J84/J16-J85 -> 0 | Y85: =K84/K16-K85 -> 0 | AA85: =O84/O16-O85 -> 0 | AB85: =P84/P16-P85 -> 0
C86: EBITDA Check (F-N) | E86: =E84-'2a. Dispatch Natural P&L'!E94 -> 0.01097497 | F86: =F84-'2a. Dispatch Natural P&L'!F94 -> -2.3283064e-10 | J86: =J84-'2a. Dispatch Natural P&L'!J94 -> 0.13169964 | K86: ='Dispatch Monthly Func P&L'!AV85 -> -3.4924597e-10 | O86: =E86 -> 0.01097497 | P86: =P84-'2a. Dispatch Natural P&L'!P94 -> 0.01097497
C88: Capitalized Software Costs | E88: ='Dispatch Monthly Func P&L'!Q87 -> 0 | F88: =INDEX('Dispatch Monthly Func P&L'!$AI87:$AT87,MATCH(EOMONTH(Inputs!$C$2,0),'Dispatch Monthly Func P&L'!$AI$5:$AT$5,0)) -> 0 | G88: =IFERROR(E88-F88,"N/A") -> 0 | H88: =IFERROR((E88/F88-1),"N/A") -> N/A | J88: ='Dispatch Monthly Func P&L'!X87 -> 0 | K88: ='Dispatch Monthly Func P&L'!AV87 -> 0 | L88: =IFERROR(J88-K88,"N/A") -> 0 | M88: =IFERROR((J88/K88-1),"N/A") -> N/A | O88: =E88 -> 0 | P88: ='Dispatch Monthly Func P&L'!$BM87 -> 0 | Q88: =O88-P88 -> 0 | R88: =IFERROR((O88/P88-1),"N/A") -> N/A
C90: EBITDAC | E90: ='Dispatch Monthly Func P&L'!Q89 -> 246778.48 | F90: =INDEX('Dispatch Monthly Func P&L'!$AI89:$AT89,MATCH(EOMONTH(Inputs!$C$2,0),'Dispatch Monthly Func P&L'!$AI$5:$AT$5,0)) -> 98053.145 | G90: =IFERROR(E90-F90,"N/A") -> 148725.34 | H90: =IFERROR((E90/F90-1),"N/A") -> 1.5167829 | J90: ='Dispatch Monthly Func P&L'!X89 -> 1037206 | K90: ='Dispatch Monthly Func P&L'!AV89 -> -581586.27 | L90: =IFERROR(J90-K90,"N/A") -> 1618792.3 | M90: =IFERROR((J90/K90-1),"N/A") -> -2.7834087 | O90: =E90 -> 246778.48 | P90: ='Dispatch Monthly Func P&L'!$BM89 -> 11013.611 | Q90: =O90-P90 -> 235764.87 | R90: =IFERROR((O90/P90-1),"N/A") -> 21.406682 | U90: =E84-E88-E90 -> 0 | V90: =F84-F88-F90 -> 0 | X90: =J84-J88-J90 -> 0 | Y90: =K84-K88-K90 -> 0 | AA90: =O84-O88-O90 -> 0 | AB90: =P84-P88-P90 -> 0
C91: EBITDAC Margin % | E91: ='Dispatch Monthly Func P&L'!Q90 -> 0.21505453 | F91: =INDEX('Dispatch Monthly Func P&L'!$AI90:$AT90,MATCH(EOMONTH(Inputs!$C$2,0),'Dispatch Monthly Func P&L'!$AI$5:$AT$5,0)) -> 0.079769134 | G91: =IFERROR(E91-F91,"N/A") -> 0.1352854 | J91: ='Dispatch Monthly Func P&L'!X90 -> 0.075832999 | K91: ='Dispatch Monthly Func P&L'!AV90 -> -0.042794912 | L91: =IFERROR(J91-K91,"N/A") -> 0.11862791 | O91: =E91 -> 0.21505453 | P91: ='Dispatch Monthly Func P&L'!$BM90 -> 0.0099886912 | Q91: =O91-P91 -> 0.20506584 | U91: =E90/E16-E91 -> 0 | V91: =F90/F16-F91 -> 0 | X91: =J90/J16-J91 -> 0 | Y91: =K90/K16-K91 -> 0 | AA91: =O90/O16-O91 -> 0 | AB91: =P90/P16-P91 -> 0
C93: Compensation by Function
C94: COS Compensation | E94: ='Dispatch Monthly Func P&L'!Q93 -> 130893.01 | F94: =INDEX('Dispatch Monthly Func P&L'!$AI93:$AT93,MATCH(EOMONTH(Inputs!$C$2,0),'Dispatch Monthly Func P&L'!$AI$5:$AT$5,0)) -> 117046.9 | G94: =IFERROR(E94-F94,"N/A") -> 13846.108 | H94: =IFERROR((E94/F94-1),"N/A") -> 0.11829539 | J94: ='Dispatch Monthly Func P&L'!X93 -> 1513600.3 | K94: ='Dispatch Monthly Func P&L'!AV93 -> 1422848.4 | L94: =IFERROR(J94-K94,"N/A") -> 90751.917 | M94: =IFERROR((J94/K94-1),"N/A") -> 0.063781861 | O94: =E94 -> 130893.01 | P94: ='Dispatch Monthly Func P&L'!$BM93 -> 119315.87 | Q94: =O94-P94 -> 11577.14 | R94: =IFERROR((O94/P94-1),"N/A") -> 0.097029339
C95: Product & Engineering Compensation | E95: ='Dispatch Monthly Func P&L'!Q94 -> 272957.94 | F95: =INDEX('Dispatch Monthly Func P&L'!$AI94:$AT94,MATCH(EOMONTH(Inputs!$C$2,0),'Dispatch Monthly Func P&L'!$AI$5:$AT$5,0)) -> 354975.69 | G95: =IFERROR(E95-F95,"N/A") -> -82017.752 | H95: =IFERROR((E95/F95-1),"N/A") -> -0.23105174 | J95: ='Dispatch Monthly Func P&L'!X94 -> 3883909.8 | K95: ='Dispatch Monthly Func P&L'!AV94 -> 4453378.4 | L95: =IFERROR(J95-K95,"N/A") -> -569468.61 | M95: =IFERROR((J95/K95-1),"N/A") -> -0.12787339 | O95: =E95 -> 272957.94 | P95: ='Dispatch Monthly Func P&L'!$BM94 -> 370356.99 | Q95: =O95-P95 -> -97399.05 | R95: =IFERROR((O95/P95-1),"N/A") -> -0.26298694
C96: General & Administrative Compensation | E96: ='Dispatch Monthly Func P&L'!Q95 -> 129241.79 | F96: =INDEX('Dispatch Monthly Func P&L'!$AI95:$AT95,MATCH(EOMONTH(Inputs!$C$2,0),'Dispatch Monthly Func P&L'!$AI$5:$AT$5,0)) -> 139396.26 | G96: =IFERROR(E96-F96,"N/A") -> -10154.466 | H96: =IFERROR((E96/F96-1),"N/A") -> -0.072846045 | J96: ='Dispatch Monthly Func P&L'!X95 -> 1563736.8 | K96: ='Dispatch Monthly Func P&L'!AV95 -> 1685604.1 | L96: =IFERROR(J96-K96,"N/A") -> -121867.3 | M96: =IFERROR((J96/K96-1),"N/A") -> -0.07229889 | O96: =E96 -> 129241.79 | P96: ='Dispatch Monthly Func P&L'!$BM95 -> 130260.69 | Q96: =O96-P96 -> -1018.9 | R96: =IFERROR((O96/P96-1),"N/A") -> -0.0078220068
C97: Sales Compensation | E97: ='Dispatch Monthly Func P&L'!Q96 -> 151260.26 | F97: =INDEX('Dispatch Monthly Func P&L'!$AI96:$AT96,MATCH(EOMONTH(Inputs!$C$2,0),'Dispatch Monthly Func P&L'!$AI$5:$AT$5,0)) -> 209831.36 | G97: =IFERROR(E97-F97,"N/A") -> -58571.101 | H97: =IFERROR((E97/F97-1),"N/A") -> -0.27913416 | J97: ='Dispatch Monthly Func P&L'!X96 -> 1990872.8 | K97: ='Dispatch Monthly Func P&L'!AV96 -> 2602457.1 | L97: =IFERROR(J97-K97,"N/A") -> -611584.29 | M97: =IFERROR((J97/K97-1),"N/A") -> -0.23500264 | O97: =E97 -> 151260.26 | P97: ='Dispatch Monthly Func P&L'!$BM96 -> 202013.36 | Q97: =O97-P97 -> -50753.1 | R97: =IFERROR((O97/P97-1),"N/A") -> -0.25123635
C98: Marketing Compensation | E98: ='Dispatch Monthly Func P&L'!Q97 -> 29576.96 | F98: =INDEX('Dispatch Monthly Func P&L'!$AI97:$AT97,MATCH(EOMONTH(Inputs!$C$2,0),'Dispatch Monthly Func P&L'!$AI$5:$AT$5,0)) -> 30011.053 | G98: =IFERROR(E98-F98,"N/A") -> -434.09253 | H98: =IFERROR((E98/F98-1),"N/A") -> -0.014464422 | J98: ='Dispatch Monthly Func P&L'!X97 -> 368060.06 | K98: ='Dispatch Monthly Func P&L'!AV97 -> 391946.14 | L98: =IFERROR(J98-K98,"N/A") -> -23886.077 | M98: =IFERROR((J98/K98-1),"N/A") -> -0.060942243 | O98: =E98 -> 29576.96 | P98: ='Dispatch Monthly Func P&L'!$BM97 -> 37014.25 | Q98: =O98-P98 -> -7437.29 | R98: =IFERROR((O98/P98-1),"N/A") -> -0.20093045
C99: Payroll Fees | E99: ='Dispatch Monthly Func P&L'!Q98 -> 3432.73 | F99: =INDEX('Dispatch Monthly Func P&L'!$AI98:$AT98,MATCH(EOMONTH(Inputs!$C$2,0),'Dispatch Monthly Func P&L'!$AI$5:$AT$5,0)) -> 3465 | G99: =IFERROR(E99-F99,"N/A") -> -32.27 | H99: =IFERROR((E99/F99-1),"N/A") -> -0.0093131313 | J99: ='Dispatch Monthly Func P&L'!X98 -> 40748.57 | K99: ='Dispatch Monthly Func P&L'!AV98 -> 42732 | L99: =IFERROR(J99-K99,"N/A") -> -1983.43 | M99: =IFERROR((J99/K99-1),"N/A") -> -0.046415567 | O99: =E99 -> 3432.73 | P99: ='Dispatch Monthly Func P&L'!$BM98 -> 3298.57 | Q99: =O99-P99 -> 134.16 | R99: =IFERROR((O99/P99-1),"N/A") -> 0.04067217
C100: Total - Compensation | E100: ='Dispatch Monthly Func P&L'!Q99 -> 717362.69 | F100: =INDEX('Dispatch Monthly Func P&L'!$AI99:$AT99,MATCH(EOMONTH(Inputs!$C$2,0),'Dispatch Monthly Func P&L'!$AI$5:$AT$5,0)) -> 854726.26 | G100: =IFERROR(E100-F100,"N/A") -> -137363.57 | H100: =IFERROR((E100/F100-1),"N/A") -> -0.1607106 | J100: ='Dispatch Monthly Func P&L'!X99 -> 9360928.3 | K100: ='Dispatch Monthly Func P&L'!AV99 -> 10598966 | L100: =IFERROR(J100-K100,"N/A") -> -1238037.8 | M100: =IFERROR((J100/K100-1),"N/A") -> -0.11680741 | O100: =E100 -> 717362.69 | P100: ='Dispatch Monthly Func P&L'!$BM99 -> 862259.73 | Q100: =O100-P100 -> -144897.04 | R100: =IFERROR((O100/P100-1),"N/A") -> -0.16804338 | U100: =SUM(E94:E99)-E100 -> 0 | V100: =SUM(F94:F99)-F100 -> 0 | X100: =SUM(J94:J99)-J100 -> 0 | Y100: =SUM(K94:K99)-K100 -> 0 | AA100: =SUM(O94:O99)-O100 -> 0 | AB100: =SUM(P94:P99)-P100 -> 0
E103: =E100-'Dispatch Monthly Func P&L'!$Q99 -> 0 | J103: =J100-'Dispatch Monthly Func P&L'!$X99 -> 0 | P103: =P100-'Dispatch Monthly Func P&L'!$BM99 -> 0

Sheet 1b. Youreka Functional P&L
C1: Youreka | Monthly Profit & Loss (Functional View)
E4: Current Month | J4: Year-to-Date | O4: Year-over-Year
U5: Current Month | X5: YTD | AA5: YoY
C6: Revenue | E6: =Inputs!C2 -> 46022 | F6: Budget | G6: Difference | H6: % Difference | J6: =E6 -> 46022 | K6: Budget | L6: Difference | M6: % Difference | O6: =J6 -> 46022 | P6: =EOMONTH(E6,-12) -> 45657 | Q6: Difference | R6: % Difference | U6: Checks | X6: Checks | AA6: Checks
C7: Recurring Revenue
C8: Recurring Enterprise License Revenue | E8: ='Youreka Monthly Func P&L'!Q7 -> 861057.99 | F8: =INDEX('Youreka Monthly Func P&L'!$AI7:$AT7,MATCH(EOMONTH(Inputs!$C$2,0),'Youreka Monthly Func P&L'!$AI$5:$AT$5,0)) -> 961921.24 | G8: =IFERROR(E8-F8,"N/A") -> -100863.25 | H8: =IFERROR((E8/F8-1),"N/A") -> -0.10485604 | J8: ='Youreka Monthly Func P&L'!X7 -> 10181920 | K8: ='Youreka Monthly Func P&L'!AV7 -> 10945484 | L8: =IFERROR(J8-K8,"N/A") -> -763563.38 | M8: =IFERROR((J8/K8-1),"N/A") -> -0.069760588 | O8: =E8 -> 861057.99 | P8: ='Youreka Monthly Func P&L'!$BM7 -> 757665 | Q8: =O8-P8 -> 103392.99 | R8: =IFERROR((O8/P8-1),"N/A") -> 0.13646267
C9: Recurring Services Revenue | E9: ='Youreka Monthly Func P&L'!Q8 -> 132806.87 | F9: =INDEX('Youreka Monthly Func P&L'!$AI8:$AT8,MATCH(EOMONTH(Inputs!$C$2,0),'Youreka Monthly Func P&L'!$AI$5:$AT$5,0)) -> 118739.5 | G9: =IFERROR(E9-F9,"N/A") -> 14067.368 | H9: =IFERROR((E9/F9-1),"N/A") -> 0.11847252 | J9: ='Youreka Monthly Func P&L'!X8 -> 1534400.6 | K9: ='Youreka Monthly Func P&L'!AV8 -> 1423624 | L9: =IFERROR(J9-K9,"N/A") -> 110776.62 | M9: =IFERROR((J9/K9-1),"N/A") -> 0.077813115 | O9: =E9 -> 132806.87 | P9: ='Youreka Monthly Func P&L'!$BM8 -> 107438.75 | Q9: =O9-P9 -> 25368.12 | R9: =IFERROR((O9/P9-1),"N/A") -> 0.23611704
C10: Recurring Service Provider (SMB) Revenue | E10: ='Youreka Monthly Func P&L'!Q9 -> 0 | F10: =INDEX('Youreka Monthly Func P&L'!$AI9:$AT9,MATCH(EOMONTH(Inputs!$C$2,0),'Youreka Monthly Func P&L'!$AI$5:$AT$5,0)) -> 0 | G10: =IFERROR(E10-F10,"N/A") -> 0 | H10: =IFERROR((E10/F10-1),"N/A") -> N/A | J10: ='Youreka Monthly Func P&L'!X9 -> 0 | K10: ='Youreka Monthly Func P&L'!AV9 -> 0 | L10: =IFERROR(J10-K10,"N/A") -> 0 | M10: =IFERROR((J10/K10-1),"N/A") -> N/A | O10: =E10 -> 0 | P10: ='Youreka Monthly Func P&L'!$BM9 -> 0 | Q10: =O10-P10 -> 0 | R10: =IFERROR((O10/P10-1),"N/A") -> N/A
C11: Total Recurring Revenue | E11: ='Youreka Monthly Func P&L'!Q10 -> 993864.86 | F11: =INDEX('Youreka Monthly Func P&L'!$AI10:$AT10,MATCH(EOMONTH(Inputs!$C$2,0),'Youreka Monthly Func P&L'!$AI$5:$AT$5,0)) -> 1080660.7 | G11: =IFERROR(E11-F11,"N/A") -> -86795.881 | H11: =IFERROR((E11/F11-1),"N/A") -> -0.080317418 | J11: ='Youreka Monthly Func P&L'!X10 -> 11716321 | K11: ='Youreka Monthly Func P&L'!AV10 -> 12369108 | L11: =IFERROR(J11-K11,"N/A") -> -652786.76 | M11: =IFERROR((J11/K11-1),"N/A") -> -0.052775574 | O11: =E11 -> 993864.86 | P11: ='Youreka Monthly Func P&L'!$BM10 -> 865103.75 | Q11: =O11-P11 -> 128761.11 | R11: =IFERROR((O11/P11-1),"N/A") -> 0.14883892 | U11: =SUM(E8:E10)-E11 -> 0 | V11: =SUM(F8:F10)-F11 -> 0 | X11: =SUM(J8:J10)-J11 -> 0 | Y11: =SUM(K8:K10)-K11 -> 0 | AA11: =SUM(O8:O10)-O11 -> 0 | AB11: =SUM(P8:P10)-P11 -> 0
C12: Non-Recurring Revenue
C13: Non-Recurring Professional Services Revenue | E13: ='Youreka Monthly Func P&L'!Q12 -> 22500 | F13: =INDEX('Youreka Monthly Func P&L'!$AI12:$AT12,MATCH(EOMONTH(Inputs!$C$2,0),'Youreka Monthly Func P&L'!$AI$5:$AT$5,0)) -> 10583.333 | G13: =IFERROR(E13-F13,"N/A") -> 11916.667 | H13: =IFERROR((E13/F13-1),"N/A") -> 1.1259843 | J13: ='Youreka Monthly Func P&L'!X12 -> 292269.96 | K13: ='Youreka Monthly Func P&L'!AV12 -> 256375 | L13: =IFERROR(J13-K13,"N/A") -> 35894.96 | M13: =IFERROR((J13/K13-1),"N/A") -> 0.1400096 | O13: =E13 -> 22500 | P13: ='Youreka Monthly Func P&L'!$BM12 -> 37019.05 | Q13: =O13-P13 -> -14519.05 | R13: =IFERROR((O13/P13-1),"N/A") -> -0.39220482
C14: Other Non-Recurring Revenue | E14: ='Youreka Monthly Func P&L'!Q13 -> 0 | F14: =INDEX('Youreka Monthly Func P&L'!$AI13:$AT13,MATCH(EOMONTH(Inputs!$C$2,0),'Youreka Monthly Func P&L'!$AI$5:$AT$5,0)) -> 0 | G14: =IFERROR(E14-F14,"N/A") -> 0 | H14: =IFERROR((E14/F14-1),"N/A") -> N/A | J14: ='Youreka Monthly Func P&L'!X13 -> 0 | K14: ='Youreka Monthly Func P&L'!AV13 -> 0 | L14: =IFERROR(J14-K14,"N/A") -> 0 | M14: =IFERROR((J14/K14-1),"N/A") -> N/A | O14: =E14 -> 0 | P14: ='Youreka Monthly Func P&L'!$BM13 -> 0 | Q14: =O14-P14 -> 0 | R14: =IFERROR((O14/P14-1),"N/A") -> N/A
C15: Total Non-Recurring Revenue | E15: ='Youreka Monthly Func P&L'!Q14 -> 22500 | F15: =INDEX('Youreka Monthly Func P&L'!$AI14:$AT14,MATCH(EOMONTH(Inputs!$C$2,0),'Youreka Monthly Func P&L'!$AI$5:$AT$5,0)) -> 10583.333 | G15: =IFERROR(E15-F15,"N/A") -> 11916.667 | H15: =IFERROR((E15/F15-1),"N/A") -> 1.1259843 | J15: ='Youreka Monthly Func P&L'!X14 -> 292269.96 | K15: ='Youreka Monthly Func P&L'!AV14 -> 256375 | L15: =IFERROR(J15-K15,"N/A") -> 35894.96 | M15: =IFERROR((J15/K15-1),"N/A") -> 0.1400096 | O15: =E15 -> 22500 | P15: ='Youreka Monthly Func P&L'!$BM14 -> 37019.05 | Q15: =O15-P15 -> -14519.05 | R15: =IFERROR((O15/P15-1),"N/A") -> -0.39220482 | U15: =SUM(E13:E14)-E15 -> 0 | V15: =SUM(F13:F14)-F15 -> 0 | X15: =SUM(J13:J14)-J15 -> 0 | Y15: =SUM(K13:K14)-K15 -> 0 | AA15: =SUM(O13:O14)-O15 -> 0 | AB15: =SUM(P13:P14)-P15 -> 0
C16: Total Revenue | E16: ='Youreka Monthly Func P&L'!Q15 -> 1016364.9 | F16: =INDEX('Youreka Monthly Func P&L'!$AI15:$AT15,MATCH(EOMONTH(Inputs!$C$2,0),'Youreka Monthly Func P&L'!$AI$5:$AT$5,0)) -> 1091244.1 | G16: =IFERROR(E16-F16,"N/A") -> -74879.214 | H16: =IFERROR((E16/F16-1),"N/A") -> -0.068618209 | J16: ='Youreka Monthly Func P&L'!X15 -> 12008591 | K16: ='Youreka Monthly Func P&L'!AV15 -> 12625483 | L16: =IFERROR(J16-K16,"N/A") -> -616891.8 | M16: =IFERROR((J16/K16-1),"N/A") -> -0.048860849 | O16: =E16 -> 1016364.9 | P16: ='Youreka Monthly Func P&L'!$BM15 -> 902122.8 | Q16: =O16-P16 -> 114242.06 | R16: =IFERROR((O16/P16-1),"N/A") -> 0.12663693 | U16: =E11+E15-E16 -> 0 | V16: =F11+F15-F16 -> 0 | X16: =J11+J15-J16 -> 0 | Y16: =K11+K15-K16 -> 0 | AA16: =O11+O15-O16 -> 0 | AB16: =P11+P15-P16 -> 0
C17: % Reccurring Revenue | E17: ='Youreka Monthly Func P&L'!Q16 -> 0.97786228 | F17: =INDEX('Youreka Monthly Func P&L'!$AI16:$AT16,MATCH(EOMONTH(Inputs!$C$2,0),'Youreka Monthly Func P&L'!$AI$5:$AT$5,0)) -> 0.99030159 | G17: =IFERROR(E17-F17,"N/A") -> -0.012439309 | J17: ='Youreka Monthly Func P&L'!X16 -> 0.97566159 | K17: ='Youreka Monthly Func P&L'!AV16 -> 0.97969385 | L17: =IFERROR(J17-K17,"N/A") -> -0.0040322516 | O17: =E17 -> 0.97786228 | P17: ='Youreka Monthly Func P&L'!$BM16 -> 0.95896451 | Q17: =O17-P17 -> 0.018897769 | U17: =E11/E16-E17 -> 0 | V17: =F11/F16-F17 -> 0 | X17: =J11/J16-J17 -> 0 | Y17: =K11/K16-K17 -> 0 | AA17: =O11/O16-O17 -> 0 | AB17: =P11/P16-P17 -> 0
C19: Recurring Cost of Sales - Functional
C20: Cost of Sales (Functional) - Direct Compensation (R) | E20: ='Youreka Monthly Func P&L'!Q19 -> 61698.83 | F20: =INDEX('Youreka Monthly Func P&L'!$AI19:$AT19,MATCH(EOMONTH(Inputs!$C$2,0),'Youreka Monthly Func P&L'!$AI$5:$AT$5,0)) -> 63208.06 | G20: =IFERROR(E20-F20,"N/A") -> -1509.2298 | H20: =IFERROR((E20/F20-1),"N/A") -> -0.023877173 | J20: ='Youreka Monthly Func P&L'!X19 -> 756630.63 | K20: ='Youreka Monthly Func P&L'!AV19 -> 755545.42 | L20: =IFERROR(J20-K20,"N/A") -> 1085.2061 | M20: =IFERROR((J20/K20-1),"N/A") -> 0.0014363215 | O20: =E20 -> 61698.83 | P20: ='Youreka Monthly Func P&L'!$BM19 -> 60512.42 | Q20: =O20-P20 -> 1186.41 | R20: =IFERROR((O20/P20-1),"N/A") -> 0.019606058
C21: Cost of Sales (Functional) - Hosting & Infrastructure | E21: ='Youreka Monthly Func P&L'!Q20 -> 128354.55 | F21: =INDEX('Youreka Monthly Func P&L'!$AI20:$AT20,MATCH(EOMONTH(Inputs!$C$2,0),'Youreka Monthly Func P&L'!$AI$5:$AT$5,0)) -> 138755.85 | G21: =IFERROR(E21-F21,"N/A") -> -10401.296 | H21: =IFERROR((E21/F21-1),"N/A") -> -0.074961134 | J21: ='Youreka Monthly Func P&L'!X20 -> 1485649.6 | K21: ='Youreka Monthly Func P&L'!AV20 -> 1575724.1 | L21: =IFERROR(J21-K21,"N/A") -> -90074.449 | M21: =IFERROR((J21/K21-1),"N/A") -> -0.057163847 | O21: =E21 -> 128354.55 | P21: ='Youreka Monthly Func P&L'!$BM20 -> 119853.83 | Q21: =O21-P21 -> 8500.72 | R21: =IFERROR((O21/P21-1),"N/A") -> 0.070925727
C22: Cost of Sales (Functional) - Software & Subscriptions | E22: ='Youreka Monthly Func P&L'!Q21 -> 11647 | F22: =INDEX('Youreka Monthly Func P&L'!$AI21:$AT21,MATCH(EOMONTH(Inputs!$C$2,0),'Youreka Monthly Func P&L'!$AI$5:$AT$5,0)) -> 13205.5 | G22: =IFERROR(E22-F22,"N/A") -> -1558.5 | H22: =IFERROR((E22/F22-1),"N/A") -> -0.11801901 | J22: ='Youreka Monthly Func P&L'!X21 -> 151547.53 | K22: ='Youreka Monthly Func P&L'!AV21 -> 158466 | L22: =IFERROR(J22-K22,"N/A") -> -6918.47 | M22: =IFERROR((J22/K22-1),"N/A") -> -0.043659018 | O22: =E22 -> 11647 | P22: ='Youreka Monthly Func P&L'!$BM21 -> 13205.05 | Q22: =O22-P22 -> -1558.05 | R22: =IFERROR((O22/P22-1),"N/A") -> -0.11798895
C23: Total Recurring Cost of Sales - Functional | E23: ='Youreka Monthly Func P&L'!Q22 -> 201700.38 | F23: =INDEX('Youreka Monthly Func P&L'!$AI22:$AT22,MATCH(EOMONTH(Inputs!$C$2,0),'Youreka Monthly Func P&L'!$AI$5:$AT$5,0)) -> 215169.41 | G23: =IFERROR(E23-F23,"N/A") -> -13469.025 | H23: =IFERROR((E23/F23-1),"N/A") -> -0.062597307 | J23: ='Youreka Monthly Func P&L'!X22 -> 2393827.8 | K23: ='Youreka Monthly Func P&L'!AV22 -> 2489735.5 | L23: =IFERROR(J23-K23,"N/A") -> -95907.713 | M23: =IFERROR((J23/K23-1),"N/A") -> -0.038521246 | O23: =E23 -> 201700.38 | P23: ='Youreka Monthly Func P&L'!$BM22 -> 193571.3 | Q23: =O23-P23 -> 8129.08 | R23: =IFERROR((O23/P23-1),"N/A") -> 0.041995275 | U23: =SUM(E20:E22)-E23 -> 0 | V23: =SUM(F20:F22)-F23 -> 0 | X23: =SUM(J20:J22)-J23 -> 0 | Y23: =SUM(K20:K22)-K23 -> 0 | AA23: =SUM(O20:O22)-O23 -> 0 | AB23: =SUM(P20:P22)-P23 -> 0
C24: Non-recurring Cost of Sales - Functional
C25: Cost of Sales (Functional) - Consultants & Contractors | E25: ='Youreka Monthly Func P&L'!Q24 -> 10632.75 | F25: =INDEX('Youreka Monthly Func P&L'!$AI24:$AT24,MATCH(EOMONTH(Inputs!$C$2,0),'Youreka Monthly Func P&L'!$AI$5:$AT$5,0)) -> 0 | G25: =IFERROR(E25-F25,"N/A") -> 10632.75 | H25: =IFERROR((E25/F25-1),"N/A") -> N/A | J25: ='Youreka Monthly Func P&L'!X24 -> 51263.75 | K25: ='Youreka Monthly Func P&L'!AV24 -> 0 | L25: =IFERROR(J25-K25,"N/A") -> 51263.75 | M25: =IFERROR((J25/K25-1),"N/A") -> N/A | O25: =E25 -> 10632.75 | P25: ='Youreka Monthly Func P&L'!$BM24 -> 0 | Q25: =O25-P25 -> 10632.75 | R25: =IFERROR((O25/P25-1),"N/A") -> N/A
C26: Cost of Sales (Functional) - Direct Compensation (NR) | E26: ='Youreka Monthly Func P&L'!Q25 -> 40902.79 | F26: =INDEX('Youreka Monthly Func P&L'!$AI25:$AT25,MATCH(EOMONTH(Inputs!$C$2,0),'Youreka Monthly Func P&L'!$AI$5:$AT$5,0)) -> 41173.085 | G26: =IFERROR(E26-F26,"N/A") -> -270.29487 | H26: =IFERROR((E26/F26-1),"N/A") -> -0.0065648437 | J26: ='Youreka Monthly Func P&L'!X25 -> 497386.27 | K26: ='Youreka Monthly Func P&L'!AV25 -> 489159.1 | L26: =IFERROR(J26-K26,"N/A") -> 8227.1661 | M26: =IFERROR((J26/K26-1),"N/A") -> 0.016818998 | O26: =E26 -> 40902.79 | P26: ='Youreka Monthly Func P&L'!$BM25 -> 38945.33 | Q26: =O26-P26 -> 1957.46 | R26: =IFERROR((O26/P26-1),"N/A") -> 0.050261739
C27: Total Non-recurring Cost of Sales - Functional | E27: ='Youreka Monthly Func P&L'!Q26 -> 51535.54 | F27: =INDEX('Youreka Monthly Func P&L'!$AI26:$AT26,MATCH(EOMONTH(Inputs!$C$2,0),'Youreka Monthly Func P&L'!$AI$5:$AT$5,0)) -> 41173.085 | G27: =IFERROR(E27-F27,"N/A") -> 10362.455 | H27: =IFERROR((E27/F27-1),"N/A") -> 0.25168032 | J27: ='Youreka Monthly Func P&L'!X26 -> 548650.02 | K27: ='Youreka Monthly Func P&L'!AV26 -> 489159.1 | L27: =IFERROR(J27-K27,"N/A") -> 59490.916 | M27: =IFERROR((J27/K27-1),"N/A") -> 0.12161874 | O27: =E27 -> 51535.54 | P27: ='Youreka Monthly Func P&L'!$BM26 -> 38945.33 | Q27: =O27-P27 -> 12590.21 | R27: =IFERROR((O27/P27-1),"N/A") -> 0.32327907 | U27: =E27-E26 -> 10632.75 | V27: =F27-F26 -> 0 | X27: =J27-J26 -> 51263.75 | Y27: =K27-K26 -> 0 | AA27: =O27-O26 -> 10632.75 | AB27: =P27-P26 -> 0
C28: Total Cost of Sales - Functional | E28: ='Youreka Monthly Func P&L'!Q27 -> 253235.92 | F28: =INDEX('Youreka Monthly Func P&L'!$AI27:$AT27,MATCH(EOMONTH(Inputs!$C$2,0),'Youreka Monthly Func P&L'!$AI$5:$AT$5,0)) -> 256342.49 | G28: =IFERROR(E28-F28,"N/A") -> -3106.5702 | H28: =IFERROR((E28/F28-1),"N/A") -> -0.012118827 | J28: ='Youreka Monthly Func P&L'!X27 -> 2942477.8 | K28: ='Youreka Monthly Func P&L'!AV27 -> 2978894.6 | L28: =IFERROR(J28-K28,"N/A") -> -36416.797 | M28: =IFERROR((J28/K28-1),"N/A") -> -0.012224936 | O28: =E28 -> 253235.92 | P28: ='Youreka Monthly Func P&L'!$BM27 -> 232516.63 | Q28: =O28-P28 -> 20719.29 | R28: =IFERROR((O28/P28-1),"N/A") -> 0.089108852 | U28: =E28-E27-E23 -> 0 | V28: =F28-F27-F23 -> 0 | X28: =J28-J27-J23 -> 0 | Y28: =K28-K27-K23 -> 0 | AA28: =O28-O27-O23 -> 0 | AB28: =P28-P27-P23 -> 0
C29: Gross Profit - Functional
C30: Recurring Gross Profit - Functional | E30: ='Youreka Monthly Func P&L'!Q29 -> 792164.48 | F30: =INDEX('Youreka Monthly Func P&L'!$AI29:$AT29,MATCH(EOMONTH(Inputs!$C$2,0),'Youreka Monthly Func P&L'!$AI$5:$AT$5,0)) -> 865491.34 | G30: =IFERROR(E30-F30,"N/A") -> -73326.855 | H30: =IFERROR((E30/F30-1),"N/A") -> -0.084722807 | J30: ='Youreka Monthly Func P&L'!X29 -> 9322493.3 | K30: ='Youreka Monthly Func P&L'!AV29 -> 9879372.3 | L30: =IFERROR(J30-K30,"N/A") -> -556879.05 | M30: =IFERROR((J30/K30-1),"N/A") -> -0.056367857 | O30: =E30 -> 792164.48 | P30: ='Youreka Monthly Func P&L'!$BM29 -> 671532.45 | Q30: =O30-P30 -> 120632.03 | R30: =IFERROR((O30/P30-1),"N/A") -> 0.17963693
C31: Non-recurring Gross Profit - Functional | E31: ='Youreka Monthly Func P&L'!Q30 -> -29035.54 | F31: =INDEX('Youreka Monthly Func P&L'!$AI30:$AT30,MATCH(EOMONTH(Inputs!$C$2,0),'Youreka Monthly Func P&L'!$AI$5:$AT$5,0)) -> -30589.752 | G31: =IFERROR(E31-F31,"N/A") -> 1554.2115 | H31: =IFERROR((E31/F31-1),"N/A") -> -0.050808243 | J31: ='Youreka Monthly Func P&L'!X30 -> -256380.06 | K31: ='Youreka Monthly Func P&L'!AV30 -> -232784.1 | L31: =IFERROR(J31-K31,"N/A") -> -23595.956 | M31: =IFERROR((J31/K31-1),"N/A") -> 0.10136412 | O31: =E31 -> -29035.54 | P31: ='Youreka Monthly Func P&L'!$BM30 -> -1926.28 | Q31: =O31-P31 -> -27109.26 | R31: =IFERROR((O31/P31-1),"N/A") -> 14.073375
C32: Total Gross Profit - Functional | E32: ='Youreka Monthly Func P&L'!Q31 -> 763128.94 | F32: =INDEX('Youreka Monthly Func P&L'!$AI31:$AT31,MATCH(EOMONTH(Inputs!$C$2,0),'Youreka Monthly Func P&L'!$AI$5:$AT$5,0)) -> 834901.58 | G32: =IFERROR(E32-F32,"N/A") -> -71772.644 | H32: =IFERROR((E32/F32-1),"N/A") -> -0.085965394 | J32: ='Youreka Monthly Func P&L'!X31 -> 9066113.2 | K32: ='Youreka Monthly Func P&L'!AV31 -> 9646588.2 | L32: =IFERROR(J32-K32,"N/A") -> -580475.01 | M32: =IFERROR((J32/K32-1),"N/A") -> -0.060174125 | O32: =E32 -> 763128.94 | P32: ='Youreka Monthly Func P&L'!$BM31 -> 669606.17 | Q32: =O32-P32 -> 93522.77 | R32: =IFERROR((O32/P32-1),"N/A") -> 0.13966832 | U32: =E16-E28-E32 -> 0 | V32: =F16-F28-F32 -> 0 | X32: =J16-J28-J32 -> 0 | Y32: =K16-K28-K32 -> 0 | AA32: =O16-O28-O32 -> 0 | AB32: =P16-P28-P32 -> 0
C33: Recurring Gross Profit Margin % - Functional | E33: ='Youreka Monthly Func P&L'!Q32 -> 0.79705452 | F33: =INDEX('Youreka Monthly Func P&L'!$AI32:$AT32,MATCH(EOMONTH(Inputs!$C$2,0),'Youreka Monthly Func P&L'!$AI$5:$AT$5,0)) -> 0.80089088 | G33: =IFERROR(E33-F33,"N/A") -> -0.0038363624 | J33: ='Youreka Monthly Func P&L'!X32 -> 0.79568435 | K33: ='Youreka Monthly Func P&L'!AV32 -> 0.79871341 | L33: =IFERROR(J33-K33,"N/A") -> -0.0030290657 | O33: =E33 -> 0.79705452 | P33: ='Youreka Monthly Func P&L'!$BM32 -> 0.77624499 | Q33: =O33-P33 -> 0.020809533
C34: Non-recurring Gross Profit Margin % - Functional | E34: ='Youreka Monthly Func P&L'!Q33 -> -1.2904684 | F34: =INDEX('Youreka Monthly Func P&L'!$AI33:$AT33,MATCH(EOMONTH(Inputs!$C$2,0),'Youreka Monthly Func P&L'!$AI$5:$AT$5,0)) -> -2.8903702 | G34: =IFERROR(E34-F34,"N/A") -> 1.5999018 | J34: ='Youreka Monthly Func P&L'!X33 -> -0.87720291 | K34: ='Youreka Monthly Func P&L'!AV33 -> -0.90798285 | L34: =IFERROR(J34-K34,"N/A") -> 0.030779941 | O34: =E34 -> -1.2904684 | P34: ='Youreka Monthly Func P&L'!$BM33 -> -0.052034831 | Q34: =O34-P34 -> -1.2384336
C35: Total Gross Profit Margin % - Functional | E35: ='Youreka Monthly Func P&L'!Q34 -> 0.75084152 | F35: =INDEX('Youreka Monthly Func P&L'!$AI34:$AT34,MATCH(EOMONTH(Inputs!$C$2,0),'Youreka Monthly Func P&L'!$AI$5:$AT$5,0)) -> 0.76509152 | G35: =IFERROR(E35-F35,"N/A") -> -0.014249993 | J35: ='Youreka Monthly Func P&L'!X34 -> 0.75496894 | K35: ='Youreka Monthly Func P&L'!AV34 -> 0.76405698 | L35: =IFERROR(J35-K35,"N/A") -> -0.0090880371 | O35: =E35 -> 0.75084152 | P35: ='Youreka Monthly Func P&L'!$BM34 -> 0.74225612 | Q35: =O35-P35 -> 0.0085854028 | U35: =E32/E16-E35 -> 0 | V35: =F32/F16-F35 -> 0 | X35: =J32/J16-J35 -> 0 | Y35: =K32/K16-K35 -> 0 | AA35: =O32/O16-O35 -> 0 | AB35: =P32/P16-P35 -> 0
C37: Functional Operating Expenses
C38: Product & Engineering Expense - Functional | E38: ='Youreka Monthly Func P&L'!Q37 -> 146510.32 | F38: =INDEX('Youreka Monthly Func P&L'!$AI37:$AT37,MATCH(EOMONTH(Inputs!$C$2,0),'Youreka Monthly Func P&L'!$AI$5:$AT$5,0)) -> 211091.21 | G38: =IFERROR(E38-F38,"N/A") -> -64580.886 | H38: =IFERROR((E38/F38-1),"N/A") -> -0.30593831 | J38: ='Youreka Monthly Func P&L'!X37 -> 2164058.1 | K38: ='Youreka Monthly Func P&L'!AV37 -> 2567673.9 | L38: =IFERROR(J38-K38,"N/A") -> -403615.7 | M38: =IFERROR((J38/K38-1),"N/A") -> -0.15719119 | O38: =E38 -> 146510.32 | P38: ='Youreka Monthly Func P&L'!$BM37 -> 209813.8 | Q38: =O38-P38 -> -63303.48 | R38: =IFERROR((O38/P38-1),"N/A") -> -0.30171266
C39: General & Administrative Expense - Functional | E39: ='Youreka Monthly Func P&L'!Q38 -> 58148.88 | F39: =INDEX('Youreka Monthly Func P&L'!$AI38:$AT38,MATCH(EOMONTH(Inputs!$C$2,0),'Youreka Monthly Func P&L'!$AI$5:$AT$5,0)) -> 98381.648 | G39: =IFERROR(E39-F39,"N/A") -> -40232.768 | H39: =IFERROR((E39/F39-1),"N/A") -> -0.40894586 | J39: ='Youreka Monthly Func P&L'!X38 -> 947938.15 | K39: ='Youreka Monthly Func P&L'!AV38 -> 1170086.7 | L39: =IFERROR(J39-K39,"N/A") -> -222148.55 | M39: =IFERROR((J39/K39-1),"N/A") -> -0.18985648 | O39: =E39 -> 58148.88 | P39: ='Youreka Monthly Func P&L'!$BM38 -> 75269.43 | Q39: =O39-P39 -> -17120.55 | R39: =IFERROR((O39/P39-1),"N/A") -> -0.22745688
C40: Human Resources - Functional | E40: ='Youreka Monthly Func P&L'!Q39 -> 499.83 | F40: =INDEX('Youreka Monthly Func P&L'!$AI39:$AT39,MATCH(EOMONTH(Inputs!$C$2,0),'Youreka Monthly Func P&L'!$AI$5:$AT$5,0)) -> 2583.3333 | G40: =IFERROR(E40-F40,"N/A") -> -2083.5033 | H40: =IFERROR((E40/F40-1),"N/A") -> -0.80651742 | J40: ='Youreka Monthly Func P&L'!X39 -> 5182.42 | K40: ='Youreka Monthly Func P&L'!AV39 -> 23125 | L40: =IFERROR(J40-K40,"N/A") -> -17942.58 | M40: =IFERROR((J40/K40-1),"N/A") -> -0.77589535 | O40: =E40 -> 499.83 | P40: ='Youreka Monthly Func P&L'!$BM39 -> 989.93 | Q40: =O40-P40 -> -490.1 | R40: =IFERROR((O40/P40-1),"N/A") -> -0.49508551
C41: Sales Expense - Functional | E41: ='Youreka Monthly Func P&L'!Q40 -> 175087.99 | F41: =INDEX('Youreka Monthly Func P&L'!$AI40:$AT40,MATCH(EOMONTH(Inputs!$C$2,0),'Youreka Monthly Func P&L'!$AI$5:$AT$5,0)) -> 214762.44 | G41: =IFERROR(E41-F41,"N/A") -> -39674.453 | H41: =IFERROR((E41/F41-1),"N/A") -> -0.18473646 | J41: ='Youreka Monthly Func P&L'!X40 -> 2398158.9 | K41: ='Youreka Monthly Func P&L'!AV40 -> 2617749.1 | L41: =IFERROR(J41-K41,"N/A") -> -219590.19 | M41: =IFERROR((J41/K41-1),"N/A") -> -0.083885116 | O41: =E41 -> 175087.99 | P41: ='Youreka Monthly Func P&L'!$BM40 -> 210736.13 | Q41: =O41-P41 -> -35648.14 | R41: =IFERROR((O41/P41-1),"N/A") -> -0.16916008
C42: Marketing Expense - Functional | E42: ='Youreka Monthly Func P&L'!Q41 -> 27880.19 | F42: =INDEX('Youreka Monthly Func P&L'!$AI41:$AT41,MATCH(EOMONTH(Inputs!$C$2,0),'Youreka Monthly Func P&L'!$AI$5:$AT$5,0)) -> 41154.138 | G42: =IFERROR(E42-F42,"N/A") -> -13273.948 | H42: =IFERROR((E42/F42-1),"N/A") -> -0.32254225 | J42: ='Youreka Monthly Func P&L'!X41 -> 567200.15 | K42: ='Youreka Monthly Func P&L'!AV41 -> 546897.73 | L42: =IFERROR(J42-K42,"N/A") -> 20302.422 | M42: =IFERROR((J42/K42-1),"N/A") -> 0.037122886 | O42: =E42 -> 27880.19 | P42: ='Youreka Monthly Func P&L'!$BM41 -> 39478.82 | Q42: =O42-P42 -> -11598.63 | R42: =IFERROR((O42/P42-1),"N/A") -> -0.29379374
C43: Other Functional Operating Expense (incl. D&A) | E43: ='Youreka Monthly Func P&L'!Q42 -> 822808.07 | F43: =INDEX('Youreka Monthly Func P&L'!$AI42:$AT42,MATCH(EOMONTH(Inputs!$C$2,0),'Youreka Monthly Func P&L'!$AI$5:$AT$5,0)) -> 813726.99 | G43: =IFERROR(E43-F43,"N/A") -> 9081.076 | H43: =IFERROR((E43/F43-1),"N/A") -> 0.011159856 | J43: ='Youreka Monthly Func P&L'!X42 -> 9781676.6 | K43: ='Youreka Monthly Func P&L'!AV42 -> 9864723.9 | L43: =IFERROR(J43-K43,"N/A") -> -83047.348 | M43: =IFERROR((J43/K43-1),"N/A") -> -0.0084186186 | O43: =E43 -> 822808.07 | P43: ='Youreka Monthly Func P&L'!$BM42 -> 814186.93 | Q43: =O43-P43 -> 8621.14 | R43: =IFERROR((O43/P43-1),"N/A") -> 0.010588649
C44: Total - Functional Operating Expenses | E44: ='Youreka Monthly Func P&L'!Q43 -> 1230935.3 | F44: =INDEX('Youreka Monthly Func P&L'!$AI43:$AT43,MATCH(EOMONTH(Inputs!$C$2,0),'Youreka Monthly Func P&L'!$AI$5:$AT$5,0)) -> 1381699.8 | G44: =IFERROR(E44-F44,"N/A") -> -150764.48 | H44: =IFERROR((E44/F44-1),"N/A") -> -0.10911523 | J44: ='Youreka Monthly Func P&L'!X43 -> 15864214 | K44: ='Youreka Monthly Func P&L'!AV43 -> 16790256 | L44: =IFERROR(J44-K44,"N/A") -> -926041.94 | M44: =IFERROR((J44/K44-1),"N/A") -> -0.055153532 | O44: =E44 -> 1230935.3 | P44: ='Youreka Monthly Func P&L'!$BM43 -> 1350475 | Q44: =O44-P44 -> -119539.76 | R44: =IFERROR((O44/P44-1),"N/A") -> -0.088516823 | U44: =SUM(E38:E43)-E44 -> 0 | V44: =SUM(F38:F43)-F44 -> 0 | X44: =SUM(J38:J43)-J44 -> 0 | Y44: =SUM(K38:K43)-K44 -> 0 | AA44: =SUM(O38:O43)-O44 -> 0 | AB44: =SUM(P38:P43)-P44 -> 0
C45: w/o Depreciation, Amoritization, or Bad Debt | E45: ='Youreka Monthly Func P&L'!Q44 -> 408127.21 | F45: =INDEX('Youreka Monthly Func P&L'!$AI44:$AT44,MATCH(EOMONTH(Inputs!$C$2,0),'Youreka Monthly Func P&L'!$AI$5:$AT$5,0)) -> 567972.77 | G45: =IFERROR(E45-F45,"N/A") -> -159845.56 | H45: =IFERROR((E45/F45-1),"N/A") -> -0.28143173 | J45: ='Youreka Monthly Func P&L'!X44 -> 6082537.8 | K45: ='Youreka Monthly Func P&L'!AV44 -> 7025532.4 | L45: =IFERROR(J45-K45,"N/A") -> -942994.59 | M45: =IFERROR((J45/K45-1),"N/A") -> -0.13422393 | O45: =E45 -> 408127.21 | P45: ='Youreka Monthly Func P&L'!$BM44 -> 536288.11 | Q45: =O45-P45 -> -128160.9 | R45: =IFERROR((O45/P45-1),"N/A") -> -0.2389777 | U45: =E44-SUM(E79:E81)-E45 -> 0 | V45: =F44-SUM(F79:F81)-F45 -> 0 | X45: =J44-SUM(J79:J81)-J45 -> 0 | Y45: =K44-SUM(K79:K81)-K45 -> -100000 | AA45: =O44-SUM(O79:O81)-O45 -> 0 | AB45: =P44-SUM(P79:P81)-P45 -> 0
F46: =INDEX('Youreka Monthly Func P&L'!$AI45:$AT45,MATCH(EOMONTH(Inputs!$C$2,0),'Youreka Monthly Func P&L'!$AI$5:$AT$5,0)) -> 0 | G46: =IFERROR(E46-F46,"N/A") -> 0
C47: Operating Margin | E47: ='Youreka Monthly Func P&L'!Q46 -> -467806.34 | F47: =INDEX('Youreka Monthly Func P&L'!$AI46:$AT46,MATCH(EOMONTH(Inputs!$C$2,0),'Youreka Monthly Func P&L'!$AI$5:$AT$5,0)) -> -546798.18 | G47: =IFERROR(E47-F47,"N/A") -> 78991.838 | H47: =IFERROR((E47/F47-1),"N/A") -> -0.14446251 | J47: ='Youreka Monthly Func P&L'!X46 -> -6798101.2 | K47: ='Youreka Monthly Func P&L'!AV46 -> -7143668.1 | L47: =IFERROR(J47-K47,"N/A") -> 345566.93 | M47: =IFERROR((J47/K47-1),"N/A") -> -0.048373878 | O47: =E47 -> -467806.34 | P47: ='Youreka Monthly Func P&L'!$BM46 -> -680868.87 | Q47: =O47-P47 -> 213062.53 | R47: =IFERROR((O47/P47-1),"N/A") -> -0.31292741 | U47: =E32-E44-E47 -> 0 | V47: =F32-F44-F47 -> 0 | X47: =J32-J44-J47 -> 0 | Y47: =K32-K44-K47 -> 0 | AA47: =O32-O44-O47 -> 0 | AB47: =P32-P44-P47 -> 0
C48: Operating Margin % | E48: ='Youreka Monthly Func P&L'!Q47 -> -0.46027402 | F48: =INDEX('Youreka Monthly Func P&L'!$AI47:$AT47,MATCH(EOMONTH(Inputs!$C$2,0),'Youreka Monthly Func P&L'!$AI$5:$AT$5,0)) -> -0.5010778 | G48: =IFERROR(E48-F48,"N/A") -> 0.040803779 | J48: ='Youreka Monthly Func P&L'!X47 -> -0.56610315 | K48: ='Youreka Monthly Func P&L'!AV47 -> -0.56581346 | L48: =IFERROR(J48-K48,"N/A") -> -0.00028968869 | O48: =E48 -> -0.46027402 | P48: ='Youreka Monthly Func P&L'!$BM47 -> -0.75474079 | Q48: =O48-P48 -> 0.29446676 | U48: =E47/E16-E48 -> 0 | V48: =F47/F16-F48 -> 0 | X48: =J47/J16-J48 -> 0 | Y48: =K47/K16-K48 -> 0 | AA48: =O47/O16-O48 -> 0 | AB48: =P47/P16-P48 -> 0
C49: Operating Margin Check (F-N) | E49: =E47-'2b. Youreka Natural P&L'!E58 -> 0 | F49: =F47-'2b. Youreka Natural P&L'!F58 -> 0 | J49: =J47-'2b. Youreka Natural P&L'!J58 -> 0 | K49: =K47-'2b. Youreka Natural P&L'!K58 -> 0
C51: Non-Operating Expenses / (Income)
C52: Interest Expense | E52: ='Youreka Monthly Func P&L'!Q51 -> 0 | F52: =INDEX('Youreka Monthly Func P&L'!$AI51:$AT51,MATCH(EOMONTH(Inputs!$C$2,0),'Youreka Monthly Func P&L'!$AI$5:$AT$5,0)) -> 0 | G52: =IFERROR(E52-F52,"N/A") -> 0 | H52: =IFERROR((E52/F52-1),"N/A") -> N/A | J52: ='Youreka Monthly Func P&L'!X51 -> 0 | K52: ='Youreka Monthly Func P&L'!AV51 -> 0 | L52: =IFERROR(J52-K52,"N/A") -> 0 | M52: =IFERROR((J52/K52-1),"N/A") -> N/A | O52: =E52 -> 0 | P52: ='Youreka Monthly Func P&L'!$BM51 -> 0 | Q52: =O52-P52 -> 0 | R52: =IFERROR((O52/P52-1),"N/A") -> N/A
C53: Interest Income | E53: ='Youreka Monthly Func P&L'!Q52 -> 0 | F53: =INDEX('Youreka Monthly Func P&L'!$AI52:$AT52,MATCH(EOMONTH(Inputs!$C$2,0),'Youreka Monthly Func P&L'!$AI$5:$AT$5,0)) -> 0 | G53: =IFERROR(E53-F53,"N/A") -> 0 | H53: =IFERROR((E53/F53-1),"N/A") -> N/A | J53: ='Youreka Monthly Func P&L'!X52 -> 0 | K53: ='Youreka Monthly Func P&L'!AV52 -> 0 | L53: =IFERROR(J53-K53,"N/A") -> 0 | M53: =IFERROR((J53/K53-1),"N/A") -> N/A | O53: =E53 -> 0 | P53: ='Youreka Monthly Func P&L'!$BM52 -> 0 | Q53: =O53-P53 -> 0 | R53: =IFERROR((O53/P53-1),"N/A") -> N/A
C54: Other Expense / (Income) | E54: ='Youreka Monthly Func P&L'!Q53 -> 0 | F54: =INDEX('Youreka Monthly Func P&L'!$AI53:$AT53,MATCH(EOMONTH(Inputs!$C$2,0),'Youreka Monthly Func P&L'!$AI$5:$AT$5,0)) -> 0 | G54: =IFERROR(E54-F54,"N/A") -> 0 | H54: =IFERROR((E54/F54-1),"N/A") -> N/A | J54: ='Youreka Monthly Func P&L'!X53 -> 78.03 | K54: ='Youreka Monthly Func P&L'!AV53 -> 0 | L54: =IFERROR(J54-K54,"N/A") -> 78.03 | M54: =IFERROR((J54/K54-1),"N/A") -> N/A | O54: =E54 -> 0 | P54: ='Youreka Monthly Func P&L'!$BM53 -> -1430.84 | Q54: =O54-P54 -> 1430.84 | R54: =IFERROR((O54/P54-1),"N/A") -> -1
C55: Stock-Based Compensation | E55: ='Youreka Monthly Func P&L'!Q54 -> 0 | F55: =INDEX('Youreka Monthly Func P&L'!$AI54:$AT54,MATCH(EOMONTH(Inputs!$C$2,0),'Youreka Monthly Func P&L'!$AI$5:$AT$5,0)) -> 0 | G55: =IFERROR(E55-F55,"N/A") -> 0 | H55: =IFERROR((E55/F55-1),"N/A") -> N/A | J55: ='Youreka Monthly Func P&L'!X54 -> 0 | K55: ='Youreka Monthly Func P&L'!AV54 -> 0 | L55: =IFERROR(J55-K55,"N/A") -> 0 | M55: =IFERROR((J55/K55-1),"N/A") -> N/A | O55: =E55 -> 0 | P55: ='Youreka Monthly Func P&L'!$BM54 -> 0 | Q55: =O55-P55 -> 0 | R55: =IFERROR((O55/P55-1),"N/A") -> N/A
C56: Acquisition-Related Costs | E56: ='Youreka Monthly Func P&L'!Q55 -> 0 | F56: =INDEX('Youreka Monthly Func P&L'!$AI55:$AT55,MATCH(EOMONTH(Inputs!$C$2,0),'Youreka Monthly Func P&L'!$AI$5:$AT$5,0)) -> 0 | G56: =IFERROR(E56-F56,"N/A") -> 0 | H56: =IFERROR((E56/F56-1),"N/A") -> N/A | J56: ='Youreka Monthly Func P&L'!X55 -> 0 | K56: ='Youreka Monthly Func P&L'!AV55 -> 0 | L56: =IFERROR(J56-K56,"N/A") -> 0 | M56: =IFERROR((J56/K56-1),"N/A") -> N/A | O56: =E56 -> 0 | P56: ='Youreka Monthly Func P&L'!$BM55 -> 0 | Q56: =O56-P56 -> 0 | R56: =IFERROR((O56/P56-1),"N/A") -> N/A
C57: Deferred Revenue - Purchase Accounting Haircut | E57: ='Youreka Monthly Func P&L'!Q56 -> 0 | F57: =INDEX('Youreka Monthly Func P&L'!$AI56:$AT56,MATCH(EOMONTH(Inputs!$C$2,0),'Youreka Monthly Func P&L'!$AI$5:$AT$5,0)) -> 0 | G57: =IFERROR(E57-F57,"N/A") -> 0 | H57: =IFERROR((E57/F57-1),"N/A") -> N/A | J57: ='Youreka Monthly Func P&L'!X56 -> 0 | K57: ='Youreka Monthly Func P&L'!AV56 -> 0 | L57: =IFERROR(J57-K57,"N/A") -> 0 | M57: =IFERROR((J57/K57-1),"N/A") -> N/A | O57: =E57 -> 0 | P57: ='Youreka Monthly Func P&L'!$BM56 -> 0 | Q57: =O57-P57 -> 0 | R57: =IFERROR((O57/P57-1),"N/A") -> N/A
C58: Restructuring Fees and Expenses / Severance | E58: ='Youreka Monthly Func P&L'!Q57 -> 0 | F58: =INDEX('Youreka Monthly Func P&L'!$AI57:$AT57,MATCH(EOMONTH(Inputs!$C$2,0),'Youreka Monthly Func P&L'!$AI$5:$AT$5,0)) -> 0 | G58: =IFERROR(E58-F58,"N/A") -> 0 | H58: =IFERROR((E58/F58-1),"N/A") -> N/A | J58: ='Youreka Monthly Func P&L'!X57 -> 39383.28 | K58: ='Youreka Monthly Func P&L'!AV57 -> 0 | L58: =IFERROR(J58-K58,"N/A") -> 39383.28 | M58: =IFERROR((J58/K58-1),"N/A") -> N/A | O58: =E58 -> 0 | P58: ='Youreka Monthly Func P&L'!$BM57 -> 0 | Q58: =O58-P58 -> 0 | R58: =IFERROR((O58/P58-1),"N/A") -> N/A
C59: VEP & VCG Expenses | E59: ='Youreka Monthly Func P&L'!Q58 -> 0 | F59: =INDEX('Youreka Monthly Func P&L'!$AI58:$AT58,MATCH(EOMONTH(Inputs!$C$2,0),'Youreka Monthly Func P&L'!$AI$5:$AT$5,0)) -> 0 | G59: =IFERROR(E59-F59,"N/A") -> 0 | H59: =IFERROR((E59/F59-1),"N/A") -> N/A | J59: ='Youreka Monthly Func P&L'!X58 -> 0 | K59: ='Youreka Monthly Func P&L'!AV58 -> 0 | L59: =IFERROR(J59-K59,"N/A") -> 0 | M59: =IFERROR((J59/K59-1),"N/A") -> N/A | O59: =E59 -> 0 | P59: ='Youreka Monthly Func P&L'!$BM58 -> 0 | Q59: =O59-P59 -> 0 | R59: =IFERROR((O59/P59-1),"N/A") -> N/A
C60: Total - Non-Operating Expenses / (Income) | E60: ='Youreka Monthly Func P&L'!Q59 -> 0 | F60: =INDEX('Youreka Monthly Func P&L'!$AI59:$AT59,MATCH(EOMONTH(Inputs!$C$2,0),'Youreka Monthly Func P&L'!$AI$5:$AT$5,0)) -> 0 | G60: =IFERROR(E60-F60,"N/A") -> 0 | H60: =IFERROR((E60/F60-1),"N/A") -> N/A | J60: ='Youreka Monthly Func P&L'!X59 -> 39461.31 | K60: ='Youreka Monthly Func P&L'!AV59 -> 0 | L60: =IFERROR(J60-K60,"N/A") -> 39461.31 | M60: =IFERROR((J60/K60-1),"N/A") -> N/A | O60: =E60 -> 0 | P60: ='Youreka Monthly Func P&L'!$BM59 -> -1430.84 | Q60: =O60-P60 -> 1430.84 | R60: =IFERROR((O60/P60-1),"N/A") -> -1 | U60: =SUM(E52:E59)-E60 -> 0 | V60: =SUM(F52:F59)-F60 -> 0 | X60: =SUM(J52:J59)-J60 -> 0 | Y60: =SUM(K52:K59)-K60 -> 0 | AA60: =SUM(O52:O59)-O60 -> 0 | AB60: =SUM(P52:P59)-P60 -> 0
C62: Pre-Tax Income | E62: ='Youreka Monthly Func P&L'!Q61 -> -467806.34 | F62: =INDEX('Youreka Monthly Func P&L'!$AI61:$AT61,MATCH(EOMONTH(Inputs!$C$2,0),'Youreka Monthly Func P&L'!$AI$5:$AT$5,0)) -> -546798.18 | G62: =IFERROR(E62-F62,"N/A") -> 78991.838 | H62: =IFERROR((E62/F62-1),"N/A") -> -0.14446251 | J62: ='Youreka Monthly Func P&L'!X61 -> -6837562.5 | K62: ='Youreka Monthly Func P&L'!AV61 -> -7143668.1 | L62: =IFERROR(J62-K62,"N/A") -> 306105.62 | M62: =IFERROR((J62/K62-1),"N/A") -> -0.042849922 | O62: =E62 -> -467806.34 | P62: ='Youreka Monthly Func P&L'!$BM61 -> -679438.03 | Q62: =O62-P62 -> 211631.69 | R62: =IFERROR((O62/P62-1),"N/A") -> -0.31148049 | U62: =E47-E60-E62 -> 0 | V62: =F47-F60-F62 -> 0 | X62: =J47-J60-J62 -> 0 | Y62: =K47-K60-K62 -> 0 | AA62: =O47-O60-O62 -> 0 | AB62: =P47-P60-P62 -> 0
C63: Provision for Income Taxes | E63: ='Youreka Monthly Func P&L'!Q62 -> 0 | F63: =INDEX('Youreka Monthly Func P&L'!$AI62:$AT62,MATCH(EOMONTH(Inputs!$C$2,0),'Youreka Monthly Func P&L'!$AI$5:$AT$5,0)) -> 0 | G63: =IFERROR(E63-F63,"N/A") -> 0 | H63: =IFERROR((E63/F63-1),"N/A") -> N/A | J63: ='Youreka Monthly Func P&L'!X62 -> 0 | K63: ='Youreka Monthly Func P&L'!AV62 -> 0 | L63: =IFERROR(J63-K63,"N/A") -> 0 | M63: =IFERROR((J63/K63-1),"N/A") -> N/A | O63: =E63 -> 0 | P63: ='Youreka Monthly Func P&L'!$BM62 -> 0 | Q63: =O63-P63 -> 0 | R63: =IFERROR((O63/P63-1),"N/A") -> N/A
C64: Implied Tax Rate | E64: ='Youreka Monthly Func P&L'!Q63 -> 0 | F64: =INDEX('Youreka Monthly Func P&L'!$AI63:$AT63,MATCH(EOMONTH(Inputs!$C$2,0),'Youreka Monthly Func P&L'!$AI$5:$AT$5,0)) -> 0 | G64: =IFERROR(E64-F64,"N/A") -> 0 | J64: ='Youreka Monthly Func P&L'!X63 -> 0 | K64: ='Youreka Monthly Func P&L'!AV63 -> 0 | L64: =IFERROR(J64-K64,"N/A") -> 0 | O64: =E64 -> 0 | P64: ='Youreka Monthly Func P&L'!$BM63 -> 0 | Q64: =O64-P64 -> 0
C66: Net Income | E66: ='Youreka Monthly Func P&L'!Q65 -> -467806.34 | F66: =INDEX('Youreka Monthly Func P&L'!$AI65:$AT65,MATCH(EOMONTH(Inputs!$C$2,0),'Youreka Monthly Func P&L'!$AI$5:$AT$5,0)) -> -546798.18 | G66: =IFERROR(E66-F66,"N/A") -> 78991.838 | H66: =IFERROR((E66/F66-1),"N/A") -> -0.14446251 | J66: ='Youreka Monthly Func P&L'!X65 -> -6837562.5 | K66: ='Youreka Monthly Func P&L'!AV65 -> -7143668.1 | L66: =IFERROR(J66-K66,"N/A") -> 306105.62 | M66: =IFERROR((J66/K66-1),"N/A") -> -0.042849922 | O66: =E66 -> -467806.34 | P66: ='Youreka Monthly Func P&L'!$BM65 -> -679438.03 | Q66: =O66-P66 -> 211631.69 | R66: =IFERROR((O66/P66-1),"N/A") -> -0.31148049 | U66: =E62-E63-E66 -> 0 | V66: =F62-F63-F66 -> 0 | X66: =J62-J63-J66 -> 0 | Y66: =K62-K63-K66 -> 0 | AA66: =O62-O63-O66 -> 0 | AB66: =P62-P63-P66 -> 0
C67: Net Income (% of Revenue) | E67: ='Youreka Monthly Func P&L'!Q66 -> -0.46027402 | F67: =INDEX('Youreka Monthly Func P&L'!$AI66:$AT66,MATCH(EOMONTH(Inputs!$C$2,0),'Youreka Monthly Func P&L'!$AI$5:$AT$5,0)) -> -0.5010778 | G67: =IFERROR(E67-F67,"N/A") -> 0.040803779 | J67: ='Youreka Monthly Func P&L'!X66 -> -0.56938924 | K67: ='Youreka Monthly Func P&L'!AV66 -> -0.56581346 | L67: =IFERROR(J67-K67,"N/A") -> -0.0035757786 | O67: =E67 -> -0.46027402 | P67: ='Youreka Monthly Func P&L'!$BM66 -> -0.7531547 | Q67: =O67-P67 -> 0.29288068 | U67: =E66/E16-E67 -> 0 | V67: =F66/F16-F67 -> 0 | X67: =J66/J16-J67 -> 0 | Y67: =K66/K16-K67 -> 0 | AA67: =O66/O16-O67 -> 0 | AB67: =P66/P16-P67 -> 0
C69: EBITDA Addbacks
C70: Interest Expense | E70: ='Youreka Monthly Func P&L'!Q69 -> 0 | F70: =INDEX('Youreka Monthly Func P&L'!$AI69:$AT69,MATCH(EOMONTH(Inputs!$C$2,0),'Youreka Monthly Func P&L'!$AI$5:$AT$5,0)) -> 0 | G70: =IFERROR(E70-F70,"N/A") -> 0 | H70: =IFERROR((E70/F70-1),"N/A") -> N/A | J70: ='Youreka Monthly Func P&L'!X69 -> 0 | K70: ='Youreka Monthly Func P&L'!AV69 -> 0 | L70: =IFERROR(J70-K70,"N/A") -> 0 | M70: =IFERROR((J70/K70-1),"N/A") -> N/A | O70: =E70 -> 0 | P70: ='Youreka Monthly Func P&L'!$BM69 -> 0 | Q70: =O70-P70 -> 0 | R70: =IFERROR((O70/P70-1),"N/A") -> N/A
C71: Interest Income | E71: ='Youreka Monthly Func P&L'!Q70 -> 0 | F71: =INDEX('Youreka Monthly Func P&L'!$AI70:$AT70,MATCH(EOMONTH(Inputs!$C$2,0),'Youreka Monthly Func P&L'!$AI$5:$AT$5,0)) -> 0 | G71: =IFERROR(E71-F71,"N/A") -> 0 | H71: =IFERROR((E71/F71-1),"N/A") -> N/A | J71: ='Youreka Monthly Func P&L'!X70 -> 0 | K71: ='Youreka Monthly Func P&L'!AV70 -> 0 | L71: =IFERROR(J71-K71,"N/A") -> 0 | M71: =IFERROR((J71/K71-1),"N/A") -> N/A | O71: =E71 -> 0 | P71: ='Youreka Monthly Func P&L'!$BM70 -> 0 | Q71: =O71-P71 -> 0 | R71: =IFERROR((O71/P71-1),"N/A") -> N/A
C72: Other Expense / Income | E72: ='Youreka Monthly Func P&L'!Q71 -> 0 | F72: =INDEX('Youreka Monthly Func P&L'!$AI71:$AT71,MATCH(EOMONTH(Inputs!$C$2,0),'Youreka Monthly Func P&L'!$AI$5:$AT$5,0)) -> 0 | G72: =IFERROR(E72-F72,"N/A") -> 0 | H72: =IFERROR((E72/F72-1),"N/A") -> N/A | J72: ='Youreka Monthly Func P&L'!X71 -> 78.03 | K72: ='Youreka Monthly Func P&L'!AV71 -> 0 | L72: =IFERROR(J72-K72,"N/A") -> 78.03 | M72: =IFERROR((J72/K72-1),"N/A") -> N/A | O72: =E72 -> 0 | P72: ='Youreka Monthly Func P&L'!$BM71 -> -1430.84 | Q72: =O72-P72 -> 1430.84 | R72: =IFERROR((O72/P72-1),"N/A") -> -1
C73: Stock-Based Compensation | E73: ='Youreka Monthly Func P&L'!Q72 -> 0 | F73: =INDEX('Youreka Monthly Func P&L'!$AI72:$AT72,MATCH(EOMONTH(Inputs!$C$2,0),'Youreka Monthly Func P&L'!$AI$5:$AT$5,0)) -> 0 | G73: =IFERROR(E73-F73,"N/A") -> 0 | H73: =IFERROR((E73/F73-1),"N/A") -> N/A | J73: ='Youreka Monthly Func P&L'!X72 -> 0 | K73: ='Youreka Monthly Func P&L'!AV72 -> 0 | L73: =IFERROR(J73-K73,"N/A") -> 0 | M73: =IFERROR((J73/K73-1),"N/A") -> N/A | O73: =E73 -> 0 | P73: ='Youreka Monthly Func P&L'!$BM72 -> 0 | Q73: =O73-P73 -> 0 | R73: =IFERROR((O73/P73-1),"N/A") -> N/A
C74: Acquisition-Related Costs | E74: ='Youreka Monthly Func P&L'!Q73 -> 0 | F74: =INDEX('Youreka Monthly Func P&L'!$AI73:$AT73,MATCH(EOMONTH(Inputs!$C$2,0),'Youreka Monthly Func P&L'!$AI$5:$AT$5,0)) -> 0 | G74: =IFERROR(E74-F74,"N/A") -> 0 | H74: =IFERROR((E74/F74-1),"N/A") -> N/A | J74: ='Youreka Monthly Func P&L'!X73 -> 0 | K74: ='Youreka Monthly Func P&L'!AV73 -> 0 | L74: =IFERROR(J74-K74,"N/A") -> 0 | M74: =IFERROR((J74/K74-1),"N/A") -> N/A | O74: =E74 -> 0 | P74: ='Youreka Monthly Func P&L'!$BM73 -> 0 | Q74: =O74-P74 -> 0 | R74: =IFERROR((O74/P74-1),"N/A") -> N/A
C75: Deferred Revenue - Purchase Accounting Haircut | E75: ='Youreka Monthly Func P&L'!Q74 -> 0 | F75: =INDEX('Youreka Monthly Func P&L'!$AI74:$AT74,MATCH(EOMONTH(Inputs!$C$2,0),'Youreka Monthly Func P&L'!$AI$5:$AT$5,0)) -> 0 | G75: =IFERROR(E75-F75,"N/A") -> 0 | H75: =IFERROR((E75/F75-1),"N/A") -> N/A | J75: ='Youreka Monthly Func P&L'!X74 -> 0 | K75: ='Youreka Monthly Func P&L'!AV74 -> 0 | L75: =IFERROR(J75-K75,"N/A") -> 0 | M75: =IFERROR((J75/K75-1),"N/A") -> N/A | O75: =E75 -> 0 | P75: ='Youreka Monthly Func P&L'!$BM74 -> 0 | Q75: =O75-P75 -> 0 | R75: =IFERROR((O75/P75-1),"N/A") -> N/A
C76: Restructuring Fees and Expenses / Severance | E76: ='Youreka Monthly Func P&L'!Q75 -> 0 | F76: =INDEX('Youreka Monthly Func P&L'!$AI75:$AT75,MATCH(EOMONTH(Inputs!$C$2,0),'Youreka Monthly Func P&L'!$AI$5:$AT$5,0)) -> 0 | G76: =IFERROR(E76-F76,"N/A") -> 0 | H76: =IFERROR((E76/F76-1),"N/A") -> N/A | J76: ='Youreka Monthly Func P&L'!X75 -> 39383.28 | K76: ='Youreka Monthly Func P&L'!AV75 -> 0 | L76: =IFERROR(J76-K76,"N/A") -> 39383.28 | M76: =IFERROR((J76/K76-1),"N/A") -> N/A | O76: =E76 -> 0 | P76: ='Youreka Monthly Func P&L'!$BM75 -> 0 | Q76: =O76-P76 -> 0 | R76: =IFERROR((O76/P76-1),"N/A") -> N/A
C77: VEP & VCG Expenses | E77: ='Youreka Monthly Func P&L'!Q76 -> 0 | F77: =INDEX('Youreka Monthly Func P&L'!$AI76:$AT76,MATCH(EOMONTH(Inputs!$C$2,0),'Youreka Monthly Func P&L'!$AI$5:$AT$5,0)) -> 0 | G77: =IFERROR(E77-F77,"N/A") -> 0 | H77: =IFERROR((E77/F77-1),"N/A") -> N/A | J77: ='Youreka Monthly Func P&L'!X76 -> 0 | K77: ='Youreka Monthly Func P&L'!AV76 -> 0 | L77: =IFERROR(J77-K77,"N/A") -> 0 | M77: =IFERROR((J77/K77-1),"N/A") -> N/A | O77: =E77 -> 0 | P77: ='Youreka Monthly Func P&L'!$BM76 -> 0 | Q77: =O77-P77 -> 0 | R77: =IFERROR((O77/P77-1),"N/A") -> N/A
C78: Provision for Income Taxes | E78: ='Youreka Monthly Func P&L'!Q77 -> 0 | F78: =INDEX('Youreka Monthly Func P&L'!$AI77:$AT77,MATCH(EOMONTH(Inputs!$C$2,0),'Youreka Monthly Func P&L'!$AI$5:$AT$5,0)) -> 0 | G78: =IFERROR(E78-F78,"N/A") -> 0 | H78: =IFERROR((E78/F78-1),"N/A") -> N/A | J78: ='Youreka Monthly Func P&L'!X77 -> 0 | K78: ='Youreka Monthly Func P&L'!AV77 -> 0 | L78: =IFERROR(J78-K78,"N/A") -> 0 | M78: =IFERROR((J78/K78-1),"N/A") -> N/A | O78: =E78 -> 0 | P78: ='Youreka Monthly Func P&L'!$BM77 -> 0 | Q78: =O78-P78 -> 0 | R78: =IFERROR((O78/P78-1),"N/A") -> N/A
C79: Bad Debt Expense | E79: ='Youreka Monthly Func P&L'!Q78 -> 9000 | F79: =INDEX('Youreka Monthly Func P&L'!$AI78:$AT78,MATCH(EOMONTH(Inputs!$C$2,0),'Youreka Monthly Func P&L'!$AI$5:$AT$5,0)) -> 0 | G79: =IFERROR(E79-F79,"N/A") -> 9000 | H79: =IFERROR((E79/F79-1),"N/A") -> N/A | J79: ='Youreka Monthly Func P&L'!X78 -> 16466.59 | K79: ='Youreka Monthly Func P&L'!AV78 -> 100000 | L79: =IFERROR(J79-K79,"N/A") -> -83533.41 | M79: =IFERROR((J79/K79-1),"N/A") -> -0.8353341 | O79: =E79 -> 9000 | P79: ='Youreka Monthly Func P&L'!$BM78 -> 460 | Q79: =O79-P79 -> 8540 | R79: =IFERROR((O79/P79-1),"N/A") -> 18.565217
C80: Depreciation | E80: ='Youreka Monthly Func P&L'!Q79 -> 291.74 | F80: =INDEX('Youreka Monthly Func P&L'!$AI79:$AT79,MATCH(EOMONTH(Inputs!$C$2,0),'Youreka Monthly Func P&L'!$AI$5:$AT$5,0)) -> 210.5975 | G80: =IFERROR(E80-F80,"N/A") -> 81.1425 | H80: =IFERROR((E80/F80-1),"N/A") -> 0.3852966 | J80: ='Youreka Monthly Func P&L'!X79 -> 3014.03 | K80: ='Youreka Monthly Func P&L'!AV79 -> 2527.17 | L80: =IFERROR(J80-K80,"N/A") -> 486.86 | M80: =IFERROR((J80/K80-1),"N/A") -> 0.19265028 | O80: =E80 -> 291.74 | P80: ='Youreka Monthly Func P&L'!$BM79 -> 210.6 | Q80: =O80-P80 -> 81.14 | R80: =IFERROR((O80/P80-1),"N/A") -> 0.38528015
C81: Amortization | E81: ='Youreka Monthly Func P&L'!Q80 -> 813516.33 | F81: =INDEX('Youreka Monthly Func P&L'!$AI80:$AT80,MATCH(EOMONTH(Inputs!$C$2,0),'Youreka Monthly Func P&L'!$AI$5:$AT$5,0)) -> 813516.4 | G81: =IFERROR(E81-F81,"N/A") -> -0.0665 | H81: =IFERROR((E81/F81-1),"N/A") -> -8.1743896e-08 | J81: ='Youreka Monthly Func P&L'!X80 -> 9762196 | K81: ='Youreka Monthly Func P&L'!AV80 -> 9762196.8 | L81: =IFERROR(J81-K81,"N/A") -> -0.798 | M81: =IFERROR((J81/K81-1),"N/A") -> -8.1743896e-08 | O81: =E81 -> 813516.33 | P81: ='Youreka Monthly Func P&L'!$BM80 -> 813516.33 | Q81: =O81-P81 -> 0 | R81: =IFERROR((O81/P81-1),"N/A") -> 0
C82: Total - EBITDA Addbacks | E82: ='Youreka Monthly Func P&L'!Q81 -> 822808.07 | F82: =INDEX('Youreka Monthly Func P&L'!$AI81:$AT81,MATCH(EOMONTH(Inputs!$C$2,0),'Youreka Monthly Func P&L'!$AI$5:$AT$5,0)) -> 813726.99 | G82: =IFERROR(E82-F82,"N/A") -> 9081.076 | H82: =IFERROR((E82/F82-1),"N/A") -> 0.011159856 | J82: ='Youreka Monthly Func P&L'!X81 -> 9821137.9 | K82: ='Youreka Monthly Func P&L'!AV81 -> 9864723.9 | L82: =IFERROR(J82-K82,"N/A") -> -43586.038 | M82: =IFERROR((J82/K82-1),"N/A") -> -0.0044183738 | O82: =E82 -> 822808.07 | P82: ='Youreka Monthly Func P&L'!$BM81 -> 812756.09 | Q82: =O82-P82 -> 10051.98 | R82: =IFERROR((O82/P82-1),"N/A") -> 0.01236777 | U82: =SUM(E70:E81)-E82 -> 0 | V82: =SUM(F70:F81)-F82 -> 0 | X82: =SUM(J70:J81)-J82 -> 0 | Y82: =SUM(K70:K81)-K82 -> 0 | AA82: =SUM(O70:O81)-O82 -> 0 | AB82: =SUM(P70:P81)-P82 -> 0
C84: EBITDA | E84: ='Youreka Monthly Func P&L'!Q83 -> 355001.73 | F84: =INDEX('Youreka Monthly Func P&L'!$AI83:$AT83,MATCH(EOMONTH(Inputs!$C$2,0),'Youreka Monthly Func P&L'!$AI$5:$AT$5,0)) -> 266928.82 | G84: =IFERROR(E84-F84,"N/A") -> 88072.914 | H84: =IFERROR((E84/F84-1),"N/A") -> 0.32994907 | J84: ='Youreka Monthly Func P&L'!X83 -> 2983575.4 | K84: ='Youreka Monthly Func P&L'!AV83 -> 2721055.8 | L84: =IFERROR(J84-K84,"N/A") -> 262519.59 | M84: =IFERROR((J84/K84-1),"N/A") -> 0.096477104 | O84: =E84 -> 355001.73 | P84: ='Youreka Monthly Func P&L'!$BM83 -> 133318.06 | Q84: =O84-P84 -> 221683.67 | R84: =IFERROR((O84/P84-1),"N/A") -> 1.662818 | U84: =E66+E82-E84 -> 0 | V84: =F66+F82-F84 -> 0 | X84: =J66+J82-J84 -> 0 | Y84: =K66+K82-K84 -> 0 | AA84: =O66+O82-O84 -> 0 | AB84: =P66+P82-P84 -> 0
C85: EBITDA Margin % | E85: ='Youreka Monthly Func P&L'!Q84 -> 0.34928572 | F85: =INDEX('Youreka Monthly Func P&L'!$AI84:$AT84,MATCH(EOMONTH(Inputs!$C$2,0),'Youreka Monthly Func P&L'!$AI$5:$AT$5,0)) -> 0.24460964 | G85: =IFERROR(E85-F85,"N/A") -> 0.10467608 | J85: ='Youreka Monthly Func P&L'!X84 -> 0.24845341 | K85: ='Youreka Monthly Func P&L'!AV84 -> 0.21552093 | L85: =IFERROR(J85-K85,"N/A") -> 0.03293248 | O85: =E85 -> 0.34928572 | P85: ='Youreka Monthly Func P&L'!$BM84 -> 0.14778261 | U85: =E84/E16-E85 -> 0 | V85: =F84/F16-F85 -> 0 | X85: =J84/J16-J85 -> 0 | Y85: =K84/K16-K85 -> 0 | AA85: =O84/O16-O85 -> 0 | AB85: =P84/P16-P85 -> 0
C86: EBITDA Check (F-N) | E86: =E84-'2b. Youreka Natural P&L'!E94 -> 0 | F86: =F84-'2b. Youreka Natural P&L'!F94 -> 0 | J86: =J84-'2b. Youreka Natural P&L'!J94 -> 0 | K86: =K84-'2b. Youreka Natural P&L'!K94 -> 0
C88: Capitalized Software Costs | E88: ='Youreka Monthly Func P&L'!Q87 -> 0 | F88: =INDEX('Youreka Monthly Func P&L'!$AI87:$AT87,MATCH(EOMONTH(Inputs!$C$2,0),'Youreka Monthly Func P&L'!$AI$5:$AT$5,0)) -> 0 | G88: =IFERROR(E88-F88,"N/A") -> 0 | H88: =IFERROR((E88/F88-1),"N/A") -> N/A | J88: ='Youreka Monthly Func P&L'!X87 -> 0 | K88: ='Youreka Monthly Func P&L'!AV87 -> 0 | L88: =IFERROR(J88-K88,"N/A") -> 0 | M88: =IFERROR((J88/K88-1),"N/A") -> N/A | O88: =E88 -> 0 | P88: ='Youreka Monthly Func P&L'!$BM87 -> 0 | Q88: =O88-P88 -> 0 | R88: =IFERROR((O88/P88-1),"N/A") -> N/A
C90: EBITDAC | E90: ='Youreka Monthly Func P&L'!Q89 -> 355001.73 | F90: =INDEX('Youreka Monthly Func P&L'!$AI89:$AT89,MATCH(EOMONTH(Inputs!$C$2,0),'Youreka Monthly Func P&L'!$AI$5:$AT$5,0)) -> 266928.82 | G90: =IFERROR(E90-F90,"N/A") -> 88072.914 | H90: =IFERROR((E90/F90-1),"N/A") -> 0.32994907 | J90: ='Youreka Monthly Func P&L'!X89 -> 2983575.4 | K90: ='Youreka Monthly Func P&L'!AV89 -> 2721055.8 | L90: =IFERROR(J90-K90,"N/A") -> 262519.59 | M90: =IFERROR((J90/K90-1),"N/A") -> 0.096477104 | O90: =E90 -> 355001.73 | P90: ='Youreka Monthly Func P&L'!$BM89 -> 133318.06 | Q90: =O90-P90 -> 221683.67 | R90: =IFERROR((O90/P90-1),"N/A") -> 1.662818 | U90: =E84-E88-E90 -> 0 | V90: =F84-F88-F90 -> 0 | X90: =J84-J88-J90 -> 0 | Y90: =K84-K88-K90 -> 0 | AA90: =O84-O88-O90 -> 0 | AB90: =P84-P88-P90 -> 0
C91: EBITDAC Margin % | E91: ='Youreka Monthly Func P&L'!Q90 -> 0.34928572 | F91: =INDEX('Youreka Monthly Func P&L'!$AI90:$AT90,MATCH(EOMONTH(Inputs!$C$2,0),'Youreka Monthly Func P&L'!$AI$5:$AT$5,0)) -> 0.24460964 | G91: =IFERROR(E91-F91,"N/A") -> 0.10467608 | J91: ='Youreka Monthly Func P&L'!X90 -> 0.24845341 | K91: ='Youreka Monthly Func P&L'!AV90 -> 0.21552093 | L91: =IFERROR(J91-K91,"N/A") -> 0.03293248 | O91: =E91 -> 0.34928572 | P91: ='Youreka Monthly Func P&L'!$BM90 -> 0.14778261 | Q91: =O91-P91 -> 0.20150311 | U91: =E90/E16-E91 -> 0 | V91: =F90/F16-F91 -> 0 | X91: =J90/J16-J91 -> 0 | Y91: =K90/K16-K91 -> 0 | AA91: =O90/O16-O91 -> 0 | AB91: =P90/P16-P91 -> 0
C93: Compensation by Function
C94: COS Compensation | E94: ='Youreka Monthly Func P&L'!Q93 -> 102601.62 | F94: =INDEX('Youreka Monthly Func P&L'!$AI93:$AT93,MATCH(EOMONTH(Inputs!$C$2,0),'Youreka Monthly Func P&L'!$AI$5:$AT$5,0)) -> 104381.14 | G94: =IFERROR(E94-F94,"N/A") -> -1779.5247 | H94: =IFERROR((E94/F94-1),"N/A") -> -0.017048334 | J94: ='Youreka Monthly Func P&L'!X93 -> 1254016.9 | K94: ='Youreka Monthly Func P&L'!AV93 -> 1244704.5 | L94: =IFERROR(J94-K94,"N/A") -> 9312.3722 | M94: =IFERROR((J94/K94-1),"N/A") -> 0.0074815926 | O94: =E94 -> 102601.62 | P94: ='Youreka Monthly Func P&L'!$BM93 -> 99457.75 | Q94: =O94-P94 -> 3143.87 | R94: =IFERROR((O94/P94-1),"N/A") -> 0.031610106
C95: Product & Engineering Compensation | E95: ='Youreka Monthly Func P&L'!Q94 -> 145779.51 | F95: =INDEX('Youreka Monthly Func P&L'!$AI94:$AT94,MATCH(EOMONTH(Inputs!$C$2,0),'Youreka Monthly Func P&L'!$AI$5:$AT$5,0)) -> 210411.81 | G95: =IFERROR(E95-F95,"N/A") -> -64632.298 | H95: =IFERROR((E95/F95-1),"N/A") -> -0.30717049 | J95: ='Youreka Monthly Func P&L'!X94 -> 2154067.4 | K95: ='Youreka Monthly Func P&L'!AV94 -> 2559769.7 | L95: =IFERROR(J95-K95,"N/A") -> -405702.28 | M95: =IFERROR((J95/K95-1),"N/A") -> -0.15849171 | O95: =E95 -> 145779.51 | P95: ='Youreka Monthly Func P&L'!$BM94 -> 209179.04 | Q95: =O95-P95 -> -63399.53 | R95: =IFERROR((O95/P95-1),"N/A") -> -0.30308739
C96: General & Administrative Compensation | E96: ='Youreka Monthly Func P&L'!Q95 -> 39060.21 | F96: =INDEX('Youreka Monthly Func P&L'!$AI95:$AT95,MATCH(EOMONTH(Inputs!$C$2,0),'Youreka Monthly Func P&L'!$AI$5:$AT$5,0)) -> 62363.376 | G96: =IFERROR(E96-F96,"N/A") -> -23303.166 | H96: =IFERROR((E96/F96-1),"N/A") -> -0.37366749 | J96: ='Youreka Monthly Func P&L'!X95 -> 648323.97 | K96: ='Youreka Monthly Func P&L'!AV95 -> 744595.44 | L96: =IFERROR(J96-K96,"N/A") -> -96271.465 | M96: =IFERROR((J96/K96-1),"N/A") -> -0.12929365 | O96: =E96 -> 39060.21 | P96: ='Youreka Monthly Func P&L'!$BM95 -> 57761.5 | Q96: =O96-P96 -> -18701.29 | R96: =IFERROR((O96/P96-1),"N/A") -> -0.32376739
C97: Sales Compensation | E97: ='Youreka Monthly Func P&L'!Q96 -> 172115.03 | F97: =INDEX('Youreka Monthly Func P&L'!$AI96:$AT96,MATCH(EOMONTH(Inputs!$C$2,0),'Youreka Monthly Func P&L'!$AI$5:$AT$5,0)) -> 211773.32 | G97: =IFERROR(E97-F97,"N/A") -> -39658.288 | H97: =IFERROR((E97/F97-1),"N/A") -> -0.18726763 | J97: ='Youreka Monthly Func P&L'!X96 -> 2363056.6 | K97: ='Youreka Monthly Func P&L'!AV96 -> 2579332.6 | L97: =IFERROR(J97-K97,"N/A") -> -216276.05 | M97: =IFERROR((J97/K97-1),"N/A") -> -0.083849615 | O97: =E97 -> 172115.03 | P97: ='Youreka Monthly Func P&L'!$BM96 -> 204194.37 | Q97: =O97-P97 -> -32079.34 | R97: =IFERROR((O97/P97-1),"N/A") -> -0.15710198
C98: Marketing Compensation | E98: ='Youreka Monthly Func P&L'!Q97 -> 16745.71 | F98: =INDEX('Youreka Monthly Func P&L'!$AI97:$AT97,MATCH(EOMONTH(Inputs!$C$2,0),'Youreka Monthly Func P&L'!$AI$5:$AT$5,0)) -> 26079.138 | G98: =IFERROR(E98-F98,"N/A") -> -9333.4283 | H98: =IFERROR((E98/F98-1),"N/A") -> -0.35788868 | J98: ='Youreka Monthly Func P&L'!X97 -> 331752.4 | K98: ='Youreka Monthly Func P&L'!AV97 -> 314522.73 | L98: =IFERROR(J98-K98,"N/A") -> 17229.672 | M98: =IFERROR((J98/K98-1),"N/A") -> 0.054780373 | O98: =E98 -> 16745.71 | P98: ='Youreka Monthly Func P&L'!$BM97 -> 27234.31 | Q98: =O98-P98 -> -10488.6 | R98: =IFERROR((O98/P98-1),"N/A") -> -0.3851245
C99: Payroll Fees | E99: ='Youreka Monthly Func P&L'!Q98 -> 709.76 | F99: =INDEX('Youreka Monthly Func P&L'!$AI98:$AT98,MATCH(EOMONTH(Inputs!$C$2,0),'Youreka Monthly Func P&L'!$AI$5:$AT$5,0)) -> 630 | G99: =IFERROR(E99-F99,"N/A") -> 79.76 | H99: =IFERROR((E99/F99-1),"N/A") -> 0.12660317 | J99: ='Youreka Monthly Func P&L'!X98 -> 10333.1 | K99: ='Youreka Monthly Func P&L'!AV98 -> 7848 | L99: =IFERROR(J99-K99,"N/A") -> 2485.1 | M99: =IFERROR((J99/K99-1),"N/A") -> 0.31665392 | O99: =E99 -> 709.76 | P99: ='Youreka Monthly Func P&L'!$BM98 -> 869.23 | Q99: =O99-P99 -> -159.47 | R99: =IFERROR((O99/P99-1),"N/A") -> -0.18346122
C100: Total - Compensation | E100: ='Youreka Monthly Func P&L'!Q99 -> 477011.84 | F100: =INDEX('Youreka Monthly Func P&L'!$AI99:$AT99,MATCH(EOMONTH(Inputs!$C$2,0),'Youreka Monthly Func P&L'!$AI$5:$AT$5,0)) -> 615638.78 | G100: =IFERROR(E100-F100,"N/A") -> -138626.94 | H100: =IFERROR((E100/F100-1),"N/A") -> -0.22517578 | J100: ='Youreka Monthly Func P&L'!X99 -> 6761550.3 | K100: ='Youreka Monthly Func P&L'!AV99 -> 7450773 | L100: =IFERROR(J100-K100,"N/A") -> -689222.65 | M100: =IFERROR((J100/K100-1),"N/A") -> -0.09250351 | O100: =E100 -> 477011.84 | P100: ='Youreka Monthly Func P&L'!$BM99 -> 598696.2 | Q100: =O100-P100 -> -121684.36 | R100: =IFERROR((O100/P100-1),"N/A") -> -0.20324893 | U100: =SUM(E94:E99)-E100 -> 0 | V100: =SUM(F94:F99)-F100 -> 0 | X100: =SUM(J94:J99)-J100 -> 0 | Y100: =SUM(K94:K99)-K100 -> 0 | AA100: =SUM(O94:O99)-O100 -> 0 | AB100: =SUM(P94:P99)-P100 -> 0
E103: =E100-'Youreka Monthly Func P&L'!$Q99 -> 0 | J103: =J100-'Youreka Monthly Func P&L'!$X99 -> 0 | P103: =P100-'Youreka Monthly Func P&L'!$BM99 -> 0

Sheet 2. Consolidated Natural P&L
C1: Dispatch | Monthly Profit & Loss (Natural View)
E4: Current Month | J4: Year-to-Date | O4: Year-over-Year
U5: Current Month | X5: YTD | AA5: YoY
C6: Revenue | E6: =Inputs!C2 -> 46022 | F6: Budget | G6: Difference | H6: % Difference | J6: =E6 -> 46022 | K6: Budget | L6: Difference | M6: % Difference | O6: =J6 -> 46022 | P6: =EOMONTH(O6,-12) -> 45657 | Q6: Difference | R6: % Difference | U6: Checks | X6: Checks | AA6: Checks
C7: Recurring Revenue
C8: Recurring Enterprise License Revenue | E8: ='2a. Dispatch Natural P&L'!E8+'2b. Youreka Natural P&L'!E8 -> 1886430.2 | F8: ='2a. Dispatch Natural P&L'!F8+'2b. Youreka Natural P&L'!F8 -> 2054472.9 | G8: =IFERROR(E8-F8,"N/A") -> -168042.7 | H8: =IFERROR((E8/F8-1),"N/A") -> -0.081793584 | J8: ='2a. Dispatch Natural P&L'!J8+'2b. Youreka Natural P&L'!J8 -> 22220506 | K8: ='2a. Dispatch Natural P&L'!K8+'2b. Youreka Natural P&L'!K8 -> 23068278 | L8: =IFERROR(J8-K8,"N/A") -> -847772.07 | M8: =IFERROR((J8/K8-1),"N/A") -> -0.036750557 | O8: ='2a. Dispatch Natural P&L'!O8+'2b. Youreka Natural P&L'!O8 -> 1886430.2 | P8: ='2a. Dispatch Natural P&L'!P8+'2b. Youreka Natural P&L'!P8 -> 1736049.1 | Q8: =O8-P8 -> 150381.11 | R8: =IFERROR((O8/P8-1),"N/A") -> 0.086622615
C9: Recurring Services Revenue | E9: ='2a. Dispatch Natural P&L'!E9+'2b. Youreka Natural P&L'!E9 -> 132806.87 | F9: ='2a. Dispatch Natural P&L'!F9+'2b. Youreka Natural P&L'!F9 -> 118739.5 | G9: =IFERROR(E9-F9,"N/A") -> 14067.368 | H9: =IFERROR((E9/F9-1),"N/A") -> 0.11847252 | J9: ='2a. Dispatch Natural P&L'!J9+'2b. Youreka Natural P&L'!J9 -> 1534400.6 | K9: ='2a. Dispatch Natural P&L'!K9+'2b. Youreka Natural P&L'!K9 -> 1423624 | L9: =IFERROR(J9-K9,"N/A") -> 110776.62 | M9: =IFERROR((J9/K9-1),"N/A") -> 0.077813115 | O9: ='2a. Dispatch Natural P&L'!O9+'2b. Youreka Natural P&L'!O9 -> 132806.87 | P9: ='2a. Dispatch Natural P&L'!P9+'2b. Youreka Natural P&L'!P9 -> 107855.4 | Q9: =O9-P9 -> 24951.47 | R9: =IFERROR((O9/P9-1),"N/A") -> 0.23134187
C10: Recurring Service Provider (SMB) Revenue | E10: ='2a. Dispatch Natural P&L'!E10+'2b. Youreka Natural P&L'!E10 -> 95643.67 | F10: ='2a. Dispatch Natural P&L'!F10+'2b. Youreka Natural P&L'!F10 -> 107993.31 | G10: =IFERROR(E10-F10,"N/A") -> -12349.642 | H10: =IFERROR((E10/F10-1),"N/A") -> -0.11435562 | J10: ='2a. Dispatch Natural P&L'!J10+'2b. Youreka Natural P&L'!J10 -> 1158666.8 | K10: ='2a. Dispatch Natural P&L'!K10+'2b. Youreka Natural P&L'!K10 -> 1217243.8 | L10: =IFERROR(J10-K10,"N/A") -> -58577.008 | M10: =IFERROR((J10/K10-1),"N/A") -> -0.048122658 | O10: ='2a. Dispatch Natural P&L'!O10+'2b. Youreka Natural P&L'!O10 -> 95643.67 | P10: ='2a. Dispatch Natural P&L'!P10+'2b. Youreka Natural P&L'!P10 -> 91808.3 | Q10: =O10-P10 -> 3835.37 | R10: =IFERROR((O10/P10-1),"N/A") -> 0.041775853
C11: Total Recurring Revenue | E11: ='2a. Dispatch Natural P&L'!E11+'2b. Youreka Natural P&L'!E11 -> 2114880.7 | F11: ='2a. Dispatch Natural P&L'!F11+'2b. Youreka Natural P&L'!F11 -> 2281205.7 | G11: =IFERROR(E11-F11,"N/A") -> -166324.97 | H11: =IFERROR((E11/F11-1),"N/A") -> -0.072910994 | J11: ='2a. Dispatch Natural P&L'!J11+'2b. Youreka Natural P&L'!J11 -> 24913573 | K11: ='2a. Dispatch Natural P&L'!K11+'2b. Youreka Natural P&L'!K11 -> 25709146 | L11: =IFERROR(J11-K11,"N/A") -> -795572.46 | M11: =IFERROR((J11/K11-1),"N/A") -> -0.030945115 | O11: ='2a. Dispatch Natural P&L'!O11+'2b. Youreka Natural P&L'!O11 -> 2114880.7 | P11: ='2a. Dispatch Natural P&L'!P11+'2b. Youreka Natural P&L'!P11 -> 1935712.8 | Q11: =O11-P11 -> 179167.95 | R11: =IFERROR((O11/P11-1),"N/A") -> 0.092559162 | U11: =SUM(E8:E10)-E11 -> 0 | V11: =SUM(F8:F10)-F11 -> 0 | X11: =SUM(J8:J10)-J11 -> 0 | Y11: =SUM(K8:K10)-K11 -> 0 | AA11: =SUM(O8:O10)-O11 -> 0 | AB11: =SUM(P8:P10)-P11 -> 0
C12: Non-Recurring Revenue
C13: Non-Recurring Professional Services Revenue | E13: ='2a. Dispatch Natural P&L'!E13+'2b. Youreka Natural P&L'!E13 -> 49000 | F13: ='2a. Dispatch Natural P&L'!F13+'2b. Youreka Natural P&L'!F13 -> 39250 | G13: =IFERROR(E13-F13,"N/A") -> 9750 | H13: =IFERROR((E13/F13-1),"N/A") -> 0.24840764 | J13: ='2a. Dispatch Natural P&L'!J13+'2b. Youreka Natural P&L'!J13 -> 772519.96 | K13: ='2a. Dispatch Natural P&L'!K13+'2b. Youreka Natural P&L'!K13 -> 506416.67 | L13: =IFERROR(J13-K13,"N/A") -> 266103.29 | M13: =IFERROR((J13/K13-1),"N/A") -> 0.52546314 | O13: ='2a. Dispatch Natural P&L'!O13+'2b. Youreka Natural P&L'!O13 -> 49000 | P13: ='2a. Dispatch Natural P&L'!P13+'2b. Youreka Natural P&L'!P13 -> 69018.05 | Q13: =O13-P13 -> -20018.05 | R13: =IFERROR((O13/P13-1),"N/A") -> -0.29004079
C14: Other Non-Recurring Revenue | E14: ='2a. Dispatch Natural P&L'!E14+'2b. Youreka Natural P&L'!E14 -> 0 | F14: ='2a. Dispatch Natural P&L'!F14+'2b. Youreka Natural P&L'!F14 -> 0 | G14: =IFERROR(E14-F14,"N/A") -> 0 | H14: =IFERROR((E14/F14-1),"N/A") -> N/A | J14: ='2a. Dispatch Natural P&L'!J14+'2b. Youreka Natural P&L'!J14 -> 0 | K14: ='2a. Dispatch Natural P&L'!K14+'2b. Youreka Natural P&L'!K14 -> 0 | L14: =IFERROR(J14-K14,"N/A") -> 0 | M14: =IFERROR((J14/K14-1),"N/A") -> N/A | O14: ='2a. Dispatch Natural P&L'!O14+'2b. Youreka Natural P&L'!O14 -> 0 | P14: ='2a. Dispatch Natural P&L'!P14+'2b. Youreka Natural P&L'!P14 -> 0 | Q14: =O14-P14 -> 0 | R14: =IFERROR((O14/P14-1),"N/A") -> N/A
C15: Total Non-Recurring Revenue | E15: ='2a. Dispatch Natural P&L'!E15+'2b. Youreka Natural P&L'!E15 -> 49000 | F15: ='2a. Dispatch Natural P&L'!F15+'2b. Youreka Natural P&L'!F15 -> 39250 | G15: =IFERROR(E15-F15,"N/A") -> 9750 | H15: =IFERROR((E15/F15-1),"N/A") -> 0.24840764 | J15: ='2a. Dispatch Natural P&L'!J15+'2b. Youreka Natural P&L'!J15 -> 772519.96 | K15: ='2a. Dispatch Natural P&L'!K15+'2b. Youreka Natural P&L'!K15 -> 506416.67 | L15: =IFERROR(J15-K15,"N/A") -> 266103.29 | M15: =IFERROR((J15/K15-1),"N/A") -> 0.52546314 | O15: ='2a. Dispatch Natural P&L'!O15+'2b. Youreka Natural P&L'!O15 -> 49000 | P15: ='2a. Dispatch Natural P&L'!P15+'2b. Youreka Natural P&L'!P15 -> 69018.05 | Q15: =O15-P15 -> -20018.05 | R15: =IFERROR((O15/P15-1),"N/A") -> -0.29004079 | U15: =SUM(E13:E14)-E15 -> 0 | V15: =SUM(F13:F14)-F15 -> 0 | X15: =SUM(J13:J14)-J15 -> 0 | Y15: =SUM(K13:K14)-K15 -> 0 | AA15: =SUM(O13:O14)-O15 -> 0 | AB15: =SUM(P13:P14)-P15 -> 0
C16: Total Revenue | E16: ='2a. Dispatch Natural P&L'!E16+'2b. Youreka Natural P&L'!E16 -> 2163880.7 | F16: ='2a. Dispatch Natural P&L'!F16+'2b. Youreka Natural P&L'!F16 -> 2320455.7 | G16: =IFERROR(E16-F16,"N/A") -> -156574.97 | H16: =IFERROR((E16/F16-1),"N/A") -> -0.067475959 | J16: ='2a. Dispatch Natural P&L'!J16+'2b. Youreka Natural P&L'!J16 -> 25686093 | K16: ='2a. Dispatch Natural P&L'!K16+'2b. Youreka Natural P&L'!K16 -> 26215562 | L16: =IFERROR(J16-K16,"N/A") -> -529469.17 | M16: =IFERROR((J16/K16-1),"N/A") -> -0.02019675 | O16: ='2a. Dispatch Natural P&L'!O16+'2b. Youreka Natural P&L'!O16 -> 2163880.7 | P16: ='2a. Dispatch Natural P&L'!P16+'2b. Youreka Natural P&L'!P16 -> 2004730.8 | Q16: =O16-P16 -> 159149.9 | R16: =IFERROR((O16/P16-1),"N/A") -> 0.079387167 | U16: =E11+E15-E16 -> 0 | V16: =F11+F15-F16 -> 0 | X16: =J11+J15-J16 -> 0 | Y16: =K11+K15-K16 -> 0 | AA16: =O11+O15-O16 -> 0 | AB16: =P11+P15-P16 -> 0
C17: % Reccurring Revenue | E17: =E11/E16 -> 0.9773555 | F17: =F11/F16 -> 0.98308522 | G17: =IFERROR(E17-F17,"N/A") -> -0.0057297204 | J17: =J11/J16 -> 0.96992458 | K17: =K11/K16 -> 0.98068259 | L17: =IFERROR(J17-K17,"N/A") -> -0.010758011 | O17: =O11/O16 -> 0.9773555 | P17: =P11/P16 -> 0.96557241 | Q17: =O17-P17 -> 0.011783088 | U17: =E11/E16-E17 -> 0 | V17: =F11/F16-F17 -> 0 | X17: =J11/J16-J17 -> 0 | Y17: =K11/K16-K17 -> 0 | AA17: =O11/O16-O17 -> 0 | AB17: =P11/P16-P17 -> 0
C19: Cost of Sales (Natural)
C20: Cost of Sales (Natural) - Consultants & Contractors | E20: ='2a. Dispatch Natural P&L'!E20+'2b. Youreka Natural P&L'!E20 -> 10632.75 | F20: ='2a. Dispatch Natural P&L'!F20+'2b. Youreka Natural P&L'!F20 -> 0 | G20: =IFERROR(E20-F20,"N/A") -> 10632.75 | H20: =IFERROR((E20/F20-1),"N/A") -> N/A | J20: ='2a. Dispatch Natural P&L'!J20+'2b. Youreka Natural P&L'!J20 -> 51263.75 | K20: ='2a. Dispatch Natural P&L'!K20+'2b. Youreka Natural P&L'!K20 -> 0 | L20: =IFERROR(J20-K20,"N/A") -> 51263.75 | M20: =IFERROR((J20/K20-1),"N/A") -> N/A | O20: ='2a. Dispatch Natural P&L'!O20+'2b. Youreka Natural P&L'!O20 -> 10632.75 | P20: ='2a. Dispatch Natural P&L'!P20+'2b. Youreka Natural P&L'!P20 -> 0 | Q20: =O20-P20 -> 10632.75 | R20: =IFERROR((O20/P20-1),"N/A") -> N/A
C21: Cost of Sales (Natural) - Hosting & Infrastructure | E21: ='2a. Dispatch Natural P&L'!E21+'2b. Youreka Natural P&L'!E21 -> 159319.81 | F21: ='2a. Dispatch Natural P&L'!F21+'2b. Youreka Natural P&L'!F21 -> 169122.85 | G21: =IFERROR(E21-F21,"N/A") -> -9803.0355 | H21: =IFERROR((E21/F21-1),"N/A") -> -0.057963994 | J21: ='2a. Dispatch Natural P&L'!J21+'2b. Youreka Natural P&L'!J21 -> 1869794.5 | K21: ='2a. Dispatch Natural P&L'!K21+'2b. Youreka Natural P&L'!K21 -> 1958808.1 | L21: =IFERROR(J21-K21,"N/A") -> -89013.559 | M21: =IFERROR((J21/K21-1),"N/A") -> -0.045442716 | O21: ='2a. Dispatch Natural P&L'!O21+'2b. Youreka Natural P&L'!O21 -> 159319.81 | P21: ='2a. Dispatch Natural P&L'!P21+'2b. Youreka Natural P&L'!P21 -> 145877.6 | Q21: =O21-P21 -> 13442.21 | R21: =IFERROR((O21/P21-1),"N/A") -> 0.092147184
C22: Cost of Sales (Natural) - Software & Subscriptions | E22: ='2a. Dispatch Natural P&L'!E22+'2b. Youreka Natural P&L'!E22 -> 60407.04 | F22: ='2a. Dispatch Natural P&L'!F22+'2b. Youreka Natural P&L'!F22 -> 60127.688 | G22: =IFERROR(E22-F22,"N/A") -> 279.3525 | H22: =IFERROR((E22/F22-1),"N/A") -> 0.0046459878 | J22: ='2a. Dispatch Natural P&L'!J22+'2b. Youreka Natural P&L'!J22 -> 736470.03 | K22: ='2a. Dispatch Natural P&L'!K22+'2b. Youreka Natural P&L'!K22 -> 751768.25 | L22: =IFERROR(J22-K22,"N/A") -> -15298.22 | M22: =IFERROR((J22/K22-1),"N/A") -> -0.020349649 | O22: ='2a. Dispatch Natural P&L'!O22+'2b. Youreka Natural P&L'!O22 -> 60407.04 | P22: ='2a. Dispatch Natural P&L'!P22+'2b. Youreka Natural P&L'!P22 -> 58677.8 | Q22: =O22-P22 -> 1729.24 | R22: =IFERROR((O22/P22-1),"N/A") -> 0.029470089
C23: Total Cost of Sales - Natural | E23: ='2a. Dispatch Natural P&L'!E23+'2b. Youreka Natural P&L'!E23 -> 230359.6 | F23: ='2a. Dispatch Natural P&L'!F23+'2b. Youreka Natural P&L'!F23 -> 229250.53 | G23: =IFERROR(E23-F23,"N/A") -> 1109.067 | H23: =IFERROR((E23/F23-1),"N/A") -> 0.0048377945 | J23: ='2a. Dispatch Natural P&L'!J23+'2b. Youreka Natural P&L'!J23 -> 2657528.3 | K23: ='2a. Dispatch Natural P&L'!K23+'2b. Youreka Natural P&L'!K23 -> 2710576.3 | L23: =IFERROR(J23-K23,"N/A") -> -53048.029 | M23: =IFERROR((J23/K23-1),"N/A") -> -0.019570756 | O23: ='2a. Dispatch Natural P&L'!O23+'2b. Youreka Natural P&L'!O23 -> 230359.6 | P23: ='2a. Dispatch Natural P&L'!P23+'2b. Youreka Natural P&L'!P23 -> 204555.4 | Q23: =O23-P23 -> 25804.2 | R23: =IFERROR((O23/P23-1),"N/A") -> 0.12614773 | U23: =SUM(E20:E22)-E23 -> 0 | V23: =SUM(F20:F22)-F23 -> 0 | X23: =SUM(J20:J22)-J23 -> 0 | Y23: =SUM(K20:K22)-K23 -> 0 | AA23: =SUM(O20:O22)-O23 -> 0 | AB23: =SUM(P20:P22)-P23 -> 0
C24: Total Gross Profit - Natural | E24: ='2a. Dispatch Natural P&L'!E24+'2b. Youreka Natural P&L'!E24 -> 1933521.1 | F24: ='2a. Dispatch Natural P&L'!F24+'2b. Youreka Natural P&L'!F24 -> 2091205.2 | G24: =IFERROR(E24-F24,"N/A") -> -157684.04 | H24: =IFERROR((E24/F24-1),"N/A") -> -0.07540343 | J24: ='2a. Dispatch Natural P&L'!J24+'2b. Youreka Natural P&L'!J24 -> 23028565 | K24: ='2a. Dispatch Natural P&L'!K24+'2b. Youreka Natural P&L'!K24 -> 23504986 | L24: =IFERROR(J24-K24,"N/A") -> -476421.14 | M24: =IFERROR((J24/K24-1),"N/A") -> -0.020268939 | O24: ='2a. Dispatch Natural P&L'!O24+'2b. Youreka Natural P&L'!O24 -> 1933521.1 | P24: ='2a. Dispatch Natural P&L'!P24+'2b. Youreka Natural P&L'!P24 -> 1800175.4 | Q24: =O24-P24 -> 133345.7 | R24: =IFERROR((O24/P24-1),"N/A") -> 0.074073726 | U24: =E16-E23-E24 -> 0 | V24: =F16-F23-F24 -> 0 | X24: =J16-J23-J24 -> 0 | Y24: =K16-K23-K24 -> 0 | AA24: =O16-O23-O24 -> 0 | AB24: =P16-P23-P24 -> 0
C25: Gross Profit Margin % - Natural | E25: =E24/E16 -> 0.8935433 | F25: =F24/F16 -> 0.90120452 | G25: =IFERROR(E25-F25,"N/A") -> -0.0076612202 | J25: =J24/J16 -> 0.89653825 | K25: =K24/K16 -> 0.8966043 | L25: =IFERROR(J25-K25,"N/A") -> -6.6059255e-05 | O25: =O24/O16 -> 0.8935433 | P25: =P24/P16 -> 0.89796366 | Q25: =O25-P25 -> -0.0044203575 | U25: =E24/E16-E25 -> 0 | V25: =F24/F16-F25 -> 0 | X25: =J24/J16-J25 -> 0 | Y25: =K24/K16-K25 -> 0 | AA25: =O24/O16-O25 -> 0 | AB25: =P24/P16-P25 -> 0
C27: Operating Expenses
C28: Compensation Expenses
C29: Salaries & Wages | E29: ='2a. Dispatch Natural P&L'!E29+'2b. Youreka Natural P&L'!E29 -> 846609.42 | F29: ='2a. Dispatch Natural P&L'!F29+'2b. Youreka Natural P&L'!F29 -> 1016333.3 | G29: =IFERROR(E29-F29,"N/A") -> -169723.84 | H29: =IFERROR((E29/F29-1),"N/A") -> -0.16699625 | J29: ='2a. Dispatch Natural P&L'!J29+'2b. Youreka Natural P&L'!J29 -> 11370150 | K29: ='2a. Dispatch Natural P&L'!K29+'2b. Youreka Natural P&L'!K29 -> 12424859 | L29: =IFERROR(J29-K29,"N/A") -> -1054709.4 | M29: =IFERROR((J29/K29-1),"N/A") -> -0.084887032 | O29: ='2a. Dispatch Natural P&L'!O29+'2b. Youreka Natural P&L'!O29 -> 846609.42 | P29: ='2a. Dispatch Natural P&L'!P29+'2b. Youreka Natural P&L'!P29 -> 1054615.6 | Q29: =O29-P29 -> -208006.18 | R29: =IFERROR((O29/P29-1),"N/A") -> -0.19723412
C30: Commission & Bonus | E30: ='2a. Dispatch Natural P&L'!E30+'2b. Youreka Natural P&L'!E30 -> 131765.87 | F30: ='2a. Dispatch Natural P&L'!F30+'2b. Youreka Natural P&L'!F30 -> 194549.9 | G30: =IFERROR(E30-F30,"N/A") -> -62784.028 | H30: =IFERROR((E30/F30-1),"N/A") -> -0.32271427 | J30: ='2a. Dispatch Natural P&L'!J30+'2b. Youreka Natural P&L'!J30 -> 1626260.3 | K30: ='2a. Dispatch Natural P&L'!K30+'2b. Youreka Natural P&L'!K30 -> 2312240.3 | L30: =IFERROR(J30-K30,"N/A") -> -685980 | M30: =IFERROR((J30/K30-1),"N/A") -> -0.29667332 | O30: ='2a. Dispatch Natural P&L'!O30+'2b. Youreka Natural P&L'!O30 -> 131765.87 | P30: ='2a. Dispatch Natural P&L'!P30+'2b. Youreka Natural P&L'!P30 -> 157458.87 | Q30: =O30-P30 -> -25693 | R30: =IFERROR((O30/P30-1),"N/A") -> -0.16317277
C31: Taxes & Benefits | E31: ='2a. Dispatch Natural P&L'!E31+'2b. Youreka Natural P&L'!E31 -> 168637.33 | F31: ='2a. Dispatch Natural P&L'!F31+'2b. Youreka Natural P&L'!F31 -> 209384.33 | G31: =IFERROR(E31-F31,"N/A") -> -40747 | H31: =IFERROR((E31/F31-1),"N/A") -> -0.19460387 | J31: ='2a. Dispatch Natural P&L'!J31+'2b. Youreka Natural P&L'!J31 -> 2552005.2 | K31: ='2a. Dispatch Natural P&L'!K31+'2b. Youreka Natural P&L'!K31 -> 2710029.1 | L31: =IFERROR(J31-K31,"N/A") -> -158023.84 | M31: =IFERROR((J31/K31-1),"N/A") -> -0.058310755 | O31: ='2a. Dispatch Natural P&L'!O31+'2b. Youreka Natural P&L'!O31 -> 168637.33 | P31: ='2a. Dispatch Natural P&L'!P31+'2b. Youreka Natural P&L'!P31 -> 201357.4 | Q31: =O31-P31 -> -32720.07 | R31: =IFERROR((O31/P31-1),"N/A") -> -0.16249748
C32: Payroll Fees | E32: ='2a. Dispatch Natural P&L'!E32+'2b. Youreka Natural P&L'!E32 -> 4142.49 | F32: ='2a. Dispatch Natural P&L'!F32+'2b. Youreka Natural P&L'!F32 -> 4095 | G32: =IFERROR(E32-F32,"N/A") -> 47.49 | H32: =IFERROR((E32/F32-1),"N/A") -> 0.01159707 | J32: ='2a. Dispatch Natural P&L'!J32+'2b. Youreka Natural P&L'!J32 -> 51081.67 | K32: ='2a. Dispatch Natural P&L'!K32+'2b. Youreka Natural P&L'!K32 -> 50580 | L32: =IFERROR(J32-K32,"N/A") -> 501.67 | M32: =IFERROR((J32/K32-1),"N/A") -> 0.0099183472 | O32: ='2a. Dispatch Natural P&L'!O32+'2b. Youreka Natural P&L'!O32 -> 4142.49 | P32: ='2a. Dispatch Natural P&L'!P32+'2b. Youreka Natural P&L'!P32 -> 4167.8 | Q32: =O32-P32 -> -25.31 | R32: =IFERROR((O32/P32-1),"N/A") -> -0.0060727482
C33: Consultants & Contractors | E33: ='2a. Dispatch Natural P&L'!E33+'2b. Youreka Natural P&L'!E33 -> 44669.42 | F33: ='2a. Dispatch Natural P&L'!F33+'2b. Youreka Natural P&L'!F33 -> 49002.562 | G33: =IFERROR(E33-F33,"N/A") -> -4333.1425 | H33: =IFERROR((E33/F33-1),"N/A") -> -0.088426855 | J33: ='2a. Dispatch Natural P&L'!J33+'2b. Youreka Natural P&L'!J33 -> 579399.38 | K33: ='2a. Dispatch Natural P&L'!K33+'2b. Youreka Natural P&L'!K33 -> 598630.75 | L33: =IFERROR(J33-K33,"N/A") -> -19231.37 | M33: =IFERROR((J33/K33-1),"N/A") -> -0.032125597 | O33: ='2a. Dispatch Natural P&L'!O33+'2b. Youreka Natural P&L'!O33 -> 44669.42 | P33: ='2a. Dispatch Natural P&L'!P33+'2b. Youreka Natural P&L'!P33 -> 48856.26 | Q33: =O33-P33 -> -4186.84 | R33: =IFERROR((O33/P33-1),"N/A") -> -0.085697104
C34: Total - Compensation Expenses | E34: ='2a. Dispatch Natural P&L'!E34+'2b. Youreka Natural P&L'!E34 -> 1195824.5 | F34: ='2a. Dispatch Natural P&L'!F34+'2b. Youreka Natural P&L'!F34 -> 1473365 | G34: =IFERROR(E34-F34,"N/A") -> -277540.52 | H34: =IFERROR((E34/F34-1),"N/A") -> -0.18837186 | J34: ='2a. Dispatch Natural P&L'!J34+'2b. Youreka Natural P&L'!J34 -> 16178896 | K34: ='2a. Dispatch Natural P&L'!K34+'2b. Youreka Natural P&L'!K34 -> 18096339 | L34: =IFERROR(J34-K34,"N/A") -> -1917442.9 | M34: =IFERROR((J34/K34-1),"N/A") -> -0.10595751 | O34: ='2a. Dispatch Natural P&L'!O34+'2b. Youreka Natural P&L'!O34 -> 1195824.5 | P34: ='2a. Dispatch Natural P&L'!P34+'2b. Youreka Natural P&L'!P34 -> 1466455.9 | Q34: =O34-P34 -> -270631.4 | R34: =IFERROR((O34/P34-1),"N/A") -> -0.18454793 | U34: =SUM(E29:E33)-E34 -> 0 | V34: =SUM(F29:F33)-F34 -> 0 | X34: =SUM(J29:J33)-J34 -> 0 | Y34: =SUM(K29:K33)-K34 -> 0 | AA34: =SUM(O29:O33)-O34 -> 0 | AB34: =SUM(P29:P33)-P34 -> 0
C36: Non-Compensation Expenses
C37: Travel & Entertainment | E37: ='2a. Dispatch Natural P&L'!E37+'2b. Youreka Natural P&L'!E37 -> 8873.53 | F37: ='2a. Dispatch Natural P&L'!F37+'2b. Youreka Natural P&L'!F37 -> 31820 | G37: =IFERROR(E37-F37,"N/A") -> -22946.47 | H37: =IFERROR((E37/F37-1),"N/A") -> -0.72113356 | J37: ='2a. Dispatch Natural P&L'!J37+'2b. Youreka Natural P&L'!J37 -> 288877.89 | K37: ='2a. Dispatch Natural P&L'!K37+'2b. Youreka Natural P&L'!K37 -> 453390 | L37: =IFERROR(J37-K37,"N/A") -> -164512.11 | M37: =IFERROR((J37/K37-1),"N/A") -> -0.362849 | O37: ='2a. Dispatch Natural P&L'!O37+'2b. Youreka Natural P&L'!O37 -> 8873.53 | P37: ='2a. Dispatch Natural P&L'!P37+'2b. Youreka Natural P&L'!P37 -> 21073.94 | Q37: =O37-P37 -> -12200.41 | R37: =IFERROR((O37/P37-1),"N/A") -> -0.57893351
C38: Facilities | E38: ='2a. Dispatch Natural P&L'!E38+'2b. Youreka Natural P&L'!E38 -> 28220.53 | F38: ='2a. Dispatch Natural P&L'!F38+'2b. Youreka Natural P&L'!F38 -> 29121.499 | G38: =IFERROR(E38-F38,"N/A") -> -900.96895 | H38: =IFERROR((E38/F38-1),"N/A") -> -0.030938275 | J38: ='2a. Dispatch Natural P&L'!J38+'2b. Youreka Natural P&L'!J38 -> 346774.93 | K38: ='2a. Dispatch Natural P&L'!K38+'2b. Youreka Natural P&L'!K38 -> 344457.99 | L38: =IFERROR(J38-K38,"N/A") -> 2316.9426 | M38: =IFERROR((J38/K38-1),"N/A") -> 0.0067263432 | O38: ='2a. Dispatch Natural P&L'!O38+'2b. Youreka Natural P&L'!O38 -> 28220.53 | P38: ='2a. Dispatch Natural P&L'!P38+'2b. Youreka Natural P&L'!P38 -> 28210.84 | Q38: =O38-P38 -> 9.69 | R38: =IFERROR((O38/P38-1),"N/A") -> 0.00034348499
C39: Marketing & Advertising | E39: ='2a. Dispatch Natural P&L'!E39+'2b. Youreka Natural P&L'!E39 -> 13340.54 | F39: ='2a. Dispatch Natural P&L'!F39+'2b. Youreka Natural P&L'!F39 -> 30150 | G39: =IFERROR(E39-F39,"N/A") -> -16809.46 | H39: =IFERROR((E39/F39-1),"N/A") -> -0.55752769 | J39: ='2a. Dispatch Natural P&L'!J39+'2b. Youreka Natural P&L'!J39 -> 298255.8 | K39: ='2a. Dispatch Natural P&L'!K39+'2b. Youreka Natural P&L'!K39 -> 497250 | L39: =IFERROR(J39-K39,"N/A") -> -198994.2 | M39: =IFERROR((J39/K39-1),"N/A") -> -0.40018944 | O39: ='2a. Dispatch Natural P&L'!O39+'2b. Youreka Natural P&L'!O39 -> 13340.54 | P39: ='2a. Dispatch Natural P&L'!P39+'2b. Youreka Natural P&L'!P39 -> 13696.19 | Q39: =O39-P39 -> -355.65 | R39: =IFERROR((O39/P39-1),"N/A") -> -0.025967076
C40: Computer Hardware / Software License & Maintenance | E40: ='2a. Dispatch Natural P&L'!E40+'2b. Youreka Natural P&L'!E40 -> 81099.05 | F40: ='2a. Dispatch Natural P&L'!F40+'2b. Youreka Natural P&L'!F40 -> 76323.22 | G40: =IFERROR(E40-F40,"N/A") -> 4775.8304 | H40: =IFERROR((E40/F40-1),"N/A") -> 0.062573755 | J40: ='2a. Dispatch Natural P&L'!J40+'2b. Youreka Natural P&L'!J40 -> 925608.27 | K40: ='2a. Dispatch Natural P&L'!K40+'2b. Youreka Natural P&L'!K40 -> 906343.25 | L40: =IFERROR(J40-K40,"N/A") -> 19265.018 | M40: =IFERROR((J40/K40-1),"N/A") -> 0.021255764 | O40: ='2a. Dispatch Natural P&L'!O40+'2b. Youreka Natural P&L'!O40 -> 81099.05 | P40: ='2a. Dispatch Natural P&L'!P40+'2b. Youreka Natural P&L'!P40 -> 73620.16 | Q40: =O40-P40 -> 7478.89 | R40: =IFERROR((O40/P40-1),"N/A") -> 0.10158753
C41: Telecommunications | E41: ='2a. Dispatch Natural P&L'!E41+'2b. Youreka Natural P&L'!E41 -> 1182.18 | F41: ='2a. Dispatch Natural P&L'!F41+'2b. Youreka Natural P&L'!F41 -> 2250 | G41: =IFERROR(E41-F41,"N/A") -> -1067.82 | H41: =IFERROR((E41/F41-1),"N/A") -> -0.47458667 | J41: ='2a. Dispatch Natural P&L'!J41+'2b. Youreka Natural P&L'!J41 -> 21554.38 | K41: ='2a. Dispatch Natural P&L'!K41+'2b. Youreka Natural P&L'!K41 -> 27000 | L41: =IFERROR(J41-K41,"N/A") -> -5445.62 | M41: =IFERROR((J41/K41-1),"N/A") -> -0.20168963 | O41: ='2a. Dispatch Natural P&L'!O41+'2b. Youreka Natural P&L'!O41 -> 1182.18 | P41: ='2a. Dispatch Natural P&L'!P41+'2b. Youreka Natural P&L'!P41 -> 1350.71 | Q41: =O41-P41 -> -168.53 | R41: =IFERROR((O41/P41-1),"N/A") -> -0.12477142
